Workbook

Sheet 小红书-订单明细
A1: 订单号 | B1: 1 | C1: 订单状态 | D1: 售后状态 | E1: 订单类型 | F1: 订单标记 | G1: 收件人姓名 | H1: 收件人电话 | I1: 收件人地址 | J1: 省 | K1: 市 | L1: 区 | M1: 区域编码 | N1: 小红书编码 | O1: 条形码 | P1: 规格ID | Q1: 达人ID | R1: 达人名称 | S1: SKU名称 | T1: SKU规格 | U1: SKU件数 | V1: 是否为赠品 | W1: 发票/Invoice | X1: 商品总价(元) | Y1: 用户应付金额(元) | Z1: 平台优惠(元) | AA1: 店铺优惠(元) | AB1: 支付渠道优惠(元) | AC1: SKU商家改价(元) | AD1: 商家应收金额(元)（支付金额） | AE1: 支付方式 | AF1: 支付渠道订单号 | AG1: 支付期数 | AH1: 利息费用 | AI1: 手续费承担方 | AJ1: 支付时间 | AK1: sku净重(kg) | AL1: 包裹总净重(kg) | AM1: 包裹总运费(元) | AN1: 快递公司 | AO1: 快递单号 | AP1: 大头笔/Paint Marker | AQ1: 集包地/Express Extend 1 | AR1: 三段码/Express Extend 2 | AS1: 订购人身份证姓名/ID Name | AT1: 订购人身份证号/ID Number | AU1: 收件人身份证姓名 | AV1: 收件人身份证号 | AW1: 订单创建时间 | AX1: 预售订单开始发货时间 | AY1: 预售订单截止发货时间 | AZ1: 承诺发货时间 | BA1: 订单发货时间 | BB1: 订单完成时间 | BC1: 发货仓库 | BD1: 确认收货类型 | BE1: 是否延迟收货 | BF1: 用户备注 | BG1: 包裹备注标记 | BH1: 包裹备注信息 | BI1: 异常原因 | BJ1: 店铺名称 | BK1: 用户编号 | BL1: 运费模版名称 | BM1: 物流方案名称 | BN1: 第三方机构订单号 | BO1: 国补模式 | BP1: 供应商id | BQ1: 供应商名称 | BR1: 商家编码 | BS1: 商品ID | BT1: 商品名称
A2: P776450506670185383 | B2: =_xlfn.XLOOKUP(A2,'小红书-结算账单'!R:R,'小红书-结算账单'!R:R) -> P776450506670185383 | C2: 已完成 | D2: 无售后 | E2: 预售订单 | G2: 陈* | H2: 185****9339 | I2: 广东省 深圳市 龙岗区 *** | J2: 广东省 | K2: 深圳市 | L2: 龙岗区 | M2: 440307017 | N2: 689d98fa3b9d470015b74585 | O2: XHS-33LDRKIY2HOG | P2: 689d98fa3b9d470015b74584 | S2: 【老板周】小众休闲 春季单口袋翻领设计感廓形百搭衬衫 黑色 S（80-100斤） | T2: 黑色 S（80-100斤） | U2: 1 | X2: 289 | Y2: 254.47 | Z2: 34.53 | AA2: 0 | AC2: 0 | AD2: 289 | AE2: 银联 | AF2: 762510200228279916448 | AJ2: 2025-10-20 02:29:15 | AL2: 0.000 | AM2: 0.00 | AN2: 中通速递 | AO2: 73577344950969 | AW2: 2025-10-20 02:28:27 | AZ2: 2025-11-04 02:29:15 | BA2: 2025-10-20 16:00:35 | BB2: 2025-10-27 16:00:36 | BC2: 第三方平台卖家电子库存 | BD2: 系统自动收货 | BE2: 否 | BJ2: LAO BAN ZHOU的店 | BK2: 5a573d4d4eacab4e1f29f9a8 | BL2: 公司店运费模版 | BM2: 小红书公司 | BR2: Z1744-黑色-S | BS2: 689d98fa3b9d470015b74583 | BT2: 【老板周】小众休闲 春季单口袋翻领设计感廓形百搭衬衫
A3: P776413384104295891 | B3: =_xlfn.XLOOKUP(A3,'小红书-结算账单'!R:R,'小红书-结算账单'!R:R) -> P776413384104295891 | C3: 已完成 | D3: 无售后 | E3: 预售订单 | G3: 王* | H3: 186****2222 | I3: 山东省 青岛市 李沧区 *** | J3: 山东省 | K3: 青岛市 | L3: 李沧区 | M3: 370213 | N3: 68bc2b917be29900156dcb03 | O3: XHS-3M8510F0MEPT | P3: 68bc2b917be29900156dcb02 | Q3: 650d6e9f000000001603a6ac | R3: 老板周. | S3: LAO BAN ZHOU 【老板周】百搭经典 定制混纺半高领舒适打底衫 黑色 M（95-110斤） | T3: 黑色 M（95-110斤） | U3: 1 | X3: 180 | Y3: 180 | Z3: 0 | AA3: 0 | AC3: 0 | AD3: 180 | AE3: 微信 | AF3: 4345302459202510196711849700 | AJ3: 2025-10-19 16:09:48 | AL3: 0.000 | AM3: 0.00 | AN3: 中通速递 | AO3: 73577367911306 | AW3: 2025-10-19 16:09:44 | AZ3: 2025-11-03 16:09:48 | BA3: 2025-10-20 17:58:51 | BB3: 2025-10-27 17:58:52 | BC3: 第三方平台卖家电子库存 | BD3: 系统自动收货 | BE3: 否 | BJ3: LAO BAN ZHOU的店 | BK3: 5b1ff1b3e8ac2b622a40a237 | BL3: 公司店运费模版 | BM3: 小红书公司 | BR3: Z119-黑色-M | BS3: 68bc2b917be29900156dcaff | BT3: 【老板周】百搭经典 定制混纺半高领舒适打底衫
A4: P776212592782130361 | B4: =_xlfn.XLOOKUP(A4,'小红书-结算账单'!R:R,'小红书-结算账单'!R:R) -> P776212592782130361 | C4: 已关闭 | D4: 售后完成 | E4: 预售订单 | G4: 王** | H4: 180****5179 | I4: 北京 北京市 西城区 *** | J4: 北京 | K4: 北京市 | L4: 西城区 | M4: 110102 | N4: 68e90d604290ae0015508d8f | O4: XHS-3PLL9MH2YQDC | P4: 68e90d604290ae0015508d8e | Q4: 650d6e9f000000001603a6ac | R4: 老板周. | S4: LAO BAN ZHOU 【老板周】慵懒松弛 秋冬新品连帽半拉链奶咖针织马甲 深灰色 M（80-100斤） | T4: 深灰色 M（80-100斤） | U4: 1 | X4: 299 | Y4: 299 | Z4: 0 | AA4: 0 | AC4: 0 | AD4: 299 | AE4: 支付宝 | AF4: 2025101722001435471407497525 | AJ4: 2025-10-17 08:23:24 | AL4: 0.000 | AM4: 0.00 | AN4: 中通速递 | AO4: 73577405756360 | AW4: 2025-10-17 08:23:13 | AZ4: 2025-11-01 08:23:24 | BA4: 2025-10-20 23:14:08 | BC4: 第三方平台卖家电子库存 | BE4: 否 | BG4: 灰旗 | BH4: ;(收)[Z2561-深灰色-M]*[1]# | BJ4: LAO BAN ZHOU的店 | BK4: 59a2ec9350c4b42e5cdd8ca8 | BL4: 公司店运费模版 | BM4: 小红书公司 | BR4: Z2561-深灰色-M | BS4: 68e90d604290ae0015508d8d | BT4: 【老板周】慵懒松弛 秋冬新品连帽半拉链奶咖针织马甲
A5: P776035102571191292 | B5: =_xlfn.XLOOKUP(A5,'小红书-结算账单'!R:R,'小红书-结算账单'!R:R) -> P776035102571191292 | C5: 已完成 | D5: 无售后 | E5: 预售订单 | G5: 麦** | H5: 136****7549 | I5: 上海 上海市 黄浦区 *** | J5: 上海 | K5: 上海市 | L5: 黄浦区 | M5: 310101002000 | N5: XHS-3N0YAR11BAPS | O5: XHS-3N0YAR11BAPS | P5: 68c6d0daf9d8290001dcb02d | S5: LAO BAN ZHOU 【老板周】极简主义 秋冬立体裁剪弧形设计感休闲私服裤 咖色 M（95-110斤） | T5: 咖色 M（95-110斤） | U5: 1 | X5: 339 | Y5: 288.16 | Z5: 50.84 | AA5: 0 | AC5: 0 | AD5: 339 | AE5: 支付宝 | AJ5: 2025-10-15 07:05:08 | AL5: 0.000 | AM5: 0.00 | AN5: 中通速递 | AO5: 73577344923853 | AW5: 2025-10-15 07:05:02 | AZ5: 2025-10-30 07:05:08 | BA5: 2025-10-20 15:55:30 | BB5: 2025-10-27 15:55:30 | BC5: 第三方平台卖家电子库存 | BD5: 系统自动收货 | BE5: 否 | BJ5: LAO BAN ZHOU的店 | BK5: 569589dc1c07df4b71df8cf0 | BL5: 公司店运费模版 | BM5: 小红书公司 | BR5: Z1436-咖色-M | BS5: 68aaf74f581ea20015bf4bc3 | BT5: 【老板周】极简主义 秋冬立体裁剪弧形设计感休闲私服裤
A6: P775954589917164071 | B6: =_xlfn.XLOOKUP(A6,'小红书-结算账单'!R:R,'小红书-结算账单'!R:R) -> P775954589917164071 | C6: 已关闭 | D6: 售后完成 | E6: 预售订单 | G6: 悠* | H6: 183****2650 | I6: 辽宁省 铁岭市 铁岭县 *** | J6: 辽宁省 | K6: 铁岭市 | L6: 铁岭县 | M6: 211221105 | N6: 68cea8f7f6cbe500156c0154 | O6: XHS-3NM6LSUL0W75 | P6: 68cea8f7f6cbe500156c0153 | Q6: 650d6e9f000000001603a6ac | R6: 老板周. | S6: LAO BAN ZHOU 【老板周】气质优雅 秋冬亲肤有型百搭奶茶圆领针织上衣 奶茶色 M（100-120斤） | T6: 奶茶色 M（100-120斤） | U6: 1 | X6: 139 | Y6: 139 | Z6: 0 | AA6: 0 | AC6: 0 | AD6: 139 | AE6: 支付宝 | AF6: 2025101422001431591459480137 | AJ6: 2025-10-14 08:43:15 | AL6: 0.000 | AM6: 0.00 | AN6: 中通速递 | AO6: 73577344916376 | AW6: 2025-10-14 08:43:10 | AZ6: 2025-10-29 08:43:15 | BA6: 2025-10-20 15:18:42 | BB6: 2025-10-27 15:18:42 | BC6: 第三方平台卖家电子库存 | BD6: 系统自动收货 | BE6: 否 | BG6: 灰旗 | BH6: ;(收)[Z1326-奶茶色-M]*[1]# | BJ6: LAO BAN ZHOU的店 | BK6: 63b2bddb0000000026012f42 | BL6: 公司店运费模版 | BM6: 小红书公司 | BR6: Z1326-奶茶色-M | BS6: 68cea8f7f6cbe500156c0150 | BT6: 【老板周】气质优雅 秋冬亲肤有型百搭奶茶圆领针织上衣
A7: P775810157576298981 | B7: =_xlfn.XLOOKUP(A7,'小红书-结算账单'!R:R,'小红书-结算账单'!R:R) -> P775810157576298981 | C7: 已完成 | D7: 无售后 | E7: 预售订单 | G7: 谭** | H7: 135****1587 | I7: 湖南省 株洲市 攸县 *** | J7: 湖南省 | K7: 株洲市 | L7: 攸县 | M7: 430223001000 | N7: XHS-3N0YAR1BAW3K | O7: XHS-3N0YAR1BAW3K | P7: 68c6d0daf9d8290001dcb033 | Q7: 650d6e9f000000001603a6ac | R7: 老板周. | S7: LAO BAN ZHOU 【老板周】极简主义 秋冬立体裁剪弧形设计感休闲私服裤 咖色 XL（125-140斤） | T7: 咖色 XL（125-140斤） | U7: 1 | X7: 339 | Y7: 304 | Z7: 35 | AA7: 0 | AC7: 0 | AD7: 339 | AE7: 支付宝 | AF7: 2025101222001453241431496470 | AJ7: 2025-10-12 16:36:04 | AL7: 0.000 | AM7: 0.00 | AN7: 中通速递 | AO7: 73576648943793 | AW7: 2025-10-12 16:35:57 | AZ7: 2025-10-27 16:36:04 | BA7: 2025-10-15 17:47:17 | BB7: 2025-10-22 17:47:18 | BC7: 第三方平台卖家电子库存 | BD7: 系统自动收货 | BE7: 否 | BG7: 灰旗 | BH7: ;(收)[Z1436-咖色-L]*[1]# | BJ7: LAO BAN ZHOU的店 | BK7: 59b6b84e82ec3931c55e004b | BL7: 公司店运费模版 | BM7: 小红书公司 | BR7: Z1436-咖色-XL | BS7: 68aaf74f581ea20015bf4bc3 | BT7: 【老板周】极简主义 秋冬立体裁剪弧形设计感休闲私服裤
A8: P775810157576298981 | B8: =_xlfn.XLOOKUP(A8,'小红书-结算账单'!R:R,'小红书-结算账单'!R:R) -> P775810157576298981 | C8: 已完成 | D8: 售后完成 | E8: 预售订单 | G8: 谭** | H8: 135****1587 | I8: 湖南省 株洲市 攸县 *** | J8: 湖南省 | K8: 株洲市 | L8: 攸县 | M8: 430223001000 | N8: XHS-3N0YAR16B3EO | O8: XHS-3N0YAR16B3EO | P8: 68c6d0daf9d8290001dcb030 | Q8: 650d6e9f000000001603a6ac | R8: 老板周. | S8: LAO BAN ZHOU 【老板周】极简主义 秋冬立体裁剪弧形设计感休闲私服裤 咖色 L（110-125斤） | T8: 咖色 L（110-125斤） | U8: 1 | X8: 339 | Y8: 304 | Z8: 35 | AA8: 0 | AC8: 0 | AD8: 339 | AE8: 支付宝 | AF8: 2025101222001453241431496470 | AJ8: 2025-10-12 16:36:04 | AL8: 0.000 | AM8: 0.00 | AN8: 中通速递 | AO8: 73576648943793 | AW8: 2025-10-12 16:35:57 | AZ8: 2025-10-27 16:36:04 | BA8: 2025-10-15 17:47:17 | BB8: 2025-10-22 17:47:18 | BC8: 第三方平台卖家电子库存 | BD8: 系统自动收货 | BE8: 否 | BG8: 灰旗 | BH8: ;(收)[Z1436-咖色-L]*[1]# | BJ8: LAO BAN ZHOU的店 | BK8: 59b6b84e82ec3931c55e004b | BL8: 公司店运费模版 | BM8: 小红书公司 | BR8: Z1436-咖色-L | BS8: 68aaf74f581ea20015bf4bc3 | BT8: 【老板周】极简主义 秋冬立体裁剪弧形设计感休闲私服裤

Sheet 小红书-结算账单
A1: 年 | B1: 月 | C1: 订单号 | D1: 订单行数 | E1: 订单序位 | F1: 平台商品编码 | G1: 商品编码 | H1: 销售数量 | I1: 应收客户 | J1: 应收平台 | K1: 收：价外收费 | L1: 扣：平台佣金用 | M1: 扣：分销佣金 | N1: 扣其它费用 | O1: 应到账金额 | Q1: 留用 | R1: 订单号 | S1: 校验 | T1: 售后单号 | U1: 下单时间 | V1: 完成时间 | W1: 结算时间 | X1: 交易类型 | Y1: 结算账户 | Z1: 动账金额 | AA1: 商品名称 | AB1: 类目 | AC1: SKU条码 | AD1: 规格ID | AE1: 校验 | AF1: 商品数量 | AG1: 计佣基数 | AH1: 商品实付/实退 | AI1: 优惠类型 | AJ1: 商家优惠 | AK1: 平台优惠补贴 | AL1: 平台运费补贴 | AM1: 佣金率 | AN1: 返利率 | AO1: 佣金总额 | AP1: 计税价格(含税) | AQ1: 计税价格(未税) | AR1: 税率 | AS1: 跨境税代缴 | AT1: 商品税金 | AU1: 卖家CPS佣金率 | AV1: 分销佣金 | AW1: _x0008__x0008_推广_x0008_达人ID | AX1: 达人昵称 | AY1: 带货类型 | AZ1: 代运营服务商佣金 | BA1: 代开发服务商佣金 | BB1: 运费 | BC1: 运费税金 | BD1: 支付渠道费 | BE1: 花呗分期手续费 | BF1: 国补订单毛保金额 | BG1: 备注
A2: =YEAR(W2) -> 2025 | B2: =MONTH(W2) -> 10 | C2: =R2 -> P775810157576298981 | D2: =COUNTIF(R:R,R2) -> 3 | E2: =COUNTIF($R$2:R2,R2) -> 1 | F2: {=INDEX('小红书-订单明细'!BR:BR,MATCH(R2&AD2,'小红书-订单明细'!A:A&'小红书-订单明细'!P:P,0))} -> Z1436-咖色-L | G2: =LEFT(F2,FIND("-",F2)-1) -> Z1436 | H2: {=IF(ABS(SUM(AH2,AJ2:AK2)/(INDEX('小红书-订单明细'!X:X,MATCH(R2&AD2,'小红书-订单明细'!A:A&'小红书-订单明细'!P:P,0))/(INDEX('小红书-订单明细'!U:U,MATCH(R2&AD2,'小红书-订单明细'!A:A&'小红书-订单明细'!P:P,0)))))>15%,ROUNDUP(SUM(AH2,AJ2:AK2)/(INDEX('小红书-订单明细'!X:X,MATCH(R2&AD2,'小红书-订单明细'!A:A&'小红书-订单明细'!P:P,0))/(INDEX('小红书-订单明细'!U:U,MATCH(R2&AD2,'小红书-订单明细'!A:A&'小红书-订单明细'!P:P,0)))),0),ROUNDDOWN(SUM(AH2,AJ2:AK2)/(INDEX('小红书-订单明细'!X:X,MATCH(R2&AD2,'小红书-订单明细'!A:A&'小红书-订单明细'!P:P,0))/(INDEX('小红书-订单明细'!U:U,MATCH(R2&AD2,'小红书-订单明细'!A:A&'小红书-订单明细'!P:P,0)))),0))} -> -1 | I2: =AH2 -> -304 | J2: =AK2+AL2 -> -35 | K2: =IF(BB2<=0,BB2,BB2/COUNTIFS(R:R,R2,BB:BB,">0")) -> 0 | L2: =-AO2 -> -16.95 | M2: =-AV2 -> 0 | O2: =I2+J2+K2-L2-M2-N2 -> -322.05 | Q2: {=SUM(AH2,AJ2:AK2)/(INDEX('小红书-订单明细'!X:X,MATCH(R2&AD2,'小红书-订单明细'!A:A&'小红书-订单明细'!P:P,0))/(INDEX('小红书-订单明细'!U:U,MATCH(R2&AD2,'小红书-订单明细'!A:A&'小红书-订单明细'!P:P,0))))} -> -1 | R2: P775810157576298981 | S2: =_xlfn.XLOOKUP(R2,'小红书-订单明细'!A:A,'小红书-订单明细'!A:A) -> P775810157576298981 | T2: R7629898138099819 | U2: 2025-10-12 16:35:57 | V2: 2025-10-21 17:34:49 | W2: 2025-10-31 18:57:25 | X2: 退款 | Y2: 店铺余额 | Z2: -322.05 | AA2: 【老板周】极简主义 秋冬 · 【老板周】极简主义 秋冬立体裁剪弧形设计感休闲私服裤 咖色 L（110-125斤） | AB2: 女装/女士精品>裤子>休闲裤 | AC2: XHS-3N0YAR16B3EO | AD2: 68c6d0daf9d8290001dcb030 | AE2: =_xlfn.XLOOKUP(AD2,'小红书-订单明细'!P:P,'小红书-订单明细'!P:P) -> 68c6d0daf9d8290001dcb030 | AG2: -339 | AH2: -304 | AJ2: 0 | AK2: -35 | AL2: 0 | AO2: 16.95 | AS2: 否 | AT2: 0 | AV2: 0 | BB2: 0 | BC2: 0 | BD2: 0 | BE2: 0 | BF2: 0
A3: =YEAR(W3) -> 2025 | B3: =MONTH(W3) -> 10 | C3: =R3 -> P775810157576298981 | D3: =COUNTIF(R:R,R3) -> 3 | E3: =COUNTIF($R$2:R3,R3) -> 2 | F3: {=INDEX('小红书-订单明细'!BR:BR,MATCH(R3&AD3,'小红书-订单明细'!A:A&'小红书-订单明细'!P:P,0))} -> Z1436-咖色-L | G3: =LEFT(F3,FIND("-",F3)-1) -> Z1436 | H3: {=IF(ABS(SUM(AH3,AJ3:AK3)/(INDEX('小红书-订单明细'!X:X,MATCH(R3&AD3,'小红书-订单明细'!A:A&'小红书-订单明细'!P:P,0))/(INDEX('小红书-订单明细'!U:U,MATCH(R3&AD3,'小红书-订单明细'!A:A&'小红书-订单明细'!P:P,0)))))>15%,ROUNDUP(SUM(AH3,AJ3:AK3)/(INDEX('小红书-订单明细'!X:X,MATCH(R3&AD3,'小红书-订单明细'!A:A&'小红书-订单明细'!P:P,0))/(INDEX('小红书-订单明细'!U:U,MATCH(R3&AD3,'小红书-订单明细'!A:A&'小红书-订单明细'!P:P,0)))),0),ROUNDDOWN(SUM(AH3,AJ3:AK3)/(INDEX('小红书-订单明细'!X:X,MATCH(R3&AD3,'小红书-订单明细'!A:A&'小红书-订单明细'!P:P,0))/(INDEX('小红书-订单明细'!U:U,MATCH(R3&AD3,'小红书-订单明细'!A:A&'小红书-订单明细'!P:P,0)))),0))} -> 1 | I3: =AH3 -> 304 | J3: =AK3+AL3 -> 35 | K3: =IF(BB3<=0,BB3,BB3/COUNTIFS(R:R,R3,BB:BB,">0")) -> 0 | L3: =-AO3 -> 16.95 | M3: =-AV3 -> 0 | O3: =I3+J3+K3-L3-M3-N3 -> 322.05 | Q3: {=SUM(AH3,AJ3:AK3)/(INDEX('小红书-订单明细'!X:X,MATCH(R3&AD3,'小红书-订单明细'!A:A&'小红书-订单明细'!P:P,0))/(INDEX('小红书-订单明细'!U:U,MATCH(R3&AD3,'小红书-订单明细'!A:A&'小红书-订单明细'!P:P,0))))} -> 1 | R3: P775810157576298981 | S3: =_xlfn.XLOOKUP(R3,'小红书-订单明细'!A:A,'小红书-订单明细'!A:A) -> P775810157576298981 | U3: 2025-10-12 16:35:57 | V3: 2025-10-27 17:47:18 | W3: 2025-10-31 18:57:25 | X3: 结算入账 | Y3: 店铺余额 | Z3: 644.1 | AA3: 【老板周】极简主义 秋冬 · 【老板周】极简主义 秋冬立体裁剪弧形设计感休闲私服裤 咖色 L（110-125斤） | AB3: 女装/女士精品>裤子>休闲裤 | AC3: XHS-3N0YAR16B3EO | AD3: 68c6d0daf9d8290001dcb030 | AE3: =_xlfn.XLOOKUP(AD3,'小红书-订单明细'!P:P,'小红书-订单明细'!P:P) -> 68c6d0daf9d8290001dcb030 | AF3: 1 | AG3: 339 | AH3: 304 | AI3: 1年1度狂欢礼券,参与计税; | AJ3: 0 | AK3: 35 | AL3: 0 | AM3: 0.0500 | AN3: 0.0000 | AO3: -16.95 | AP3: 339 | AQ3: 339 | AR3: 0.0000 | AS3: 否 | AT3: 0 | AU3: 0 | AV3: 0 | BB3: 0 | BC3: 0 | BD3: 0 | BE3: 0 | BF3: 0
A4: =YEAR(W4) -> 2025 | B4: =MONTH(W4) -> 10 | C4: =R4 -> P775810157576298981 | D4: =COUNTIF(R:R,R4) -> 3 | E4: =COUNTIF($R$2:R4,R4) -> 3 | F4: {=INDEX('小红书-订单明细'!BR:BR,MATCH(R4&AD4,'小红书-订单明细'!A:A&'小红书-订单明细'!P:P,0))} -> Z1436-咖色-XL | G4: =LEFT(F4,FIND("-",F4)-1) -> Z1436 | H4: {=IF(ABS(SUM(AH4,AJ4:AK4)/(INDEX('小红书-订单明细'!X:X,MATCH(R4&AD4,'小红书-订单明细'!A:A&'小红书-订单明细'!P:P,0))/(INDEX('小红书-订单明细'!U:U,MATCH(R4&AD4,'小红书-订单明细'!A:A&'小红书-订单明细'!P:P,0)))))>15%,ROUNDUP(SUM(AH4,AJ4:AK4)/(INDEX('小红书-订单明细'!X:X,MATCH(R4&AD4,'小红书-订单明细'!A:A&'小红书-订单明细'!P:P,0))/(INDEX('小红书-订单明细'!U:U,MATCH(R4&AD4,'小红书-订单明细'!A:A&'小红书-订单明细'!P:P,0)))),0),ROUNDDOWN(SUM(AH4,AJ4:AK4)/(INDEX('小红书-订单明细'!X:X,MATCH(R4&AD4,'小红书-订单明细'!A:A&'小红书-订单明细'!P:P,0))/(INDEX('小红书-订单明细'!U:U,MATCH(R4&AD4,'小红书-订单明细'!A:A&'小红书-订单明细'!P:P,0)))),0))} -> 1 | I4: =AH4 -> 304 | J4: =AK4+AL4 -> 35 | K4: =IF(BB4<=0,BB4,BB4/COUNTIFS(R:R,R4,BB:BB,">0")) -> 0 | L4: =-AO4 -> 16.95 | M4: =-AV4 -> 0 | O4: =I4+J4+K4-L4-M4-N4 -> 322.05 | Q4: {=SUM(AH4,AJ4:AK4)/(INDEX('小红书-订单明细'!X:X,MATCH(R4&AD4,'小红书-订单明细'!A:A&'小红书-订单明细'!P:P,0))/(INDEX('小红书-订单明细'!U:U,MATCH(R4&AD4,'小红书-订单明细'!A:A&'小红书-订单明细'!P:P,0))))} -> 1 | R4: P775810157576298981 | S4: =_xlfn.XLOOKUP(R4,'小红书-订单明细'!A:A,'小红书-订单明细'!A:A) -> P775810157576298981 | U4: 2025-10-12 16:35:57 | V4: 2025-10-27 17:47:18 | W4: 2025-10-31 18:57:25 | X4: 结算入账 | Y4: 店铺余额 | Z4: 644.1 | AA4: 【老板周】极简主义 秋冬 · 【老板周】极简主义 秋冬立体裁剪弧形设计感休闲私服裤 咖色 XL（125-140斤） | AB4: 女装/女士精品>裤子>休闲裤 | AC4: XHS-3N0YAR1BAW3K | AD4: 68c6d0daf9d8290001dcb033 | AE4: =_xlfn.XLOOKUP(AD4,'小红书-订单明细'!P:P,'小红书-订单明细'!P:P) -> 68c6d0daf9d8290001dcb033 | AF4: 1 | AG4: 339 | AH4: 304 | AI4: 1年1度狂欢礼券,参与计税; | AJ4: 0 | AK4: 35 | AL4: 0 | AM4: 0.0500 | AN4: 0.0000 | AO4: -16.95 | AP4: 339 | AQ4: 339 | AR4: 0.0000 | AS4: 否 | AT4: 0 | AU4: 0 | AV4: 0 | BB4: 0 | BC4: 0 | BD4: 0 | BE4: 0 | BF4: 0
A5: =YEAR(W5) -> 2025 | B5: =MONTH(W5) -> 10 | C5: =R5 -> P776413384104295891 | D5: =COUNTIF(R:R,R5) -> 1 | E5: =COUNTIF($R$2:R5,R5) -> 1 | F5: {=INDEX('小红书-订单明细'!BR:BR,MATCH(R5&AD5,'小红书-订单明细'!A:A&'小红书-订单明细'!P:P,0))} -> Z119-黑色-M | G5: =LEFT(F5,FIND("-",F5)-1) -> Z119 | H5: {=IF(ABS(SUM(AH5,AJ5:AK5)/(INDEX('小红书-订单明细'!X:X,MATCH(R5&AD5,'小红书-订单明细'!A:A&'小红书-订单明细'!P:P,0))/(INDEX('小红书-订单明细'!U:U,MATCH(R5&AD5,'小红书-订单明细'!A:A&'小红书-订单明细'!P:P,0)))))>15%,ROUNDUP(SUM(AH5,AJ5:AK5)/(INDEX('小红书-订单明细'!X:X,MATCH(R5&AD5,'小红书-订单明细'!A:A&'小红书-订单明细'!P:P,0))/(INDEX('小红书-订单明细'!U:U,MATCH(R5&AD5,'小红书-订单明细'!A:A&'小红书-订单明细'!P:P,0)))),0),ROUNDDOWN(SUM(AH5,AJ5:AK5)/(INDEX('小红书-订单明细'!X:X,MATCH(R5&AD5,'小红书-订单明细'!A:A&'小红书-订单明细'!P:P,0))/(INDEX('小红书-订单明细'!U:U,MATCH(R5&AD5,'小红书-订单明细'!A:A&'小红书-订单明细'!P:P,0)))),0))} -> 1 | I5: =AH5 -> 180 | J5: =AK5+AL5 -> 0 | K5: =IF(BB5<=0,BB5,BB5/COUNTIFS(R:R,R5,BB:BB,">0")) -> 0 | L5: =-AO5 -> 9 | M5: =-AV5 -> 1.08 | O5: =I5+J5+K5-L5-M5-N5 -> 169.92 | Q5: {=SUM(AH5,AJ5:AK5)/(INDEX('小红书-订单明细'!X:X,MATCH(R5&AD5,'小红书-订单明细'!A:A&'小红书-订单明细'!P:P,0))/(INDEX('小红书-订单明细'!U:U,MATCH(R5&AD5,'小红书-订单明细'!A:A&'小红书-订单明细'!P:P,0))))} -> 1 | R5: P776413384104295891 | S5: =_xlfn.XLOOKUP(R5,'小红书-订单明细'!A:A,'小红书-订单明细'!A:A) -> P776413384104295891 | U5: 2025-10-19 16:09:44 | V5: 2025-10-27 17:58:52 | W5: 2025-10-31 18:32:16 | X5: 结算入账 | Y5: 店铺余额 | Z5: 169.92 | AA5: 【老板周】百搭经典 定制 · 【老板周】百搭经典 定制混纺半高领舒适打底衫 黑色 M（95-110斤） | AB5: 女装/女士精品>毛针织衫 | AC5: XHS-3M8510F0MEPT | AD5: 68bc2b917be29900156dcb02 | AE5: =_xlfn.XLOOKUP(AD5,'小红书-订单明细'!P:P,'小红书-订单明细'!P:P) -> 68bc2b917be29900156dcb02 | AF5: 1 | AG5: 180 | AH5: 180 | AJ5: 0 | AK5: 0 | AL5: 0 | AM5: 0.0500 | AN5: 0.0000 | AO5: -9 | AP5: 180 | AQ5: 180 | AR5: 0.0000 | AS5: 否 | AT5: 0 | AU5: 0.006 | AV5: -1.08 | AW5: 650d6e9f000000001603a6ac | AX5: 老板周. | AY5: 达人带货 | BB5: 0 | BC5: 0 | BD5: 0 | BE5: 0 | BF5: 0
A6: =YEAR(W6) -> 2025 | B6: =MONTH(W6) -> 10 | C6: =R6 -> P776212592782130361 | D6: =COUNTIF(R:R,R6) -> 2 | E6: =COUNTIF($R$2:R6,R6) -> 1 | F6: {=INDEX('小红书-订单明细'!BR:BR,MATCH(R6&AD6,'小红书-订单明细'!A:A&'小红书-订单明细'!P:P,0))} -> Z2561-深灰色-M | G6: =LEFT(F6,FIND("-",F6)-1) -> Z2561 | H6: {=IF(ABS(SUM(AH6,AJ6:AK6)/(INDEX('小红书-订单明细'!X:X,MATCH(R6&AD6,'小红书-订单明细'!A:A&'小红书-订单明细'!P:P,0))/(INDEX('小红书-订单明细'!U:U,MATCH(R6&AD6,'小红书-订单明细'!A:A&'小红书-订单明细'!P:P,0)))))>15%,ROUNDUP(SUM(AH6,AJ6:AK6)/(INDEX('小红书-订单明细'!X:X,MATCH(R6&AD6,'小红书-订单明细'!A:A&'小红书-订单明细'!P:P,0))/(INDEX('小红书-订单明细'!U:U,MATCH(R6&AD6,'小红书-订单明细'!A:A&'小红书-订单明细'!P:P,0)))),0),ROUNDDOWN(SUM(AH6,AJ6:AK6)/(INDEX('小红书-订单明细'!X:X,MATCH(R6&AD6,'小红书-订单明细'!A:A&'小红书-订单明细'!P:P,0))/(INDEX('小红书-订单明细'!U:U,MATCH(R6&AD6,'小红书-订单明细'!A:A&'小红书-订单明细'!P:P,0)))),0))} -> -1 | I6: =AH6 -> -299 | J6: =AK6+AL6 -> 0 | K6: =IF(BB6<=0,BB6,BB6/COUNTIFS(R:R,R6,BB:BB,">0")) -> 0 | L6: =-AO6 -> -14.95 | M6: =-AV6 -> -1.79 | O6: =I6+J6+K6-L6-M6-N6 -> -282.26 | Q6: {=SUM(AH6,AJ6:AK6)/(INDEX('小红书-订单明细'!X:X,MATCH(R6&AD6,'小红书-订单明细'!A:A&'小红书-订单明细'!P:P,0))/(INDEX('小红书-订单明细'!U:U,MATCH(R6&AD6,'小红书-订单明细'!A:A&'小红书-订单明细'!P:P,0))))} -> -1 | R6: P776212592782130361 | S6: =_xlfn.XLOOKUP(R6,'小红书-订单明细'!A:A,'小红书-订单明细'!A:A) -> P776212592782130361 | T6: R8213036198852621 | U6: 2025-10-17 08:23:12 | V6: 2025-10-25 09:30:12 | W6: 2025-10-31 18:25:11 | X6: 退款 | Y6: 店铺余额 | Z6: -282.26 | AA6: 【老板周】慵懒松弛 秋冬 · 【老板周】慵懒松弛 秋冬新品连帽半拉链奶咖针织马甲 深灰色 M（80-100斤） | AB6: 女装/女士精品>马夹 | AC6: XHS-3PLL9MH2YQDC | AD6: 68e90d604290ae0015508d8e | AE6: =_xlfn.XLOOKUP(AD6,'小红书-订单明细'!P:P,'小红书-订单明细'!P:P) -> 68e90d604290ae0015508d8e | AG6: -299 | AH6: -299 | AJ6: 0 | AK6: 0 | AL6: 0 | AO6: 14.95 | AS6: 否 | AT6: 0 | AV6: 1.79 | AW6: 650d6e9f000000001603a6ac | AX6: 老板周. | AY6: 达人带货 | BB6: 0 | BC6: 0 | BD6: 0 | BE6: 0 | BF6: 0
A7: =YEAR(W7) -> 2025 | B7: =MONTH(W7) -> 10 | C7: =R7 -> P776212592782130361 | D7: =COUNTIF(R:R,R7) -> 2 | E7: =COUNTIF($R$2:R7,R7) -> 2 | F7: {=INDEX('小红书-订单明细'!BR:BR,MATCH(R7&AD7,'小红书-订单明细'!A:A&'小红书-订单明细'!P:P,0))} -> Z2561-深灰色-M | G7: =LEFT(F7,FIND("-",F7)-1) -> Z2561 | H7: {=IF(ABS(SUM(AH7,AJ7:AK7)/(INDEX('小红书-订单明细'!X:X,MATCH(R7&AD7,'小红书-订单明细'!A:A&'小红书-订单明细'!P:P,0))/(INDEX('小红书-订单明细'!U:U,MATCH(R7&AD7,'小红书-订单明细'!A:A&'小红书-订单明细'!P:P,0)))))>15%,ROUNDUP(SUM(AH7,AJ7:AK7)/(INDEX('小红书-订单明细'!X:X,MATCH(R7&AD7,'小红书-订单明细'!A:A&'小红书-订单明细'!P:P,0))/(INDEX('小红书-订单明细'!U:U,MATCH(R7&AD7,'小红书-订单明细'!A:A&'小红书-订单明细'!P:P,0)))),0),ROUNDDOWN(SUM(AH7,AJ7:AK7)/(INDEX('小红书-订单明细'!X:X,MATCH(R7&AD7,'小红书-订单明细'!A:A&'小红书-订单明细'!P:P,0))/(INDEX('小红书-订单明细'!U:U,MATCH(R7&AD7,'小红书-订单明细'!A:A&'小红书-订单明细'!P:P,0)))),0))} -> 1 | I7: =AH7 -> 299 | J7: =AK7+AL7 -> 0 | K7: =IF(BB7<=0,BB7,BB7/COUNTIFS(R:R,R7,BB:BB,">0")) -> 0 | L7: =-AO7 -> 14.95 | M7: =-AV7 -> 1.79 | O7: =I7+J7+K7-L7-M7-N7 -> 282.26 | Q7: {=SUM(AH7,AJ7:AK7)/(INDEX('小红书-订单明细'!X:X,MATCH(R7&AD7,'小红书-订单明细'!A:A&'小红书-订单明细'!P:P,0))/(INDEX('小红书-订单明细'!U:U,MATCH(R7&AD7,'小红书-订单明细'!A:A&'小红书-订单明细'!P:P,0))))} -> 1 | R7: P776212592782130361 | S7: =_xlfn.XLOOKUP(R7,'小红书-订单明细'!A:A,'小红书-订单明细'!A:A) -> P776212592782130361 | U7: 2025-10-17 08:23:12 | V7: 2025-10-27 17:49:59 | W7: 2025-10-31 18:25:11 | X7: 结算入账 | Y7: 店铺余额 | Z7: 282.26 | AA7: 【老板周】慵懒松弛 秋冬 · 【老板周】慵懒松弛 秋冬新品连帽半拉链奶咖针织马甲 深灰色 M（80-100斤） | AB7: 女装/女士精品>马夹 | AC7: XHS-3PLL9MH2YQDC | AD7: 68e90d604290ae0015508d8e | AE7: =_xlfn.XLOOKUP(AD7,'小红书-订单明细'!P:P,'小红书-订单明细'!P:P) -> 68e90d604290ae0015508d8e | AF7: 1 | AG7: 299 | AH7: 299 | AJ7: 0 | AK7: 0 | AL7: 0 | AM7: 0.0500 | AN7: 0.0000 | AO7: -14.95 | AP7: 299 | AQ7: 299 | AR7: 0.0000 | AS7: 否 | AT7: 0 | AU7: 0.006 | AV7: -1.79 | AW7: 650d6e9f000000001603a6ac | AX7: 老板周. | AY7: 达人带货 | BB7: 0 | BC7: 0 | BD7: 0 | BE7: 0 | BF7: 0
A8: =YEAR(W8) -> 2025 | B8: =MONTH(W8) -> 10 | C8: =R8 -> P776450506670185383 | D8: =COUNTIF(R:R,R8) -> 1 | E8: =COUNTIF($R$2:R8,R8) -> 1 | F8: {=INDEX('小红书-订单明细'!BR:BR,MATCH(R8&AD8,'小红书-订单明细'!A:A&'小红书-订单明细'!P:P,0))} -> Z1744-黑色-S | G8: =LEFT(F8,FIND("-",F8)-1) -> Z1744 | H8: {=IF(ABS(SUM(AH8,AJ8:AK8)/(INDEX('小红书-订单明细'!X:X,MATCH(R8&AD8,'小红书-订单明细'!A:A&'小红书-订单明细'!P:P,0))/(INDEX('小红书-订单明细'!U:U,MATCH(R8&AD8,'小红书-订单明细'!A:A&'小红书-订单明细'!P:P,0)))))>15%,ROUNDUP(SUM(AH8,AJ8:AK8)/(INDEX('小红书-订单明细'!X:X,MATCH(R8&AD8,'小红书-订单明细'!A:A&'小红书-订单明细'!P:P,0))/(INDEX('小红书-订单明细'!U:U,MATCH(R8&AD8,'小红书-订单明细'!A:A&'小红书-订单明细'!P:P,0)))),0),ROUNDDOWN(SUM(AH8,AJ8:AK8)/(INDEX('小红书-订单明细'!X:X,MATCH(R8&AD8,'小红书-订单明细'!A:A&'小红书-订单明细'!P:P,0))/(INDEX('小红书-订单明细'!U:U,MATCH(R8&AD8,'小红书-订单明细'!A:A&'小红书-订单明细'!P:P,0)))),0))} -> 1 | I8: =AH8 -> 254.47 | J8: =AK8+AL8 -> 34.53 | K8: =IF(BB8<=0,BB8,BB8/COUNTIFS(R:R,R8,BB:BB,">0")) -> 0 | L8: =-AO8 -> 14.45 | M8: =-AV8 -> 0 | O8: =I8+J8+K8-L8-M8-N8 -> 274.55 | Q8: {=SUM(AH8,AJ8:AK8)/(INDEX('小红书-订单明细'!X:X,MATCH(R8&AD8,'小红书-订单明细'!A:A&'小红书-订单明细'!P:P,0))/(INDEX('小红书-订单明细'!U:U,MATCH(R8&AD8,'小红书-订单明细'!A:A&'小红书-订单明细'!P:P,0))))} -> 1 | R8: P776450506670185383 | S8: =_xlfn.XLOOKUP(R8,'小红书-订单明细'!A:A,'小红书-订单明细'!A:A) -> P776450506670185383 | U8: 2025-10-20 02:28:26 | V8: 2025-10-27 16:00:36 | W8: 2025-10-31 17:59:32 | X8: 结算入账 | Y8: 店铺余额 | Z8: 274.55 | AA8: 【老板周】小众休闲 春季 · 【老板周】小众休闲 春季单口袋翻领设计感廓形百搭衬衫 黑色 S（80-100斤） | AB8: 女装/女士精品>衬衫 | AC8: XHS-33LDRKIY2HOG | AD8: 689d98fa3b9d470015b74584 | AE8: =_xlfn.XLOOKUP(AD8,'小红书-订单明细'!P:P,'小红书-订单明细'!P:P) -> 689d98fa3b9d470015b74584 | AF8: 1 | AG8: 289 | AH8: 254.47 | AI8: 1年1度狂欢礼券,参与计税; | AJ8: 0 | AK8: 34.53 | AL8: 0 | AM8: 0.0500 | AN8: 0.0000 | AO8: -14.45 | AP8: 289 | AQ8: 289 | AR8: 0.0000 | AS8: 否 | AT8: 0 | AU8: 0 | AV8: 0 | BB8: 0 | BC8: 0 | BD8: 0 | BE8: 0 | BF8: 0
A9: =YEAR(W9) -> 2025 | B9: =MONTH(W9) -> 10 | C9: =R9 -> P776035102571191292 | D9: =COUNTIF(R:R,R9) -> 1 | E9: =COUNTIF($R$2:R9,R9) -> 1 | F9: {=INDEX('小红书-订单明细'!BR:BR,MATCH(R9&AD9,'小红书-订单明细'!A:A&'小红书-订单明细'!P:P,0))} -> Z1436-咖色-M | G9: =LEFT(F9,FIND("-",F9)-1) -> Z1436 | H9: {=IF(ABS(SUM(AH9,AJ9:AK9)/(INDEX('小红书-订单明细'!X:X,MATCH(R9&AD9,'小红书-订单明细'!A:A&'小红书-订单明细'!P:P,0))/(INDEX('小红书-订单明细'!U:U,MATCH(R9&AD9,'小红书-订单明细'!A:A&'小红书-订单明细'!P:P,0)))))>15%,ROUNDUP(SUM(AH9,AJ9:AK9)/(INDEX('小红书-订单明细'!X:X,MATCH(R9&AD9,'小红书-订单明细'!A:A&'小红书-订单明细'!P:P,0))/(INDEX('小红书-订单明细'!U:U,MATCH(R9&AD9,'小红书-订单明细'!A:A&'小红书-订单明细'!P:P,0)))),0),ROUNDDOWN(SUM(AH9,AJ9:AK9)/(INDEX('小红书-订单明细'!X:X,MATCH(R9&AD9,'小红书-订单明细'!A:A&'小红书-订单明细'!P:P,0))/(INDEX('小红书-订单明细'!U:U,MATCH(R9&AD9,'小红书-订单明细'!A:A&'小红书-订单明细'!P:P,0)))),0))} -> 1 | I9: =AH9 -> 288.16 | J9: =AK9+AL9 -> 50.84 | K9: =IF(BB9<=0,BB9,BB9/COUNTIFS(R:R,R9,BB:BB,">0")) -> 0 | L9: =-AO9 -> 16.95 | M9: =-AV9 -> 0 | O9: =I9+J9+K9-L9-M9-N9 -> 322.05 | Q9: {=SUM(AH9,AJ9:AK9)/(INDEX('小红书-订单明细'!X:X,MATCH(R9&AD9,'小红书-订单明细'!A:A&'小红书-订单明细'!P:P,0))/(INDEX('小红书-订单明细'!U:U,MATCH(R9&AD9,'小红书-订单明细'!A:A&'小红书-订单明细'!P:P,0))))} -> 1 | R9: P776035102571191292 | S9: =_xlfn.XLOOKUP(R9,'小红书-订单明细'!A:A,'小红书-订单明细'!A:A) -> P776035102571191292 | U9: 2025-10-15 07:05:02 | V9: 2025-10-27 15:55:30 | W9: 2025-10-31 17:50:14 | X9: 结算入账 | Y9: 店铺余额 | Z9: 322.05 | AA9: 【老板周】极简主义 秋冬 · 【老板周】极简主义 秋冬立体裁剪弧形设计感休闲私服裤 咖色 M（95-110斤） | AB9: 女装/女士精品>裤子>休闲裤 | AC9: XHS-3N0YAR11BAPS | AD9: 68c6d0daf9d8290001dcb02d | AE9: =_xlfn.XLOOKUP(AD9,'小红书-订单明细'!P:P,'小红书-订单明细'!P:P) -> 68c6d0daf9d8290001dcb02d | AF9: 1 | AG9: 339 | AH9: 288.16 | AI9: 1年1度狂欢礼券,参与计税; | AJ9: 0 | AK9: 50.84 | AL9: 0 | AM9: 0.0500 | AN9: 0.0000 | AO9: -16.95 | AP9: 339 | AQ9: 339 | AR9: 0.0000 | AS9: 否 | AT9: 0 | AU9: 0 | AV9: 0 | BB9: 0 | BC9: 0 | BD9: 0 | BE9: 0 | BF9: 0
A10: =YEAR(W10) -> 2025 | B10: =MONTH(W10) -> 10 | C10: =R10 -> P775954589917164071 | D10: =COUNTIF(R:R,R10) -> 2 | E10: =COUNTIF($R$2:R10,R10) -> 1 | F10: {=INDEX('小红书-订单明细'!BR:BR,MATCH(R10&AD10,'小红书-订单明细'!A:A&'小红书-订单明细'!P:P,0))} -> Z1326-奶茶色-M | G10: =LEFT(F10,FIND("-",F10)-1) -> Z1326 | H10: {=IF(ABS(SUM(AH10,AJ10:AK10)/(INDEX('小红书-订单明细'!X:X,MATCH(R10&AD10,'小红书-订单明细'!A:A&'小红书-订单明细'!P:P,0))/(INDEX('小红书-订单明细'!U:U,MATCH(R10&AD10,'小红书-订单明细'!A:A&'小红书-订单明细'!P:P,0)))))>15%,ROUNDUP(SUM(AH10,AJ10:AK10)/(INDEX('小红书-订单明细'!X:X,MATCH(R10&AD10,'小红书-订单明细'!A:A&'小红书-订单明细'!P:P,0))/(INDEX('小红书-订单明细'!U:U,MATCH(R10&AD10,'小红书-订单明细'!A:A&'小红书-订单明细'!P:P,0)))),0),ROUNDDOWN(SUM(AH10,AJ10:AK10)/(INDEX('小红书-订单明细'!X:X,MATCH(R10&AD10,'小红书-订单明细'!A:A&'小红书-订单明细'!P:P,0))/(INDEX('小红书-订单明细'!U:U,MATCH(R10&AD10,'小红书-订单明细'!A:A&'小红书-订单明细'!P:P,0)))),0))} -> -1 | I10: =AH10 -> -139 | J10: =AK10+AL10 -> 0 | K10: =IF(BB10<=0,BB10,BB10/COUNTIFS(R:R,R10,BB:BB,">0")) -> 0 | L10: =-AO10 -> -6.95 | M10: =-AV10 -> -0.83 | O10: =I10+J10+K10-L10-M10-N10 -> -131.22 | Q10: {=SUM(AH10,AJ10:AK10)/(INDEX('小红书-订单明细'!X:X,MATCH(R10&AD10,'小红书-订单明细'!A:A&'小红书-订单明细'!P:P,0))/(INDEX('小红书-订单明细'!U:U,MATCH(R10&AD10,'小红书-订单明细'!A:A&'小红书-订单明细'!P:P,0))))} -> -1 | R10: P775954589917164071 | S10: =_xlfn.XLOOKUP(R10,'小红书-订单明细'!A:A,'小红书-订单明细'!A:A) -> P775954589917164071 | T10: R1716407110088374 | U10: 2025-10-14 08:43:09 | V10: 2025-10-24 10:57:10 | W10: 2025-10-31 17:24:05 | X10: 退款 | Y10: 店铺余额 | Z10: -131.22 | AA10: 【老板周】气质优雅 秋冬 · 【老板周】气质优雅 秋冬亲肤有型百搭奶茶圆领针织上衣 奶茶色 M（100-120斤） | AB10: 女装/女士精品>毛针织衫 | AC10: XHS-3NM6LSUL0W75 | AD10: 68cea8f7f6cbe500156c0153 | AE10: =_xlfn.XLOOKUP(AD10,'小红书-订单明细'!P:P,'小红书-订单明细'!P:P) -> 68cea8f7f6cbe500156c0153 | AG10: -139 | AH10: -139 | AJ10: 0 | AK10: 0 | AL10: 0 | AO10: 6.95 | AS10: 否 | AT10: 0 | AV10: 0.83 | AW10: 650d6e9f000000001603a6ac | AX10: 老板周. | AY10: 达人带货 | BB10: 0 | BC10: 0 | BD10: 0 | BE10: 0 | BF10: 0
A11: =YEAR(W11) -> 2025 | B11: =MONTH(W11) -> 10 | C11: =R11 -> P775954589917164071 | D11: =COUNTIF(R:R,R11) -> 2 | E11: =COUNTIF($R$2:R11,R11) -> 2 | F11: {=INDEX('小红书-订单明细'!BR:BR,MATCH(R11&AD11,'小红书-订单明细'!A:A&'小红书-订单明细'!P:P,0))} -> Z1326-奶茶色-M | G11: =LEFT(F11,FIND("-",F11)-1) -> Z1326 | H11: {=IF(ABS(SUM(AH11,AJ11:AK11)/(INDEX('小红书-订单明细'!X:X,MATCH(R11&AD11,'小红书-订单明细'!A:A&'小红书-订单明细'!P:P,0))/(INDEX('小红书-订单明细'!U:U,MATCH(R11&AD11,'小红书-订单明细'!A:A&'小红书-订单明细'!P:P,0)))))>15%,ROUNDUP(SUM(AH11,AJ11:AK11)/(INDEX('小红书-订单明细'!X:X,MATCH(R11&AD11,'小红书-订单明细'!A:A&'小红书-订单明细'!P:P,0))/(INDEX('小红书-订单明细'!U:U,MATCH(R11&AD11,'小红书-订单明细'!A:A&'小红书-订单明细'!P:P,0)))),0),ROUNDDOWN(SUM(AH11,AJ11:AK11)/(INDEX('小红书-订单明细'!X:X,MATCH(R11&AD11,'小红书-订单明细'!A:A&'小红书-订单明细'!P:P,0))/(INDEX('小红书-订单明细'!U:U,MATCH(R11&AD11,'小红书-订单明细'!A:A&'小红书-订单明细'!P:P,0)))),0))} -> 1 | I11: =AH11 -> 139 | J11: =AK11+AL11 -> 0 | K11: =IF(BB11<=0,BB11,BB11/COUNTIFS(R:R,R11,BB:BB,">0")) -> 0 | L11: =-AO11 -> 6.95 | M11: =-AV11 -> 0.83 | O11: =I11+J11+K11-L11-M11-N11 -> 131.22 | Q11: {=SUM(AH11,AJ11:AK11)/(INDEX('小红书-订单明细'!X:X,MATCH(R11&AD11,'小红书-订单明细'!A:A&'小红书-订单明细'!P:P,0))/(INDEX('小红书-订单明细'!U:U,MATCH(R11&AD11,'小红书-订单明细'!A:A&'小红书-订单明细'!P:P,0))))} -> 1 | R11: P775954589917164071 | S11: =_xlfn.XLOOKUP(R11,'小红书-订单明细'!A:A,'小红书-订单明细'!A:A) -> P775954589917164071 | U11: 2025-10-14 08:43:09 | V11: 2025-10-27 16:41:15 | W11: 2025-10-31 17:24:05 | X11: 结算入账 | Y11: 店铺余额 | Z11: 131.22 | AA11: 【老板周】气质优雅 秋冬 · 【老板周】气质优雅 秋冬亲肤有型百搭奶茶圆领针织上衣 奶茶色 M（100-120斤） | AB11: 女装/女士精品>毛针织衫 | AC11: XHS-3NM6LSUL0W75 | AD11: 68cea8f7f6cbe500156c0153 | AE11: =_xlfn.XLOOKUP(AD11,'小红书-订单明细'!P:P,'小红书-订单明细'!P:P) -> 68cea8f7f6cbe500156c0153 | AF11: 1 | AG11: 139 | AH11: 139 | AJ11: 0 | AK11: 0 | AL11: 0 | AM11: 0.0500 | AN11: 0.0000 | AO11: -6.95 | AP11: 139 | AQ11: 139 | AR11: 0.0000 | AS11: 否 | AT11: 0 | AU11: 0.006 | AV11: -0.83 | AW11: 650d6e9f000000001603a6ac | AX11: 老板周. | AY11: 达人带货 | BB11: 0 | BC11: 0 | BD11: 0 | BE11: 0 | BF11: 0
