Workbook

Sheet 抖音订单-按支付日期-原表
A1: 主订单编号 | B1: 子订单编号 | C1: 选购商品 | D1: 商品规格 | E1: 商品数量 | F1: 商品ID | G1: 商家编码 | H1: 商品单价 | I1: 订单应付金额 | J1: 运费 | K1: 优惠总金额 | L1: 平台优惠 | M1: 商家优惠 | N1: 达人优惠 | O1: 商家改价 | P1: 支付优惠 | Q1: 红包抵扣 | R1: 支付方式 | S1: 手续费 | T1: 收件人 | U1: 收件人手机号 | V1: 省 | W1: 市 | X1: 区 | Y1: 街道 | Z1: 详细地址 | AA1: 是否修改过地址 | AB1: 买家留言 | AC1: 订单提交时间 | AD1: 旗帜颜色 | AE1: 商家备注 | AF1: 订单完成时间 | AG1: 支付完成时间 | AH1: APP渠道 | AI1: 流量来源 | AJ1: 订单状态 | AK1: 承诺发货时间 | AL1: 订单类型 | AM1: 鲁班落地页ID | AN1: 达人ID | AO1: 达人昵称 | AP1: 所属门店ID | AQ1: 售后状态 | AR1: 取消原因 | AS1: 预约发货时间 | AT1: 仓库ID | AU1: 仓库名称 | AV1: 序列号 | AW1: 是否安心购 | AX1: 广告渠道 | AY1: 流量类型 | AZ1: 流量体裁 | BA1: 流量渠道 | BB1: 发货主体 | BC1: 发货主体明细 | BD1: 发货时间 | BE1: 降价类优惠 | BF1: 平台实际承担优惠金额 | BG1: 商家实际承担优惠金额 | BH1: 达人实际承担优惠金额 | BI1: 预计送达时间 | BJ1: 是否平台仓自流转 | BK1: 车型 | BL1: 商品69码 | BM1: 发货SN码 | BN1: 发货IMEI码1 | BO1: 发货IMEI码2 | BP1: 预约送达时间 | BQ1: 建议发货时间（起） | BR1: 建议发货时间（止） | BS1: 物流SN码 | BT1: 物流IMEI码1 | BU1: 物流IMEI码2
A2: 6921014879971867995 | B2: 6921014879971867995 | C2: 【老板周】复古风格 秋冬新款立体麻花织纹针织毛衣 | D2: 灰色;L(120-135斤);15天内发货 | E2: 1 | F2: 3772185880568135686 | G2: Z2418-灰色-L | H2: 329 | I2: 329 | J2: 0 | K2: 0 | L2: - | M2: - | N2: - | O2: 0 | P2: 0 | Q2: 0 | R2: 抖音月付 | S2: 0 | T2: *** | U2: *** | V2: 安徽省 | W2: 宿州市 | X2: 埇桥区 | Y2: 西关街道 | Z2: *** | AA2: 否 | AC2: 2025-08-31 22:51:27 | AD2: 灰色 | AE2: (收)[Z2418-灰色-L]*[1]# | AF2: 2025-09-22 10:48:28 | AG2: 2025-08-31 22:51:31 | AH2: 抖音 | AI2: 精选联盟 | AJ2: 已完成 | AK2: 2025-09-15 22:51:31 | AL2: 普通订单 | AM2: 0 | AN2: 2353393836764088 | AO2: 老板周 | AP2: - | AQ2: 退款成功 | AS2: - | AT2: - | AU2: - | AW2: 否 | AX2: 无 | AY2: 其他 | AZ2: 直播 | BA2: 商城推荐 | BB2: - | BC2: - | BD2: 2025-09-15 10:48:28 | BE2: 0 | BF2: 0 | BG2: 0 | BH2: 0 | BJ2: 否 | BP2: - | BQ2: - | BR2: -
A3: 6945703385201317436 | B3: 6945703385201317436 | C3: 【老板周】日系极简 春季新品圆领简约设计感无袖马甲 | D3: 黑色;M(100-120斤);15天内发货 | E3: 1 | F3: 3767004410471907465 | G3: Z1640-黑色-M | H3: 289 | I3: 289 | J3: 0 | K3: 0 | L3: - | M3: - | N3: - | O3: 0 | P3: 0 | Q3: 0 | R3: 支付宝 | S3: 0 | T3: *** | U3: *** | V3: 广东省 | W3: 深圳市 | X3: 龙华区 | Y3: 龙华街道 | Z3: *** | AA3: 否 | AC3: 2025-08-31 22:28:56 | AD3: 灰色 | AF3: 2025-09-18 23:58:12 | AG3: 2025-08-31 22:29:01 | AH3: 抖音 | AI3: 精选联盟 | AJ3: 已完成 | AK3: 2025-09-15 22:29:02 | AL3: 普通订单 | AM3: 0 | AN3: 2353393836764088 | AO3: 老板周 | AP3: - | AQ3: - | AS3: - | AT3: - | AU3: - | AW3: 否 | AX3: 无 | AY3: 其他 | AZ3: 直播 | BA3: 关注来源 | BB3: - | BC3: - | BD3: 2025-09-11 23:58:12 | BE3: 0 | BF3: 0 | BG3: 0 | BH3: 0 | BJ3: 否 | BP3: - | BQ3: - | BR3: -
A4: 6945727588250948678 | B4: 6945727588250948678 | C4: 【老板周】日系极简 春季新品圆领简约设计感无袖马甲 | D4: 黑色;L(120-135斤);15天内发货 | E4: 1 | F4: 3767004410471907465 | G4: Z1640-黑色-L | H4: 289 | I4: 289 | J4: 0 | K4: 0 | L4: - | M4: - | N4: - | O4: 0 | P4: 0 | Q4: 0 | R4: 抖音支付 | S4: 0 | T4: *** | U4: *** | V4: 山东省 | W4: 德州市 | X4: 德城区 | Y4: - | Z4: *** | AA4: 否 | AC4: 2025-08-31 22:26:00 | AD4: 灰色 | AG4: 2025-08-31 22:26:05 | AH4: 抖音 | AI4: 精选联盟 | AJ4: 已关闭 | AK4: 2025-09-15 22:26:05 | AL4: 普通订单 | AM4: 0 | AN4: 2353393836764088 | AO4: 老板周 | AP4: - | AQ4: 退款成功 | AS4: - | AT4: - | AU4: - | AW4: 否 | AX4: 无 | AY4: 其他 | AZ4: 直播 | BA4: 直播推荐 | BB4: - | BC4: - | BE4: 0 | BF4: 0 | BG4: 0 | BH4: 0 | BJ4: 否 | BP4: - | BQ4: - | BR4: -
A5: 6945714505452361238 | B5: 6945714505452361238 | C5: 【老板周】日系极简 春季新品圆领简约设计感无袖马甲 | D5: 黑色;S(80-100斤);15天内发货 | E5: 1 | F5: 3767004410471907465 | G5: Z1640-黑色-S | H5: 289 | I5: 286 | J5: 0 | K5: 4 | L5: 平台晚发即赔券-3.00 | M5: - | N5: - | O5: 0 | P5: 1 | Q5: 0 | R5: 抖音支付 | S5: 0 | T5: *** | U5: *** | V5: 河南省 | W5: 平顶山市 | X5: 湛河区 | Y5: 九里山街道 | Z5: *** | AA5: 否 | AC5: 2025-08-31 22:01:43 | AD5: 灰色 | AG5: 2025-08-31 22:01:46 | AH5: 抖音 | AI5: 精选联盟 | AJ5: 已关闭 | AK5: 2025-09-15 22:01:47 | AL5: 普通订单 | AM5: 0 | AN5: 2353393836764088 | AO5: 老板周 | AP5: - | AQ5: 退款成功 | AS5: - | AT5: - | AU5: - | AW5: 否 | AX5: 无 | AY5: 其他 | AZ5: 商品卡 | BA5: 橱窗 | BB5: - | BC5: - | BE5: 0 | BF5: 3 | BG5: 0 | BH5: 0 | BJ5: 否 | BP5: - | BQ5: - | BR5: -
A6: 6945700999501124814 | B6: 6945700999501124814 | C6: 【老板周】极简设计 秋冬毛绒感圆领套头舒适针织毛衣 | D6: 红色;M(100-135斤);15天内发货 | E6: 1 | F6: 3772189127454359773 | G6: Z2425-红色-M | H6: 289 | I6: 289 | J6: 0 | K6: 0 | L6: - | M6: - | N6: - | O6: 0 | P6: 0 | Q6: 0 | R6: 抖音支付 | S6: 0 | T6: *** | U6: *** | V6: 湖南省 | W6: 常德市 | X6: 武陵区 | Y6: 穿紫河街道 | Z6: *** | AA6: 否 | AC6: 2025-08-31 20:25:26 | AD6: 灰色 | AG6: 2025-08-31 20:25:28 | AH6: 抖音 | AI6: 精选联盟 | AJ6: 已关闭 | AK6: 2025-09-15 20:25:28 | AL6: 普通订单 | AM6: 0 | AN6: 2353393836764088 | AO6: 老板周 | AP6: - | AQ6: 退款成功 | AS6: - | AT6: - | AU6: - | AW6: 否 | AX6: 直播 | AY6: 广告 | AZ6: 直播 | BA6: 商城推荐 | BB6: - | BC6: - | BE6: 0 | BF6: 0 | BG6: 0 | BH6: 0 | BJ6: 否 | BP6: - | BQ6: - | BR6: -
A7: 6921014170429783498 | B7: 6921014170429783498 | C7: 【老板周】日系极简 春季新品圆领简约设计感无袖马甲 | D7: 黑色;M(100-120斤);15天内发货 | E7: 1 | F7: 3767004410471907465 | G7: Z1640-黑色-M | H7: 289 | I7: 289 | J7: 0 | K7: 0 | L7: - | M7: - | N7: - | O7: 0 | P7: 0 | Q7: 0 | R7: 支付宝 | S7: 0 | T7: *** | U7: *** | V7: 上海市 | W7: 上海市 | X7: 浦东新区 | Y7: - | Z7: *** | AA7: 否 | AC7: 2025-08-31 19:29:31 | AD7: 灰色 | AF7: 2025-09-18 23:58:12 | AG7: 2025-08-31 19:29:36 | AH7: 抖音 | AI7: 精选联盟 | AJ7: 已完成 | AK7: 2025-09-15 19:29:36 | AL7: 普通订单 | AM7: 0 | AN7: 2353393836764088 | AO7: 老板周 | AP7: - | AQ7: - | AS7: - | AT7: - | AU7: - | AW7: 否 | AX7: 无 | AY7: 其他 | AZ7: 直播 | BA7: 直播推荐 | BB7: - | BC7: - | BD7: 2025-09-11 23:58:12 | BE7: 0 | BF7: 0 | BG7: 0 | BH7: 0 | BJ7: 否 | BP7: - | BQ7: - | BR7: -
A8: 6945712098356630732 | B8: 6945712098356630732 | C8: 【老板周】日系极简 春季新品圆领简约设计感无袖马甲 | D8: 黑色;M(100-120斤);15天内发货 | E8: 1 | F8: 3767004410471907465 | G8: Z1640-黑色-M | H8: 289 | I8: 289 | J8: 0 | K8: 0 | L8: - | M8: - | N8: - | O8: 0 | P8: 0 | Q8: 0 | R8: 抖音月付 | S8: 0 | T8: *** | U8: *** | V8: 山西省 | W8: 太原市 | X8: 晋源区 | Y8: 义井街道 | Z8: *** | AA8: 否 | AC8: 2025-08-31 19:13:06 | AD8: 灰色 | AF8: 2025-09-18 23:58:12 | AG8: 2025-08-31 19:13:08 | AH8: 抖音 | AI8: 精选联盟 | AJ8: 已完成 | AK8: 2025-09-15 19:13:08 | AL8: 普通订单 | AM8: 0 | AN8: 2353393836764088 | AO8: 老板周 | AP8: - | AQ8: 退款成功 | AS8: - | AT8: - | AU8: - | AW8: 否 | AX8: 无 | AY8: 其他 | AZ8: 直播 | BA8: 直播推荐 | BB8: - | BC8: - | BD8: 2025-09-11 23:58:12 | BE8: 0 | BF8: 0 | BG8: 0 | BH8: 0 | BJ8: 否 | BP8: - | BQ8: - | BR8: -
A9: 6921016389061410674 | B9: 6921016389061410674 | C9: 【老板周】极简设计 秋冬毛绒感圆领套头舒适针织毛衣 | D9: 红色;S(80-100斤);15天内发货 | E9: 1 | F9: 3772189127454359773 | G9: Z2425-红色-S | H9: 289 | I9: 284 | J9: 0 | K9: 5 | L9: 平台晚发即赔券-5.00 | M9: - | N9: - | O9: 0 | P9: 0 | Q9: 0 | R9: 抖音月付 | S9: 0 | T9: *** | U9: *** | V9: 重庆市 | W9: 重庆市 | X9: 九龙坡区 | Y9: 中梁山街道 | Z9: *** | AA9: 否 | AC9: 2025-08-31 18:07:41 | AD9: 灰色 | AG9: 2025-08-31 18:07:42 | AH9: 头条lite-抖音电商 | AI9: 精选联盟 | AJ9: 已关闭 | AK9: 2025-09-15 18:07:43 | AL9: 普通订单 | AM9: 0 | AN9: 2353393836764088 | AO9: 老板周 | AP9: - | AQ9: 退款成功 | AS9: - | AT9: - | AU9: - | AW9: 否 | AX9: 直播 | AY9: 广告 | AZ9: 直播 | BA9: 头条西瓜 | BB9: - | BC9: - | BE9: 0 | BF9: 5 | BG9: 0 | BH9: 0 | BJ9: 否 | BP9: - | BQ9: - | BR9: -
A10: 6945711936320509468 | B10: 6945711936320509468 | C10: 【老板周】极简设计 秋冬毛绒感圆领套头舒适针织毛衣 | D10: 蓝色;S(80-100斤);15天内发货 | E10: 1 | F10: 3772189127454359773 | G10: Z2425-蓝色-S | H10: 289 | I10: 289 | J10: 0 | K10: 0 | L10: - | M10: - | N10: - | O10: 0 | P10: 0 | Q10: 0 | R10: 抖音支付 | S10: 0 | T10: *** | U10: *** | V10: 贵州省 | W10: 贵阳市 | X10: 乌当区 | Y10: 新创路街道 | Z10: *** | AA10: 否 | AC10: 2025-08-31 18:05:55 | AD10: 灰色 | AH10: 抖音 | AI10: 精选联盟 | AJ10: 已关闭 | AK10: 2025-09-15 18:05:55 | AL10: 普通订单 | AM10: 0 | AN10: 2353393836764088 | AO10: 老板周 | AP10: - | AQ10: - | AR10: 你已取消订单：暂时不需要这个商品 | AS10: - | AT10: - | AU10: - | AW10: 否 | AX10: 无 | AY10: 其他 | AZ10: 直播 | BA10: 直播推荐 | BB10: - | BC10: - | BE10: 0 | BF10: 0 | BG10: 0 | BH10: 0 | BJ10: 否 | BP10: - | BQ10: - | BR10: -
A11: 6921016313814548201 | B11: 6921016313814548201 | C11: 【老板周】极简设计 秋冬毛绒感圆领套头舒适针织毛衣 | D11: 红色;M(100-135斤);15天内发货 | E11: 1 | F11: 3772189127454359773 | G11: Z2425-红色-M | H11: 289 | I11: 267 | J11: 0 | K11: 22 | L11: 平台全额返现满减券-22.00 | M11: - | N11: - | O11: 0 | P11: 0 | Q11: 0 | R11: 抖音月付 | S11: 0 | T11: *** | U11: *** | V11: 广东省 | W11: 阳江市 | X11: 江城区 | Y11: 城北街道 | Z11: *** | AA11: 否 | AC11: 2025-08-31 18:05:31 | AD11: 蓝色 | AE11: YT2532916536267(收） Z2425-红色-M*1# | AG11: 2025-08-31 18:05:36 | AH11: 抖音 | AI11: 精选联盟 | AJ11: 已关闭 | AK11: 2025-09-15 18:05:36 | AL11: 普通订单 | AM11: 0 | AN11: 2353393836764088 | AO11: 老板周 | AP11: - | AQ11: 退款成功 | AS11: - | AT11: - | AU11: - | AW11: 否 | AX11: 无 | AY11: 其他 | AZ11: 直播 | BA11: 商城推荐 | BB11: - | BC11: - | BD11: 2025-09-09 23:55:16 | BE11: 0 | BF11: 22 | BG11: 0 | BH11: 0 | BJ11: 否 | BP11: - | BQ11: - | BR11: -
A12: 6945707477692061056 | B12: 6945707477692061056 | C12: 【老板周】简约松弛 秋冬纯色弧形下摆宽松百搭上衣 | D12: 白色;S(80-100斤);15天内发货 | E12: 1 | F12: 3771440658552848740 | G12: Z2311-白色-S | H12: 229 | I12: 229 | J12: 0 | K12: 0 | L12: - | M12: - | N12: - | O12: 0 | P12: 0 | Q12: 0 | R12: 抖音支付 | S12: 0 | T12: *** | U12: *** | V12: 湖南省 | W12: 常德市 | X12: 武陵区 | Y12: 府坪街道 | Z12: *** | AA12: 否 | AC12: 2025-08-31 18:01:07 | AD12: 蓝色 | AE12: 73571847180415(收） Z2311-白色-S*1# | AG12: 2025-08-31 18:01:08 | AH12: 抖音 | AI12: 小店自卖 | AJ12: 已关闭 | AK12: 2025-09-15 18:01:09 | AL12: 普通订单 | AM12: 0 | AN12: 0 | AP12: - | AQ12: 退款成功 | AS12: - | AT12: - | AU12: - | AW12: 否 | AX12: 无 | AY12: 其他 | AZ12: 商品卡 | BA12: 搜索 | BB12: - | BC12: - | BD12: 2025-09-07 16:39:45 | BE12: 0 | BF12: 0 | BG12: 0 | BH12: 0 | BJ12: 否 | BP12: - | BQ12: - | BR12: -
A13: 6945694166426850837 | B13: 6945694166426850837 | C13: 【老板周】复古风格 秋冬新款立体麻花织纹针织毛衣 | D13: 灰色;L(120-135斤);15天内发货 | E13: 1 | F13: 3772185880568135686 | G13: Z2418-灰色-L | H13: 329 | I13: 329 | J13: 0 | K13: 0 | L13: - | M13: - | N13: - | O13: 0 | P13: 0 | Q13: 0 | R13: 支付宝 | S13: 0 | T13: *** | U13: *** | V13: 辽宁省 | W13: 本溪市 | X13: 明山区 | Y13: 北地街道 | Z13: *** | AA13: 否 | AC13: 2025-08-31 17:51:10 | AD13: 灰色 | AG13: 2025-08-31 17:51:20 | AH13: 抖音极速版 | AI13: 精选联盟 | AJ13: 已关闭 | AK13: 2025-09-15 17:51:20 | AL13: 普通订单 | AM13: 0 | AN13: 2353393836764088 | AO13: 老板周 | AP13: - | AQ13: 退款成功 | AS13: - | AT13: - | AU13: - | AW13: 否 | AX13: 无 | AY13: 其他 | AZ13: 直播 | BA13: 商城推荐 | BB13: - | BC13: - | BE13: 0 | BF13: 0 | BG13: 0 | BH13: 0 | BJ13: 否 | BP13: - | BQ13: - | BR13: -
A14: 6945716113981314698 | B14: 6945716113981314698 | C14: 【老板周】复古风格 秋冬新款立体麻花织纹针织毛衣 | D14: 灰色;S(80-100斤);15天内发货 | E14: 1 | F14: 3772185880568135686 | G14: Z2418-灰色-S | H14: 329 | I14: 329 | J14: 0 | K14: 0 | L14: - | M14: - | N14: - | O14: 0 | P14: 0 | Q14: 0 | R14: 抖音月付 | S14: 0 | T14: *** | U14: *** | V14: 山西省 | W14: 吕梁市 | X14: 交城县 | Y14: 天宁镇 | Z14: *** | AA14: 否 | AC14: 2025-08-31 17:50:43 | AD14: 灰色 | AG14: 2025-08-31 17:50:44 | AH14: 抖音 | AI14: 精选联盟 | AJ14: 已关闭 | AK14: 2025-09-15 17:50:44 | AL14: 普通订单 | AM14: 0 | AN14: 2353393836764088 | AO14: 老板周 | AP14: - | AQ14: 退款成功 | AS14: - | AT14: - | AU14: - | AW14: 否 | AX14: 无 | AY14: 其他 | AZ14: 直播 | BA14: 直播推荐 | BB14: - | BC14: - | BE14: 0 | BF14: 0 | BG14: 0 | BH14: 0 | BJ14: 否 | BP14: - | BQ14: - | BR14: -
A15: 6921011676079357340 | B15: 6921011676079357340 | C15: 【老板周】复古风格 秋冬新款立体麻花织纹针织毛衣 | D15: 灰色;S(80-100斤);15天内发货 | E15: 1 | F15: 3772185880568135686 | G15: Z2418-灰色-S | H15: 329 | I15: 329 | J15: 0 | K15: 0 | L15: - | M15: - | N15: - | O15: 0 | P15: 0 | Q15: 0 | R15: 抖音月付 | S15: 0 | T15: *** | U15: *** | V15: 河北省 | W15: 沧州市 | X15: 黄骅市 | Y15: - | Z15: *** | AA15: 否 | AC15: 2025-08-31 17:46:12 | AD15: 灰色 | AG15: 2025-08-31 17:46:16 | AH15: 抖音 | AI15: 精选联盟 | AJ15: 已关闭 | AK15: 2025-09-15 17:46:16 | AL15: 普通订单 | AM15: 0 | AN15: 2353393836764088 | AO15: 老板周 | AP15: - | AQ15: 退款成功 | AS15: - | AT15: - | AU15: - | AW15: 否 | AX15: 无 | AY15: 其他 | AZ15: 直播 | BA15: 个人主页&店铺&橱窗进入直播间 | BB15: - | BC15: - | BE15: 0 | BF15: 0 | BG15: 0 | BH15: 0 | BJ15: 否 | BP15: - | BQ15: - | BR15: -
A16: 6945711886863766847 | B16: 6945711886863766847 | C16: 【老板周】复古风格 秋冬新款立体麻花织纹针织毛衣 | D16: 灰色;M(100-120斤);15天内发货 | E16: 1 | F16: 3772185880568135686 | G16: Z2418-灰色-M | H16: 329 | I16: 329 | J16: 0 | K16: 0 | L16: - | M16: - | N16: - | O16: 0 | P16: 0 | Q16: 0 | R16: 支付宝 | S16: 0 | T16: *** | U16: *** | V16: 湖南省 | W16: 张家界市 | X16: 永定区 | Y16: 崇文街道 | Z16: *** | AA16: 否 | AC16: 2025-08-31 17:39:51 | AD16: 灰色 | AG16: 2025-08-31 17:39:57 | AH16: 红果短剧-抖音电商 | AI16: 精选联盟 | AJ16: 已关闭 | AK16: 2025-09-15 17:39:58 | AL16: 普通订单 | AM16: 0 | AN16: 2353393836764088 | AO16: 老板周 | AP16: - | AQ16: 退款成功 | AS16: - | AT16: - | AU16: - | AW16: 否 | AX16: 直播 | AY16: 广告 | AZ16: 直播 | BA16: 其他 | BB16: - | BC16: - | BE16: 0 | BF16: 0 | BG16: 0 | BH16: 0 | BJ16: 否 | BP16: - | BQ16: - | BR16: -
A17: 6921009635296968526 | B17: 6921009635296968526 | C17: 【老板周】复古风格 秋冬新款立体麻花织纹针织毛衣 | D17: 灰色;M(100-120斤);15天内发货 | E17: 1 | F17: 3772185880568135686 | G17: Z2418-灰色-M | H17: 329 | I17: 329 | J17: 0 | K17: 0 | L17: - | M17: - | N17: - | O17: 0 | P17: 0 | Q17: 0 | R17: 抖音支付 | S17: 0 | T17: *** | U17: *** | V17: 天津市 | W17: 天津市 | X17: 滨海新区 | Y17: - | Z17: *** | AA17: 否 | AC17: 2025-08-31 17:39:47 | AD17: 灰色 | AG17: 2025-08-31 17:39:48 | AH17: 抖音 | AI17: 精选联盟 | AJ17: 已关闭 | AK17: 2025-09-15 17:39:48 | AL17: 普通订单 | AM17: 0 | AN17: 2353393836764088 | AO17: 老板周 | AP17: - | AQ17: 退款成功 | AS17: - | AT17: - | AU17: - | AW17: 否 | AX17: 无 | AY17: 其他 | AZ17: 直播 | BA17: 个人主页&店铺&橱窗进入直播间 | BB17: - | BC17: - | BE17: 0 | BF17: 0 | BG17: 0 | BH17: 0 | BJ17: 否 | BP17: - | BQ17: - | BR17: -
A18: 6921016365371785140 | B18: 6921016365371785140 | C18: 【老板周】复古风格 秋冬新款立体麻花织纹针织毛衣 | D18: 灰色;M(100-120斤);15天内发货 | E18: 1 | F18: 3772185880568135686 | G18: Z2418-灰色-M | H18: 329 | I18: 329 | J18: 0 | K18: 0 | L18: - | M18: - | N18: - | O18: 0 | P18: 0 | Q18: 0 | R18: 支付宝 | S18: 0 | T18: *** | U18: *** | V18: 河北省 | W18: 石家庄市 | X18: 赵县 | Y18: 赵州镇 | Z18: *** | AA18: 否 | AC18: 2025-08-31 17:39:46 | AD18: 蓝色 | AE18: JT5414067073138(收） Z2418-灰色-M*1# | AG18: 2025-08-31 17:39:54 | AH18: 抖音 | AI18: 精选联盟 | AJ18: 已关闭 | AK18: 2025-09-15 17:39:54 | AL18: 普通订单 | AM18: 0 | AN18: 2353393836764088 | AO18: 老板周 | AP18: - | AQ18: 退款成功 | AS18: - | AT18: - | AU18: - | AW18: 否 | AX18: 无 | AY18: 其他 | AZ18: 直播 | BA18: 直播推荐 | BB18: - | BC18: - | BD18: 2025-09-15 10:48:28 | BE18: 0 | BF18: 0 | BG18: 0 | BH18: 0 | BJ18: 否 | BP18: - | BQ18: - | BR18: -
A19: 6921009588551319487 | B19: 6921009588551319487 | C19: 【老板周】复古风格 秋冬新款立体麻花织纹针织毛衣 | D19: 灰色;S(80-100斤);15天内发货 | E19: 1 | F19: 3772185880568135686 | G19: Z2418-灰色-S | H19: 329 | I19: 329 | J19: 0 | K19: 0 | L19: - | M19: - | N19: - | O19: 0 | P19: 0 | Q19: 0 | R19: 抖音支付 | S19: 0 | T19: *** | U19: *** | V19: 江苏省 | W19: 苏州市 | X19: 虎丘区 | Y19: 东渚街道 | Z19: *** | AA19: 否 | AC19: 2025-08-31 17:39:43 | AD19: 灰色 | AG19: 2025-08-31 17:39:46 | AH19: 抖音 | AI19: 精选联盟 | AJ19: 已关闭 | AK19: 2025-09-15 17:39:46 | AL19: 普通订单 | AM19: 0 | AN19: 2353393836764088 | AO19: 老板周 | AP19: - | AQ19: 退款成功 | AS19: - | AT19: - | AU19: - | AW19: 否 | AX19: 无 | AY19: 其他 | AZ19: 直播 | BA19: 关注来源 | BB19: - | BC19: - | BE19: 0 | BF19: 0 | BG19: 0 | BH19: 0 | BJ19: 否 | BP19: - | BQ19: - | BR19: -
A20: 6921018615091854571 | B20: 6921018615091854571 | C20: 【老板周】复古风格 秋冬新款立体麻花织纹针织毛衣 | D20: 灰色;L(120-135斤);15天内发货 | E20: 1 | F20: 3772185880568135686 | G20: Z2418-灰色-L | H20: 329 | I20: 329 | J20: 0 | K20: 0 | L20: - | M20: - | N20: - | O20: 0 | P20: 0 | Q20: 0 | R20: 抖音支付 | S20: 0 | T20: *** | U20: *** | V20: 河北省 | W20: 邢台市 | X20: 信都区 | Y20: 泉西街道 | Z20: *** | AA20: 否 | AC20: 2025-08-31 17:33:32 | AD20: 灰色 | AG20: 2025-08-31 17:33:35 | AH20: 抖音 | AI20: 精选联盟 | AJ20: 已关闭 | AK20: 2025-09-15 17:33:35 | AL20: 普通订单 | AM20: 0 | AN20: 2353393836764088 | AO20: 老板周 | AP20: - | AQ20: 退款成功 | AS20: - | AT20: - | AU20: - | AW20: 否 | AX20: 无 | AY20: 其他 | AZ20: 直播 | BA20: 直播推荐 | BB20: - | BC20: - | BE20: 0 | BF20: 0 | BG20: 0 | BH20: 0 | BJ20: 否 | BP20: - | BQ20: - | BR20: -
A21: 6945702914926777790 | B21: 6945702914926777790 | C21: 【老板周】复古风格 秋冬新款立体麻花织纹针织毛衣 | D21: 灰色;M(100-120斤);15天内发货 | E21: 1 | F21: 3772185880568135686 | G21: Z2418-灰色-M | H21: 329 | I21: 329 | J21: 0 | K21: 0 | L21: - | M21: - | N21: - | O21: 0 | P21: 0 | Q21: 0 | R21: 抖音支付 | S21: 0 | T21: *** | U21: *** | V21: 山西省 | W21: 大同市 | X21: 云冈区 | Y21: 新平旺街道 | Z21: *** | AA21: 否 | AC21: 2025-08-31 17:33:15 | AD21: 灰色 | AF21: 2025-09-21 10:50:13 | AG21: 2025-08-31 17:33:16 | AH21: 抖音极速版 | AI21: 精选联盟 | AJ21: 已完成 | AK21: 2025-09-15 17:33:17 | AL21: 普通订单 | AM21: 0 | AN21: 2353393836764088 | AO21: 老板周 | AP21: - | AQ21: - | AS21: - | AT21: - | AU21: - | AW21: 否 | AX21: 直播 | AY21: 广告 | AZ21: 直播 | BA21: 直播推荐 | BB21: - | BC21: - | BD21: 2025-09-15 10:48:28 | BE21: 0 | BF21: 0 | BG21: 0 | BH21: 0 | BJ21: 否 | BP21: - | BQ21: - | BR21: -
A22: 6945716202524317053 | B22: 6945716202524317053 | C22: 【老板周】复古风格 秋冬新款立体麻花织纹针织毛衣 | D22: 灰色;M(100-120斤);15天内发货 | E22: 1 | F22: 3772185880568135686 | G22: Z2418-灰色-M | H22: 329 | I22: 329 | J22: 0 | K22: 0 | L22: - | M22: - | N22: - | O22: 0 | P22: 0 | Q22: 0 | R22: 抖音月付 | S22: 0 | T22: *** | U22: *** | V22: 重庆市 | W22: 重庆市 | X22: 梁平区 | Y22: 双桂街道 | Z22: *** | AA22: 否 | AC22: 2025-08-31 17:32:47 | AD22: 蓝色 | AE22: SF3282428122123(收） Z2418-灰色-M*1# | AG22: 2025-08-31 17:32:49 | AH22: 抖音商城版 | AI22: 精选联盟 | AJ22: 已关闭 | AK22: 2025-09-15 17:32:50 | AL22: 普通订单 | AM22: 0 | AN22: 2353393836764088 | AO22: 老板周 | AP22: - | AQ22: 退款成功 | AS22: - | AT22: - | AU22: - | AW22: 否 | AX22: 无 | AY22: 其他 | AZ22: 直播 | BA22: 商城推荐 | BB22: - | BC22: - | BD22: 2025-09-14 23:53:25 | BE22: 0 | BF22: 0 | BG22: 0 | BH22: 0 | BJ22: 否 | BP22: - | BQ22: - | BR22: -
A23: 6921018667371494935 | B23: 6921018667371494935 | C23: 【老板周】复古风格 秋冬新款立体麻花织纹针织毛衣 | D23: 灰色;S(80-100斤);15天内发货 | E23: 1 | F23: 3772185880568135686 | G23: Z2418-灰色-S | H23: 329 | I23: 329 | J23: 0 | K23: 0 | L23: - | M23: - | N23: - | O23: 0 | P23: 0 | Q23: 0 | R23: 支付宝 | S23: 0 | T23: *** | U23: *** | V23: 浙江省 | W23: 丽水市 | X23: 莲都区 | Y23: 岩泉街道 | Z23: *** | AA23: 否 | AC23: 2025-08-31 17:32:37 | AD23: 蓝色 | AE23: 拦截;76740677006606(收） Z2418-灰色-S*1# | AG23: 2025-08-31 17:32:50 | AH23: 抖音 | AI23: 精选联盟 | AJ23: 已关闭 | AK23: 2025-09-15 17:32:50 | AL23: 普通订单 | AM23: 0 | AN23: 2353393836764088 | AO23: 老板周 | AP23: - | AQ23: 退款成功 | AS23: - | AT23: - | AU23: - | AW23: 否 | AX23: 直播 | AY23: 广告 | AZ23: 直播 | BA23: 商城推荐 | BB23: - | BC23: - | BD23: 2025-09-15 10:48:28 | BE23: 0 | BF23: 0 | BG23: 0 | BH23: 0 | BJ23: 否 | BP23: - | BQ23: - | BR23: -
A24: 6945696235709732402 | B24: 6945696235709732402 | C24: 【老板周】复古风格 秋冬新款立体麻花织纹针织毛衣 | D24: 灰色;S(80-100斤);15天内发货 | E24: 1 | F24: 3772185880568135686 | G24: Z2418-灰色-S | H24: 329 | I24: 329 | J24: 0 | K24: 2.05 | L24: - | M24: - | N24: - | O24: 0 | P24: 2.05 | Q24: 0 | R24: 抖音支付 | S24: 0 | T24: *** | U24: *** | V24: 浙江省 | W24: 丽水市 | X24: 青田县 | Y24: 瓯南街道 | Z24: *** | AA24: 否 | AC24: 2025-08-31 17:32:36 | AD24: 灰色 | AF24: 2025-09-22 10:48:28 | AG24: 2025-08-31 17:32:40 | AH24: 抖音 | AI24: 精选联盟 | AJ24: 已完成 | AK24: 2025-09-15 17:32:40 | AL24: 普通订单 | AM24: 0 | AN24: 2353393836764088 | AO24: 老板周 | AP24: - | AQ24: - | AS24: - | AT24: - | AU24: - | AW24: 否 | AX24: 无 | AY24: 其他 | AZ24: 直播 | BA24: 个人主页&店铺&橱窗进入直播间 | BB24: - | BC24: - | BD24: 2025-09-15 10:48:28 | BE24: 0 | BF24: 0 | BG24: 0 | BH24: 0 | BJ24: 否 | BP24: - | BQ24: - | BR24: -
A25: 6921009624776736703 | B25: 6921009624776736703 | C25: 【老板周】复古风格 秋冬新款立体麻花织纹针织毛衣 | D25: 灰色;M(100-120斤);15天内发货 | E25: 1 | F25: 3772185880568135686 | G25: Z2418-灰色-M | H25: 329 | I25: 329 | J25: 0 | K25: 0 | L25: - | M25: - | N25: - | O25: 0 | P25: 0 | Q25: 0 | R25: 抖音支付 | S25: 0 | T25: *** | U25: *** | V25: 江苏省 | W25: 苏州市 | X25: 虎丘区 | Y25: 东渚街道 | Z25: *** | AA25: 否 | AC25: 2025-08-31 17:32:33 | AD25: 灰色 | AG25: 2025-08-31 17:32:38 | AH25: 抖音 | AI25: 精选联盟 | AJ25: 已关闭 | AK25: 2025-09-15 17:32:39 | AL25: 普通订单 | AM25: 0 | AN25: 2353393836764088 | AO25: 老板周 | AP25: - | AQ25: 退款成功 | AS25: - | AT25: - | AU25: - | AW25: 否 | AX25: 无 | AY25: 其他 | AZ25: 直播 | BA25: 关注来源 | BB25: - | BC25: - | BE25: 0 | BF25: 0 | BG25: 0 | BH25: 0 | BJ25: 否 | BP25: - | BQ25: - | BR25: -
A26: 6921013958667763428 | B26: 6921013958667763428 | C26: 【老板周】复古风格 秋冬新款立体麻花织纹针织毛衣 | D26: 灰色;S(80-100斤);15天内发货 | E26: 1 | F26: 3772185880568135686 | G26: Z2418-灰色-S | H26: 329 | I26: 329 | J26: 0 | K26: 0 | L26: - | M26: - | N26: - | O26: 0 | P26: 0 | Q26: 0 | R26: 支付宝 | S26: 0 | T26: *** | U26: *** | V26: 贵州省 | W26: 贵阳市 | X26: 南明区 | Y26: 中曹司街道 | Z26: *** | AA26: 否 | AC26: 2025-08-31 17:32:31 | AD26: 灰色 | AG26: 2025-08-31 17:32:38 | AH26: 抖音 | AI26: 精选联盟 | AJ26: 已关闭 | AK26: 2025-09-15 17:32:38 | AL26: 普通订单 | AM26: 0 | AN26: 2353393836764088 | AO26: 老板周 | AP26: - | AQ26: 退款成功 | AS26: - | AT26: - | AU26: - | AW26: 否 | AX26: 无 | AY26: 其他 | AZ26: 直播 | BA26: 直播推荐 | BB26: - | BC26: - | BE26: 0 | BF26: 0 | BG26: 0 | BH26: 0 | BJ26: 否 | BP26: - | BQ26: - | BR26: -
A27: 6945698443959669805 | B27: 6945698443959669805 | C27: 【老板周】日系极简 春季新品圆领简约设计感无袖马甲 | D27: 黑色;L(120-135斤);15天内发货 | E27: 1 | F27: 3767004410471907465 | G27: Z1640-黑色-L | H27: 289 | I27: 314 | J27: 25 | K27: 0 | L27: - | M27: - | N27: - | O27: 0 | P27: 0 | Q27: 0 | R27: 抖音月付 | S27: 0 | T27: *** | U27: *** | V27: 陕西省 | W27: 咸阳市 | X27: 渭城区 | Y27: 周陵街道 | Z27: *** | AA27: 否 | AC27: 2025-08-31 16:17:00 | AD27: 灰色 | AF27: 2025-09-19 16:35:27 | AG27: 2025-08-31 16:17:05 | AH27: 抖音 | AI27: 精选联盟 | AJ27: 已完成 | AK27: 2025-09-15 16:17:05 | AL27: 普通订单 | AM27: 0 | AN27: 2353393836764088 | AO27: 老板周 | AP27: - | AQ27: - | AS27: - | AT27: - | AU27: - | AW27: 否 | AX27: 无 | AY27: 其他 | AZ27: 直播 | BA27: 直播推荐 | BB27: - | BC27: - | BD27: 2025-09-12 16:35:27 | BE27: 0 | BF27: 0 | BG27: 0 | BH27: 0 | BJ27: 否 | BP27: - | BQ27: - | BR27: -
A28: 6945649067193472893 | B28: 6945649067193472893 | C28: 【老板周】日系极简 春季新品圆领简约设计感无袖马甲 | D28: 黑色;S(80-100斤);15天内发货 | E28: 1 | F28: 3767004410471907465 | G28: Z1640-黑色-S | H28: 289 | I28: 254.06 | J28: 0 | K28: 35.86 | L28: 平台七夕消费券-34.94 | M28: - | N28: - | O28: 0 | P28: 0.92 | Q28: 0 | R28: 抖音支付 | S28: 0 | T28: *** | U28: *** | V28: 辽宁省 | W28: 大连市 | X28: 中山区 | Y28: - | Z28: *** | AA28: 否 | AC28: 2025-08-29 20:47:38 | AD28: 灰色 | AE28: (收)[Z1640-黑色-S]*[1]# | AF28: 2025-09-18 23:58:12 | AG28: 2025-08-29 20:47:40 | AH28: 抖音 | AI28: 精选联盟 | AJ28: 已完成 | AK28: 2025-09-13 20:47:41 | AL28: 普通订单 | AM28: 0 | AN28: 2353393836764088 | AO28: 老板周 | AP28: - | AQ28: 退款成功 | AS28: - | AT28: - | AU28: - | AW28: 否 | AX28: 无 | AY28: 其他 | AZ28: 直播 | BA28: 搜索 | BB28: - | BC28: - | BD28: 2025-09-11 23:58:12 | BE28: 0 | BF28: 34.94 | BG28: 0 | BH28: 0 | BJ28: 否 | BP28: - | BQ28: - | BR28: -
A29: 6920964153135168659 | B29: 6920964153135168659 | C29: 【老板周】小众休闲 压褶松紧腰宽松百搭裤裙 | D29: 藏蓝色;M(95-110斤);15天内发货 | E29: 1 | F29: 3770653191356678342 | G29: Z575-藏蓝色-M | H29: 299 | I29: 299 | J29: 0 | K29: 0 | L29: - | M29: - | N29: - | O29: 0 | P29: 0 | Q29: 0 | R29: 抖音支付 | S29: 0 | T29: *** | U29: *** | V29: 内蒙古自治区 | W29: 呼和浩特市 | X29: 新城区 | Y29: 成吉思汗大街街道 | Z29: *** | AA29: 否 | AC29: 2025-08-28 22:10:07 | AD29: 灰色 | AH29: 抖音 | AI29: 小店自卖 | AJ29: 已关闭 | AK29: 2025-09-12 22:10:07 | AL29: 普通订单 | AM29: 0 | AN29: 0 | AP29: - | AQ29: - | AR29: 用户超时未支付自动取消 | AS29: - | AT29: - | AU29: - | AW29: 否 | AX29: 无 | AY29: 其他 | AZ29: 商品卡 | BA29: 店铺页面 | BB29: - | BC29: - | BE29: 0 | BF29: 0 | BG29: 0 | BH29: 0 | BJ29: 否 | BP29: - | BQ29: - | BR29: -
A30: 6920966085271780499 | B30: 6920966085271780499 | C30: 【老板周】小众休闲 压褶松紧腰宽松百搭裤裙 | D30: 藏蓝色;M(95-110斤);15天内发货 | E30: 1 | F30: 3770653191356678342 | G30: Z575-藏蓝色-M | H30: 299 | I30: 299 | J30: 0 | K30: 0 | L30: - | M30: - | N30: - | O30: 0 | P30: 0 | Q30: 0 | R30: 抖音支付 | S30: 0 | T30: *** | U30: *** | V30: 内蒙古自治区 | W30: 呼和浩特市 | X30: 新城区 | Y30: 成吉思汗大街街道 | Z30: *** | AA30: 否 | AC30: 2025-08-28 22:09:25 | AD30: 灰色 | AH30: 抖音 | AI30: 小店自卖 | AJ30: 已关闭 | AK30: 2025-09-12 22:09:25 | AL30: 普通订单 | AM30: 0 | AN30: 0 | AP30: - | AQ30: - | AR30: 用户超时未支付自动取消 | AS30: - | AT30: - | AU30: - | AW30: 否 | AX30: 无 | AY30: 其他 | AZ30: 商品卡 | BA30: 店铺页面 | BB30: - | BC30: - | BE30: 0 | BF30: 0 | BG30: 0 | BH30: 0 | BJ30: 否 | BP30: - | BQ30: - | BR30: -
A31: 6945610806981695196 | B31: 6945610806981695196 | C31: 【老板周】日系极简 春季新品圆领简约设计感无袖马甲 | D31: 黑色;M(100-120斤);15天内发货 | E31: 1 | F31: 3767004410471907465 | G31: Z1640-黑色-M | H31: 289 | I31: 260.12 | J31: 0 | K31: 28.88 | L31: 平台七夕消费券-28.88 | M31: - | N31: - | O31: 0 | P31: 0 | Q31: 0 | R31: 抖音月付 | S31: 0 | T31: *** | U31: *** | V31: 河北省 | W31: 邢台市 | X31: 信都区 | Y31: 达活泉街道 | Z31: *** | AA31: 否 | AC31: 2025-08-28 11:04:59 | AD31: 红色 | AE31: SF3234099112861(收） Z1640-黑色-M*1#;换货(6298912)#;换货76743232979811 收到退款 不换货了 | AF31: 2025-09-14 23:31:58 | AG31: 2025-08-28 11:05:06 | AH31: 抖音 | AI31: 精选联盟 | AJ31: 已完成 | AK31: 2025-09-12 11:05:07 | AL31: 普通订单 | AM31: 0 | AN31: 2353393836764088 | AO31: 老板周 | AP31: - | AQ31: 退款成功 | AS31: - | AT31: - | AU31: - | AW31: 否 | AX31: 无 | AY31: 其他 | AZ31: 商品卡 | BA31: 橱窗 | BB31: - | BC31: - | BD31: 2025-09-07 23:31:58 | BE31: 0 | BF31: 28.88 | BG31: 0 | BH31: 0 | BJ31: 否 | BP31: - | BQ31: - | BR31: -
A32: 6920952081164304100 | B32: 6920952081164304100 | C32: 【老板周】日系极简 春季新品圆领简约设计感无袖马甲 | D32: 黑色;M(100-120斤);15天内发货 | E32: 1 | F32: 3767004410471907465 | G32: Z1640-黑色-M | H32: 289 | I32: 289 | J32: 0 | K32: 0 | L32: - | M32: - | N32: - | O32: 0 | P32: 0 | Q32: 0 | R32: 抖音支付 | S32: 0 | T32: *** | U32: *** | V32: 山东省 | W32: 菏泽市 | X32: 牡丹区 | Y32: 牡丹街道 | Z32: *** | AA32: 否 | AC32: 2025-08-28 00:21:12 | AD32: 灰色 | AG32: 2025-08-28 00:21:13 | AH32: 抖音 | AI32: 小店自卖 | AJ32: 已关闭 | AK32: 2025-09-12 00:21:13 | AL32: 普通订单 | AM32: 0 | AN32: 0 | AP32: - | AQ32: 退款成功 | AS32: - | AT32: - | AU32: - | AW32: 否 | AX32: 无 | AY32: 其他 | AZ32: 商品卡 | BA32: 搜索 | BB32: - | BC32: - | BE32: 0 | BF32: 0 | BG32: 0 | BH32: 0 | BJ32: 否 | BP32: - | BQ32: - | BR32: -
A33: 6945587885982618859 | B33: 6945587885982618859 | C33: 【老板周】日系极简 春季新品圆领简约设计感无袖马甲 | D33: 黑色;M(100-120斤);15天内发货 | E33: 1 | F33: 3767004410471907465 | G33: Z1640-黑色-M | H33: 289 | I33: 278 | J33: 0 | K33: 11 | L33: 平台专属限时优惠券-11.00 | M33: - | N33: - | O33: 0 | P33: 0 | Q33: 0 | R33: 抖音支付 | S33: 0 | T33: *** | U33: *** | V33: 山东省 | W33: 青岛市 | X33: 市北区 | Y33: 河西街道 | Z33: *** | AA33: 否 | AC33: 2025-08-27 22:38:33 | AD33: 灰色 | AG33: 2025-08-27 22:38:44 | AH33: 抖音商城版 | AI33: 精选联盟 | AJ33: 已关闭 | AK33: 2025-09-11 22:38:44 | AL33: 普通订单 | AM33: 0 | AN33: 2353393836764088 | AO33: 老板周 | AP33: - | AQ33: 退款成功 | AS33: - | AT33: - | AU33: - | AW33: 否 | AX33: 直播 | AY33: 广告 | AZ33: 直播 | BA33: 商城推荐 | BB33: - | BC33: - | BE33: 0 | BF33: 11 | BG33: 0 | BH33: 0 | BJ33: 否 | BP33: - | BQ33: - | BR33: -
A34: 6945598979942323318 | B34: 6945598979942323318 | C34: 【老板周】日系极简 春季新品圆领简约设计感无袖马甲 | D34: 黑色;M(100-120斤);15天内发货 | E34: 1 | F34: 3767004410471907465 | G34: Z1640-黑色-M | H34: 289 | I34: 289 | J34: 0 | K34: 0 | L34: - | M34: - | N34: - | O34: 0 | P34: 0 | Q34: 0 | R34: 抖音支付 | S34: 0 | T34: *** | U34: *** | V34: 天津市 | W34: 天津市 | X34: 武清区 | Y34: 东蒲洼街道 | Z34: *** | AA34: 否 | AC34: 2025-08-27 22:12:00 | AD34: 灰色 | AF34: 2025-09-14 23:31:58 | AG34: 2025-08-27 22:12:06 | AH34: 头条lite-抖音电商 | AI34: 精选联盟 | AJ34: 已完成 | AK34: 2025-09-11 22:12:06 | AL34: 普通订单 | AM34: 0 | AN34: 2353393836764088 | AO34: 老板周 | AP34: - | AQ34: - | AS34: - | AT34: - | AU34: - | AW34: 否 | AX34: 无 | AY34: 其他 | AZ34: 直播 | BA34: 头条西瓜 | BB34: - | BC34: - | BD34: 2025-09-07 23:31:58 | BE34: 0 | BF34: 0 | BG34: 0 | BH34: 0 | BJ34: 否 | BP34: - | BQ34: - | BR34: -
A35: 6945583048360597411 | B35: 6945583048360597411 | C35: 【老板周】日系极简 春季新品圆领简约设计感无袖马甲 | D35: 黑色;M(100-120斤);15天内发货 | E35: 1 | F35: 3767004410471907465 | G35: Z1640-黑色-M | H35: 289 | I35: 289 | J35: 0 | K35: 0 | L35: - | M35: - | N35: - | O35: 0 | P35: 0 | Q35: 0 | R35: 抖音月付 | S35: 0 | T35: *** | U35: *** | V35: 山东省 | W35: 日照市 | X35: 莒县 | Y35: 城阳街道 | Z35: *** | AA35: 否 | AC35: 2025-08-27 20:47:29 | AD35: 蓝色 | AE35: 73572507159291(收） Z1640-黑色-M*1# | AG35: 2025-08-27 20:47:31 | AH35: 抖音 | AI35: 精选联盟 | AJ35: 已关闭 | AK35: 2025-09-11 20:47:32 | AL35: 普通订单 | AM35: 0 | AN35: 2353393836764088 | AO35: 老板周 | AP35: - | AQ35: 退款成功 | AS35: - | AT35: - | AU35: - | AW35: 否 | AX35: 无 | AY35: 其他 | AZ35: 直播 | BA35: 直播推荐 | BB35: - | BC35: - | BD35: 2025-09-07 23:31:58 | BE35: 0 | BF35: 0 | BG35: 0 | BH35: 0 | BJ35: 否 | BP35: - | BQ35: - | BR35: -
A36: 6945609733810165452 | B36: 6945609733810165452 | C36: 【老板周】日系极简 春季新品圆领简约设计感无袖马甲 | D36: 黑色;M(100-120斤);15天内发货 | E36: 1 | F36: 3767004410471907465 | G36: Z1640-黑色-M | H36: 289 | I36: 289 | J36: 0 | K36: 0 | L36: - | M36: - | N36: - | O36: 0 | P36: 0 | Q36: 0 | R36: 支付宝 | S36: 0 | T36: *** | U36: *** | V36: 山西省 | W36: 太原市 | X36: 杏花岭区 | Y36: 中涧河镇 | Z36: *** | AA36: 否 | AC36: 2025-08-27 19:52:03 | AD36: 灰色 | AH36: 番茄小说-抖音电商 | AI36: 精选联盟 | AJ36: 已关闭 | AK36: 2025-09-11 19:52:03 | AL36: 普通订单 | AM36: 0 | AN36: 2353393836764088 | AO36: 老板周 | AP36: - | AQ36: - | AR36: 用户超时未支付自动取消 | AS36: - | AT36: - | AU36: - | AW36: 否 | AX36: 直播 | AY36: 广告 | AZ36: 直播 | BA36: 其他 | BB36: - | BC36: - | BE36: 0 | BF36: 0 | BG36: 0 | BH36: 0 | BJ36: 否 | BP36: - | BQ36: - | BR36: -
A37: 6945592088900211946 | B37: 6945592088900211946 | C37: 【老板周】日系极简 春季新品圆领简约设计感无袖马甲 | D37: 黑色;M(100-120斤);15天内发货 | E37: 1 | F37: 3767004410471907465 | G37: Z1640-黑色-M | H37: 289 | I37: 289 | J37: 0 | K37: 0 | L37: - | M37: - | N37: - | O37: 0 | P37: 0 | Q37: 0 | R37: 抖音支付 | S37: 0 | T37: *** | U37: *** | V37: 江苏省 | W37: 常州市 | X37: 钟楼区 | Y37: 南大街道 | Z37: *** | AA37: 否 | AC37: 2025-08-27 18:21:49 | AD37: 蓝色 | AE37: SF3232586273829(收） Z1640-黑色-M*1# | AG37: 2025-08-27 18:21:55 | AH37: 抖音 | AI37: 精选联盟 | AJ37: 已关闭 | AK37: 2025-09-11 18:21:55 | AL37: 普通订单 | AM37: 0 | AN37: 2353393836764088 | AO37: 老板周 | AP37: - | AQ37: 退款成功 | AS37: - | AT37: - | AU37: - | AW37: 否 | AX37: 直播 | AY37: 广告 | AZ37: 直播 | BA37: 搜索 | BB37: - | BC37: - | BD37: 2025-09-07 23:31:58 | BE37: 0 | BF37: 0 | BG37: 0 | BH37: 0 | BJ37: 否 | BP37: - | BQ37: - | BR37: -
A38: 6945600734649980653 | B38: 6945600734649980653 | C38: 【老板周】日系极简 春季新品圆领简约设计感无袖马甲 | D38: 黑色;M(100-120斤);15天内发货 | E38: 1 | F38: 3767004410471907465 | G38: Z1640-黑色-M | H38: 289 | I38: 289 | J38: 0 | K38: 0 | L38: - | M38: - | N38: - | O38: 0 | P38: 0 | Q38: 0 | R38: 抖音支付 | S38: 0 | T38: *** | U38: *** | V38: 浙江省 | W38: 杭州市 | X38: 临平区 | Y38: 乔司街道 | Z38: *** | AA38: 否 | AC38: 2025-08-27 17:46:07 | AD38: 蓝色 | AE38: 78939136440697(收） Z1640-黑色-S*1# | AG38: 2025-08-27 17:46:08 | AH38: 抖音 | AI38: 精选联盟 | AJ38: 已关闭 | AK38: 2025-09-11 17:46:09 | AL38: 普通订单 | AM38: 0 | AN38: 2353393836764088 | AO38: 老板周 | AP38: - | AQ38: 退款成功 | AS38: - | AT38: - | AU38: - | AW38: 否 | AX38: 无 | AY38: 其他 | AZ38: 直播 | BA38: 短视频引流直播间 | BB38: - | BC38: - | BD38: 2025-09-07 23:31:58 | BE38: 0 | BF38: 0 | BG38: 0 | BH38: 0 | BJ38: 否 | BP38: - | BQ38: - | BR38: -
A39: 6945589601420317825 | B39: 6945589601420317825 | C39: 【老板周】日系极简 春季新品圆领简约设计感无袖马甲 | D39: 黑色;M(100-120斤);15天内发货 | E39: 1 | F39: 3767004410471907465 | G39: Z1640-黑色-M | H39: 289 | I39: 289 | J39: 0 | K39: 0 | L39: - | M39: - | N39: - | O39: 0 | P39: 0 | Q39: 0 | R39: 抖音支付 | S39: 0 | T39: *** | U39: *** | V39: 江苏省 | W39: 南通市 | X39: 崇川区 | Y39: 观音山街道 | Z39: *** | AA39: 否 | AC39: 2025-08-27 17:31:54 | AD39: 红色 | AE39: SF3232813766922(收） Z1640-黑色-M*1#;换货(6280100)#;换货76742192082926 | AF39: 2025-09-14 23:31:58 | AG39: 2025-08-27 17:31:55 | AH39: 抖音 | AI39: 精选联盟 | AJ39: 已完成 | AK39: 2025-09-11 17:31:56 | AL39: 普通订单 | AM39: 0 | AN39: 2353393836764088 | AO39: 老板周 | AP39: - | AQ39: 换货成功 | AS39: - | AT39: - | AU39: - | AW39: 否 | AX39: 无 | AY39: 其他 | AZ39: 直播 | BA39: 直播推荐 | BB39: - | BC39: - | BD39: 2025-09-07 23:31:58 | BE39: 0 | BF39: 0 | BG39: 0 | BH39: 0 | BJ39: 否 | BP39: - | BQ39: - | BR39: -
A40: 6920950993200905666 | B40: 6920950993200905666 | C40: 【老板周】日系极简 春季新品圆领简约设计感无袖马甲 | D40: 黑色;M(100-120斤);15天内发货 | E40: 8 | F40: 3767004410471907465 | G40: Z1640-黑色-M | H40: 289 | I40: 2312 | J40: 0 | K40: 0 | L40: - | M40: - | N40: - | O40: 0 | P40: 0 | Q40: 0 | R40: 支付宝 | S40: 0 | T40: *** | U40: *** | V40: 山东省 | W40: 济宁市 | X40: 微山县 | Y40: - | Z40: *** | AA40: 否 | AC40: 2025-08-27 17:23:35 | AD40: 灰色 | AH40: 头条lite-抖音电商 | AI40: 精选联盟 | AJ40: 已关闭 | AK40: 2025-09-11 17:23:35 | AL40: 普通订单 | AM40: 0 | AN40: 2353393836764088 | AO40: 老板周 | AP40: - | AQ40: - | AR40: 用户超时未支付自动取消 | AS40: - | AT40: - | AU40: - | AW40: 否 | AX40: 直播 | AY40: 广告 | AZ40: 直播 | BA40: 头条西瓜 | BB40: - | BC40: - | BE40: 0 | BF40: 0 | BG40: 0 | BH40: 0 | BJ40: 否 | BP40: - | BQ40: - | BR40: -
A41: 6945602769375205012 | B41: 6945602769375205012 | C41: 【老板周】日系极简 春季新品圆领简约设计感无袖马甲 | D41: 黑色;L(120-135斤);15天内发货 | E41: 1 | F41: 3767004410471907465 | G41: Z1640-黑色-L | H41: 289 | I41: 289 | J41: 0 | K41: 0 | L41: - | M41: - | N41: - | O41: 0 | P41: 0 | Q41: 0 | R41: 抖音支付 | S41: 0 | T41: *** | U41: *** | V41: 安徽省 | W41: 芜湖市 | X41: 南陵县 | Y41: 许镇镇 | Z41: *** | AA41: 否 | AC41: 2025-08-27 16:36:08 | AD41: 灰色 | AF41: 2025-09-14 17:22:20 | AG41: 2025-08-27 16:36:13 | AH41: 抖音 | AI41: 精选联盟 | AJ41: 已完成 | AK41: 2025-09-11 16:36:13 | AL41: 普通订单 | AM41: 0 | AN41: 2353393836764088 | AO41: 老板周 | AP41: - | AQ41: - | AS41: - | AT41: - | AU41: - | AW41: 否 | AX41: 无 | AY41: 其他 | AZ41: 直播 | BA41: 直播推荐 | BB41: - | BC41: - | BD41: 2025-09-07 17:22:20 | BE41: 0 | BF41: 0 | BG41: 0 | BH41: 0 | BJ41: 否 | BP41: - | BQ41: - | BR41: -
A42: 6945580306812376109 | B42: 6945580306812376109 | C42: 【老板周】简约法式 秋冬复古叠穿日系开叉百搭马甲 | D42: 黑色;S(80-100斤);15天内发货 | E42: 1 | F42: 3770720616102101370 | G42: Z2328-黑色-S | H42: 319 | I42: 319 | J42: 0 | K42: 0 | L42: - | M42: - | N42: - | O42: 0 | P42: 0 | Q42: 0 | R42: 抖音月付 | S42: 0 | T42: *** | U42: *** | V42: 宁夏回族自治区 | W42: 银川市 | X42: 金凤区 | Y42: 北京中路街道 | Z42: *** | AA42: 否 | AC42: 2025-08-27 16:11:55 | AD42: 蓝色 | AE42: SF3239328943996(收） Z2328-黑色-S*1# | AG42: 2025-08-27 16:11:56 | AH42: 抖音 | AI42: 小店自卖 | AJ42: 已关闭 | AK42: 2025-09-11 16:11:57 | AL42: 普通订单 | AM42: 0 | AN42: 0 | AP42: - | AQ42: 退款成功 | AS42: - | AT42: - | AU42: - | AW42: 否 | AX42: 无 | AY42: 其他 | AZ42: 商品卡 | BA42: 店铺页面 | BB42: - | BC42: - | BD42: 2025-08-27 18:02:40 | BE42: 0 | BF42: 0 | BG42: 0 | BH42: 0 | BJ42: 否 | BP42: - | BQ42: - | BR42: -
A43: 6945596186333484482 | B43: 6945596186333484482 | C43: 【老板周】日系极简 春季新品圆领简约设计感无袖马甲 | D43: 黑色;M(100-120斤);15天内发货 | E43: 1 | F43: 3767004410471907465 | G43: Z1640-黑色-M | H43: 289 | I43: 289 | J43: 0 | K43: 0 | L43: - | M43: - | N43: - | O43: 0 | P43: 0 | Q43: 0 | R43: 抖音月付 | S43: 0 | T43: *** | U43: *** | V43: 安徽省 | W43: 亳州市 | X43: 谯城区 | Y43: 花戏楼街道 | Z43: *** | AA43: 否 | AC43: 2025-08-27 15:44:54 | AD43: 灰色 | AG43: 2025-08-27 15:44:59 | AH43: 抖音 | AI43: 精选联盟 | AJ43: 已关闭 | AK43: 2025-09-11 15:44:59 | AL43: 普通订单 | AM43: 0 | AN43: 2353393836764088 | AO43: 老板周 | AP43: - | AQ43: 退款成功 | AS43: - | AT43: - | AU43: - | AW43: 否 | AX43: 无 | AY43: 其他 | AZ43: 直播 | BA43: 直播推荐 | BB43: - | BC43: - | BE43: 0 | BF43: 0 | BG43: 0 | BH43: 0 | BJ43: 否 | BP43: - | BQ43: - | BR43: -
A44: 6920955047060602569 | B44: 6920955047060602569 | C44: 【老板周】日系极简 春季新品圆领简约设计感无袖马甲 | D44: 黑色;M(100-120斤);15天内发货 | E44: 1 | F44: 3767004410471907465 | G44: Z1640-黑色-M | H44: 289 | I44: 289 | J44: 0 | K44: 0 | L44: - | M44: - | N44: - | O44: 0 | P44: 0 | Q44: 0 | R44: 抖音支付 | S44: 0 | T44: *** | U44: *** | V44: 黑龙江省 | W44: 牡丹江市 | X44: 绥芬河市 | Y44: 绥芬河镇 | Z44: *** | AA44: 否 | AC44: 2025-08-27 15:44:26 | AD44: 蓝色 | AE44: SF3282828296194(收） Z1640-黑色-M*1# | AG44: 2025-08-27 15:44:27 | AH44: 抖音 | AI44: 精选联盟 | AJ44: 已关闭 | AK44: 2025-09-11 15:44:27 | AL44: 普通订单 | AM44: 0 | AN44: 2353393836764088 | AO44: 老板周 | AP44: - | AQ44: 退款成功 | AS44: - | AT44: - | AU44: - | AW44: 否 | AX44: 无 | AY44: 其他 | AZ44: 直播 | BA44: 个人主页&店铺&橱窗进入直播间 | BB44: - | BC44: - | BD44: 2025-09-07 23:31:59 | BE44: 0 | BF44: 0 | BG44: 0 | BH44: 0 | BJ44: 否 | BP44: - | BQ44: - | BR44: -
A45: 6945604921919543082 | B45: 6945604921919543082 | C45: 【老板周】日系极简 春季新品圆领简约设计感无袖马甲 | D45: 黑色;L(120-135斤);15天内发货 | E45: 1 | F45: 3767004410471907465 | G45: Z1640-黑色-L | H45: 289 | I45: 289 | J45: 0 | K45: 0 | L45: - | M45: - | N45: - | O45: 0 | P45: 0 | Q45: 0 | R45: 支付宝 | S45: 0 | T45: *** | U45: *** | V45: 上海市 | W45: 上海市 | X45: 杨浦区 | Y45: 控江路街道 | Z45: *** | AA45: 否 | AC45: 2025-08-27 15:37:02 | AD45: 灰色 | AG45: 2025-08-27 15:37:07 | AH45: 抖音 | AI45: 精选联盟 | AJ45: 已关闭 | AK45: 2025-09-11 15:37:08 | AL45: 普通订单 | AM45: 0 | AN45: 2353393836764088 | AO45: 老板周 | AP45: - | AQ45: 退款成功 | AS45: - | AT45: - | AU45: - | AW45: 否 | AX45: 无 | AY45: 其他 | AZ45: 直播 | BA45: 直播推荐 | BB45: - | BC45: - | BE45: 0 | BF45: 0 | BG45: 0 | BH45: 0 | BJ45: 否 | BP45: - | BQ45: - | BR45: -
A46: 6945582609766290962 | B46: 6945582609766290962 | C46: 【老板周】日系极简 春季新品圆领简约设计感无袖马甲 | D46: 黑色;M(100-120斤);15天内发货 | E46: 1 | F46: 3767004410471907465 | G46: Z1640-黑色-M | H46: 289 | I46: 274.3 | J46: 0 | K46: 14.7 | L46: 平台七夕消费券-14.70 | M46: - | N46: - | O46: 0 | P46: 0 | Q46: 0 | R46: 抖音月付 | S46: 0 | T46: *** | U46: *** | V46: 安徽省 | W46: 安庆市 | X46: 宜秀区 | Y46: 菱北街道 | Z46: *** | AA46: 否 | AC46: 2025-08-27 15:34:06 | AD46: 灰色 | AF46: 2025-09-14 23:31:58 | AG46: 2025-08-27 15:34:12 | AH46: 抖音 | AI46: 精选联盟 | AJ46: 已完成 | AK46: 2025-09-11 15:34:13 | AL46: 普通订单 | AM46: 0 | AN46: 2353393836764088 | AO46: 老板周 | AP46: - | AQ46: - | AS46: - | AT46: - | AU46: - | AW46: 否 | AX46: 无 | AY46: 其他 | AZ46: 直播 | BA46: 直播推荐 | BB46: - | BC46: - | BD46: 2025-09-07 23:31:58 | BE46: 0 | BF46: 14.7 | BG46: 0 | BH46: 0 | BJ46: 否 | BP46: - | BQ46: - | BR46: -
A47: 6945579848162809517 | B47: 6945579848162809517 | C47: 【老板周】日系极简 春季新品圆领简约设计感无袖马甲 | D47: 黑色;M(100-120斤);15天内发货 | E47: 1 | F47: 3767004410471907465 | G47: Z1640-黑色-M | H47: 289 | I47: 261 | J47: 0 | K47: 28 | L47: 平台商城爆神券-28.00 | M47: - | N47: - | O47: 0 | P47: 0 | Q47: 0 | R47: 抖音月付 | S47: 0 | T47: *** | U47: *** | V47: 天津市 | W47: 天津市 | X47: 河北区 | Y47: 建昌道街道 | Z47: *** | AA47: 否 | AC47: 2025-08-27 12:05:08 | AD47: 灰色 | AG47: 2025-08-27 12:05:09 | AH47: 抖音 | AI47: 小店自卖 | AJ47: 已关闭 | AK47: 2025-09-11 12:05:09 | AL47: 普通订单 | AM47: 0 | AN47: 0 | AP47: - | AQ47: 退款成功 | AS47: - | AT47: - | AU47: - | AW47: 否 | AX47: 无 | AY47: 其他 | AZ47: 商品卡 | BA47: 其他 | BB47: - | BC47: - | BE47: 0 | BF47: 28 | BG47: 0 | BH47: 0 | BJ47: 否 | BP47: - | BQ47: - | BR47: -
A48: 6945600144409499309 | B48: 6945600144409499309 | C48: 【老板周】日系极简 春季新品圆领简约设计感无袖马甲 | D48: 黑色;M(100-120斤);15天内发货 | E48: 1 | F48: 3767004410471907465 | G48: Z1640-黑色-M | H48: 289 | I48: 269 | J48: 0 | K48: 20 | L48: 平台商城爆神券-20.00 | M48: - | N48: - | O48: 0 | P48: 0 | Q48: 0 | R48: 抖音月付 | S48: 0 | T48: *** | U48: *** | V48: 天津市 | W48: 天津市 | X48: 河北区 | Y48: 建昌道街道 | Z48: *** | AA48: 否 | AC48: 2025-08-27 12:04:05 | AD48: 灰色 | AG48: 2025-08-27 12:04:07 | AH48: 抖音 | AI48: 小店自卖 | AJ48: 已关闭 | AK48: 2025-09-11 12:04:07 | AL48: 普通订单 | AM48: 0 | AN48: 0 | AP48: - | AQ48: 退款成功 | AS48: - | AT48: - | AU48: - | AW48: 否 | AX48: 无 | AY48: 其他 | AZ48: 商品卡 | BA48: 其他 | BB48: - | BC48: - | BE48: 0 | BF48: 20 | BG48: 0 | BH48: 0 | BJ48: 否 | BP48: - | BQ48: - | BR48: -
A49: 6920942457770770369 | B49: 6920942457770770369 | C49: 【老板周】日系极简 春季新品圆领简约设计感无袖马甲 | D49: 黑色;M(100-120斤);15天内发货 | E49: 1 | F49: 3767004410471907465 | G49: Z1640-黑色-M | H49: 289 | I49: 289 | J49: 0 | K49: 0 | L49: - | M49: - | N49: - | O49: 0 | P49: 0 | Q49: 0 | R49: 抖音支付 | S49: 0 | T49: *** | U49: *** | V49: 吉林省 | W49: 长春市 | X49: 宽城区 | Y49: 北湖街道 | Z49: *** | AA49: 是 | AC49: 2025-08-27 09:37:49 | AD49: 灰色 | AG49: 2025-08-27 09:37:52 | AH49: 抖音 | AI49: 小店自卖 | AJ49: 已关闭 | AK49: 2025-09-11 09:37:52 | AL49: 普通订单 | AM49: 0 | AN49: 0 | AP49: - | AQ49: 退款成功 | AS49: - | AT49: - | AU49: - | AW49: 否 | AX49: 无 | AY49: 其他 | AZ49: 商品卡 | BA49: 店铺页面 | BB49: - | BC49: - | BE49: 0 | BF49: 0 | BG49: 0 | BH49: 0 | BJ49: 否 | BP49: - | BQ49: - | BR49: -
A50: 6945586204071892038 | B50: 6945586204071892038 | C50: 【老板周】日系极简 春季新品圆领简约设计感无袖马甲 | D50: 黑色;M(100-120斤);15天内发货 | E50: 1 | F50: 3767004410471907465 | G50: Z1640-黑色-M | H50: 289 | I50: 289 | J50: 0 | K50: 0 | L50: - | M50: - | N50: - | O50: 0 | P50: 0 | Q50: 0 | R50: 抖音支付 | S50: 0 | T50: *** | U50: *** | V50: 四川省 | W50: 凉山彝族自治州 | X50: 西昌市 | Y50: 西城街道 | Z50: *** | AA50: 否 | AC50: 2025-08-27 00:48:22 | AD50: 灰色 | AG50: 2025-08-27 00:48:30 | AH50: 抖音 | AI50: 精选联盟 | AJ50: 已关闭 | AK50: 2025-09-11 00:48:30 | AL50: 普通订单 | AM50: 0 | AN50: 2353393836764088 | AO50: 老板周 | AP50: - | AQ50: 退款成功 | AS50: - | AT50: - | AU50: - | AW50: 否 | AX50: 无 | AY50: 其他 | AZ50: 商品卡 | BA50: 橱窗 | BB50: - | BC50: - | BE50: 0 | BF50: 0 | BG50: 0 | BH50: 0 | BJ50: 否 | BP50: - | BQ50: - | BR50: -
A51: 6945547648096343360 | B51: 6945547648096343360 | C51: 【老板周】日系极简 春季新品圆领简约设计感无袖马甲 | D51: 黑色;L(120-135斤);15天内发货 | E51: 1 | F51: 3767004410471907465 | G51: Z1640-黑色-L | H51: 289 | I51: 265.32 | J51: 0 | K51: 23.68 | L51: 平台七夕消费券-23.68 | M51: - | N51: - | O51: 0 | P51: 0 | Q51: 0 | R51: 抖音月付 | S51: 0 | T51: *** | U51: *** | V51: 山东省 | W51: 济南市 | X51: 市中区 | Y51: 魏家庄街道 | Z51: *** | AA51: 否 | AC51: 2025-08-26 16:11:45 | AD51: 蓝色 | AE51: 73570762450162(收） Z1576-黑色-L*1# | AG51: 2025-08-26 16:11:50 | AH51: 抖音 | AI51: 小店自卖 | AJ51: 已关闭 | AK51: 2025-09-10 16:11:51 | AL51: 普通订单 | AM51: 0 | AN51: 0 | AP51: - | AQ51: 退款成功 | AS51: - | AT51: - | AU51: - | AW51: 否 | AX51: 无 | AY51: 其他 | AZ51: 商品卡 | BA51: 购后页面 | BB51: - | BC51: - | BE51: 0 | BF51: 23.68 | BG51: 0 | BH51: 0 | BJ51: 否 | BP51: - | BQ51: - | BR51: -
A52: 6945547648096343360 | B52: 6945547648096408896 | C52: 【老板周】时髦撞色 春季新款假两件显瘦长袖打底T恤上衣 | D52: 黑色;L(120-135斤);15天内发货 | E52: 1 | F52: 3770648898645918626 | G52: Z1576-黑色-L | H52: 199 | I52: 182.68 | J52: 0 | K52: 16.32 | L52: 平台七夕消费券-16.32 | M52: - | N52: - | O52: 0 | P52: 0 | Q52: 0 | R52: 抖音月付 | S52: 0 | T52: *** | U52: *** | V52: 山东省 | W52: 济南市 | X52: 市中区 | Y52: 魏家庄街道 | Z52: *** | AA52: 否 | AC52: 2025-08-26 16:11:45 | AD52: 蓝色 | AE52: 73570762450162(收） Z1576-黑色-L*1# | AG52: 2025-08-26 16:11:50 | AH52: 抖音 | AI52: 小店自卖 | AJ52: 已关闭 | AK52: 2025-09-10 16:11:51 | AL52: 普通订单 | AM52: 0 | AN52: 0 | AP52: - | AQ52: 退款成功 | AS52: - | AT52: - | AU52: - | AW52: 否 | AX52: 无 | AY52: 其他 | AZ52: 商品卡 | BA52: 购后页面 | BB52: - | BC52: - | BD52: 2025-08-31 23:42:42 | BE52: 0 | BF52: 16.32 | BG52: 0 | BH52: 0 | BJ52: 否 | BP52: - | BQ52: - | BR52: -
A53: 6945550015473390912 | B53: 6945550015473390912 | C53: 【老板周】时髦撞色 春季新款假两件显瘦长袖打底T恤上衣 | D53: 黑色;L(120-135斤);15天内发货 | E53: 1 | F53: 3770648898645918626 | G53: Z1576-黑色-L | H53: 199 | I53: 182.69 | J53: 0 | K53: 16.31 | L53: 平台七夕消费券-16.31 | M53: - | N53: - | O53: 0 | P53: 0 | Q53: 0 | R53: 抖音月付 | S53: 0 | T53: *** | U53: *** | V53: 山东省 | W53: 济南市 | X53: 市中区 | Y53: 魏家庄街道 | Z53: *** | AA53: 否 | AC53: 2025-08-26 16:04:55 | AD53: 灰色 | AH53: 抖音 | AI53: 精选联盟 | AJ53: 已关闭 | AK53: 2025-09-10 16:04:55 | AL53: 普通订单 | AM53: 0 | AN53: 2353393836764088 | AO53: 老板周 | AP53: - | AQ53: - | AR53: 你已取消订单：价格有点贵 | AS53: - | AT53: - | AU53: - | AW53: 否 | AX53: 无 | AY53: 其他 | AZ53: 直播 | BA53: 直播推荐 | BB53: - | BC53: - | BE53: 0 | BF53: 16.31 | BG53: 0 | BH53: 0 | BJ53: 否 | BP53: - | BQ53: - | BR53: -
A54: 6945550015473390912 | B54: 6945550015473456448 | C54: 【老板周】日系极简 春季新品圆领简约设计感无袖马甲 | D54: 黑色;L(120-135斤);15天内发货 | E54: 1 | F54: 3767004410471907465 | G54: Z1640-黑色-L | H54: 289 | I54: 265.31 | J54: 0 | K54: 23.69 | L54: 平台七夕消费券-23.69 | M54: - | N54: - | O54: 0 | P54: 0 | Q54: 0 | R54: 抖音月付 | S54: 0 | T54: *** | U54: *** | V54: 山东省 | W54: 济南市 | X54: 市中区 | Y54: 魏家庄街道 | Z54: *** | AA54: 否 | AC54: 2025-08-26 16:04:55 | AD54: 灰色 | AH54: 抖音 | AI54: 精选联盟 | AJ54: 已关闭 | AK54: 2025-09-10 16:04:55 | AL54: 普通订单 | AM54: 0 | AN54: 2353393836764088 | AO54: 老板周 | AP54: - | AQ54: - | AR54: 你已取消订单：价格有点贵 | AS54: - | AT54: - | AU54: - | AW54: 否 | AX54: 无 | AY54: 其他 | AZ54: 直播 | BA54: 直播推荐 | BB54: - | BC54: - | BE54: 0 | BF54: 23.69 | BG54: 0 | BH54: 0 | BJ54: 否 | BP54: - | BQ54: - | BR54: -
A55: 6920932842713087724 | B55: 6920932842713087724 | C55: 【老板周】时髦撞色 春季新款假两件显瘦长袖打底T恤上衣 | D55: 黑色;S(80-100斤);15天内发货 | E55: 1 | F55: 3770648898645918626 | G55: Z1576-黑色-S | H55: 199 | I55: 184.73 | J55: 0 | K55: 14.78 | L55: 平台商城满减券-14.27 | M55: - | N55: - | O55: 0 | P55: 0.51 | Q55: 0 | R55: 抖音支付 | S55: 0 | T55: *** | U55: *** | V55: 黑龙江省 | W55: 哈尔滨市 | X55: 南岗区 | Y55: 先锋路街道 | Z55: *** | AA55: 否 | AC55: 2025-08-26 12:31:01 | AD55: 灰色 | AF55: 2025-09-06 21:47:17 | AG55: 2025-08-26 12:31:04 | AH55: 抖音 | AI55: 小店自卖 | AJ55: 已完成 | AK55: 2025-09-10 12:31:04 | AL55: 普通订单 | AM55: 0 | AN55: 0 | AP55: - | AQ55: - | AS55: - | AT55: - | AU55: - | AW55: 否 | AX55: 无 | AY55: 其他 | AZ55: 商品卡 | BA55: 搜索 | BB55: - | BC55: - | BD55: 2025-08-30 21:47:17 | BE55: 0 | BF55: 14.27 | BG55: 0 | BH55: 0 | BJ55: 否 | BP55: - | BQ55: - | BR55: -
A56: 6920932842713087724 | B56: 6920932842713153260 | C56: 【老板周】日系极简 春季新品圆领简约设计感无袖马甲 | D56: 黑色;S(80-100斤);15天内发货 | E56: 1 | F56: 3767004410471907465 | G56: Z1640-黑色-S | H56: 289 | I56: 268.27 | J56: 0 | K56: 21.46 | L56: 平台商城满减券-20.73 | M56: - | N56: - | O56: 0 | P56: 0.73 | Q56: 0 | R56: 抖音支付 | S56: 0 | T56: *** | U56: *** | V56: 黑龙江省 | W56: 哈尔滨市 | X56: 南岗区 | Y56: 先锋路街道 | Z56: *** | AA56: 否 | AC56: 2025-08-26 12:31:01 | AD56: 灰色 | AF56: 2025-09-17 15:51:38 | AG56: 2025-08-26 12:31:04 | AH56: 抖音 | AI56: 小店自卖 | AJ56: 已完成 | AK56: 2025-09-10 12:31:04 | AL56: 普通订单 | AM56: 0 | AN56: 0 | AP56: - | AQ56: - | AS56: - | AT56: - | AU56: - | AW56: 否 | AX56: 无 | AY56: 其他 | AZ56: 商品卡 | BA56: 搜索 | BB56: - | BC56: - | BD56: 2025-09-05 15:51:38 | BE56: 0 | BF56: 20.73 | BG56: 0 | BH56: 0 | BJ56: 否 | BP56: - | BQ56: - | BR56: -
A57: 6945569726276310761 | B57: 6945569726276310761 | C57: 【老板周】日系极简 春季新品圆领简约设计感无袖马甲 | D57: 黑色;M(100-120斤);15天内发货 | E57: 1 | F57: 3767004410471907465 | G57: Z1640-黑色-M | H57: 289 | I57: 250.82 | J57: 0 | K57: 38.18 | L57: 平台七夕消费券-38.18 | M57: - | N57: - | O57: 0 | P57: 0 | Q57: 0 | R57: 抖音月付 | S57: 0 | T57: *** | U57: *** | V57: 湖北省 | W57: 武汉市 | X57: 洪山区 | Y57: 关山街道 | Z57: *** | AA57: 否 | AC57: 2025-08-26 12:22:42 | AD57: 灰色 | AF57: 2025-09-09 19:26:40 | AG57: 2025-08-26 12:22:45 | AH57: 抖音 | AI57: 精选联盟 | AJ57: 已完成 | AK57: 2025-09-10 12:22:46 | AL57: 普通订单 | AM57: 0 | AN57: 2353393836764088 | AO57: 老板周 | AP57: - | AQ57: - | AS57: - | AT57: - | AU57: - | AW57: 否 | AX57: 无 | AY57: 其他 | AZ57: 直播 | BA57: 直播推荐 | BB57: - | BC57: - | BD57: 2025-09-05 20:29:09 | BE57: 0 | BF57: 38.18 | BG57: 0 | BH57: 0 | BJ57: 否 | BP57: - | BQ57: - | BR57: -
A58: 6920928532274839276 | B58: 6920928532274839276 | C58: 【老板周】日系极简 春季新品圆领简约设计感无袖马甲 | D58: 黑色;S(80-100斤);15天内发货 | E58: 1 | F58: 3767004410471907465 | G58: Z1640-黑色-S | H58: 289 | I58: 268.28 | J58: 0 | K58: 21.48 | L58: 平台商城满减券-20.72 | M58: - | N58: - | O58: 0 | P58: 0.76 | Q58: 0 | R58: 抖音支付 | S58: 0 | T58: *** | U58: *** | V58: 黑龙江省 | W58: 哈尔滨市 | X58: 南岗区 | Y58: 先锋路街道 | Z58: *** | AA58: 否 | AC58: 2025-08-26 12:10:21 | AD58: 灰色 | AG58: 2025-08-26 12:10:23 | AH58: 抖音 | AI58: 精选联盟 | AJ58: 已关闭 | AK58: 2025-09-10 12:10:24 | AL58: 普通订单 | AM58: 0 | AN58: 2353393836764088 | AO58: 老板周 | AP58: - | AQ58: 退款成功 | AS58: - | AT58: - | AU58: - | AW58: 否 | AX58: 无 | AY58: 其他 | AZ58: 商品卡 | BA58: 橱窗 | BB58: - | BC58: - | BE58: 0 | BF58: 20.72 | BG58: 0 | BH58: 0 | BJ58: 否 | BP58: - | BQ58: - | BR58: -
A59: 6920928532274839276 | B59: 6920928532274904812 | C59: 【老板周】时髦撞色 春季新款假两件显瘦长袖打底T恤上衣 | D59: 黑色;S(80-100斤);15天内发货 | E59: 1 | F59: 3770648898645918626 | G59: Z1576-黑色-S | H59: 199 | I59: 184.72 | J59: 0 | K59: 14.81 | L59: 平台商城满减券-14.28 | M59: - | N59: - | O59: 0 | P59: 0.53 | Q59: 0 | R59: 抖音支付 | S59: 0 | T59: *** | U59: *** | V59: 黑龙江省 | W59: 哈尔滨市 | X59: 南岗区 | Y59: 先锋路街道 | Z59: *** | AA59: 否 | AC59: 2025-08-26 12:10:21 | AD59: 灰色 | AG59: 2025-08-26 12:10:23 | AH59: 抖音 | AI59: 精选联盟 | AJ59: 已关闭 | AK59: 2025-09-10 12:10:24 | AL59: 普通订单 | AM59: 0 | AN59: 2353393836764088 | AO59: 老板周 | AP59: - | AQ59: 退款成功 | AS59: - | AT59: - | AU59: - | AW59: 否 | AX59: 无 | AY59: 其他 | AZ59: 直播 | BA59: 商城推荐 | BB59: - | BC59: - | BE59: 0 | BF59: 14.28 | BG59: 0 | BH59: 0 | BJ59: 否 | BP59: - | BQ59: - | BR59: -
A60: 6945529053386118931 | B60: 6945529053386118931 | C60: 【老板周】日系极简 春季新品圆领简约设计感无袖马甲 | D60: 黑色;M(100-120斤);15天内发货 | E60: 1 | F60: 3767004410471907465 | G60: Z1640-黑色-M | H60: 289 | I60: 260.96 | J60: 0 | K60: 28.04 | L60: 平台七夕消费券-28.04 | M60: - | N60: - | O60: 0 | P60: 0 | Q60: 0 | R60: 抖音支付 | S60: 0 | T60: *** | U60: *** | V60: 北京市 | W60: 北京市 | X60: 朝阳区 | Y60: 和平街街道 | Z60: *** | AA60: 否 | AC60: 2025-08-25 23:06:06 | AD60: 灰色 | AF60: 2025-09-11 23:19:44 | AG60: 2025-08-25 23:06:10 | AH60: 抖音 | AI60: 精选联盟 | AJ60: 已完成 | AK60: 2025-09-09 23:06:11 | AL60: 普通订单 | AM60: 0 | AN60: 2353393836764088 | AO60: 老板周 | AP60: - | AQ60: - | AS60: - | AT60: - | AU60: - | AW60: 否 | AX60: 无 | AY60: 其他 | AZ60: 直播 | BA60: 关注来源 | BB60: - | BC60: - | BD60: 2025-09-04 23:19:44 | BE60: 0 | BF60: 28.04 | BG60: 0 | BH60: 0 | BJ60: 否 | BP60: - | BQ60: - | BR60: -
A61: 6945548577267651706 | B61: 6945548577267651706 | C61: 【老板周】日系极简 春季新品圆领简约设计感无袖马甲 | D61: 黑色;M(100-120斤);15天内发货 | E61: 1 | F61: 3767004410471907465 | G61: Z1640-黑色-M | H61: 289 | I61: 289 | J61: 0 | K61: 0 | L61: - | M61: - | N61: - | O61: 0 | P61: 0 | Q61: 0 | R61: 抖音月付 | S61: 0 | T61: *** | U61: *** | V61: 云南省 | W61: 昆明市 | X61: 官渡区 | Y61: 矣六街道 | Z61: *** | AA61: 否 | AC61: 2025-08-25 22:18:24 | AD61: 灰色 | AF61: 2025-09-11 23:19:44 | AG61: 2025-08-25 22:18:29 | AH61: 抖音 | AI61: 精选联盟 | AJ61: 已完成 | AK61: 2025-09-09 22:18:29 | AL61: 普通订单 | AM61: 0 | AN61: 2353393836764088 | AO61: 老板周 | AP61: - | AQ61: - | AS61: - | AT61: - | AU61: - | AW61: 否 | AX61: 无 | AY61: 其他 | AZ61: 直播 | BA61: 直播推荐 | BB61: - | BC61: - | BD61: 2025-09-04 23:19:44 | BE61: 0 | BF61: 0 | BG61: 0 | BH61: 0 | BJ61: 否 | BP61: - | BQ61: - | BR61: -
A62: 6945543583900899197 | B62: 6945543583900899197 | C62: 【老板周】日系极简 春季新品圆领简约设计感无袖马甲 | D62: 黑色;S(80-100斤);15天内发货 | E62: 1 | F62: 3767004410471907465 | G62: Z1640-黑色-S | H62: 289 | I62: 260.66 | J62: 0 | K62: 28.34 | L62: 平台七夕消费券-28.34 | M62: - | N62: - | O62: 0 | P62: 0 | Q62: 0 | R62: 抖音月付 | S62: 0 | T62: *** | U62: *** | V62: 山东省 | W62: 潍坊市 | X62: 寿光市 | Y62: 稻田镇 | Z62: *** | AA62: 否 | AC62: 2025-08-25 22:04:55 | AD62: 灰色 | AG62: 2025-08-25 22:04:59 | AH62: 抖音 | AI62: 精选联盟 | AJ62: 已关闭 | AK62: 2025-09-09 22:04:59 | AL62: 普通订单 | AM62: 0 | AN62: 2353393836764088 | AO62: 老板周 | AP62: - | AQ62: 退款成功 | AS62: - | AT62: - | AU62: - | AW62: 否 | AX62: 直播 | AY62: 广告 | AZ62: 直播 | BA62: 商城推荐 | BB62: - | BC62: - | BE62: 0 | BF62: 28.34 | BG62: 0 | BH62: 0 | BJ62: 否 | BP62: - | BQ62: - | BR62: -
A63: 6920929009547574969 | B63: 6920929009547574969 | C63: 【老板周】日系极简 春季新品圆领简约设计感无袖马甲 | D63: 黑色;M(100-120斤);15天内发货 | E63: 1 | F63: 3767004410471907465 | G63: Z1640-黑色-M | H63: 289 | I63: 289 | J63: 0 | K63: 0 | L63: - | M63: - | N63: - | O63: 0 | P63: 0 | Q63: 0 | R63: 抖音月付 | S63: 0 | T63: *** | U63: *** | V63: 辽宁省 | W63: 沈阳市 | X63: 皇姑区 | Y63: 明廉街道 | Z63: *** | AA63: 否 | AC63: 2025-08-25 22:02:22 | AD63: 灰色 | AF63: 2025-09-07 19:43:29 | AG63: 2025-08-25 22:02:24 | AH63: 抖音 | AI63: 精选联盟 | AJ63: 已完成 | AK63: 2025-09-09 22:02:24 | AL63: 普通订单 | AM63: 0 | AN63: 2353393836764088 | AO63: 老板周 | AP63: - | AQ63: - | AS63: - | AT63: - | AU63: - | AW63: 否 | AX63: 无 | AY63: 其他 | AZ63: 直播 | BA63: 短视频引流直播间 | BB63: - | BC63: - | BD63: 2025-09-04 23:19:45 | BE63: 0 | BF63: 0 | BG63: 0 | BH63: 0 | BJ63: 否 | BP63: - | BQ63: - | BR63: -
A64: 6920935968749813406 | B64: 6920935968749813406 | C64: 【老板周】日系极简 春季新品圆领简约设计感无袖马甲 | D64: 黑色;L(120-135斤);15天内发货 | E64: 1 | F64: 3767004410471907465 | G64: Z1640-黑色-L | H64: 289 | I64: 289 | J64: 0 | K64: 0 | L64: - | M64: - | N64: - | O64: 0 | P64: 0 | Q64: 0 | R64: 抖音月付 | S64: 0 | T64: *** | U64: *** | V64: 湖南省 | W64: 岳阳市 | X64: 平江县 | Y64: 汉昌街道 | Z64: *** | AA64: 否 | AC64: 2025-08-25 21:33:22 | AD64: 灰色 | AF64: 2025-09-08 23:13:48 | AG64: 2025-08-25 21:33:25 | AH64: 抖音 | AI64: 精选联盟 | AJ64: 已完成 | AK64: 2025-09-09 21:33:26 | AL64: 普通订单 | AM64: 0 | AN64: 2353393836764088 | AO64: 老板周 | AP64: - | AQ64: - | AS64: - | AT64: - | AU64: - | AW64: 否 | AX64: 无 | AY64: 其他 | AZ64: 直播 | BA64: 直播推荐 | BB64: - | BC64: - | BD64: 2025-09-01 23:13:48 | BE64: 0 | BF64: 0 | BG64: 0 | BH64: 0 | BJ64: 否 | BP64: - | BQ64: - | BR64: -
A65: 6920923676778724668 | B65: 6920923676778724668 | C65: 【老板周】日系极简 春季新品圆领简约设计感无袖马甲 | D65: 黑色;L(120-135斤);15天内发货 | E65: 1 | F65: 3767004410471907465 | G65: Z1640-黑色-L | H65: 289 | I65: 289 | J65: 0 | K65: 0 | L65: - | M65: - | N65: - | O65: 0 | P65: 0 | Q65: 0 | R65: 抖音支付 | S65: 0 | T65: *** | U65: *** | V65: 四川省 | W65: 内江市 | X65: 威远县 | Y65: 严陵镇 | Z65: *** | AA65: 否 | AC65: 2025-08-25 18:11:22 | AD65: 灰色 | AH65: 抖音极速版 | AI65: 精选联盟 | AJ65: 已关闭 | AK65: 2025-09-09 18:11:22 | AL65: 普通订单 | AM65: 0 | AN65: 2353393836764088 | AO65: 老板周 | AP65: - | AQ65: - | AR65: 你已取消订单：暂时不需要这个商品 | AS65: - | AT65: - | AU65: - | AW65: 否 | AX65: 直播 | AY65: 广告 | AZ65: 直播 | BA65: 个人主页&店铺&橱窗进入直播间 | BB65: - | BC65: - | BE65: 0 | BF65: 0 | BG65: 0 | BH65: 0 | BJ65: 否 | BP65: - | BQ65: - | BR65: -
A66: 6945514875424281953 | B66: 6945514875424281953 | C66: 【老板周】日系极简 春季新品圆领简约设计感无袖马甲 | D66: 黑色;M(100-120斤);15天内发货 | E66: 1 | F66: 3767004410471907465 | G66: Z1640-黑色-M | H66: 289 | I66: 289 | J66: 0 | K66: 0 | L66: - | M66: - | N66: - | O66: 0 | P66: 0 | Q66: 0 | R66: 抖音月付 | S66: 0 | T66: *** | U66: *** | V66: 四川省 | W66: 成都市 | X66: 锦江区 | Y66: 双桂路街道 | Z66: *** | AA66: 否 | AC66: 2025-08-25 17:52:19 | AD66: 灰色 | AG66: 2025-08-25 17:52:21 | AH66: 抖音 | AI66: 精选联盟 | AJ66: 已关闭 | AK66: 2025-09-09 17:52:22 | AL66: 普通订单 | AM66: 0 | AN66: 2353393836764088 | AO66: 老板周 | AP66: - | AQ66: 退款成功 | AS66: - | AT66: - | AU66: - | AW66: 否 | AX66: 无 | AY66: 其他 | AZ66: 直播 | BA66: 直播推荐 | BB66: - | BC66: - | BE66: 0 | BF66: 0 | BG66: 0 | BH66: 0 | BJ66: 否 | BP66: - | BQ66: - | BR66: -
A67: 6945539203760789124 | B67: 6945539203760789124 | C67: 【老板周】日系极简 春季新品圆领简约设计感无袖马甲 | D67: 黑色;L(120-135斤);15天内发货 | E67: 1 | F67: 3767004410471907465 | G67: Z1640-黑色-L | H67: 289 | I67: 289 | J67: 0 | K67: 0 | L67: - | M67: - | N67: - | O67: 0 | P67: 0 | Q67: 0 | R67: 支付宝 | S67: 0 | T67: *** | U67: *** | V67: 陕西省 | W67: 榆林市 | X67: 榆阳区 | Y67: 上郡路街道 | Z67: *** | AA67: 否 | AC67: 2025-08-25 17:29:18 | AD67: 灰色 | AH67: 抖音极速版 | AI67: 精选联盟 | AJ67: 已关闭 | AK67: 2025-09-09 17:29:18 | AL67: 普通订单 | AM67: 0 | AN67: 2353393836764088 | AO67: 老板周 | AP67: - | AQ67: - | AR67: 用户超时未支付自动取消 | AS67: - | AT67: - | AU67: - | AW67: 否 | AX67: 直播 | AY67: 广告 | AZ67: 直播 | BA67: 直播推荐 | BB67: - | BC67: - | BE67: 0 | BF67: 0 | BG67: 0 | BH67: 0 | BJ67: 否 | BP67: - | BQ67: - | BR67: -
A68: 6918363477932670688 | B68: 6918363477932670688 | C68: 【老板周】日系极简 春季新品圆领简约设计感无袖马甲 | D68: 黑色;M(100-120斤);15天内发货 | E68: 1 | F68: 3767004410471907465 | G68: Z1640-黑色-M | H68: 289 | I68: 263.76 | J68: 0 | K68: 25.24 | L68: 平台七夕消费券-25.24 | M68: - | N68: - | O68: 0 | P68: 0 | Q68: 0 | R68: 支付宝 | S68: 0 | T68: *** | U68: *** | V68: 黑龙江省 | W68: 绥化市 | X68: 安达市 | Y68: 安达镇 | Z68: *** | AA68: 否 | AC68: 2025-08-25 16:26:10 | AD68: 灰色 | AG68: 2025-08-25 16:26:15 | AH68: 抖音极速版 | AI68: 精选联盟 | AJ68: 已关闭 | AK68: 2025-09-09 16:26:16 | AL68: 普通订单 | AM68: 0 | AN68: 2353393836764088 | AO68: 老板周 | AP68: - | AQ68: 退款成功 | AS68: - | AT68: - | AU68: - | AW68: 否 | AX68: 直播 | AY68: 广告 | AZ68: 直播 | BA68: 关注来源 | BB68: - | BC68: - | BE68: 0 | BF68: 25.24 | BG68: 0 | BH68: 0 | BJ68: 否 | BP68: - | BQ68: - | BR68: -
A69: 6920925448404893520 | B69: 6920925448404893520 | C69: 【老板周】日系极简 春季新品圆领简约设计感无袖马甲 | D69: 黑色;S(80-100斤);15天内发货 | E69: 1 | F69: 3767004410471907465 | G69: Z1640-黑色-S | H69: 289 | I69: 289 | J69: 0 | K69: 0 | L69: - | M69: - | N69: - | O69: 0 | P69: 0 | Q69: 0 | R69: 支付宝 | S69: 0 | T69: *** | U69: *** | V69: 四川省 | W69: 成都市 | X69: 新津区 | Y69: 花源街道 | Z69: *** | AA69: 否 | AC69: 2025-08-25 16:13:31 | AD69: 灰色 | AF69: 2025-09-11 23:24:57 | AG69: 2025-08-25 16:14:00 | AH69: 抖音 | AI69: 精选联盟 | AJ69: 已完成 | AK69: 2025-09-09 16:14:01 | AL69: 普通订单 | AM69: 0 | AN69: 2353393836764088 | AO69: 老板周 | AP69: - | AQ69: - | AS69: - | AT69: - | AU69: - | AW69: 否 | AX69: 无 | AY69: 其他 | AZ69: 直播 | BA69: 直播推荐 | BB69: - | BC69: - | BD69: 2025-09-04 23:24:57 | BE69: 0 | BF69: 0 | BG69: 0 | BH69: 0 | BJ69: 否 | BP69: - | BQ69: - | BR69: -
A70: 6945539142283629576 | B70: 6945539142283629576 | C70: 【老板周】日系极简 春季新品圆领简约设计感无袖马甲 | D70: 黑色;L(120-135斤);15天内发货 | E70: 1 | F70: 3767004410471907465 | G70: Z1640-黑色-L | H70: 289 | I70: 260.1 | J70: 0 | K70: 28.9 | L70: 平台七夕消费券-28.90 | M70: - | N70: - | O70: 0 | P70: 0 | Q70: 0 | R70: 抖音月付 | S70: 0 | T70: *** | U70: *** | V70: 天津市 | W70: 天津市 | X70: 北辰区 | Y70: 双街镇 | Z70: *** | AA70: 否 | AC70: 2025-08-25 15:56:19 | AD70: 灰色 | AG70: 2025-08-25 15:56:27 | AH70: 抖音 | AI70: 精选联盟 | AJ70: 已关闭 | AK70: 2025-09-09 15:56:28 | AL70: 普通订单 | AM70: 0 | AN70: 2353393836764088 | AO70: 老板周 | AP70: - | AQ70: 退款成功 | AS70: - | AT70: - | AU70: - | AW70: 否 | AX70: 无 | AY70: 其他 | AZ70: 商品卡 | BA70: 橱窗 | BB70: - | BC70: - | BE70: 0 | BF70: 28.9 | BG70: 0 | BH70: 0 | BJ70: 否 | BP70: - | BQ70: - | BR70: -
A71: 6945511996582664089 | B71: 6945511996582664089 | C71: 【老板周】时髦撞色 春季新款假两件显瘦长袖打底T恤上衣 | D71: 黑色;L(120-135斤);15天内发货 | E71: 1 | F71: 3770648898645918626 | G71: Z1576-黑色-L | H71: 199 | I71: 194 | J71: 0 | K71: 8 | L71: 平台商城报销返券-5.00 | M71: - | N71: - | O71: 0 | P71: 3 | Q71: 0 | R71: 抖音月付 | S71: 0 | T71: *** | U71: *** | V71: 北京市 | W71: 北京市 | X71: 朝阳区 | Y71: 东坝地区 | Z71: *** | AA71: 否 | AC71: 2025-08-25 12:02:03 | AD71: 蓝色 | AE71: SF3237506934842(收） Z1576-黑色-L*1# | AG71: 2025-08-25 12:02:05 | AH71: 抖音 | AI71: 小店自卖 | AJ71: 已关闭 | AK71: 2025-09-09 12:02:05 | AL71: 普通订单 | AM71: 0 | AN71: 0 | AP71: - | AQ71: 退款成功 | AS71: - | AT71: - | AU71: - | AW71: 否 | AX71: 无 | AY71: 其他 | AZ71: 商品卡 | BA71: 购后页面 | BB71: - | BC71: - | BD71: 2025-08-31 22:00:10 | BE71: 0 | BF71: 5 | BG71: 0 | BH71: 0 | BJ71: 否 | BP71: - | BQ71: - | BR71: -
A72: 6945518268966573163 | B72: 6945518268966573163 | C72: 【老板周】日系极简 春季新品圆领简约设计感无袖马甲 | D72: 黑色;L(120-135斤);15天内发货 | E72: 1 | F72: 3767004410471907465 | G72: Z1640-黑色-L | H72: 289 | I72: 289 | J72: 0 | K72: 0 | L72: - | M72: - | N72: - | O72: 0 | P72: 0 | Q72: 0 | R72: 抖音支付 | S72: 0 | T72: *** | U72: *** | V72: 吉林省 | W72: 吉林市 | X72: 昌邑区 | Y72: 通江街道 | Z72: *** | AA72: 否 | AC72: 2025-08-25 05:34:24 | AD72: 灰色 | AH72: 抖音极速版 | AI72: 精选联盟 | AJ72: 已关闭 | AK72: 2025-09-09 05:34:24 | AL72: 普通订单 | AM72: 0 | AN72: 2353393836764088 | AO72: 老板周 | AP72: - | AQ72: - | AR72: 你已取消订单：商品规格/款式/数量错选 | AS72: - | AT72: - | AU72: - | AW72: 否 | AX72: 无 | AY72: 其他 | AZ72: 商品卡 | BA72: 橱窗 | BB72: - | BC72: - | BE72: 0 | BF72: 0 | BG72: 0 | BH72: 0 | BJ72: 否 | BP72: - | BQ72: - | BR72: -
A73: 6945515811466254054 | B73: 6945515811466254054 | C73: 【老板周】时髦撞色 春季新款假两件显瘦长袖打底T恤上衣 | D73: 黑色;M(100-120斤);15天内发货 | E73: 1 | F73: 3770648898645918626 | G73: Z1576-黑色-M | H73: 199 | I73: 179.25 | J73: 0 | K73: 19.75 | L73: 平台七夕消费券-19.75 | M73: - | N73: - | O73: 0 | P73: 0 | Q73: 0 | R73: 抖音月付 | S73: 0 | T73: *** | U73: *** | V73: 甘肃省 | W73: 平凉市 | X73: 静宁县 | Y73: 城区街道 | Z73: *** | AA73: 否 | AC73: 2025-08-24 22:33:07 | AD73: 灰色 | AG73: 2025-08-24 22:33:12 | AH73: 抖音极速版 | AI73: 小店自卖 | AJ73: 已关闭 | AK73: 2025-09-08 22:33:12 | AL73: 普通订单 | AM73: 0 | AN73: 0 | AP73: - | AQ73: 退款成功 | AS73: - | AT73: - | AU73: - | AW73: 否 | AX73: 无 | AY73: 其他 | AZ73: 商品卡 | BA73: 频道及活动页面 | BB73: - | BC73: - | BE73: 0 | BF73: 19.75 | BG73: 0 | BH73: 0 | BJ73: 否 | BP73: - | BQ73: - | BR73: -
A74: 6945513256170493793 | B74: 6945513256170493793 | C74: 【老板周】时髦撞色 春季新款假两件显瘦长袖打底T恤上衣 | D74: 黑色;M(100-120斤);15天内发货 | E74: 1 | F74: 3770648898645918626 | G74: Z1576-黑色-M | H74: 199 | I74: 199 | J74: 0 | K74: 0 | L74: - | M74: - | N74: - | O74: 0 | P74: 0 | Q74: 0 | R74: 抖音月付 | S74: 0 | T74: *** | U74: *** | V74: 云南省 | W74: 昭通市 | X74: 昭阳区 | Y74: 凤凰街道 | Z74: *** | AA74: 否 | AC74: 2025-08-24 20:06:58 | AD74: 灰色 | AF74: 2025-09-07 23:42:42 | AG74: 2025-08-24 20:07:04 | AH74: 抖音 | AI74: 精选联盟 | AJ74: 已完成 | AK74: 2025-09-08 20:07:04 | AL74: 普通订单 | AM74: 0 | AN74: 2353393836764088 | AO74: 老板周 | AP74: - | AQ74: - | AS74: - | AT74: - | AU74: - | AW74: 否 | AX74: 无 | AY74: 其他 | AZ74: 直播 | BA74: 商城推荐 | BB74: - | BC74: - | BD74: 2025-08-31 23:42:42 | BE74: 0 | BF74: 0 | BG74: 0 | BH74: 0 | BJ74: 否 | BP74: - | BQ74: - | BR74: -
A75: 6945504197030777878 | B75: 6945504197030777878 | C75: 【老板周】时髦撞色 春季新款假两件显瘦长袖打底T恤上衣 | D75: 黑色;S(80-100斤);15天内发货 | E75: 1 | F75: 3770648898645918626 | G75: Z1576-黑色-S | H75: 199 | I75: 199 | J75: 0 | K75: 0.84 | L75: - | M75: - | N75: - | O75: 0 | P75: 0.84 | Q75: 0 | R75: 抖音支付 | S75: 0 | T75: *** | U75: *** | V75: 四川省 | W75: 成都市 | X75: 锦江区 | Y75: 成龙路街道 | Z75: *** | AA75: 否 | AC75: 2025-08-24 17:27:14 | AD75: 灰色 | AF75: 2025-09-03 16:35:19 | AG75: 2025-08-24 17:27:30 | AH75: 抖音 | AI75: 精选联盟 | AJ75: 已完成 | AK75: 2025-09-08 17:27:31 | AL75: 普通订单 | AM75: 0 | AN75: 2353393836764088 | AO75: 老板周 | AP75: - | AQ75: - | AS75: - | AT75: - | AU75: - | AW75: 否 | AX75: 无 | AY75: 其他 | AZ75: 直播 | BA75: 直播推荐 | BB75: - | BC75: - | BD75: 2025-08-30 21:47:16 | BE75: 0 | BF75: 0 | BG75: 0 | BH75: 0 | BJ75: 否 | BP75: - | BQ75: - | BR75: -
A76: 6920902861000703125 | B76: 6920902861000703125 | C76: 【老板周】日系极简 春季新品圆领简约设计感无袖马甲 | D76: 黑色;L(120-135斤);15天内发货 | E76: 1 | F76: 3767004410471907465 | G76: Z1640-黑色-L | H76: 289 | I76: 289 | J76: 0 | K76: 0 | L76: - | M76: - | N76: - | O76: 0 | P76: 0 | Q76: 0 | R76: 支付宝 | S76: 0 | T76: *** | U76: *** | V76: 上海市 | W76: 上海市 | X76: 浦东新区 | Y76: 周浦镇 | Z76: *** | AA76: 否 | AC76: 2025-08-24 01:18:22 | AD76: 蓝色 | AE76: SF3284637255874(收） Z1640-黑色-L*1# | AG76: 2025-08-24 01:18:27 | AH76: 抖音 | AI76: 小店自卖 | AJ76: 已关闭 | AK76: 2025-09-08 01:18:28 | AL76: 普通订单 | AM76: 0 | AN76: 0 | AP76: - | AQ76: 退款成功 | AS76: - | AT76: - | AU76: - | AW76: 否 | AX76: 无 | AY76: 其他 | AZ76: 商品卡 | BA76: 购后页面 | BB76: - | BC76: - | BD76: 2025-08-31 23:39:54 | BE76: 0 | BF76: 0 | BG76: 0 | BH76: 0 | BJ76: 否 | BP76: - | BQ76: - | BR76: -
A77: 6920902023287176940 | B77: 6920902023287176940 | C77: 【老板周】日系极简 春季新品圆领简约设计感无袖马甲 | D77: 黑色;S(80-100斤);15天内发货 | E77: 1 | F77: 3767004410471907465 | G77: Z1640-黑色-S | H77: 289 | I77: 253.32 | J77: 0 | K77: 35.68 | L77: 平台七夕消费券-35.68 | M77: - | N77: - | O77: 0 | P77: 0 | Q77: 0 | R77: 抖音支付 | S77: 0 | T77: *** | U77: *** | V77: 黑龙江省 | W77: 哈尔滨市 | X77: 南岗区 | Y77: 先锋路街道 | Z77: *** | AA77: 否 | AC77: 2025-08-23 23:08:10 | AD77: 灰色 | AG77: 2025-08-23 23:08:26 | AH77: 抖音 | AI77: 精选联盟 | AJ77: 已关闭 | AK77: 2025-09-07 23:08:26 | AL77: 普通订单 | AM77: 0 | AN77: 2353393836764088 | AO77: 老板周 | AP77: - | AQ77: 退款成功 | AS77: - | AT77: - | AU77: - | AW77: 否 | AX77: 无 | AY77: 其他 | AZ77: 直播 | BA77: 搜索 | BB77: - | BC77: - | BE77: 0 | BF77: 35.68 | BG77: 0 | BH77: 0 | BJ77: 否 | BP77: - | BQ77: - | BR77: -
A78: 6920893032532966569 | B78: 6920893032532966569 | C78: 【老板周】日系极简 春季新品圆领简约设计感无袖马甲 | D78: 黑色;M(100-120斤);15天内发货 | E78: 1 | F78: 3767004410471907465 | G78: Z1640-黑色-M | H78: 289 | I78: 234 | J78: 0 | K78: 55 | L78: 金币抵扣金额-4.60;余额抵扣金额-50.40 | M78: - | N78: - | O78: 0 | P78: 0 | Q78: 0 | R78: 抖音支付 | S78: 0 | T78: *** | U78: *** | V78: 山东省 | W78: 青岛市 | X78: 市北区 | Y78: - | Z78: *** | AA78: 否 | AC78: 2025-08-23 22:21:10 | AD78: 灰色 | AG78: 2025-08-23 22:21:37 | AH78: 抖音极速版 | AI78: 精选联盟 | AJ78: 已关闭 | AK78: 2025-09-07 22:21:37 | AL78: 普通订单 | AM78: 0 | AN78: 2353393836764088 | AO78: 老板周 | AP78: - | AQ78: 退款成功 | AS78: - | AT78: - | AU78: - | AW78: 否 | AX78: 直播 | AY78: 广告 | AZ78: 直播 | BA78: 商城推荐 | BB78: - | BC78: - | BE78: 0 | BF78: 55 | BG78: 0 | BH78: 0 | BJ78: 否 | BP78: - | BQ78: - | BR78: -
A79: 6945478419003544648 | B79: 6945478419003544648 | C79: 【老板周】日系极简 春季新品圆领简约设计感无袖马甲 | D79: 黑色;M(100-120斤);15天内发货 | E79: 1 | F79: 3767004410471907465 | G79: Z1640-黑色-M | H79: 289 | I79: 289 | J79: 0 | K79: 0 | L79: - | M79: - | N79: - | O79: 0 | P79: 0 | Q79: 0 | R79: 抖音月付 | S79: 0 | T79: *** | U79: *** | V79: 江苏省 | W79: 南京市 | X79: 雨花台区 | Y79: 雨花街道 | Z79: *** | AA79: 否 | AC79: 2025-08-23 22:08:33 | AD79: 灰色 | AF79: 2025-09-09 19:52:48 | AG79: 2025-08-23 22:08:35 | AH79: 抖音 | AI79: 精选联盟 | AJ79: 已完成 | AK79: 2025-09-07 22:08:36 | AL79: 普通订单 | AM79: 0 | AN79: 2353393836764088 | AO79: 老板周 | AP79: - | AQ79: - | AS79: - | AT79: - | AU79: - | AW79: 否 | AX79: 无 | AY79: 其他 | AZ79: 直播 | BA79: 直播推荐 | BB79: - | BC79: - | BD79: 2025-09-02 19:52:48 | BE79: 0 | BF79: 0 | BG79: 0 | BH79: 0 | BJ79: 否 | BP79: - | BQ79: - | BR79: -
A80: 6920892838365920628 | B80: 6920892838365920628 | C80: 【老板周】日系极简 春季新品圆领简约设计感无袖马甲 | D80: 黑色;M(100-120斤);15天内发货 | E80: 1 | F80: 3767004410471907465 | G80: Z1640-黑色-M | H80: 289 | I80: 264.29 | J80: 0 | K80: 24.71 | L80: 平台七夕消费券-24.71 | M80: - | N80: - | O80: 0 | P80: 0 | Q80: 0 | R80: 抖音月付 | S80: 0 | T80: *** | U80: *** | V80: 内蒙古自治区 | W80: 包头市 | X80: 昆都仑区 | Y80: 白云路街道 | Z80: *** | AA80: 否 | AC80: 2025-08-23 21:48:56 | AD80: 灰色 | AG80: 2025-08-23 21:48:58 | AH80: 抖音极速版 | AI80: 精选联盟 | AJ80: 已关闭 | AK80: 2025-09-07 21:48:59 | AL80: 普通订单 | AM80: 0 | AN80: 2353393836764088 | AO80: 老板周 | AP80: - | AQ80: 退款成功 | AS80: - | AT80: - | AU80: - | AW80: 否 | AX80: 无 | AY80: 其他 | AZ80: 直播 | BA80: 频道及活动页面 | BB80: - | BC80: - | BE80: 0 | BF80: 24.71 | BG80: 0 | BH80: 0 | BJ80: 否 | BP80: - | BQ80: - | BR80: -
A81: 6918358695102807059 | B81: 6918358695102807059 | C81: 【老板周】时髦撞色 春季新款假两件显瘦长袖打底T恤上衣 | D81: 黑色;M(100-120斤);15天内发货 | E81: 1 | F81: 3770648898645918626 | G81: Z1576-黑色-M | H81: 199 | I81: 173.97 | J81: 0 | K81: 25.03 | L81: 平台七夕消费券-25.03 | M81: - | N81: - | O81: 0 | P81: 0 | Q81: 0 | R81: 抖音月付 | S81: 0 | T81: *** | U81: *** | V81: 湖南省 | W81: 常德市 | X81: 武陵区 | Y81: 德山街道 | Z81: *** | AA81: 否 | AC81: 2025-08-23 21:17:55 | AD81: 灰色 | AG81: 2025-08-23 21:17:58 | AH81: 抖音 | AI81: 精选联盟 | AJ81: 已关闭 | AK81: 2025-09-07 21:17:59 | AL81: 普通订单 | AM81: 0 | AN81: 2353393836764088 | AO81: 老板周 | AP81: - | AQ81: 退款成功 | AS81: - | AT81: - | AU81: - | AW81: 否 | AX81: 直播 | AY81: 广告 | AZ81: 直播 | BA81: 商城推荐 | BB81: - | BC81: - | BE81: 0 | BF81: 25.03 | BG81: 0 | BH81: 0 | BJ81: 否 | BP81: - | BQ81: - | BR81: -
A82: 6945467765155763766 | B82: 6945467765155763766 | C82: 【老板周】日系极简 春季新品圆领简约设计感无袖马甲 | D82: 黑色;M(100-120斤);15天内发货 | E82: 1 | F82: 3767004410471907465 | G82: Z1640-黑色-M | H82: 289 | I82: 259.05 | J82: 0 | K82: 29.95 | L82: 平台七夕消费券-29.95 | M82: - | N82: - | O82: 0 | P82: 0 | Q82: 0 | R82: 抖音月付 | S82: 0 | T82: *** | U82: *** | V82: 山东省 | W82: 济南市 | X82: 天桥区 | Y82: 北村街道 | Z82: *** | AA82: 否 | AC82: 2025-08-23 20:55:24 | AD82: 灰色 | AF82: 2025-09-09 15:25:39 | AG82: 2025-08-23 20:55:25 | AH82: 抖音 | AI82: 精选联盟 | AJ82: 已完成 | AK82: 2025-09-07 20:55:26 | AL82: 普通订单 | AM82: 0 | AN82: 2353393836764088 | AO82: 老板周 | AP82: - | AQ82: - | AS82: - | AT82: - | AU82: - | AW82: 否 | AX82: 无 | AY82: 其他 | AZ82: 直播 | BA82: 搜索 | BB82: - | BC82: - | BD82: 2025-09-02 15:25:39 | BE82: 0 | BF82: 29.95 | BG82: 0 | BH82: 0 | BJ82: 否 | BP82: - | BQ82: - | BR82: -
A83: 6920899223566450595 | B83: 6920899223566450595 | C83: 【老板周】日系极简 春季新品圆领简约设计感无袖马甲 | D83: 黑色;M(100-120斤);15天内发货 | E83: 1 | F83: 3767004410471907465 | G83: Z1640-黑色-M | H83: 289 | I83: 250.81 | J83: 0 | K83: 38.19 | L83: 平台七夕消费券-38.19 | M83: - | N83: - | O83: 0 | P83: 0 | Q83: 0 | R83: 抖音月付 | S83: 0 | T83: *** | U83: *** | V83: 吉林省 | W83: 长春市 | X83: 南关区 | Y83: 新立城镇 | Z83: *** | AA83: 否 | AC83: 2025-08-23 20:39:52 | AD83: 蓝色 | AE83: SF3237538166127(收） Z1640-黑色-M*1# | AG83: 2025-08-23 20:39:56 | AH83: 抖音 | AI83: 精选联盟 | AJ83: 已关闭 | AK83: 2025-09-07 20:39:56 | AL83: 普通订单 | AM83: 0 | AN83: 2353393836764088 | AO83: 老板周 | AP83: - | AQ83: 退款成功 | AS83: - | AT83: - | AU83: - | AW83: 否 | AX83: 无 | AY83: 其他 | AZ83: 直播 | BA83: 直播推荐 | BB83: - | BC83: - | BD83: 2025-09-01 23:14:20 | BE83: 0 | BF83: 38.19 | BG83: 0 | BH83: 0 | BJ83: 否 | BP83: - | BQ83: - | BR83: -
A84: 6945487810204669849 | B84: 6945487810204669849 | C84: 【老板周】日系极简 春季新品圆领简约设计感无袖马甲 | D84: 黑色;L(120-135斤);15天内发货 | E84: 1 | F84: 3767004410471907465 | G84: Z1640-黑色-L | H84: 289 | I84: 289 | J84: 0 | K84: 0 | L84: - | M84: - | N84: - | O84: 0 | P84: 0 | Q84: 0 | R84: 抖音月付 | S84: 0 | T84: *** | U84: *** | V84: 北京市 | W84: 北京市 | X84: 朝阳区 | Y84: 东坝地区 | Z84: *** | AA84: 否 | AC84: 2025-08-23 20:37:17 | AD84: 蓝色 | AE84: SF3237506934842(收） Z1640-黑色-L*1# | AG84: 2025-08-23 20:37:19 | AH84: 抖音 | AI84: 精选联盟 | AJ84: 已关闭 | AK84: 2025-09-07 20:37:20 | AL84: 普通订单 | AM84: 0 | AN84: 2353393836764088 | AO84: 老板周 | AP84: - | AQ84: 退款成功 | AS84: - | AT84: - | AU84: - | AW84: 否 | AX84: 无 | AY84: 其他 | AZ84: 直播 | BA84: 关注来源 | BB84: - | BC84: - | BD84: 2025-08-31 23:39:54 | BE84: 0 | BF84: 0 | BG84: 0 | BH84: 0 | BJ84: 否 | BP84: - | BQ84: - | BR84: -
A85: 6945485370033444761 | B85: 6945485370033444761 | C85: 【老板周】时髦撞色 春季新款假两件显瘦长袖打底T恤上衣 | D85: 黑色;L(120-135斤);15天内发货 | E85: 1 | F85: 3770648898645918626 | G85: Z1576-黑色-L | H85: 199 | I85: 199 | J85: 0 | K85: 0 | L85: - | M85: - | N85: - | O85: 0 | P85: 0 | Q85: 0 | R85: 抖音月付 | S85: 0 | T85: *** | U85: *** | V85: 北京市 | W85: 北京市 | X85: 朝阳区 | Y85: 东坝地区 | Z85: *** | AA85: 否 | AC85: 2025-08-23 20:37:07 | AD85: 灰色 | AG85: 2025-08-23 20:37:10 | AH85: 抖音 | AI85: 精选联盟 | AJ85: 已关闭 | AK85: 2025-09-07 20:37:11 | AL85: 普通订单 | AM85: 0 | AN85: 2353393836764088 | AO85: 老板周 | AP85: - | AQ85: 退款成功 | AS85: - | AT85: - | AU85: - | AW85: 否 | AX85: 无 | AY85: 其他 | AZ85: 直播 | BA85: 关注来源 | BB85: - | BC85: - | BE85: 0 | BF85: 0 | BG85: 0 | BH85: 0 | BJ85: 否 | BP85: - | BQ85: - | BR85: -
A86: 6945473693492254155 | B86: 6945473693492254155 | C86: 【老板周】时髦撞色 春季新款假两件显瘦长袖打底T恤上衣 | D86: 黑色;M(100-120斤);15天内发货 | E86: 1 | F86: 3770648898645918626 | G86: Z1576-黑色-M | H86: 199 | I86: 199 | J86: 0 | K86: 0 | L86: - | M86: - | N86: - | O86: 0 | P86: 0 | Q86: 0 | R86: 抖音支付 | S86: 0 | T86: *** | U86: *** | V86: 陕西省 | W86: 渭南市 | X86: 蒲城县 | Y86: 奉先街道 | Z86: *** | AA86: 否 | AC86: 2025-08-23 20:37:00 | AD86: 灰色 | AF86: 2025-09-07 23:42:42 | AG86: 2025-08-23 20:38:48 | AH86: 抖音 | AI86: 精选联盟 | AJ86: 已完成 | AK86: 2025-09-07 20:38:48 | AL86: 普通订单 | AM86: 0 | AN86: 2353393836764088 | AO86: 老板周 | AP86: - | AQ86: - | AS86: - | AT86: - | AU86: - | AW86: 否 | AX86: 无 | AY86: 其他 | AZ86: 直播 | BA86: 直播推荐 | BB86: - | BC86: - | BD86: 2025-08-31 23:42:42 | BE86: 0 | BF86: 0 | BG86: 0 | BH86: 0 | BJ86: 否 | BP86: - | BQ86: - | BR86: -
A87: 6920894543975054469 | B87: 6920894543975054469 | C87: 【老板周】日系极简 春季新品圆领简约设计感无袖马甲 | D87: 黑色;L(120-135斤);15天内发货 | E87: 1 | F87: 3767004410471907465 | G87: Z1640-黑色-L | H87: 289 | I87: 289 | J87: 0 | K87: 0 | L87: - | M87: - | N87: - | O87: 0 | P87: 0 | Q87: 0 | R87: 抖音月付 | S87: 0 | T87: *** | U87: *** | V87: 吉林省 | W87: 长春市 | X87: 宽城区 | Y87: 兴业街道 | Z87: *** | AA87: 否 | AC87: 2025-08-23 20:35:54 | AD87: 灰色 | AF87: 2025-09-07 23:39:54 | AG87: 2025-08-23 20:35:55 | AH87: 抖音 | AI87: 精选联盟 | AJ87: 已完成 | AK87: 2025-09-07 20:35:55 | AL87: 普通订单 | AM87: 0 | AN87: 2353393836764088 | AO87: 老板周 | AP87: - | AQ87: - | AS87: - | AT87: - | AU87: - | AW87: 否 | AX87: 无 | AY87: 其他 | AZ87: 直播 | BA87: 直播推荐 | BB87: - | BC87: - | BD87: 2025-08-31 23:39:54 | BE87: 0 | BF87: 0 | BG87: 0 | BH87: 0 | BJ87: 否 | BP87: - | BQ87: - | BR87: -
A88: 6945467619805763273 | B88: 6945467619805763273 | C88: 【老板周】时髦撞色 春季新款假两件显瘦长袖打底T恤上衣 | D88: 黑色;M(100-120斤);15天内发货 | E88: 1 | F88: 3770648898645918626 | G88: Z1576-黑色-M | H88: 199 | I88: 199 | J88: 0 | K88: 0 | L88: - | M88: - | N88: - | O88: 0 | P88: 0 | Q88: 0 | R88: 抖音月付 | S88: 0 | T88: *** | U88: *** | V88: 山西省 | W88: 晋中市 | X88: 平遥县 | Y88: 古陶镇 | Z88: *** | AA88: 否 | AC88: 2025-08-23 20:34:07 | AD88: 灰色 | AG88: 2025-08-23 20:34:09 | AH88: 抖音 | AI88: 精选联盟 | AJ88: 已关闭 | AK88: 2025-09-07 20:34:09 | AL88: 普通订单 | AM88: 0 | AN88: 2353393836764088 | AO88: 老板周 | AP88: - | AQ88: 退款成功 | AS88: - | AT88: - | AU88: - | AW88: 否 | AX88: 无 | AY88: 其他 | AZ88: 直播 | BA88: 直播推荐 | BB88: - | BC88: - | BE88: 0 | BF88: 0 | BG88: 0 | BH88: 0 | BJ88: 否 | BP88: - | BQ88: - | BR88: -
A89: 6920892563116359550 | B89: 6920892563116359550 | C89: 【老板周】时髦撞色 春季新款假两件显瘦长袖打底T恤上衣 | D89: 黑色;M(100-120斤);15天内发货 | E89: 1 | F89: 3770648898645918626 | G89: Z1576-黑色-M | H89: 199 | I89: 179 | J89: 0 | K89: 20 | L89: 平台专属限时优惠券-20.00 | M89: - | N89: - | O89: 0 | P89: 0 | Q89: 0 | R89: 支付宝 | S89: 0 | T89: *** | U89: *** | V89: 陕西省 | W89: 西安市 | X89: 未央区 | Y89: 未央宫街道 | Z89: *** | AA89: 否 | AC89: 2025-08-23 20:08:56 | AD89: 蓝色 | AE89: SF3239415831023(收） Z1576-黑色-M*1# | AG89: 2025-08-23 20:09:06 | AH89: 抖音 | AI89: 精选联盟 | AJ89: 已关闭 | AK89: 2025-09-07 20:09:07 | AL89: 普通订单 | AM89: 0 | AN89: 2353393836764088 | AO89: 老板周 | AP89: - | AQ89: 退款成功 | AS89: - | AT89: - | AU89: - | AW89: 否 | AX89: 直播 | AY89: 广告 | AZ89: 直播 | BA89: 其他 | BB89: - | BC89: - | BD89: 2025-08-31 23:42:42 | BE89: 0 | BF89: 20 | BG89: 0 | BH89: 0 | BJ89: 否 | BP89: - | BQ89: - | BR89: -
A90: 6945475825819719198 | B90: 6945475825819719198 | C90: 【老板周】时髦撞色 春季新款假两件显瘦长袖打底T恤上衣 | D90: 黑色;M(100-120斤);15天内发货 | E90: 1 | F90: 3770648898645918626 | G90: Z1576-黑色-M | H90: 199 | I90: 199 | J90: 0 | K90: 0 | L90: - | M90: - | N90: - | O90: 0 | P90: 0 | Q90: 0 | R90: 抖音月付 | S90: 0 | T90: *** | U90: *** | V90: 陕西省 | W90: 延安市 | X90: 宝塔区 | Y90: 桥沟街道 | Z90: *** | AA90: 否 | AC90: 2025-08-23 20:01:26 | AD90: 蓝色 | AE90: SF3284841807432(收） Z1576-黑色-M*1# | AG90: 2025-08-23 20:01:28 | AH90: 抖音 | AI90: 精选联盟 | AJ90: 已关闭 | AK90: 2025-09-07 20:01:28 | AL90: 普通订单 | AM90: 0 | AN90: 2353393836764088 | AO90: 老板周 | AP90: - | AQ90: 退款成功 | AS90: - | AT90: - | AU90: - | AW90: 否 | AX90: 无 | AY90: 其他 | AZ90: 直播 | BA90: 直播推荐 | BB90: - | BC90: - | BD90: 2025-08-31 23:42:42 | BE90: 0 | BF90: 0 | BG90: 0 | BH90: 0 | BJ90: 否 | BP90: - | BQ90: - | BR90: -
A91: 6945475928514172446 | B91: 6945475928514172446 | C91: 【老板周】日系极简 春季新品圆领简约设计感无袖马甲 | D91: 黑色;M(100-120斤);15天内发货 | E91: 1 | F91: 3767004410471907465 | G91: Z1640-黑色-M | H91: 289 | I91: 289 | J91: 0 | K91: 0 | L91: - | M91: - | N91: - | O91: 0 | P91: 0 | Q91: 0 | R91: 抖音月付 | S91: 0 | T91: *** | U91: *** | V91: 陕西省 | W91: 延安市 | X91: 宝塔区 | Y91: 桥沟街道 | Z91: *** | AA91: 否 | AC91: 2025-08-23 19:59:28 | AD91: 蓝色 | AE91: SF3284841807432(收） Z1640-黑色-M*1# | AG91: 2025-08-23 19:59:30 | AH91: 抖音 | AI91: 精选联盟 | AJ91: 已关闭 | AK91: 2025-09-07 19:59:30 | AL91: 普通订单 | AM91: 0 | AN91: 2353393836764088 | AO91: 老板周 | AP91: - | AQ91: 退款成功 | AS91: - | AT91: - | AU91: - | AW91: 否 | AX91: 无 | AY91: 其他 | AZ91: 直播 | BA91: 直播推荐 | BB91: - | BC91: - | BD91: 2025-09-01 23:14:20 | BE91: 0 | BF91: 0 | BG91: 0 | BH91: 0 | BJ91: 否 | BP91: - | BQ91: - | BR91: -
A92: 6945471889155364583 | B92: 6945471889155364583 | C92: 【老板周】日系极简 春季新品圆领简约设计感无袖马甲 | D92: 黑色;L(120-135斤);15天内发货 | E92: 1 | F92: 3767004410471907465 | G92: Z1640-黑色-L | H92: 289 | I92: 289 | J92: 0 | K92: 0 | L92: - | M92: - | N92: - | O92: 0 | P92: 0 | Q92: 0 | R92: 抖音支付 | S92: 0 | T92: *** | U92: *** | V92: 北京市 | W92: 北京市 | X92: 通州区 | Y92: 中仓街道 | Z92: *** | AA92: 否 | AC92: 2025-08-23 19:32:09 | AD92: 灰色 | AF92: 2025-09-02 18:47:11 | AG92: 2025-08-23 19:32:13 | AH92: 抖音 | AI92: 精选联盟 | AJ92: 已完成 | AK92: 2025-09-07 19:32:13 | AL92: 普通订单 | AM92: 0 | AN92: 2353393836764088 | AO92: 老板周 | AP92: - | AQ92: - | AS92: - | AT92: - | AU92: - | AW92: 否 | AX92: 无 | AY92: 其他 | AZ92: 直播 | BA92: 关注来源 | BB92: - | BC92: - | BD92: 2025-08-31 23:39:54 | BE92: 0 | BF92: 0 | BG92: 0 | BH92: 0 | BJ92: 否 | BP92: - | BQ92: - | BR92: -
A93: 6945469470994273593 | B93: 6945469470994273593 | C93: 【老板周】时髦撞色 春季新款假两件显瘦长袖打底T恤上衣 | D93: 黑色;S(80-100斤);15天内发货 | E93: 1 | F93: 3770648898645918626 | G93: Z1576-黑色-S | H93: 199 | I93: 199 | J93: 0 | K93: 0 | L93: - | M93: - | N93: - | O93: 0 | P93: 0 | Q93: 0 | R93: 抖音月付 | S93: 0 | T93: *** | U93: *** | V93: 广东省 | W93: 深圳市 | X93: 南山区 | Y93: 南山街道 | Z93: *** | AA93: 否 | AC93: 2025-08-23 19:17:36 | AD93: 灰色 | AG93: 2025-08-23 19:17:38 | AH93: 抖音 | AI93: 精选联盟 | AJ93: 已关闭 | AK93: 2025-09-07 19:17:38 | AL93: 普通订单 | AM93: 0 | AN93: 2353393836764088 | AO93: 老板周 | AP93: - | AQ93: 退款成功 | AS93: - | AT93: - | AU93: - | AW93: 否 | AX93: 无 | AY93: 其他 | AZ93: 直播 | BA93: 直播推荐 | BB93: - | BC93: - | BE93: 0 | BF93: 0 | BG93: 0 | BH93: 0 | BJ93: 否 | BP93: - | BQ93: - | BR93: -
A94: 6920896745472556170 | B94: 6920896745472556170 | C94: 【老板周】日系极简 春季新品圆领简约设计感无袖马甲 | D94: 黑色;M(100-120斤);15天内发货 | E94: 1 | F94: 3767004410471907465 | G94: Z1640-黑色-M | H94: 289 | I94: 289 | J94: 0 | K94: 0 | L94: - | M94: - | N94: - | O94: 0 | P94: 0 | Q94: 0 | R94: 抖音支付 | S94: 0 | T94: *** | U94: *** | V94: 上海市 | W94: 上海市 | X94: 黄浦区 | Y94: 打浦桥街道 | Z94: *** | AA94: 否 | AC94: 2025-08-23 19:15:08 | AD94: 蓝色 | AE94: 73570894834784(收） Z1640-黑色-M*1# | AG94: 2025-08-23 19:15:14 | AH94: 抖音 | AI94: 精选联盟 | AJ94: 已关闭 | AK94: 2025-09-07 19:15:14 | AL94: 普通订单 | AM94: 0 | AN94: 2353393836764088 | AO94: 老板周 | AP94: - | AQ94: 退款成功 | AS94: - | AT94: - | AU94: - | AW94: 否 | AX94: 无 | AY94: 其他 | AZ94: 直播 | BA94: 直播推荐 | BB94: - | BC94: - | BD94: 2025-09-01 23:14:20 | BE94: 0 | BF94: 0 | BG94: 0 | BH94: 0 | BJ94: 否 | BP94: - | BQ94: - | BR94: -
A95: 6920892429455490186 | B95: 6920892429455490186 | C95: 【老板周】时髦撞色 春季新款假两件显瘦长袖打底T恤上衣 | D95: 黑色;M(100-120斤);15天内发货 | E95: 1 | F95: 3770648898645918626 | G95: Z1576-黑色-M | H95: 199 | I95: 199 | J95: 0 | K95: 0 | L95: - | M95: - | N95: - | O95: 0 | P95: 0 | Q95: 0 | R95: 抖音支付 | S95: 0 | T95: *** | U95: *** | V95: 上海市 | W95: 上海市 | X95: 黄浦区 | Y95: 打浦桥街道 | Z95: *** | AA95: 否 | AC95: 2025-08-23 19:14:38 | AD95: 蓝色 | AE95: 73570769408190(收） Z1576-黑色-M*1# | AG95: 2025-08-23 19:14:48 | AH95: 抖音 | AI95: 精选联盟 | AJ95: 已关闭 | AK95: 2025-09-07 19:14:48 | AL95: 普通订单 | AM95: 0 | AN95: 2353393836764088 | AO95: 老板周 | AP95: - | AQ95: 退款成功 | AS95: - | AT95: - | AU95: - | AW95: 否 | AX95: 无 | AY95: 其他 | AZ95: 直播 | BA95: 直播推荐 | BB95: - | BC95: - | BD95: 2025-08-31 22:01:06 | BE95: 0 | BF95: 0 | BG95: 0 | BH95: 0 | BJ95: 否 | BP95: - | BQ95: - | BR95: -
A96: 6945480350198339381 | B96: 6945480350198339381 | C96: 【老板周】时髦撞色 春季新款假两件显瘦长袖打底T恤上衣 | D96: 黑色;M(100-120斤);15天内发货 | E96: 1 | F96: 3770648898645918626 | G96: Z1576-黑色-M | H96: 199 | I96: 199 | J96: 0 | K96: 0 | L96: - | M96: - | N96: - | O96: 0 | P96: 0 | Q96: 0 | R96: 抖音支付 | S96: 0 | T96: *** | U96: *** | V96: 陕西省 | W96: 西安市 | X96: 未央区 | Y96: 张家堡街道 | Z96: *** | AA96: 否 | AC96: 2025-08-23 18:57:42 | AD96: 灰色 | AH96: 番茄小说-抖音电商 | AI96: 精选联盟 | AJ96: 已关闭 | AK96: 2025-09-07 18:57:42 | AL96: 普通订单 | AM96: 0 | AN96: 2353393836764088 | AO96: 老板周 | AP96: - | AQ96: - | AR96: 用户超时未支付自动取消 | AS96: - | AT96: - | AU96: - | AW96: 否 | AX96: 直播 | AY96: 广告 | AZ96: 直播 | BA96: 其他 | BB96: - | BC96: - | BE96: 0 | BF96: 0 | BG96: 0 | BH96: 0 | BJ96: 否 | BP96: - | BQ96: - | BR96: -
A97: 6920901228969950691 | B97: 6920901228969950691 | C97: 【老板周】日系极简 春季新品圆领简约设计感无袖马甲 | D97: 黑色;M(100-120斤);15天内发货 | E97: 1 | F97: 3767004410471907465 | G97: Z1640-黑色-M | H97: 289 | I97: 289 | J97: 0 | K97: 0 | L97: - | M97: - | N97: - | O97: 0 | P97: 0 | Q97: 0 | R97: 抖音支付 | S97: 0 | T97: *** | U97: *** | V97: 辽宁省 | W97: 沈阳市 | X97: 苏家屯区 | Y97: 民主街道 | Z97: *** | AA97: 否 | AC97: 2025-08-23 18:22:38 | AD97: 灰色 | AG97: 2025-08-23 18:22:43 | AH97: 抖音 | AI97: 精选联盟 | AJ97: 已关闭 | AK97: 2025-09-07 18:22:44 | AL97: 普通订单 | AM97: 0 | AN97: 2353393836764088 | AO97: 老板周 | AP97: - | AQ97: 退款成功 | AS97: - | AT97: - | AU97: - | AW97: 否 | AX97: 无 | AY97: 其他 | AZ97: 直播 | BA97: 商城推荐 | BB97: - | BC97: - | BE97: 0 | BF97: 0 | BG97: 0 | BH97: 0 | BJ97: 否 | BP97: - | BQ97: - | BR97: -
A98: 6920901308765076963 | B98: 6920901308765076963 | C98: 【老板周】时髦撞色 春季新款假两件显瘦长袖打底T恤上衣 | D98: 黑色;M(100-120斤);15天内发货 | E98: 1 | F98: 3770648898645918626 | G98: Z1576-黑色-M | H98: 199 | I98: 199 | J98: 0 | K98: 0 | L98: - | M98: - | N98: - | O98: 0 | P98: 0 | Q98: 0 | R98: 抖音支付 | S98: 0 | T98: *** | U98: *** | V98: 辽宁省 | W98: 沈阳市 | X98: 苏家屯区 | Y98: 民主街道 | Z98: *** | AA98: 否 | AC98: 2025-08-23 18:22:00 | AD98: 灰色 | AG98: 2025-08-23 18:22:06 | AH98: 抖音 | AI98: 精选联盟 | AJ98: 已关闭 | AK98: 2025-09-07 18:22:06 | AL98: 普通订单 | AM98: 0 | AN98: 2353393836764088 | AO98: 老板周 | AP98: - | AQ98: 退款成功 | AS98: - | AT98: - | AU98: - | AW98: 否 | AX98: 无 | AY98: 其他 | AZ98: 直播 | BA98: 商城推荐 | BB98: - | BC98: - | BE98: 0 | BF98: 0 | BG98: 0 | BH98: 0 | BJ98: 否 | BP98: - | BQ98: - | BR98: -
A99: 6945487556598699454 | B99: 6945487556598699454 | C99: 【老板周】时髦撞色 春季新款假两件显瘦长袖打底T恤上衣 | D99: 黑色;M(100-120斤);15天内发货 | E99: 1 | F99: 3770648898645918626 | G99: Z1576-黑色-M | H99: 199 | I99: 199 | J99: 0 | K99: 0 | L99: - | M99: - | N99: - | O99: 0 | P99: 0 | Q99: 0 | R99: 抖音月付 | S99: 0 | T99: *** | U99: *** | V99: 山西省 | W99: 阳泉市 | X99: 矿区 | Y99: 平潭街街道 | Z99: *** | AA99: 否 | AC99: 2025-08-23 18:12:49 | AD99: 蓝色 | AE99: 9475620502178(收） Z1576-黑色-M*1# | AG99: 2025-08-23 18:12:51 | AH99: 抖音 | AI99: 精选联盟 | AJ99: 已关闭 | AK99: 2025-09-07 18:12:51 | AL99: 普通订单 | AM99: 0 | AN99: 2353393836764088 | AO99: 老板周 | AP99: - | AQ99: 退款成功 | AS99: - | AT99: - | AU99: - | AW99: 否 | AX99: 无 | AY99: 其他 | AZ99: 直播 | BA99: 直播推荐 | BB99: - | BC99: - | BD99: 2025-08-31 22:01:06 | BE99: 0 | BF99: 0 | BG99: 0 | BH99: 0 | BJ99: 否 | BP99: - | BQ99: - | BR99: -
A100: 6945469101898405538 | B100: 6945469101898405538 | C100: 【老板周】时髦撞色 春季新款假两件显瘦长袖打底T恤上衣 | D100: 黑色;L(120-135斤);15天内发货 | E100: 1 | F100: 3770648898645918626 | G100: Z1576-黑色-L | H100: 199 | I100: 199 | J100: 0 | K100: 0 | L100: - | M100: - | N100: - | O100: 0 | P100: 0 | Q100: 0 | R100: 支付宝 | S100: 0 | T100: *** | U100: *** | V100: 山东省 | W100: 菏泽市 | X100: 曹县 | Y100: 青菏街道 | Z100: *** | AA100: 否 | AC100: 2025-08-23 17:39:15 | AD100: 灰色 | AG100: 2025-08-23 17:39:22 | AH100: 抖音极速版 | AI100: 精选联盟 | AJ100: 已关闭 | AK100: 2025-09-07 17:39:22 | AL100: 普通订单 | AM100: 0 | AN100: 2353393836764088 | AO100: 老板周 | AP100: - | AQ100: 退款成功 | AS100: - | AT100: - | AU100: - | AW100: 否 | AX100: 直播 | AY100: 广告 | AZ100: 直播 | BA100: 搜索 | BB100: - | BC100: - | BE100: 0 | BF100: 0 | BG100: 0 | BH100: 0 | BJ100: 否 | BP100: - | BQ100: - | BR100: -
...

Sheet 抖音订单-按支付日期-ABF列，要先手动清除空格
A1: 主订单编号 | B1: 子订单编号 | C1: 选购商品 | D1: 商品规格 | E1: 商品数量 | F1: 商品ID | G1: 商家编码 | H1: 商品单价 | I1: 订单应付金额 | J1: 运费 | K1: 优惠总金额 | L1: 平台优惠 | M1: 商家优惠 | N1: 达人优惠 | O1: 商家改价 | P1: 支付优惠 | Q1: 红包抵扣 | R1: 支付方式 | S1: 手续费 | T1: 收件人 | U1: 收件人手机号 | V1: 省 | W1: 市 | X1: 区 | Y1: 街道 | Z1: 详细地址 | AA1: 是否修改过地址 | AB1: 买家留言 | AC1: 订单提交时间 | AD1: 旗帜颜色 | AE1: 商家备注 | AF1: 订单完成时间 | AG1: 支付完成时间 | AH1: APP渠道 | AI1: 流量来源 | AJ1: 订单状态 | AK1: 承诺发货时间 | AL1: 订单类型 | AM1: 鲁班落地页ID | AN1: 达人ID | AO1: 达人昵称 | AP1: 所属门店ID | AQ1: 售后状态 | AR1: 取消原因 | AS1: 预约发货时间 | AT1: 仓库ID | AU1: 仓库名称 | AV1: 序列号 | AW1: 是否安心购 | AX1: 广告渠道 | AY1: 流量类型 | AZ1: 流量体裁 | BA1: 流量渠道 | BB1: 发货主体 | BC1: 发货主体明细 | BD1: 发货时间 | BE1: 降价类优惠 | BF1: 平台实际承担优惠金额 | BG1: 商家实际承担优惠金额 | BH1: 达人实际承担优惠金额 | BI1: 预计送达时间 | BJ1: 是否平台仓自流转 | BK1: 车型 | BL1: 商品69码 | BM1: 发货SN码 | BN1: 发货IMEI码1 | BO1: 发货IMEI码2 | BP1: 预约送达时间 | BQ1: 建议发货时间（起） | BR1: 建议发货时间（止） | BS1: 物流SN码 | BT1: 物流IMEI码1 | BU1: 物流IMEI码2
A2: 6921014879971867995 | B2: 6921014879971867995 | C2: 【老板周】复古风格 秋冬新款立体麻花织纹针织毛衣 | D2: 灰色;L(120-135斤);15天内发货 | E2: 1 | F2: 3772185880568135686 | G2: Z2418-灰色-L | H2: 329 | I2: 329 | J2: 0 | K2: 0 | L2: - | M2: - | N2: - | O2: 0 | P2: 0 | Q2: 0 | R2: 抖音月付 | S2: 0 | T2: *** | U2: *** | V2: 安徽省 | W2: 宿州市 | X2: 埇桥区 | Y2: 西关街道 | Z2: *** | AA2: 否 | AC2: 2025-08-31 22:51:27 | AD2: 灰色 | AE2: (收)[Z2418-灰色-L]*[1]# | AF2: 2025-09-22 10:48:28 | AG2: 2025-08-31 22:51:31 | AH2: 抖音 | AI2: 精选联盟 | AJ2: 已完成 | AK2: 2025-09-15 22:51:31 | AL2: 普通订单 | AM2: 0 | AN2: 2353393836764088 | AO2: 老板周 | AP2: - | AQ2: 退款成功 | AS2: - | AT2: - | AU2: - | AW2: 否 | AX2: 无 | AY2: 其他 | AZ2: 直播 | BA2: 商城推荐 | BB2: - | BC2: - | BD2: 2025-09-15 10:48:28 | BE2: 0 | BF2: 0 | BG2: 0 | BH2: 0 | BJ2: 否 | BP2: - | BQ2: - | BR2: -
A3: 6945703385201317436 | B3: 6945703385201317436 | C3: 【老板周】日系极简 春季新品圆领简约设计感无袖马甲 | D3: 黑色;M(100-120斤);15天内发货 | E3: 1 | F3: 3767004410471907465 | G3: Z1640-黑色-M | H3: 289 | I3: 289 | J3: 0 | K3: 0 | L3: - | M3: - | N3: - | O3: 0 | P3: 0 | Q3: 0 | R3: 支付宝 | S3: 0 | T3: *** | U3: *** | V3: 广东省 | W3: 深圳市 | X3: 龙华区 | Y3: 龙华街道 | Z3: *** | AA3: 否 | AC3: 2025-08-31 22:28:56 | AD3: 灰色 | AF3: 2025-09-18 23:58:12 | AG3: 2025-08-31 22:29:01 | AH3: 抖音 | AI3: 精选联盟 | AJ3: 已完成 | AK3: 2025-09-15 22:29:02 | AL3: 普通订单 | AM3: 0 | AN3: 2353393836764088 | AO3: 老板周 | AP3: - | AQ3: - | AS3: - | AT3: - | AU3: - | AW3: 否 | AX3: 无 | AY3: 其他 | AZ3: 直播 | BA3: 关注来源 | BB3: - | BC3: - | BD3: 2025-09-11 23:58:12 | BE3: 0 | BF3: 0 | BG3: 0 | BH3: 0 | BJ3: 否 | BP3: - | BQ3: - | BR3: -
A4: 6945727588250948678 | B4: 6945727588250948678 | C4: 【老板周】日系极简 春季新品圆领简约设计感无袖马甲 | D4: 黑色;L(120-135斤);15天内发货 | E4: 1 | F4: 3767004410471907465 | G4: Z1640-黑色-L | H4: 289 | I4: 289 | J4: 0 | K4: 0 | L4: - | M4: - | N4: - | O4: 0 | P4: 0 | Q4: 0 | R4: 抖音支付 | S4: 0 | T4: *** | U4: *** | V4: 山东省 | W4: 德州市 | X4: 德城区 | Y4: - | Z4: *** | AA4: 否 | AC4: 2025-08-31 22:26:00 | AD4: 灰色 | AG4: 2025-08-31 22:26:05 | AH4: 抖音 | AI4: 精选联盟 | AJ4: 已关闭 | AK4: 2025-09-15 22:26:05 | AL4: 普通订单 | AM4: 0 | AN4: 2353393836764088 | AO4: 老板周 | AP4: - | AQ4: 退款成功 | AS4: - | AT4: - | AU4: - | AW4: 否 | AX4: 无 | AY4: 其他 | AZ4: 直播 | BA4: 直播推荐 | BB4: - | BC4: - | BE4: 0 | BF4: 0 | BG4: 0 | BH4: 0 | BJ4: 否 | BP4: - | BQ4: - | BR4: -
A5: 6945714505452361238 | B5: 6945714505452361238 | C5: 【老板周】日系极简 春季新品圆领简约设计感无袖马甲 | D5: 黑色;S(80-100斤);15天内发货 | E5: 1 | F5: 3767004410471907465 | G5: Z1640-黑色-S | H5: 289 | I5: 286 | J5: 0 | K5: 4 | L5: 平台晚发即赔券-3.00 | M5: - | N5: - | O5: 0 | P5: 1 | Q5: 0 | R5: 抖音支付 | S5: 0 | T5: *** | U5: *** | V5: 河南省 | W5: 平顶山市 | X5: 湛河区 | Y5: 九里山街道 | Z5: *** | AA5: 否 | AC5: 2025-08-31 22:01:43 | AD5: 灰色 | AG5: 2025-08-31 22:01:46 | AH5: 抖音 | AI5: 精选联盟 | AJ5: 已关闭 | AK5: 2025-09-15 22:01:47 | AL5: 普通订单 | AM5: 0 | AN5: 2353393836764088 | AO5: 老板周 | AP5: - | AQ5: 退款成功 | AS5: - | AT5: - | AU5: - | AW5: 否 | AX5: 无 | AY5: 其他 | AZ5: 商品卡 | BA5: 橱窗 | BB5: - | BC5: - | BE5: 0 | BF5: 3 | BG5: 0 | BH5: 0 | BJ5: 否 | BP5: - | BQ5: - | BR5: -
A6: 6945700999501124814 | B6: 6945700999501124814 | C6: 【老板周】极简设计 秋冬毛绒感圆领套头舒适针织毛衣 | D6: 红色;M(100-135斤);15天内发货 | E6: 1 | F6: 3772189127454359773 | G6: Z2425-红色-M | H6: 289 | I6: 289 | J6: 0 | K6: 0 | L6: - | M6: - | N6: - | O6: 0 | P6: 0 | Q6: 0 | R6: 抖音支付 | S6: 0 | T6: *** | U6: *** | V6: 湖南省 | W6: 常德市 | X6: 武陵区 | Y6: 穿紫河街道 | Z6: *** | AA6: 否 | AC6: 2025-08-31 20:25:26 | AD6: 灰色 | AG6: 2025-08-31 20:25:28 | AH6: 抖音 | AI6: 精选联盟 | AJ6: 已关闭 | AK6: 2025-09-15 20:25:28 | AL6: 普通订单 | AM6: 0 | AN6: 2353393836764088 | AO6: 老板周 | AP6: - | AQ6: 退款成功 | AS6: - | AT6: - | AU6: - | AW6: 否 | AX6: 直播 | AY6: 广告 | AZ6: 直播 | BA6: 商城推荐 | BB6: - | BC6: - | BE6: 0 | BF6: 0 | BG6: 0 | BH6: 0 | BJ6: 否 | BP6: - | BQ6: - | BR6: -
A7: 6921014170429783498 | B7: 6921014170429783498 | C7: 【老板周】日系极简 春季新品圆领简约设计感无袖马甲 | D7: 黑色;M(100-120斤);15天内发货 | E7: 1 | F7: 3767004410471907465 | G7: Z1640-黑色-M | H7: 289 | I7: 289 | J7: 0 | K7: 0 | L7: - | M7: - | N7: - | O7: 0 | P7: 0 | Q7: 0 | R7: 支付宝 | S7: 0 | T7: *** | U7: *** | V7: 上海市 | W7: 上海市 | X7: 浦东新区 | Y7: - | Z7: *** | AA7: 否 | AC7: 2025-08-31 19:29:31 | AD7: 灰色 | AF7: 2025-09-18 23:58:12 | AG7: 2025-08-31 19:29:36 | AH7: 抖音 | AI7: 精选联盟 | AJ7: 已完成 | AK7: 2025-09-15 19:29:36 | AL7: 普通订单 | AM7: 0 | AN7: 2353393836764088 | AO7: 老板周 | AP7: - | AQ7: - | AS7: - | AT7: - | AU7: - | AW7: 否 | AX7: 无 | AY7: 其他 | AZ7: 直播 | BA7: 直播推荐 | BB7: - | BC7: - | BD7: 2025-09-11 23:58:12 | BE7: 0 | BF7: 0 | BG7: 0 | BH7: 0 | BJ7: 否 | BP7: - | BQ7: - | BR7: -
A8: 6945712098356630732 | B8: 6945712098356630732 | C8: 【老板周】日系极简 春季新品圆领简约设计感无袖马甲 | D8: 黑色;M(100-120斤);15天内发货 | E8: 1 | F8: 3767004410471907465 | G8: Z1640-黑色-M | H8: 289 | I8: 289 | J8: 0 | K8: 0 | L8: - | M8: - | N8: - | O8: 0 | P8: 0 | Q8: 0 | R8: 抖音月付 | S8: 0 | T8: *** | U8: *** | V8: 山西省 | W8: 太原市 | X8: 晋源区 | Y8: 义井街道 | Z8: *** | AA8: 否 | AC8: 2025-08-31 19:13:06 | AD8: 灰色 | AF8: 2025-09-18 23:58:12 | AG8: 2025-08-31 19:13:08 | AH8: 抖音 | AI8: 精选联盟 | AJ8: 已完成 | AK8: 2025-09-15 19:13:08 | AL8: 普通订单 | AM8: 0 | AN8: 2353393836764088 | AO8: 老板周 | AP8: - | AQ8: 退款成功 | AS8: - | AT8: - | AU8: - | AW8: 否 | AX8: 无 | AY8: 其他 | AZ8: 直播 | BA8: 直播推荐 | BB8: - | BC8: - | BD8: 2025-09-11 23:58:12 | BE8: 0 | BF8: 0 | BG8: 0 | BH8: 0 | BJ8: 否 | BP8: - | BQ8: - | BR8: -
A9: 6921016389061410674 | B9: 6921016389061410674 | C9: 【老板周】极简设计 秋冬毛绒感圆领套头舒适针织毛衣 | D9: 红色;S(80-100斤);15天内发货 | E9: 1 | F9: 3772189127454359773 | G9: Z2425-红色-S | H9: 289 | I9: 284 | J9: 0 | K9: 5 | L9: 平台晚发即赔券-5.00 | M9: - | N9: - | O9: 0 | P9: 0 | Q9: 0 | R9: 抖音月付 | S9: 0 | T9: *** | U9: *** | V9: 重庆市 | W9: 重庆市 | X9: 九龙坡区 | Y9: 中梁山街道 | Z9: *** | AA9: 否 | AC9: 2025-08-31 18:07:41 | AD9: 灰色 | AG9: 2025-08-31 18:07:42 | AH9: 头条lite-抖音电商 | AI9: 精选联盟 | AJ9: 已关闭 | AK9: 2025-09-15 18:07:43 | AL9: 普通订单 | AM9: 0 | AN9: 2353393836764088 | AO9: 老板周 | AP9: - | AQ9: 退款成功 | AS9: - | AT9: - | AU9: - | AW9: 否 | AX9: 直播 | AY9: 广告 | AZ9: 直播 | BA9: 头条西瓜 | BB9: - | BC9: - | BE9: 0 | BF9: 5 | BG9: 0 | BH9: 0 | BJ9: 否 | BP9: - | BQ9: - | BR9: -
A10: 6945711936320509468 | B10: 6945711936320509468 | C10: 【老板周】极简设计 秋冬毛绒感圆领套头舒适针织毛衣 | D10: 蓝色;S(80-100斤);15天内发货 | E10: 1 | F10: 3772189127454359773 | G10: Z2425-蓝色-S | H10: 289 | I10: 289 | J10: 0 | K10: 0 | L10: - | M10: - | N10: - | O10: 0 | P10: 0 | Q10: 0 | R10: 抖音支付 | S10: 0 | T10: *** | U10: *** | V10: 贵州省 | W10: 贵阳市 | X10: 乌当区 | Y10: 新创路街道 | Z10: *** | AA10: 否 | AC10: 2025-08-31 18:05:55 | AD10: 灰色 | AH10: 抖音 | AI10: 精选联盟 | AJ10: 已关闭 | AK10: 2025-09-15 18:05:55 | AL10: 普通订单 | AM10: 0 | AN10: 2353393836764088 | AO10: 老板周 | AP10: - | AQ10: - | AR10: 你已取消订单：暂时不需要这个商品 | AS10: - | AT10: - | AU10: - | AW10: 否 | AX10: 无 | AY10: 其他 | AZ10: 直播 | BA10: 直播推荐 | BB10: - | BC10: - | BE10: 0 | BF10: 0 | BG10: 0 | BH10: 0 | BJ10: 否 | BP10: - | BQ10: - | BR10: -
A11: 6921016313814548201 | B11: 6921016313814548201 | C11: 【老板周】极简设计 秋冬毛绒感圆领套头舒适针织毛衣 | D11: 红色;M(100-135斤);15天内发货 | E11: 1 | F11: 3772189127454359773 | G11: Z2425-红色-M | H11: 289 | I11: 267 | J11: 0 | K11: 22 | L11: 平台全额返现满减券-22.00 | M11: - | N11: - | O11: 0 | P11: 0 | Q11: 0 | R11: 抖音月付 | S11: 0 | T11: *** | U11: *** | V11: 广东省 | W11: 阳江市 | X11: 江城区 | Y11: 城北街道 | Z11: *** | AA11: 否 | AC11: 2025-08-31 18:05:31 | AD11: 蓝色 | AE11: YT2532916536267(收） Z2425-红色-M*1# | AG11: 2025-08-31 18:05:36 | AH11: 抖音 | AI11: 精选联盟 | AJ11: 已关闭 | AK11: 2025-09-15 18:05:36 | AL11: 普通订单 | AM11: 0 | AN11: 2353393836764088 | AO11: 老板周 | AP11: - | AQ11: 退款成功 | AS11: - | AT11: - | AU11: - | AW11: 否 | AX11: 无 | AY11: 其他 | AZ11: 直播 | BA11: 商城推荐 | BB11: - | BC11: - | BD11: 2025-09-09 23:55:16 | BE11: 0 | BF11: 22 | BG11: 0 | BH11: 0 | BJ11: 否 | BP11: - | BQ11: - | BR11: -
A12: 6945707477692061056 | B12: 6945707477692061056 | C12: 【老板周】简约松弛 秋冬纯色弧形下摆宽松百搭上衣 | D12: 白色;S(80-100斤);15天内发货 | E12: 1 | F12: 3771440658552848740 | G12: Z2311-白色-S | H12: 229 | I12: 229 | J12: 0 | K12: 0 | L12: - | M12: - | N12: - | O12: 0 | P12: 0 | Q12: 0 | R12: 抖音支付 | S12: 0 | T12: *** | U12: *** | V12: 湖南省 | W12: 常德市 | X12: 武陵区 | Y12: 府坪街道 | Z12: *** | AA12: 否 | AC12: 2025-08-31 18:01:07 | AD12: 蓝色 | AE12: 73571847180415(收） Z2311-白色-S*1# | AG12: 2025-08-31 18:01:08 | AH12: 抖音 | AI12: 小店自卖 | AJ12: 已关闭 | AK12: 2025-09-15 18:01:09 | AL12: 普通订单 | AM12: 0 | AN12: 0 | AP12: - | AQ12: 退款成功 | AS12: - | AT12: - | AU12: - | AW12: 否 | AX12: 无 | AY12: 其他 | AZ12: 商品卡 | BA12: 搜索 | BB12: - | BC12: - | BD12: 2025-09-07 16:39:45 | BE12: 0 | BF12: 0 | BG12: 0 | BH12: 0 | BJ12: 否 | BP12: - | BQ12: - | BR12: -
A13: 6945694166426850837 | B13: 6945694166426850837 | C13: 【老板周】复古风格 秋冬新款立体麻花织纹针织毛衣 | D13: 灰色;L(120-135斤);15天内发货 | E13: 1 | F13: 3772185880568135686 | G13: Z2418-灰色-L | H13: 329 | I13: 329 | J13: 0 | K13: 0 | L13: - | M13: - | N13: - | O13: 0 | P13: 0 | Q13: 0 | R13: 支付宝 | S13: 0 | T13: *** | U13: *** | V13: 辽宁省 | W13: 本溪市 | X13: 明山区 | Y13: 北地街道 | Z13: *** | AA13: 否 | AC13: 2025-08-31 17:51:10 | AD13: 灰色 | AG13: 2025-08-31 17:51:20 | AH13: 抖音极速版 | AI13: 精选联盟 | AJ13: 已关闭 | AK13: 2025-09-15 17:51:20 | AL13: 普通订单 | AM13: 0 | AN13: 2353393836764088 | AO13: 老板周 | AP13: - | AQ13: 退款成功 | AS13: - | AT13: - | AU13: - | AW13: 否 | AX13: 无 | AY13: 其他 | AZ13: 直播 | BA13: 商城推荐 | BB13: - | BC13: - | BE13: 0 | BF13: 0 | BG13: 0 | BH13: 0 | BJ13: 否 | BP13: - | BQ13: - | BR13: -
A14: 6945716113981314698 | B14: 6945716113981314698 | C14: 【老板周】复古风格 秋冬新款立体麻花织纹针织毛衣 | D14: 灰色;S(80-100斤);15天内发货 | E14: 1 | F14: 3772185880568135686 | G14: Z2418-灰色-S | H14: 329 | I14: 329 | J14: 0 | K14: 0 | L14: - | M14: - | N14: - | O14: 0 | P14: 0 | Q14: 0 | R14: 抖音月付 | S14: 0 | T14: *** | U14: *** | V14: 山西省 | W14: 吕梁市 | X14: 交城县 | Y14: 天宁镇 | Z14: *** | AA14: 否 | AC14: 2025-08-31 17:50:43 | AD14: 灰色 | AG14: 2025-08-31 17:50:44 | AH14: 抖音 | AI14: 精选联盟 | AJ14: 已关闭 | AK14: 2025-09-15 17:50:44 | AL14: 普通订单 | AM14: 0 | AN14: 2353393836764088 | AO14: 老板周 | AP14: - | AQ14: 退款成功 | AS14: - | AT14: - | AU14: - | AW14: 否 | AX14: 无 | AY14: 其他 | AZ14: 直播 | BA14: 直播推荐 | BB14: - | BC14: - | BE14: 0 | BF14: 0 | BG14: 0 | BH14: 0 | BJ14: 否 | BP14: - | BQ14: - | BR14: -
A15: 6921011676079357340 | B15: 6921011676079357340 | C15: 【老板周】复古风格 秋冬新款立体麻花织纹针织毛衣 | D15: 灰色;S(80-100斤);15天内发货 | E15: 1 | F15: 3772185880568135686 | G15: Z2418-灰色-S | H15: 329 | I15: 329 | J15: 0 | K15: 0 | L15: - | M15: - | N15: - | O15: 0 | P15: 0 | Q15: 0 | R15: 抖音月付 | S15: 0 | T15: *** | U15: *** | V15: 河北省 | W15: 沧州市 | X15: 黄骅市 | Y15: - | Z15: *** | AA15: 否 | AC15: 2025-08-31 17:46:12 | AD15: 灰色 | AG15: 2025-08-31 17:46:16 | AH15: 抖音 | AI15: 精选联盟 | AJ15: 已关闭 | AK15: 2025-09-15 17:46:16 | AL15: 普通订单 | AM15: 0 | AN15: 2353393836764088 | AO15: 老板周 | AP15: - | AQ15: 退款成功 | AS15: - | AT15: - | AU15: - | AW15: 否 | AX15: 无 | AY15: 其他 | AZ15: 直播 | BA15: 个人主页&店铺&橱窗进入直播间 | BB15: - | BC15: - | BE15: 0 | BF15: 0 | BG15: 0 | BH15: 0 | BJ15: 否 | BP15: - | BQ15: - | BR15: -
A16: 6945711886863766847 | B16: 6945711886863766847 | C16: 【老板周】复古风格 秋冬新款立体麻花织纹针织毛衣 | D16: 灰色;M(100-120斤);15天内发货 | E16: 1 | F16: 3772185880568135686 | G16: Z2418-灰色-M | H16: 329 | I16: 329 | J16: 0 | K16: 0 | L16: - | M16: - | N16: - | O16: 0 | P16: 0 | Q16: 0 | R16: 支付宝 | S16: 0 | T16: *** | U16: *** | V16: 湖南省 | W16: 张家界市 | X16: 永定区 | Y16: 崇文街道 | Z16: *** | AA16: 否 | AC16: 2025-08-31 17:39:51 | AD16: 灰色 | AG16: 2025-08-31 17:39:57 | AH16: 红果短剧-抖音电商 | AI16: 精选联盟 | AJ16: 已关闭 | AK16: 2025-09-15 17:39:58 | AL16: 普通订单 | AM16: 0 | AN16: 2353393836764088 | AO16: 老板周 | AP16: - | AQ16: 退款成功 | AS16: - | AT16: - | AU16: - | AW16: 否 | AX16: 直播 | AY16: 广告 | AZ16: 直播 | BA16: 其他 | BB16: - | BC16: - | BE16: 0 | BF16: 0 | BG16: 0 | BH16: 0 | BJ16: 否 | BP16: - | BQ16: - | BR16: -
A17: 6921009635296968526 | B17: 6921009635296968526 | C17: 【老板周】复古风格 秋冬新款立体麻花织纹针织毛衣 | D17: 灰色;M(100-120斤);15天内发货 | E17: 1 | F17: 3772185880568135686 | G17: Z2418-灰色-M | H17: 329 | I17: 329 | J17: 0 | K17: 0 | L17: - | M17: - | N17: - | O17: 0 | P17: 0 | Q17: 0 | R17: 抖音支付 | S17: 0 | T17: *** | U17: *** | V17: 天津市 | W17: 天津市 | X17: 滨海新区 | Y17: - | Z17: *** | AA17: 否 | AC17: 2025-08-31 17:39:47 | AD17: 灰色 | AG17: 2025-08-31 17:39:48 | AH17: 抖音 | AI17: 精选联盟 | AJ17: 已关闭 | AK17: 2025-09-15 17:39:48 | AL17: 普通订单 | AM17: 0 | AN17: 2353393836764088 | AO17: 老板周 | AP17: - | AQ17: 退款成功 | AS17: - | AT17: - | AU17: - | AW17: 否 | AX17: 无 | AY17: 其他 | AZ17: 直播 | BA17: 个人主页&店铺&橱窗进入直播间 | BB17: - | BC17: - | BE17: 0 | BF17: 0 | BG17: 0 | BH17: 0 | BJ17: 否 | BP17: - | BQ17: - | BR17: -
A18: 6921016365371785140 | B18: 6921016365371785140 | C18: 【老板周】复古风格 秋冬新款立体麻花织纹针织毛衣 | D18: 灰色;M(100-120斤);15天内发货 | E18: 1 | F18: 3772185880568135686 | G18: Z2418-灰色-M | H18: 329 | I18: 329 | J18: 0 | K18: 0 | L18: - | M18: - | N18: - | O18: 0 | P18: 0 | Q18: 0 | R18: 支付宝 | S18: 0 | T18: *** | U18: *** | V18: 河北省 | W18: 石家庄市 | X18: 赵县 | Y18: 赵州镇 | Z18: *** | AA18: 否 | AC18: 2025-08-31 17:39:46 | AD18: 蓝色 | AE18: JT5414067073138(收） Z2418-灰色-M*1# | AG18: 2025-08-31 17:39:54 | AH18: 抖音 | AI18: 精选联盟 | AJ18: 已关闭 | AK18: 2025-09-15 17:39:54 | AL18: 普通订单 | AM18: 0 | AN18: 2353393836764088 | AO18: 老板周 | AP18: - | AQ18: 退款成功 | AS18: - | AT18: - | AU18: - | AW18: 否 | AX18: 无 | AY18: 其他 | AZ18: 直播 | BA18: 直播推荐 | BB18: - | BC18: - | BD18: 2025-09-15 10:48:28 | BE18: 0 | BF18: 0 | BG18: 0 | BH18: 0 | BJ18: 否 | BP18: - | BQ18: - | BR18: -
A19: 6921009588551319487 | B19: 6921009588551319487 | C19: 【老板周】复古风格 秋冬新款立体麻花织纹针织毛衣 | D19: 灰色;S(80-100斤);15天内发货 | E19: 1 | F19: 3772185880568135686 | G19: Z2418-灰色-S | H19: 329 | I19: 329 | J19: 0 | K19: 0 | L19: - | M19: - | N19: - | O19: 0 | P19: 0 | Q19: 0 | R19: 抖音支付 | S19: 0 | T19: *** | U19: *** | V19: 江苏省 | W19: 苏州市 | X19: 虎丘区 | Y19: 东渚街道 | Z19: *** | AA19: 否 | AC19: 2025-08-31 17:39:43 | AD19: 灰色 | AG19: 2025-08-31 17:39:46 | AH19: 抖音 | AI19: 精选联盟 | AJ19: 已关闭 | AK19: 2025-09-15 17:39:46 | AL19: 普通订单 | AM19: 0 | AN19: 2353393836764088 | AO19: 老板周 | AP19: - | AQ19: 退款成功 | AS19: - | AT19: - | AU19: - | AW19: 否 | AX19: 无 | AY19: 其他 | AZ19: 直播 | BA19: 关注来源 | BB19: - | BC19: - | BE19: 0 | BF19: 0 | BG19: 0 | BH19: 0 | BJ19: 否 | BP19: - | BQ19: - | BR19: -
A20: 6921018615091854571 | B20: 6921018615091854571 | C20: 【老板周】复古风格 秋冬新款立体麻花织纹针织毛衣 | D20: 灰色;L(120-135斤);15天内发货 | E20: 1 | F20: 3772185880568135686 | G20: Z2418-灰色-L | H20: 329 | I20: 329 | J20: 0 | K20: 0 | L20: - | M20: - | N20: - | O20: 0 | P20: 0 | Q20: 0 | R20: 抖音支付 | S20: 0 | T20: *** | U20: *** | V20: 河北省 | W20: 邢台市 | X20: 信都区 | Y20: 泉西街道 | Z20: *** | AA20: 否 | AC20: 2025-08-31 17:33:32 | AD20: 灰色 | AG20: 2025-08-31 17:33:35 | AH20: 抖音 | AI20: 精选联盟 | AJ20: 已关闭 | AK20: 2025-09-15 17:33:35 | AL20: 普通订单 | AM20: 0 | AN20: 2353393836764088 | AO20: 老板周 | AP20: - | AQ20: 退款成功 | AS20: - | AT20: - | AU20: - | AW20: 否 | AX20: 无 | AY20: 其他 | AZ20: 直播 | BA20: 直播推荐 | BB20: - | BC20: - | BE20: 0 | BF20: 0 | BG20: 0 | BH20: 0 | BJ20: 否 | BP20: - | BQ20: - | BR20: -
A21: 6945702914926777790 | B21: 6945702914926777790 | C21: 【老板周】复古风格 秋冬新款立体麻花织纹针织毛衣 | D21: 灰色;M(100-120斤);15天内发货 | E21: 1 | F21: 3772185880568135686 | G21: Z2418-灰色-M | H21: 329 | I21: 329 | J21: 0 | K21: 0 | L21: - | M21: - | N21: - | O21: 0 | P21: 0 | Q21: 0 | R21: 抖音支付 | S21: 0 | T21: *** | U21: *** | V21: 山西省 | W21: 大同市 | X21: 云冈区 | Y21: 新平旺街道 | Z21: *** | AA21: 否 | AC21: 2025-08-31 17:33:15 | AD21: 灰色 | AF21: 2025-09-21 10:50:13 | AG21: 2025-08-31 17:33:16 | AH21: 抖音极速版 | AI21: 精选联盟 | AJ21: 已完成 | AK21: 2025-09-15 17:33:17 | AL21: 普通订单 | AM21: 0 | AN21: 2353393836764088 | AO21: 老板周 | AP21: - | AQ21: - | AS21: - | AT21: - | AU21: - | AW21: 否 | AX21: 直播 | AY21: 广告 | AZ21: 直播 | BA21: 直播推荐 | BB21: - | BC21: - | BD21: 2025-09-15 10:48:28 | BE21: 0 | BF21: 0 | BG21: 0 | BH21: 0 | BJ21: 否 | BP21: - | BQ21: - | BR21: -
A22: 6945716202524317053 | B22: 6945716202524317053 | C22: 【老板周】复古风格 秋冬新款立体麻花织纹针织毛衣 | D22: 灰色;M(100-120斤);15天内发货 | E22: 1 | F22: 3772185880568135686 | G22: Z2418-灰色-M | H22: 329 | I22: 329 | J22: 0 | K22: 0 | L22: - | M22: - | N22: - | O22: 0 | P22: 0 | Q22: 0 | R22: 抖音月付 | S22: 0 | T22: *** | U22: *** | V22: 重庆市 | W22: 重庆市 | X22: 梁平区 | Y22: 双桂街道 | Z22: *** | AA22: 否 | AC22: 2025-08-31 17:32:47 | AD22: 蓝色 | AE22: SF3282428122123(收） Z2418-灰色-M*1# | AG22: 2025-08-31 17:32:49 | AH22: 抖音商城版 | AI22: 精选联盟 | AJ22: 已关闭 | AK22: 2025-09-15 17:32:50 | AL22: 普通订单 | AM22: 0 | AN22: 2353393836764088 | AO22: 老板周 | AP22: - | AQ22: 退款成功 | AS22: - | AT22: - | AU22: - | AW22: 否 | AX22: 无 | AY22: 其他 | AZ22: 直播 | BA22: 商城推荐 | BB22: - | BC22: - | BD22: 2025-09-14 23:53:25 | BE22: 0 | BF22: 0 | BG22: 0 | BH22: 0 | BJ22: 否 | BP22: - | BQ22: - | BR22: -
A23: 6921018667371494935 | B23: 6921018667371494935 | C23: 【老板周】复古风格 秋冬新款立体麻花织纹针织毛衣 | D23: 灰色;S(80-100斤);15天内发货 | E23: 1 | F23: 3772185880568135686 | G23: Z2418-灰色-S | H23: 329 | I23: 329 | J23: 0 | K23: 0 | L23: - | M23: - | N23: - | O23: 0 | P23: 0 | Q23: 0 | R23: 支付宝 | S23: 0 | T23: *** | U23: *** | V23: 浙江省 | W23: 丽水市 | X23: 莲都区 | Y23: 岩泉街道 | Z23: *** | AA23: 否 | AC23: 2025-08-31 17:32:37 | AD23: 蓝色 | AE23: 拦截;76740677006606(收） Z2418-灰色-S*1# | AG23: 2025-08-31 17:32:50 | AH23: 抖音 | AI23: 精选联盟 | AJ23: 已关闭 | AK23: 2025-09-15 17:32:50 | AL23: 普通订单 | AM23: 0 | AN23: 2353393836764088 | AO23: 老板周 | AP23: - | AQ23: 退款成功 | AS23: - | AT23: - | AU23: - | AW23: 否 | AX23: 直播 | AY23: 广告 | AZ23: 直播 | BA23: 商城推荐 | BB23: - | BC23: - | BD23: 2025-09-15 10:48:28 | BE23: 0 | BF23: 0 | BG23: 0 | BH23: 0 | BJ23: 否 | BP23: - | BQ23: - | BR23: -
A24: 6945696235709732402 | B24: 6945696235709732402 | C24: 【老板周】复古风格 秋冬新款立体麻花织纹针织毛衣 | D24: 灰色;S(80-100斤);15天内发货 | E24: 1 | F24: 3772185880568135686 | G24: Z2418-灰色-S | H24: 329 | I24: 329 | J24: 0 | K24: 2.05 | L24: - | M24: - | N24: - | O24: 0 | P24: 2.05 | Q24: 0 | R24: 抖音支付 | S24: 0 | T24: *** | U24: *** | V24: 浙江省 | W24: 丽水市 | X24: 青田县 | Y24: 瓯南街道 | Z24: *** | AA24: 否 | AC24: 2025-08-31 17:32:36 | AD24: 灰色 | AF24: 2025-09-22 10:48:28 | AG24: 2025-08-31 17:32:40 | AH24: 抖音 | AI24: 精选联盟 | AJ24: 已完成 | AK24: 2025-09-15 17:32:40 | AL24: 普通订单 | AM24: 0 | AN24: 2353393836764088 | AO24: 老板周 | AP24: - | AQ24: - | AS24: - | AT24: - | AU24: - | AW24: 否 | AX24: 无 | AY24: 其他 | AZ24: 直播 | BA24: 个人主页&店铺&橱窗进入直播间 | BB24: - | BC24: - | BD24: 2025-09-15 10:48:28 | BE24: 0 | BF24: 0 | BG24: 0 | BH24: 0 | BJ24: 否 | BP24: - | BQ24: - | BR24: -
A25: 6921009624776736703 | B25: 6921009624776736703 | C25: 【老板周】复古风格 秋冬新款立体麻花织纹针织毛衣 | D25: 灰色;M(100-120斤);15天内发货 | E25: 1 | F25: 3772185880568135686 | G25: Z2418-灰色-M | H25: 329 | I25: 329 | J25: 0 | K25: 0 | L25: - | M25: - | N25: - | O25: 0 | P25: 0 | Q25: 0 | R25: 抖音支付 | S25: 0 | T25: *** | U25: *** | V25: 江苏省 | W25: 苏州市 | X25: 虎丘区 | Y25: 东渚街道 | Z25: *** | AA25: 否 | AC25: 2025-08-31 17:32:33 | AD25: 灰色 | AG25: 2025-08-31 17:32:38 | AH25: 抖音 | AI25: 精选联盟 | AJ25: 已关闭 | AK25: 2025-09-15 17:32:39 | AL25: 普通订单 | AM25: 0 | AN25: 2353393836764088 | AO25: 老板周 | AP25: - | AQ25: 退款成功 | AS25: - | AT25: - | AU25: - | AW25: 否 | AX25: 无 | AY25: 其他 | AZ25: 直播 | BA25: 关注来源 | BB25: - | BC25: - | BE25: 0 | BF25: 0 | BG25: 0 | BH25: 0 | BJ25: 否 | BP25: - | BQ25: - | BR25: -
A26: 6921013958667763428 | B26: 6921013958667763428 | C26: 【老板周】复古风格 秋冬新款立体麻花织纹针织毛衣 | D26: 灰色;S(80-100斤);15天内发货 | E26: 1 | F26: 3772185880568135686 | G26: Z2418-灰色-S | H26: 329 | I26: 329 | J26: 0 | K26: 0 | L26: - | M26: - | N26: - | O26: 0 | P26: 0 | Q26: 0 | R26: 支付宝 | S26: 0 | T26: *** | U26: *** | V26: 贵州省 | W26: 贵阳市 | X26: 南明区 | Y26: 中曹司街道 | Z26: *** | AA26: 否 | AC26: 2025-08-31 17:32:31 | AD26: 灰色 | AG26: 2025-08-31 17:32:38 | AH26: 抖音 | AI26: 精选联盟 | AJ26: 已关闭 | AK26: 2025-09-15 17:32:38 | AL26: 普通订单 | AM26: 0 | AN26: 2353393836764088 | AO26: 老板周 | AP26: - | AQ26: 退款成功 | AS26: - | AT26: - | AU26: - | AW26: 否 | AX26: 无 | AY26: 其他 | AZ26: 直播 | BA26: 直播推荐 | BB26: - | BC26: - | BE26: 0 | BF26: 0 | BG26: 0 | BH26: 0 | BJ26: 否 | BP26: - | BQ26: - | BR26: -
A27: 6945698443959669805 | B27: 6945698443959669805 | C27: 【老板周】日系极简 春季新品圆领简约设计感无袖马甲 | D27: 黑色;L(120-135斤);15天内发货 | E27: 1 | F27: 3767004410471907465 | G27: Z1640-黑色-L | H27: 289 | I27: 314 | J27: 25 | K27: 0 | L27: - | M27: - | N27: - | O27: 0 | P27: 0 | Q27: 0 | R27: 抖音月付 | S27: 0 | T27: *** | U27: *** | V27: 陕西省 | W27: 咸阳市 | X27: 渭城区 | Y27: 周陵街道 | Z27: *** | AA27: 否 | AC27: 2025-08-31 16:17:00 | AD27: 灰色 | AF27: 2025-09-19 16:35:27 | AG27: 2025-08-31 16:17:05 | AH27: 抖音 | AI27: 精选联盟 | AJ27: 已完成 | AK27: 2025-09-15 16:17:05 | AL27: 普通订单 | AM27: 0 | AN27: 2353393836764088 | AO27: 老板周 | AP27: - | AQ27: - | AS27: - | AT27: - | AU27: - | AW27: 否 | AX27: 无 | AY27: 其他 | AZ27: 直播 | BA27: 直播推荐 | BB27: - | BC27: - | BD27: 2025-09-12 16:35:27 | BE27: 0 | BF27: 0 | BG27: 0 | BH27: 0 | BJ27: 否 | BP27: - | BQ27: - | BR27: -
A28: 6945649067193472893 | B28: 6945649067193472893 | C28: 【老板周】日系极简 春季新品圆领简约设计感无袖马甲 | D28: 黑色;S(80-100斤);15天内发货 | E28: 1 | F28: 3767004410471907465 | G28: Z1640-黑色-S | H28: 289 | I28: 254.06 | J28: 0 | K28: 35.86 | L28: 平台七夕消费券-34.94 | M28: - | N28: - | O28: 0 | P28: 0.92 | Q28: 0 | R28: 抖音支付 | S28: 0 | T28: *** | U28: *** | V28: 辽宁省 | W28: 大连市 | X28: 中山区 | Y28: - | Z28: *** | AA28: 否 | AC28: 2025-08-29 20:47:38 | AD28: 灰色 | AE28: (收)[Z1640-黑色-S]*[1]# | AF28: 2025-09-18 23:58:12 | AG28: 2025-08-29 20:47:40 | AH28: 抖音 | AI28: 精选联盟 | AJ28: 已完成 | AK28: 2025-09-13 20:47:41 | AL28: 普通订单 | AM28: 0 | AN28: 2353393836764088 | AO28: 老板周 | AP28: - | AQ28: 退款成功 | AS28: - | AT28: - | AU28: - | AW28: 否 | AX28: 无 | AY28: 其他 | AZ28: 直播 | BA28: 搜索 | BB28: - | BC28: - | BD28: 2025-09-11 23:58:12 | BE28: 0 | BF28: 34.94 | BG28: 0 | BH28: 0 | BJ28: 否 | BP28: - | BQ28: - | BR28: -
A29: 6920964153135168659 | B29: 6920964153135168659 | C29: 【老板周】小众休闲 压褶松紧腰宽松百搭裤裙 | D29: 藏蓝色;M(95-110斤);15天内发货 | E29: 1 | F29: 3770653191356678342 | G29: Z575-藏蓝色-M | H29: 299 | I29: 299 | J29: 0 | K29: 0 | L29: - | M29: - | N29: - | O29: 0 | P29: 0 | Q29: 0 | R29: 抖音支付 | S29: 0 | T29: *** | U29: *** | V29: 内蒙古自治区 | W29: 呼和浩特市 | X29: 新城区 | Y29: 成吉思汗大街街道 | Z29: *** | AA29: 否 | AC29: 2025-08-28 22:10:07 | AD29: 灰色 | AH29: 抖音 | AI29: 小店自卖 | AJ29: 已关闭 | AK29: 2025-09-12 22:10:07 | AL29: 普通订单 | AM29: 0 | AN29: 0 | AP29: - | AQ29: - | AR29: 用户超时未支付自动取消 | AS29: - | AT29: - | AU29: - | AW29: 否 | AX29: 无 | AY29: 其他 | AZ29: 商品卡 | BA29: 店铺页面 | BB29: - | BC29: - | BE29: 0 | BF29: 0 | BG29: 0 | BH29: 0 | BJ29: 否 | BP29: - | BQ29: - | BR29: -
A30: 6920966085271780499 | B30: 6920966085271780499 | C30: 【老板周】小众休闲 压褶松紧腰宽松百搭裤裙 | D30: 藏蓝色;M(95-110斤);15天内发货 | E30: 1 | F30: 3770653191356678342 | G30: Z575-藏蓝色-M | H30: 299 | I30: 299 | J30: 0 | K30: 0 | L30: - | M30: - | N30: - | O30: 0 | P30: 0 | Q30: 0 | R30: 抖音支付 | S30: 0 | T30: *** | U30: *** | V30: 内蒙古自治区 | W30: 呼和浩特市 | X30: 新城区 | Y30: 成吉思汗大街街道 | Z30: *** | AA30: 否 | AC30: 2025-08-28 22:09:25 | AD30: 灰色 | AH30: 抖音 | AI30: 小店自卖 | AJ30: 已关闭 | AK30: 2025-09-12 22:09:25 | AL30: 普通订单 | AM30: 0 | AN30: 0 | AP30: - | AQ30: - | AR30: 用户超时未支付自动取消 | AS30: - | AT30: - | AU30: - | AW30: 否 | AX30: 无 | AY30: 其他 | AZ30: 商品卡 | BA30: 店铺页面 | BB30: - | BC30: - | BE30: 0 | BF30: 0 | BG30: 0 | BH30: 0 | BJ30: 否 | BP30: - | BQ30: - | BR30: -
A31: 6945610806981695196 | B31: 6945610806981695196 | C31: 【老板周】日系极简 春季新品圆领简约设计感无袖马甲 | D31: 黑色;M(100-120斤);15天内发货 | E31: 1 | F31: 3767004410471907465 | G31: Z1640-黑色-M | H31: 289 | I31: 260.12 | J31: 0 | K31: 28.88 | L31: 平台七夕消费券-28.88 | M31: - | N31: - | O31: 0 | P31: 0 | Q31: 0 | R31: 抖音月付 | S31: 0 | T31: *** | U31: *** | V31: 河北省 | W31: 邢台市 | X31: 信都区 | Y31: 达活泉街道 | Z31: *** | AA31: 否 | AC31: 2025-08-28 11:04:59 | AD31: 红色 | AE31: SF3234099112861(收） Z1640-黑色-M*1#;换货(6298912)#;换货76743232979811 收到退款 不换货了 | AF31: 2025-09-14 23:31:58 | AG31: 2025-08-28 11:05:06 | AH31: 抖音 | AI31: 精选联盟 | AJ31: 已完成 | AK31: 2025-09-12 11:05:07 | AL31: 普通订单 | AM31: 0 | AN31: 2353393836764088 | AO31: 老板周 | AP31: - | AQ31: 退款成功 | AS31: - | AT31: - | AU31: - | AW31: 否 | AX31: 无 | AY31: 其他 | AZ31: 商品卡 | BA31: 橱窗 | BB31: - | BC31: - | BD31: 2025-09-07 23:31:58 | BE31: 0 | BF31: 28.88 | BG31: 0 | BH31: 0 | BJ31: 否 | BP31: - | BQ31: - | BR31: -
A32: 6920952081164304100 | B32: 6920952081164304100 | C32: 【老板周】日系极简 春季新品圆领简约设计感无袖马甲 | D32: 黑色;M(100-120斤);15天内发货 | E32: 1 | F32: 3767004410471907465 | G32: Z1640-黑色-M | H32: 289 | I32: 289 | J32: 0 | K32: 0 | L32: - | M32: - | N32: - | O32: 0 | P32: 0 | Q32: 0 | R32: 抖音支付 | S32: 0 | T32: *** | U32: *** | V32: 山东省 | W32: 菏泽市 | X32: 牡丹区 | Y32: 牡丹街道 | Z32: *** | AA32: 否 | AC32: 2025-08-28 00:21:12 | AD32: 灰色 | AG32: 2025-08-28 00:21:13 | AH32: 抖音 | AI32: 小店自卖 | AJ32: 已关闭 | AK32: 2025-09-12 00:21:13 | AL32: 普通订单 | AM32: 0 | AN32: 0 | AP32: - | AQ32: 退款成功 | AS32: - | AT32: - | AU32: - | AW32: 否 | AX32: 无 | AY32: 其他 | AZ32: 商品卡 | BA32: 搜索 | BB32: - | BC32: - | BE32: 0 | BF32: 0 | BG32: 0 | BH32: 0 | BJ32: 否 | BP32: - | BQ32: - | BR32: -
A33: 6945587885982618859 | B33: 6945587885982618859 | C33: 【老板周】日系极简 春季新品圆领简约设计感无袖马甲 | D33: 黑色;M(100-120斤);15天内发货 | E33: 1 | F33: 3767004410471907465 | G33: Z1640-黑色-M | H33: 289 | I33: 278 | J33: 0 | K33: 11 | L33: 平台专属限时优惠券-11.00 | M33: - | N33: - | O33: 0 | P33: 0 | Q33: 0 | R33: 抖音支付 | S33: 0 | T33: *** | U33: *** | V33: 山东省 | W33: 青岛市 | X33: 市北区 | Y33: 河西街道 | Z33: *** | AA33: 否 | AC33: 2025-08-27 22:38:33 | AD33: 灰色 | AG33: 2025-08-27 22:38:44 | AH33: 抖音商城版 | AI33: 精选联盟 | AJ33: 已关闭 | AK33: 2025-09-11 22:38:44 | AL33: 普通订单 | AM33: 0 | AN33: 2353393836764088 | AO33: 老板周 | AP33: - | AQ33: 退款成功 | AS33: - | AT33: - | AU33: - | AW33: 否 | AX33: 直播 | AY33: 广告 | AZ33: 直播 | BA33: 商城推荐 | BB33: - | BC33: - | BE33: 0 | BF33: 11 | BG33: 0 | BH33: 0 | BJ33: 否 | BP33: - | BQ33: - | BR33: -
A34: 6945598979942323318 | B34: 6945598979942323318 | C34: 【老板周】日系极简 春季新品圆领简约设计感无袖马甲 | D34: 黑色;M(100-120斤);15天内发货 | E34: 1 | F34: 3767004410471907465 | G34: Z1640-黑色-M | H34: 289 | I34: 289 | J34: 0 | K34: 0 | L34: - | M34: - | N34: - | O34: 0 | P34: 0 | Q34: 0 | R34: 抖音支付 | S34: 0 | T34: *** | U34: *** | V34: 天津市 | W34: 天津市 | X34: 武清区 | Y34: 东蒲洼街道 | Z34: *** | AA34: 否 | AC34: 2025-08-27 22:12:00 | AD34: 灰色 | AF34: 2025-09-14 23:31:58 | AG34: 2025-08-27 22:12:06 | AH34: 头条lite-抖音电商 | AI34: 精选联盟 | AJ34: 已完成 | AK34: 2025-09-11 22:12:06 | AL34: 普通订单 | AM34: 0 | AN34: 2353393836764088 | AO34: 老板周 | AP34: - | AQ34: - | AS34: - | AT34: - | AU34: - | AW34: 否 | AX34: 无 | AY34: 其他 | AZ34: 直播 | BA34: 头条西瓜 | BB34: - | BC34: - | BD34: 2025-09-07 23:31:58 | BE34: 0 | BF34: 0 | BG34: 0 | BH34: 0 | BJ34: 否 | BP34: - | BQ34: - | BR34: -
A35: 6945583048360597411 | B35: 6945583048360597411 | C35: 【老板周】日系极简 春季新品圆领简约设计感无袖马甲 | D35: 黑色;M(100-120斤);15天内发货 | E35: 1 | F35: 3767004410471907465 | G35: Z1640-黑色-M | H35: 289 | I35: 289 | J35: 0 | K35: 0 | L35: - | M35: - | N35: - | O35: 0 | P35: 0 | Q35: 0 | R35: 抖音月付 | S35: 0 | T35: *** | U35: *** | V35: 山东省 | W35: 日照市 | X35: 莒县 | Y35: 城阳街道 | Z35: *** | AA35: 否 | AC35: 2025-08-27 20:47:29 | AD35: 蓝色 | AE35: 73572507159291(收） Z1640-黑色-M*1# | AG35: 2025-08-27 20:47:31 | AH35: 抖音 | AI35: 精选联盟 | AJ35: 已关闭 | AK35: 2025-09-11 20:47:32 | AL35: 普通订单 | AM35: 0 | AN35: 2353393836764088 | AO35: 老板周 | AP35: - | AQ35: 退款成功 | AS35: - | AT35: - | AU35: - | AW35: 否 | AX35: 无 | AY35: 其他 | AZ35: 直播 | BA35: 直播推荐 | BB35: - | BC35: - | BD35: 2025-09-07 23:31:58 | BE35: 0 | BF35: 0 | BG35: 0 | BH35: 0 | BJ35: 否 | BP35: - | BQ35: - | BR35: -
A36: 6945609733810165452 | B36: 6945609733810165452 | C36: 【老板周】日系极简 春季新品圆领简约设计感无袖马甲 | D36: 黑色;M(100-120斤);15天内发货 | E36: 1 | F36: 3767004410471907465 | G36: Z1640-黑色-M | H36: 289 | I36: 289 | J36: 0 | K36: 0 | L36: - | M36: - | N36: - | O36: 0 | P36: 0 | Q36: 0 | R36: 支付宝 | S36: 0 | T36: *** | U36: *** | V36: 山西省 | W36: 太原市 | X36: 杏花岭区 | Y36: 中涧河镇 | Z36: *** | AA36: 否 | AC36: 2025-08-27 19:52:03 | AD36: 灰色 | AH36: 番茄小说-抖音电商 | AI36: 精选联盟 | AJ36: 已关闭 | AK36: 2025-09-11 19:52:03 | AL36: 普通订单 | AM36: 0 | AN36: 2353393836764088 | AO36: 老板周 | AP36: - | AQ36: - | AR36: 用户超时未支付自动取消 | AS36: - | AT36: - | AU36: - | AW36: 否 | AX36: 直播 | AY36: 广告 | AZ36: 直播 | BA36: 其他 | BB36: - | BC36: - | BE36: 0 | BF36: 0 | BG36: 0 | BH36: 0 | BJ36: 否 | BP36: - | BQ36: - | BR36: -
A37: 6945592088900211946 | B37: 6945592088900211946 | C37: 【老板周】日系极简 春季新品圆领简约设计感无袖马甲 | D37: 黑色;M(100-120斤);15天内发货 | E37: 1 | F37: 3767004410471907465 | G37: Z1640-黑色-M | H37: 289 | I37: 289 | J37: 0 | K37: 0 | L37: - | M37: - | N37: - | O37: 0 | P37: 0 | Q37: 0 | R37: 抖音支付 | S37: 0 | T37: *** | U37: *** | V37: 江苏省 | W37: 常州市 | X37: 钟楼区 | Y37: 南大街道 | Z37: *** | AA37: 否 | AC37: 2025-08-27 18:21:49 | AD37: 蓝色 | AE37: SF3232586273829(收） Z1640-黑色-M*1# | AG37: 2025-08-27 18:21:55 | AH37: 抖音 | AI37: 精选联盟 | AJ37: 已关闭 | AK37: 2025-09-11 18:21:55 | AL37: 普通订单 | AM37: 0 | AN37: 2353393836764088 | AO37: 老板周 | AP37: - | AQ37: 退款成功 | AS37: - | AT37: - | AU37: - | AW37: 否 | AX37: 直播 | AY37: 广告 | AZ37: 直播 | BA37: 搜索 | BB37: - | BC37: - | BD37: 2025-09-07 23:31:58 | BE37: 0 | BF37: 0 | BG37: 0 | BH37: 0 | BJ37: 否 | BP37: - | BQ37: - | BR37: -
A38: 6945600734649980653 | B38: 6945600734649980653 | C38: 【老板周】日系极简 春季新品圆领简约设计感无袖马甲 | D38: 黑色;M(100-120斤);15天内发货 | E38: 1 | F38: 3767004410471907465 | G38: Z1640-黑色-M | H38: 289 | I38: 289 | J38: 0 | K38: 0 | L38: - | M38: - | N38: - | O38: 0 | P38: 0 | Q38: 0 | R38: 抖音支付 | S38: 0 | T38: *** | U38: *** | V38: 浙江省 | W38: 杭州市 | X38: 临平区 | Y38: 乔司街道 | Z38: *** | AA38: 否 | AC38: 2025-08-27 17:46:07 | AD38: 蓝色 | AE38: 78939136440697(收） Z1640-黑色-S*1# | AG38: 2025-08-27 17:46:08 | AH38: 抖音 | AI38: 精选联盟 | AJ38: 已关闭 | AK38: 2025-09-11 17:46:09 | AL38: 普通订单 | AM38: 0 | AN38: 2353393836764088 | AO38: 老板周 | AP38: - | AQ38: 退款成功 | AS38: - | AT38: - | AU38: - | AW38: 否 | AX38: 无 | AY38: 其他 | AZ38: 直播 | BA38: 短视频引流直播间 | BB38: - | BC38: - | BD38: 2025-09-07 23:31:58 | BE38: 0 | BF38: 0 | BG38: 0 | BH38: 0 | BJ38: 否 | BP38: - | BQ38: - | BR38: -
A39: 6945589601420317825 | B39: 6945589601420317825 | C39: 【老板周】日系极简 春季新品圆领简约设计感无袖马甲 | D39: 黑色;M(100-120斤);15天内发货 | E39: 1 | F39: 3767004410471907465 | G39: Z1640-黑色-M | H39: 289 | I39: 289 | J39: 0 | K39: 0 | L39: - | M39: - | N39: - | O39: 0 | P39: 0 | Q39: 0 | R39: 抖音支付 | S39: 0 | T39: *** | U39: *** | V39: 江苏省 | W39: 南通市 | X39: 崇川区 | Y39: 观音山街道 | Z39: *** | AA39: 否 | AC39: 2025-08-27 17:31:54 | AD39: 红色 | AE39: SF3232813766922(收） Z1640-黑色-M*1#;换货(6280100)#;换货76742192082926 | AF39: 2025-09-14 23:31:58 | AG39: 2025-08-27 17:31:55 | AH39: 抖音 | AI39: 精选联盟 | AJ39: 已完成 | AK39: 2025-09-11 17:31:56 | AL39: 普通订单 | AM39: 0 | AN39: 2353393836764088 | AO39: 老板周 | AP39: - | AQ39: 换货成功 | AS39: - | AT39: - | AU39: - | AW39: 否 | AX39: 无 | AY39: 其他 | AZ39: 直播 | BA39: 直播推荐 | BB39: - | BC39: - | BD39: 2025-09-07 23:31:58 | BE39: 0 | BF39: 0 | BG39: 0 | BH39: 0 | BJ39: 否 | BP39: - | BQ39: - | BR39: -
A40: 6920950993200905666 | B40: 6920950993200905666 | C40: 【老板周】日系极简 春季新品圆领简约设计感无袖马甲 | D40: 黑色;M(100-120斤);15天内发货 | E40: 8 | F40: 3767004410471907465 | G40: Z1640-黑色-M | H40: 289 | I40: 2312 | J40: 0 | K40: 0 | L40: - | M40: - | N40: - | O40: 0 | P40: 0 | Q40: 0 | R40: 支付宝 | S40: 0 | T40: *** | U40: *** | V40: 山东省 | W40: 济宁市 | X40: 微山县 | Y40: - | Z40: *** | AA40: 否 | AC40: 2025-08-27 17:23:35 | AD40: 灰色 | AH40: 头条lite-抖音电商 | AI40: 精选联盟 | AJ40: 已关闭 | AK40: 2025-09-11 17:23:35 | AL40: 普通订单 | AM40: 0 | AN40: 2353393836764088 | AO40: 老板周 | AP40: - | AQ40: - | AR40: 用户超时未支付自动取消 | AS40: - | AT40: - | AU40: - | AW40: 否 | AX40: 直播 | AY40: 广告 | AZ40: 直播 | BA40: 头条西瓜 | BB40: - | BC40: - | BE40: 0 | BF40: 0 | BG40: 0 | BH40: 0 | BJ40: 否 | BP40: - | BQ40: - | BR40: -
A41: 6945602769375205012 | B41: 6945602769375205012 | C41: 【老板周】日系极简 春季新品圆领简约设计感无袖马甲 | D41: 黑色;L(120-135斤);15天内发货 | E41: 1 | F41: 3767004410471907465 | G41: Z1640-黑色-L | H41: 289 | I41: 289 | J41: 0 | K41: 0 | L41: - | M41: - | N41: - | O41: 0 | P41: 0 | Q41: 0 | R41: 抖音支付 | S41: 0 | T41: *** | U41: *** | V41: 安徽省 | W41: 芜湖市 | X41: 南陵县 | Y41: 许镇镇 | Z41: *** | AA41: 否 | AC41: 2025-08-27 16:36:08 | AD41: 灰色 | AF41: 2025-09-14 17:22:20 | AG41: 2025-08-27 16:36:13 | AH41: 抖音 | AI41: 精选联盟 | AJ41: 已完成 | AK41: 2025-09-11 16:36:13 | AL41: 普通订单 | AM41: 0 | AN41: 2353393836764088 | AO41: 老板周 | AP41: - | AQ41: - | AS41: - | AT41: - | AU41: - | AW41: 否 | AX41: 无 | AY41: 其他 | AZ41: 直播 | BA41: 直播推荐 | BB41: - | BC41: - | BD41: 2025-09-07 17:22:20 | BE41: 0 | BF41: 0 | BG41: 0 | BH41: 0 | BJ41: 否 | BP41: - | BQ41: - | BR41: -
A42: 6945580306812376109 | B42: 6945580306812376109 | C42: 【老板周】简约法式 秋冬复古叠穿日系开叉百搭马甲 | D42: 黑色;S(80-100斤);15天内发货 | E42: 1 | F42: 3770720616102101370 | G42: Z2328-黑色-S | H42: 319 | I42: 319 | J42: 0 | K42: 0 | L42: - | M42: - | N42: - | O42: 0 | P42: 0 | Q42: 0 | R42: 抖音月付 | S42: 0 | T42: *** | U42: *** | V42: 宁夏回族自治区 | W42: 银川市 | X42: 金凤区 | Y42: 北京中路街道 | Z42: *** | AA42: 否 | AC42: 2025-08-27 16:11:55 | AD42: 蓝色 | AE42: SF3239328943996(收） Z2328-黑色-S*1# | AG42: 2025-08-27 16:11:56 | AH42: 抖音 | AI42: 小店自卖 | AJ42: 已关闭 | AK42: 2025-09-11 16:11:57 | AL42: 普通订单 | AM42: 0 | AN42: 0 | AP42: - | AQ42: 退款成功 | AS42: - | AT42: - | AU42: - | AW42: 否 | AX42: 无 | AY42: 其他 | AZ42: 商品卡 | BA42: 店铺页面 | BB42: - | BC42: - | BD42: 2025-08-27 18:02:40 | BE42: 0 | BF42: 0 | BG42: 0 | BH42: 0 | BJ42: 否 | BP42: - | BQ42: - | BR42: -
A43: 6945596186333484482 | B43: 6945596186333484482 | C43: 【老板周】日系极简 春季新品圆领简约设计感无袖马甲 | D43: 黑色;M(100-120斤);15天内发货 | E43: 1 | F43: 3767004410471907465 | G43: Z1640-黑色-M | H43: 289 | I43: 289 | J43: 0 | K43: 0 | L43: - | M43: - | N43: - | O43: 0 | P43: 0 | Q43: 0 | R43: 抖音月付 | S43: 0 | T43: *** | U43: *** | V43: 安徽省 | W43: 亳州市 | X43: 谯城区 | Y43: 花戏楼街道 | Z43: *** | AA43: 否 | AC43: 2025-08-27 15:44:54 | AD43: 灰色 | AG43: 2025-08-27 15:44:59 | AH43: 抖音 | AI43: 精选联盟 | AJ43: 已关闭 | AK43: 2025-09-11 15:44:59 | AL43: 普通订单 | AM43: 0 | AN43: 2353393836764088 | AO43: 老板周 | AP43: - | AQ43: 退款成功 | AS43: - | AT43: - | AU43: - | AW43: 否 | AX43: 无 | AY43: 其他 | AZ43: 直播 | BA43: 直播推荐 | BB43: - | BC43: - | BE43: 0 | BF43: 0 | BG43: 0 | BH43: 0 | BJ43: 否 | BP43: - | BQ43: - | BR43: -
A44: 6920955047060602569 | B44: 6920955047060602569 | C44: 【老板周】日系极简 春季新品圆领简约设计感无袖马甲 | D44: 黑色;M(100-120斤);15天内发货 | E44: 1 | F44: 3767004410471907465 | G44: Z1640-黑色-M | H44: 289 | I44: 289 | J44: 0 | K44: 0 | L44: - | M44: - | N44: - | O44: 0 | P44: 0 | Q44: 0 | R44: 抖音支付 | S44: 0 | T44: *** | U44: *** | V44: 黑龙江省 | W44: 牡丹江市 | X44: 绥芬河市 | Y44: 绥芬河镇 | Z44: *** | AA44: 否 | AC44: 2025-08-27 15:44:26 | AD44: 蓝色 | AE44: SF3282828296194(收） Z1640-黑色-M*1# | AG44: 2025-08-27 15:44:27 | AH44: 抖音 | AI44: 精选联盟 | AJ44: 已关闭 | AK44: 2025-09-11 15:44:27 | AL44: 普通订单 | AM44: 0 | AN44: 2353393836764088 | AO44: 老板周 | AP44: - | AQ44: 退款成功 | AS44: - | AT44: - | AU44: - | AW44: 否 | AX44: 无 | AY44: 其他 | AZ44: 直播 | BA44: 个人主页&店铺&橱窗进入直播间 | BB44: - | BC44: - | BD44: 2025-09-07 23:31:59 | BE44: 0 | BF44: 0 | BG44: 0 | BH44: 0 | BJ44: 否 | BP44: - | BQ44: - | BR44: -
A45: 6945604921919543082 | B45: 6945604921919543082 | C45: 【老板周】日系极简 春季新品圆领简约设计感无袖马甲 | D45: 黑色;L(120-135斤);15天内发货 | E45: 1 | F45: 3767004410471907465 | G45: Z1640-黑色-L | H45: 289 | I45: 289 | J45: 0 | K45: 0 | L45: - | M45: - | N45: - | O45: 0 | P45: 0 | Q45: 0 | R45: 支付宝 | S45: 0 | T45: *** | U45: *** | V45: 上海市 | W45: 上海市 | X45: 杨浦区 | Y45: 控江路街道 | Z45: *** | AA45: 否 | AC45: 2025-08-27 15:37:02 | AD45: 灰色 | AG45: 2025-08-27 15:37:07 | AH45: 抖音 | AI45: 精选联盟 | AJ45: 已关闭 | AK45: 2025-09-11 15:37:08 | AL45: 普通订单 | AM45: 0 | AN45: 2353393836764088 | AO45: 老板周 | AP45: - | AQ45: 退款成功 | AS45: - | AT45: - | AU45: - | AW45: 否 | AX45: 无 | AY45: 其他 | AZ45: 直播 | BA45: 直播推荐 | BB45: - | BC45: - | BE45: 0 | BF45: 0 | BG45: 0 | BH45: 0 | BJ45: 否 | BP45: - | BQ45: - | BR45: -
A46: 6945582609766290962 | B46: 6945582609766290962 | C46: 【老板周】日系极简 春季新品圆领简约设计感无袖马甲 | D46: 黑色;M(100-120斤);15天内发货 | E46: 1 | F46: 3767004410471907465 | G46: Z1640-黑色-M | H46: 289 | I46: 274.3 | J46: 0 | K46: 14.7 | L46: 平台七夕消费券-14.70 | M46: - | N46: - | O46: 0 | P46: 0 | Q46: 0 | R46: 抖音月付 | S46: 0 | T46: *** | U46: *** | V46: 安徽省 | W46: 安庆市 | X46: 宜秀区 | Y46: 菱北街道 | Z46: *** | AA46: 否 | AC46: 2025-08-27 15:34:06 | AD46: 灰色 | AF46: 2025-09-14 23:31:58 | AG46: 2025-08-27 15:34:12 | AH46: 抖音 | AI46: 精选联盟 | AJ46: 已完成 | AK46: 2025-09-11 15:34:13 | AL46: 普通订单 | AM46: 0 | AN46: 2353393836764088 | AO46: 老板周 | AP46: - | AQ46: - | AS46: - | AT46: - | AU46: - | AW46: 否 | AX46: 无 | AY46: 其他 | AZ46: 直播 | BA46: 直播推荐 | BB46: - | BC46: - | BD46: 2025-09-07 23:31:58 | BE46: 0 | BF46: 14.7 | BG46: 0 | BH46: 0 | BJ46: 否 | BP46: - | BQ46: - | BR46: -
A47: 6945579848162809517 | B47: 6945579848162809517 | C47: 【老板周】日系极简 春季新品圆领简约设计感无袖马甲 | D47: 黑色;M(100-120斤);15天内发货 | E47: 1 | F47: 3767004410471907465 | G47: Z1640-黑色-M | H47: 289 | I47: 261 | J47: 0 | K47: 28 | L47: 平台商城爆神券-28.00 | M47: - | N47: - | O47: 0 | P47: 0 | Q47: 0 | R47: 抖音月付 | S47: 0 | T47: *** | U47: *** | V47: 天津市 | W47: 天津市 | X47: 河北区 | Y47: 建昌道街道 | Z47: *** | AA47: 否 | AC47: 2025-08-27 12:05:08 | AD47: 灰色 | AG47: 2025-08-27 12:05:09 | AH47: 抖音 | AI47: 小店自卖 | AJ47: 已关闭 | AK47: 2025-09-11 12:05:09 | AL47: 普通订单 | AM47: 0 | AN47: 0 | AP47: - | AQ47: 退款成功 | AS47: - | AT47: - | AU47: - | AW47: 否 | AX47: 无 | AY47: 其他 | AZ47: 商品卡 | BA47: 其他 | BB47: - | BC47: - | BE47: 0 | BF47: 28 | BG47: 0 | BH47: 0 | BJ47: 否 | BP47: - | BQ47: - | BR47: -
A48: 6945600144409499309 | B48: 6945600144409499309 | C48: 【老板周】日系极简 春季新品圆领简约设计感无袖马甲 | D48: 黑色;M(100-120斤);15天内发货 | E48: 1 | F48: 3767004410471907465 | G48: Z1640-黑色-M | H48: 289 | I48: 269 | J48: 0 | K48: 20 | L48: 平台商城爆神券-20.00 | M48: - | N48: - | O48: 0 | P48: 0 | Q48: 0 | R48: 抖音月付 | S48: 0 | T48: *** | U48: *** | V48: 天津市 | W48: 天津市 | X48: 河北区 | Y48: 建昌道街道 | Z48: *** | AA48: 否 | AC48: 2025-08-27 12:04:05 | AD48: 灰色 | AG48: 2025-08-27 12:04:07 | AH48: 抖音 | AI48: 小店自卖 | AJ48: 已关闭 | AK48: 2025-09-11 12:04:07 | AL48: 普通订单 | AM48: 0 | AN48: 0 | AP48: - | AQ48: 退款成功 | AS48: - | AT48: - | AU48: - | AW48: 否 | AX48: 无 | AY48: 其他 | AZ48: 商品卡 | BA48: 其他 | BB48: - | BC48: - | BE48: 0 | BF48: 20 | BG48: 0 | BH48: 0 | BJ48: 否 | BP48: - | BQ48: - | BR48: -
A49: 6920942457770770369 | B49: 6920942457770770369 | C49: 【老板周】日系极简 春季新品圆领简约设计感无袖马甲 | D49: 黑色;M(100-120斤);15天内发货 | E49: 1 | F49: 3767004410471907465 | G49: Z1640-黑色-M | H49: 289 | I49: 289 | J49: 0 | K49: 0 | L49: - | M49: - | N49: - | O49: 0 | P49: 0 | Q49: 0 | R49: 抖音支付 | S49: 0 | T49: *** | U49: *** | V49: 吉林省 | W49: 长春市 | X49: 宽城区 | Y49: 北湖街道 | Z49: *** | AA49: 是 | AC49: 2025-08-27 09:37:49 | AD49: 灰色 | AG49: 2025-08-27 09:37:52 | AH49: 抖音 | AI49: 小店自卖 | AJ49: 已关闭 | AK49: 2025-09-11 09:37:52 | AL49: 普通订单 | AM49: 0 | AN49: 0 | AP49: - | AQ49: 退款成功 | AS49: - | AT49: - | AU49: - | AW49: 否 | AX49: 无 | AY49: 其他 | AZ49: 商品卡 | BA49: 店铺页面 | BB49: - | BC49: - | BE49: 0 | BF49: 0 | BG49: 0 | BH49: 0 | BJ49: 否 | BP49: - | BQ49: - | BR49: -
A50: 6945586204071892038 | B50: 6945586204071892038 | C50: 【老板周】日系极简 春季新品圆领简约设计感无袖马甲 | D50: 黑色;M(100-120斤);15天内发货 | E50: 1 | F50: 3767004410471907465 | G50: Z1640-黑色-M | H50: 289 | I50: 289 | J50: 0 | K50: 0 | L50: - | M50: - | N50: - | O50: 0 | P50: 0 | Q50: 0 | R50: 抖音支付 | S50: 0 | T50: *** | U50: *** | V50: 四川省 | W50: 凉山彝族自治州 | X50: 西昌市 | Y50: 西城街道 | Z50: *** | AA50: 否 | AC50: 2025-08-27 00:48:22 | AD50: 灰色 | AG50: 2025-08-27 00:48:30 | AH50: 抖音 | AI50: 精选联盟 | AJ50: 已关闭 | AK50: 2025-09-11 00:48:30 | AL50: 普通订单 | AM50: 0 | AN50: 2353393836764088 | AO50: 老板周 | AP50: - | AQ50: 退款成功 | AS50: - | AT50: - | AU50: - | AW50: 否 | AX50: 无 | AY50: 其他 | AZ50: 商品卡 | BA50: 橱窗 | BB50: - | BC50: - | BE50: 0 | BF50: 0 | BG50: 0 | BH50: 0 | BJ50: 否 | BP50: - | BQ50: - | BR50: -
A51: 6945547648096343360 | B51: 6945547648096343360 | C51: 【老板周】日系极简 春季新品圆领简约设计感无袖马甲 | D51: 黑色;L(120-135斤);15天内发货 | E51: 1 | F51: 3767004410471907465 | G51: Z1640-黑色-L | H51: 289 | I51: 265.32 | J51: 0 | K51: 23.68 | L51: 平台七夕消费券-23.68 | M51: - | N51: - | O51: 0 | P51: 0 | Q51: 0 | R51: 抖音月付 | S51: 0 | T51: *** | U51: *** | V51: 山东省 | W51: 济南市 | X51: 市中区 | Y51: 魏家庄街道 | Z51: *** | AA51: 否 | AC51: 2025-08-26 16:11:45 | AD51: 蓝色 | AE51: 73570762450162(收） Z1576-黑色-L*1# | AG51: 2025-08-26 16:11:50 | AH51: 抖音 | AI51: 小店自卖 | AJ51: 已关闭 | AK51: 2025-09-10 16:11:51 | AL51: 普通订单 | AM51: 0 | AN51: 0 | AP51: - | AQ51: 退款成功 | AS51: - | AT51: - | AU51: - | AW51: 否 | AX51: 无 | AY51: 其他 | AZ51: 商品卡 | BA51: 购后页面 | BB51: - | BC51: - | BE51: 0 | BF51: 23.68 | BG51: 0 | BH51: 0 | BJ51: 否 | BP51: - | BQ51: - | BR51: -
A52: 6945547648096343360 | B52: 6945547648096408896 | C52: 【老板周】时髦撞色 春季新款假两件显瘦长袖打底T恤上衣 | D52: 黑色;L(120-135斤);15天内发货 | E52: 1 | F52: 3770648898645918626 | G52: Z1576-黑色-L | H52: 199 | I52: 182.68 | J52: 0 | K52: 16.32 | L52: 平台七夕消费券-16.32 | M52: - | N52: - | O52: 0 | P52: 0 | Q52: 0 | R52: 抖音月付 | S52: 0 | T52: *** | U52: *** | V52: 山东省 | W52: 济南市 | X52: 市中区 | Y52: 魏家庄街道 | Z52: *** | AA52: 否 | AC52: 2025-08-26 16:11:45 | AD52: 蓝色 | AE52: 73570762450162(收） Z1576-黑色-L*1# | AG52: 2025-08-26 16:11:50 | AH52: 抖音 | AI52: 小店自卖 | AJ52: 已关闭 | AK52: 2025-09-10 16:11:51 | AL52: 普通订单 | AM52: 0 | AN52: 0 | AP52: - | AQ52: 退款成功 | AS52: - | AT52: - | AU52: - | AW52: 否 | AX52: 无 | AY52: 其他 | AZ52: 商品卡 | BA52: 购后页面 | BB52: - | BC52: - | BD52: 2025-08-31 23:42:42 | BE52: 0 | BF52: 16.32 | BG52: 0 | BH52: 0 | BJ52: 否 | BP52: - | BQ52: - | BR52: -
A53: 6945550015473390912 | B53: 6945550015473390912 | C53: 【老板周】时髦撞色 春季新款假两件显瘦长袖打底T恤上衣 | D53: 黑色;L(120-135斤);15天内发货 | E53: 1 | F53: 3770648898645918626 | G53: Z1576-黑色-L | H53: 199 | I53: 182.69 | J53: 0 | K53: 16.31 | L53: 平台七夕消费券-16.31 | M53: - | N53: - | O53: 0 | P53: 0 | Q53: 0 | R53: 抖音月付 | S53: 0 | T53: *** | U53: *** | V53: 山东省 | W53: 济南市 | X53: 市中区 | Y53: 魏家庄街道 | Z53: *** | AA53: 否 | AC53: 2025-08-26 16:04:55 | AD53: 灰色 | AH53: 抖音 | AI53: 精选联盟 | AJ53: 已关闭 | AK53: 2025-09-10 16:04:55 | AL53: 普通订单 | AM53: 0 | AN53: 2353393836764088 | AO53: 老板周 | AP53: - | AQ53: - | AR53: 你已取消订单：价格有点贵 | AS53: - | AT53: - | AU53: - | AW53: 否 | AX53: 无 | AY53: 其他 | AZ53: 直播 | BA53: 直播推荐 | BB53: - | BC53: - | BE53: 0 | BF53: 16.31 | BG53: 0 | BH53: 0 | BJ53: 否 | BP53: - | BQ53: - | BR53: -
A54: 6945550015473390912 | B54: 6945550015473456448 | C54: 【老板周】日系极简 春季新品圆领简约设计感无袖马甲 | D54: 黑色;L(120-135斤);15天内发货 | E54: 1 | F54: 3767004410471907465 | G54: Z1640-黑色-L | H54: 289 | I54: 265.31 | J54: 0 | K54: 23.69 | L54: 平台七夕消费券-23.69 | M54: - | N54: - | O54: 0 | P54: 0 | Q54: 0 | R54: 抖音月付 | S54: 0 | T54: *** | U54: *** | V54: 山东省 | W54: 济南市 | X54: 市中区 | Y54: 魏家庄街道 | Z54: *** | AA54: 否 | AC54: 2025-08-26 16:04:55 | AD54: 灰色 | AH54: 抖音 | AI54: 精选联盟 | AJ54: 已关闭 | AK54: 2025-09-10 16:04:55 | AL54: 普通订单 | AM54: 0 | AN54: 2353393836764088 | AO54: 老板周 | AP54: - | AQ54: - | AR54: 你已取消订单：价格有点贵 | AS54: - | AT54: - | AU54: - | AW54: 否 | AX54: 无 | AY54: 其他 | AZ54: 直播 | BA54: 直播推荐 | BB54: - | BC54: - | BE54: 0 | BF54: 23.69 | BG54: 0 | BH54: 0 | BJ54: 否 | BP54: - | BQ54: - | BR54: -
A55: 6920932842713087724 | B55: 6920932842713087724 | C55: 【老板周】时髦撞色 春季新款假两件显瘦长袖打底T恤上衣 | D55: 黑色;S(80-100斤);15天内发货 | E55: 1 | F55: 3770648898645918626 | G55: Z1576-黑色-S | H55: 199 | I55: 184.73 | J55: 0 | K55: 14.78 | L55: 平台商城满减券-14.27 | M55: - | N55: - | O55: 0 | P55: 0.51 | Q55: 0 | R55: 抖音支付 | S55: 0 | T55: *** | U55: *** | V55: 黑龙江省 | W55: 哈尔滨市 | X55: 南岗区 | Y55: 先锋路街道 | Z55: *** | AA55: 否 | AC55: 2025-08-26 12:31:01 | AD55: 灰色 | AF55: 2025-09-06 21:47:17 | AG55: 2025-08-26 12:31:04 | AH55: 抖音 | AI55: 小店自卖 | AJ55: 已完成 | AK55: 2025-09-10 12:31:04 | AL55: 普通订单 | AM55: 0 | AN55: 0 | AP55: - | AQ55: - | AS55: - | AT55: - | AU55: - | AW55: 否 | AX55: 无 | AY55: 其他 | AZ55: 商品卡 | BA55: 搜索 | BB55: - | BC55: - | BD55: 2025-08-30 21:47:17 | BE55: 0 | BF55: 14.27 | BG55: 0 | BH55: 0 | BJ55: 否 | BP55: - | BQ55: - | BR55: -
A56: 6920932842713087724 | B56: 6920932842713153260 | C56: 【老板周】日系极简 春季新品圆领简约设计感无袖马甲 | D56: 黑色;S(80-100斤);15天内发货 | E56: 1 | F56: 3767004410471907465 | G56: Z1640-黑色-S | H56: 289 | I56: 268.27 | J56: 0 | K56: 21.46 | L56: 平台商城满减券-20.73 | M56: - | N56: - | O56: 0 | P56: 0.73 | Q56: 0 | R56: 抖音支付 | S56: 0 | T56: *** | U56: *** | V56: 黑龙江省 | W56: 哈尔滨市 | X56: 南岗区 | Y56: 先锋路街道 | Z56: *** | AA56: 否 | AC56: 2025-08-26 12:31:01 | AD56: 灰色 | AF56: 2025-09-17 15:51:38 | AG56: 2025-08-26 12:31:04 | AH56: 抖音 | AI56: 小店自卖 | AJ56: 已完成 | AK56: 2025-09-10 12:31:04 | AL56: 普通订单 | AM56: 0 | AN56: 0 | AP56: - | AQ56: - | AS56: - | AT56: - | AU56: - | AW56: 否 | AX56: 无 | AY56: 其他 | AZ56: 商品卡 | BA56: 搜索 | BB56: - | BC56: - | BD56: 2025-09-05 15:51:38 | BE56: 0 | BF56: 20.73 | BG56: 0 | BH56: 0 | BJ56: 否 | BP56: - | BQ56: - | BR56: -
A57: 6945569726276310761 | B57: 6945569726276310761 | C57: 【老板周】日系极简 春季新品圆领简约设计感无袖马甲 | D57: 黑色;M(100-120斤);15天内发货 | E57: 1 | F57: 3767004410471907465 | G57: Z1640-黑色-M | H57: 289 | I57: 250.82 | J57: 0 | K57: 38.18 | L57: 平台七夕消费券-38.18 | M57: - | N57: - | O57: 0 | P57: 0 | Q57: 0 | R57: 抖音月付 | S57: 0 | T57: *** | U57: *** | V57: 湖北省 | W57: 武汉市 | X57: 洪山区 | Y57: 关山街道 | Z57: *** | AA57: 否 | AC57: 2025-08-26 12:22:42 | AD57: 灰色 | AF57: 2025-09-09 19:26:40 | AG57: 2025-08-26 12:22:45 | AH57: 抖音 | AI57: 精选联盟 | AJ57: 已完成 | AK57: 2025-09-10 12:22:46 | AL57: 普通订单 | AM57: 0 | AN57: 2353393836764088 | AO57: 老板周 | AP57: - | AQ57: - | AS57: - | AT57: - | AU57: - | AW57: 否 | AX57: 无 | AY57: 其他 | AZ57: 直播 | BA57: 直播推荐 | BB57: - | BC57: - | BD57: 2025-09-05 20:29:09 | BE57: 0 | BF57: 38.18 | BG57: 0 | BH57: 0 | BJ57: 否 | BP57: - | BQ57: - | BR57: -
A58: 6920928532274839276 | B58: 6920928532274839276 | C58: 【老板周】日系极简 春季新品圆领简约设计感无袖马甲 | D58: 黑色;S(80-100斤);15天内发货 | E58: 1 | F58: 3767004410471907465 | G58: Z1640-黑色-S | H58: 289 | I58: 268.28 | J58: 0 | K58: 21.48 | L58: 平台商城满减券-20.72 | M58: - | N58: - | O58: 0 | P58: 0.76 | Q58: 0 | R58: 抖音支付 | S58: 0 | T58: *** | U58: *** | V58: 黑龙江省 | W58: 哈尔滨市 | X58: 南岗区 | Y58: 先锋路街道 | Z58: *** | AA58: 否 | AC58: 2025-08-26 12:10:21 | AD58: 灰色 | AG58: 2025-08-26 12:10:23 | AH58: 抖音 | AI58: 精选联盟 | AJ58: 已关闭 | AK58: 2025-09-10 12:10:24 | AL58: 普通订单 | AM58: 0 | AN58: 2353393836764088 | AO58: 老板周 | AP58: - | AQ58: 退款成功 | AS58: - | AT58: - | AU58: - | AW58: 否 | AX58: 无 | AY58: 其他 | AZ58: 商品卡 | BA58: 橱窗 | BB58: - | BC58: - | BE58: 0 | BF58: 20.72 | BG58: 0 | BH58: 0 | BJ58: 否 | BP58: - | BQ58: - | BR58: -
A59: 6920928532274839276 | B59: 6920928532274904812 | C59: 【老板周】时髦撞色 春季新款假两件显瘦长袖打底T恤上衣 | D59: 黑色;S(80-100斤);15天内发货 | E59: 1 | F59: 3770648898645918626 | G59: Z1576-黑色-S | H59: 199 | I59: 184.72 | J59: 0 | K59: 14.81 | L59: 平台商城满减券-14.28 | M59: - | N59: - | O59: 0 | P59: 0.53 | Q59: 0 | R59: 抖音支付 | S59: 0 | T59: *** | U59: *** | V59: 黑龙江省 | W59: 哈尔滨市 | X59: 南岗区 | Y59: 先锋路街道 | Z59: *** | AA59: 否 | AC59: 2025-08-26 12:10:21 | AD59: 灰色 | AG59: 2025-08-26 12:10:23 | AH59: 抖音 | AI59: 精选联盟 | AJ59: 已关闭 | AK59: 2025-09-10 12:10:24 | AL59: 普通订单 | AM59: 0 | AN59: 2353393836764088 | AO59: 老板周 | AP59: - | AQ59: 退款成功 | AS59: - | AT59: - | AU59: - | AW59: 否 | AX59: 无 | AY59: 其他 | AZ59: 直播 | BA59: 商城推荐 | BB59: - | BC59: - | BE59: 0 | BF59: 14.28 | BG59: 0 | BH59: 0 | BJ59: 否 | BP59: - | BQ59: - | BR59: -
A60: 6945529053386118931 | B60: 6945529053386118931 | C60: 【老板周】日系极简 春季新品圆领简约设计感无袖马甲 | D60: 黑色;M(100-120斤);15天内发货 | E60: 1 | F60: 3767004410471907465 | G60: Z1640-黑色-M | H60: 289 | I60: 260.96 | J60: 0 | K60: 28.04 | L60: 平台七夕消费券-28.04 | M60: - | N60: - | O60: 0 | P60: 0 | Q60: 0 | R60: 抖音支付 | S60: 0 | T60: *** | U60: *** | V60: 北京市 | W60: 北京市 | X60: 朝阳区 | Y60: 和平街街道 | Z60: *** | AA60: 否 | AC60: 2025-08-25 23:06:06 | AD60: 灰色 | AF60: 2025-09-11 23:19:44 | AG60: 2025-08-25 23:06:10 | AH60: 抖音 | AI60: 精选联盟 | AJ60: 已完成 | AK60: 2025-09-09 23:06:11 | AL60: 普通订单 | AM60: 0 | AN60: 2353393836764088 | AO60: 老板周 | AP60: - | AQ60: - | AS60: - | AT60: - | AU60: - | AW60: 否 | AX60: 无 | AY60: 其他 | AZ60: 直播 | BA60: 关注来源 | BB60: - | BC60: - | BD60: 2025-09-04 23:19:44 | BE60: 0 | BF60: 28.04 | BG60: 0 | BH60: 0 | BJ60: 否 | BP60: - | BQ60: - | BR60: -
A61: 6945548577267651706 | B61: 6945548577267651706 | C61: 【老板周】日系极简 春季新品圆领简约设计感无袖马甲 | D61: 黑色;M(100-120斤);15天内发货 | E61: 1 | F61: 3767004410471907465 | G61: Z1640-黑色-M | H61: 289 | I61: 289 | J61: 0 | K61: 0 | L61: - | M61: - | N61: - | O61: 0 | P61: 0 | Q61: 0 | R61: 抖音月付 | S61: 0 | T61: *** | U61: *** | V61: 云南省 | W61: 昆明市 | X61: 官渡区 | Y61: 矣六街道 | Z61: *** | AA61: 否 | AC61: 2025-08-25 22:18:24 | AD61: 灰色 | AF61: 2025-09-11 23:19:44 | AG61: 2025-08-25 22:18:29 | AH61: 抖音 | AI61: 精选联盟 | AJ61: 已完成 | AK61: 2025-09-09 22:18:29 | AL61: 普通订单 | AM61: 0 | AN61: 2353393836764088 | AO61: 老板周 | AP61: - | AQ61: - | AS61: - | AT61: - | AU61: - | AW61: 否 | AX61: 无 | AY61: 其他 | AZ61: 直播 | BA61: 直播推荐 | BB61: - | BC61: - | BD61: 2025-09-04 23:19:44 | BE61: 0 | BF61: 0 | BG61: 0 | BH61: 0 | BJ61: 否 | BP61: - | BQ61: - | BR61: -
A62: 6945543583900899197 | B62: 6945543583900899197 | C62: 【老板周】日系极简 春季新品圆领简约设计感无袖马甲 | D62: 黑色;S(80-100斤);15天内发货 | E62: 1 | F62: 3767004410471907465 | G62: Z1640-黑色-S | H62: 289 | I62: 260.66 | J62: 0 | K62: 28.34 | L62: 平台七夕消费券-28.34 | M62: - | N62: - | O62: 0 | P62: 0 | Q62: 0 | R62: 抖音月付 | S62: 0 | T62: *** | U62: *** | V62: 山东省 | W62: 潍坊市 | X62: 寿光市 | Y62: 稻田镇 | Z62: *** | AA62: 否 | AC62: 2025-08-25 22:04:55 | AD62: 灰色 | AG62: 2025-08-25 22:04:59 | AH62: 抖音 | AI62: 精选联盟 | AJ62: 已关闭 | AK62: 2025-09-09 22:04:59 | AL62: 普通订单 | AM62: 0 | AN62: 2353393836764088 | AO62: 老板周 | AP62: - | AQ62: 退款成功 | AS62: - | AT62: - | AU62: - | AW62: 否 | AX62: 直播 | AY62: 广告 | AZ62: 直播 | BA62: 商城推荐 | BB62: - | BC62: - | BE62: 0 | BF62: 28.34 | BG62: 0 | BH62: 0 | BJ62: 否 | BP62: - | BQ62: - | BR62: -
A63: 6920929009547574969 | B63: 6920929009547574969 | C63: 【老板周】日系极简 春季新品圆领简约设计感无袖马甲 | D63: 黑色;M(100-120斤);15天内发货 | E63: 1 | F63: 3767004410471907465 | G63: Z1640-黑色-M | H63: 289 | I63: 289 | J63: 0 | K63: 0 | L63: - | M63: - | N63: - | O63: 0 | P63: 0 | Q63: 0 | R63: 抖音月付 | S63: 0 | T63: *** | U63: *** | V63: 辽宁省 | W63: 沈阳市 | X63: 皇姑区 | Y63: 明廉街道 | Z63: *** | AA63: 否 | AC63: 2025-08-25 22:02:22 | AD63: 灰色 | AF63: 2025-09-07 19:43:29 | AG63: 2025-08-25 22:02:24 | AH63: 抖音 | AI63: 精选联盟 | AJ63: 已完成 | AK63: 2025-09-09 22:02:24 | AL63: 普通订单 | AM63: 0 | AN63: 2353393836764088 | AO63: 老板周 | AP63: - | AQ63: - | AS63: - | AT63: - | AU63: - | AW63: 否 | AX63: 无 | AY63: 其他 | AZ63: 直播 | BA63: 短视频引流直播间 | BB63: - | BC63: - | BD63: 2025-09-04 23:19:45 | BE63: 0 | BF63: 0 | BG63: 0 | BH63: 0 | BJ63: 否 | BP63: - | BQ63: - | BR63: -
A64: 6920935968749813406 | B64: 6920935968749813406 | C64: 【老板周】日系极简 春季新品圆领简约设计感无袖马甲 | D64: 黑色;L(120-135斤);15天内发货 | E64: 1 | F64: 3767004410471907465 | G64: Z1640-黑色-L | H64: 289 | I64: 289 | J64: 0 | K64: 0 | L64: - | M64: - | N64: - | O64: 0 | P64: 0 | Q64: 0 | R64: 抖音月付 | S64: 0 | T64: *** | U64: *** | V64: 湖南省 | W64: 岳阳市 | X64: 平江县 | Y64: 汉昌街道 | Z64: *** | AA64: 否 | AC64: 2025-08-25 21:33:22 | AD64: 灰色 | AF64: 2025-09-08 23:13:48 | AG64: 2025-08-25 21:33:25 | AH64: 抖音 | AI64: 精选联盟 | AJ64: 已完成 | AK64: 2025-09-09 21:33:26 | AL64: 普通订单 | AM64: 0 | AN64: 2353393836764088 | AO64: 老板周 | AP64: - | AQ64: - | AS64: - | AT64: - | AU64: - | AW64: 否 | AX64: 无 | AY64: 其他 | AZ64: 直播 | BA64: 直播推荐 | BB64: - | BC64: - | BD64: 2025-09-01 23:13:48 | BE64: 0 | BF64: 0 | BG64: 0 | BH64: 0 | BJ64: 否 | BP64: - | BQ64: - | BR64: -
A65: 6920923676778724668 | B65: 6920923676778724668 | C65: 【老板周】日系极简 春季新品圆领简约设计感无袖马甲 | D65: 黑色;L(120-135斤);15天内发货 | E65: 1 | F65: 3767004410471907465 | G65: Z1640-黑色-L | H65: 289 | I65: 289 | J65: 0 | K65: 0 | L65: - | M65: - | N65: - | O65: 0 | P65: 0 | Q65: 0 | R65: 抖音支付 | S65: 0 | T65: *** | U65: *** | V65: 四川省 | W65: 内江市 | X65: 威远县 | Y65: 严陵镇 | Z65: *** | AA65: 否 | AC65: 2025-08-25 18:11:22 | AD65: 灰色 | AH65: 抖音极速版 | AI65: 精选联盟 | AJ65: 已关闭 | AK65: 2025-09-09 18:11:22 | AL65: 普通订单 | AM65: 0 | AN65: 2353393836764088 | AO65: 老板周 | AP65: - | AQ65: - | AR65: 你已取消订单：暂时不需要这个商品 | AS65: - | AT65: - | AU65: - | AW65: 否 | AX65: 直播 | AY65: 广告 | AZ65: 直播 | BA65: 个人主页&店铺&橱窗进入直播间 | BB65: - | BC65: - | BE65: 0 | BF65: 0 | BG65: 0 | BH65: 0 | BJ65: 否 | BP65: - | BQ65: - | BR65: -
A66: 6945514875424281953 | B66: 6945514875424281953 | C66: 【老板周】日系极简 春季新品圆领简约设计感无袖马甲 | D66: 黑色;M(100-120斤);15天内发货 | E66: 1 | F66: 3767004410471907465 | G66: Z1640-黑色-M | H66: 289 | I66: 289 | J66: 0 | K66: 0 | L66: - | M66: - | N66: - | O66: 0 | P66: 0 | Q66: 0 | R66: 抖音月付 | S66: 0 | T66: *** | U66: *** | V66: 四川省 | W66: 成都市 | X66: 锦江区 | Y66: 双桂路街道 | Z66: *** | AA66: 否 | AC66: 2025-08-25 17:52:19 | AD66: 灰色 | AG66: 2025-08-25 17:52:21 | AH66: 抖音 | AI66: 精选联盟 | AJ66: 已关闭 | AK66: 2025-09-09 17:52:22 | AL66: 普通订单 | AM66: 0 | AN66: 2353393836764088 | AO66: 老板周 | AP66: - | AQ66: 退款成功 | AS66: - | AT66: - | AU66: - | AW66: 否 | AX66: 无 | AY66: 其他 | AZ66: 直播 | BA66: 直播推荐 | BB66: - | BC66: - | BE66: 0 | BF66: 0 | BG66: 0 | BH66: 0 | BJ66: 否 | BP66: - | BQ66: - | BR66: -
A67: 6945539203760789124 | B67: 6945539203760789124 | C67: 【老板周】日系极简 春季新品圆领简约设计感无袖马甲 | D67: 黑色;L(120-135斤);15天内发货 | E67: 1 | F67: 3767004410471907465 | G67: Z1640-黑色-L | H67: 289 | I67: 289 | J67: 0 | K67: 0 | L67: - | M67: - | N67: - | O67: 0 | P67: 0 | Q67: 0 | R67: 支付宝 | S67: 0 | T67: *** | U67: *** | V67: 陕西省 | W67: 榆林市 | X67: 榆阳区 | Y67: 上郡路街道 | Z67: *** | AA67: 否 | AC67: 2025-08-25 17:29:18 | AD67: 灰色 | AH67: 抖音极速版 | AI67: 精选联盟 | AJ67: 已关闭 | AK67: 2025-09-09 17:29:18 | AL67: 普通订单 | AM67: 0 | AN67: 2353393836764088 | AO67: 老板周 | AP67: - | AQ67: - | AR67: 用户超时未支付自动取消 | AS67: - | AT67: - | AU67: - | AW67: 否 | AX67: 直播 | AY67: 广告 | AZ67: 直播 | BA67: 直播推荐 | BB67: - | BC67: - | BE67: 0 | BF67: 0 | BG67: 0 | BH67: 0 | BJ67: 否 | BP67: - | BQ67: - | BR67: -
A68: 6918363477932670688 | B68: 6918363477932670688 | C68: 【老板周】日系极简 春季新品圆领简约设计感无袖马甲 | D68: 黑色;M(100-120斤);15天内发货 | E68: 1 | F68: 3767004410471907465 | G68: Z1640-黑色-M | H68: 289 | I68: 263.76 | J68: 0 | K68: 25.24 | L68: 平台七夕消费券-25.24 | M68: - | N68: - | O68: 0 | P68: 0 | Q68: 0 | R68: 支付宝 | S68: 0 | T68: *** | U68: *** | V68: 黑龙江省 | W68: 绥化市 | X68: 安达市 | Y68: 安达镇 | Z68: *** | AA68: 否 | AC68: 2025-08-25 16:26:10 | AD68: 灰色 | AG68: 2025-08-25 16:26:15 | AH68: 抖音极速版 | AI68: 精选联盟 | AJ68: 已关闭 | AK68: 2025-09-09 16:26:16 | AL68: 普通订单 | AM68: 0 | AN68: 2353393836764088 | AO68: 老板周 | AP68: - | AQ68: 退款成功 | AS68: - | AT68: - | AU68: - | AW68: 否 | AX68: 直播 | AY68: 广告 | AZ68: 直播 | BA68: 关注来源 | BB68: - | BC68: - | BE68: 0 | BF68: 25.24 | BG68: 0 | BH68: 0 | BJ68: 否 | BP68: - | BQ68: - | BR68: -
A69: 6920925448404893520 | B69: 6920925448404893520 | C69: 【老板周】日系极简 春季新品圆领简约设计感无袖马甲 | D69: 黑色;S(80-100斤);15天内发货 | E69: 1 | F69: 3767004410471907465 | G69: Z1640-黑色-S | H69: 289 | I69: 289 | J69: 0 | K69: 0 | L69: - | M69: - | N69: - | O69: 0 | P69: 0 | Q69: 0 | R69: 支付宝 | S69: 0 | T69: *** | U69: *** | V69: 四川省 | W69: 成都市 | X69: 新津区 | Y69: 花源街道 | Z69: *** | AA69: 否 | AC69: 2025-08-25 16:13:31 | AD69: 灰色 | AF69: 2025-09-11 23:24:57 | AG69: 2025-08-25 16:14:00 | AH69: 抖音 | AI69: 精选联盟 | AJ69: 已完成 | AK69: 2025-09-09 16:14:01 | AL69: 普通订单 | AM69: 0 | AN69: 2353393836764088 | AO69: 老板周 | AP69: - | AQ69: - | AS69: - | AT69: - | AU69: - | AW69: 否 | AX69: 无 | AY69: 其他 | AZ69: 直播 | BA69: 直播推荐 | BB69: - | BC69: - | BD69: 2025-09-04 23:24:57 | BE69: 0 | BF69: 0 | BG69: 0 | BH69: 0 | BJ69: 否 | BP69: - | BQ69: - | BR69: -
A70: 6945539142283629576 | B70: 6945539142283629576 | C70: 【老板周】日系极简 春季新品圆领简约设计感无袖马甲 | D70: 黑色;L(120-135斤);15天内发货 | E70: 1 | F70: 3767004410471907465 | G70: Z1640-黑色-L | H70: 289 | I70: 260.1 | J70: 0 | K70: 28.9 | L70: 平台七夕消费券-28.90 | M70: - | N70: - | O70: 0 | P70: 0 | Q70: 0 | R70: 抖音月付 | S70: 0 | T70: *** | U70: *** | V70: 天津市 | W70: 天津市 | X70: 北辰区 | Y70: 双街镇 | Z70: *** | AA70: 否 | AC70: 2025-08-25 15:56:19 | AD70: 灰色 | AG70: 2025-08-25 15:56:27 | AH70: 抖音 | AI70: 精选联盟 | AJ70: 已关闭 | AK70: 2025-09-09 15:56:28 | AL70: 普通订单 | AM70: 0 | AN70: 2353393836764088 | AO70: 老板周 | AP70: - | AQ70: 退款成功 | AS70: - | AT70: - | AU70: - | AW70: 否 | AX70: 无 | AY70: 其他 | AZ70: 商品卡 | BA70: 橱窗 | BB70: - | BC70: - | BE70: 0 | BF70: 28.9 | BG70: 0 | BH70: 0 | BJ70: 否 | BP70: - | BQ70: - | BR70: -
A71: 6945511996582664089 | B71: 6945511996582664089 | C71: 【老板周】时髦撞色 春季新款假两件显瘦长袖打底T恤上衣 | D71: 黑色;L(120-135斤);15天内发货 | E71: 1 | F71: 3770648898645918626 | G71: Z1576-黑色-L | H71: 199 | I71: 194 | J71: 0 | K71: 8 | L71: 平台商城报销返券-5.00 | M71: - | N71: - | O71: 0 | P71: 3 | Q71: 0 | R71: 抖音月付 | S71: 0 | T71: *** | U71: *** | V71: 北京市 | W71: 北京市 | X71: 朝阳区 | Y71: 东坝地区 | Z71: *** | AA71: 否 | AC71: 2025-08-25 12:02:03 | AD71: 蓝色 | AE71: SF3237506934842(收） Z1576-黑色-L*1# | AG71: 2025-08-25 12:02:05 | AH71: 抖音 | AI71: 小店自卖 | AJ71: 已关闭 | AK71: 2025-09-09 12:02:05 | AL71: 普通订单 | AM71: 0 | AN71: 0 | AP71: - | AQ71: 退款成功 | AS71: - | AT71: - | AU71: - | AW71: 否 | AX71: 无 | AY71: 其他 | AZ71: 商品卡 | BA71: 购后页面 | BB71: - | BC71: - | BD71: 2025-08-31 22:00:10 | BE71: 0 | BF71: 5 | BG71: 0 | BH71: 0 | BJ71: 否 | BP71: - | BQ71: - | BR71: -
A72: 6945518268966573163 | B72: 6945518268966573163 | C72: 【老板周】日系极简 春季新品圆领简约设计感无袖马甲 | D72: 黑色;L(120-135斤);15天内发货 | E72: 1 | F72: 3767004410471907465 | G72: Z1640-黑色-L | H72: 289 | I72: 289 | J72: 0 | K72: 0 | L72: - | M72: - | N72: - | O72: 0 | P72: 0 | Q72: 0 | R72: 抖音支付 | S72: 0 | T72: *** | U72: *** | V72: 吉林省 | W72: 吉林市 | X72: 昌邑区 | Y72: 通江街道 | Z72: *** | AA72: 否 | AC72: 2025-08-25 05:34:24 | AD72: 灰色 | AH72: 抖音极速版 | AI72: 精选联盟 | AJ72: 已关闭 | AK72: 2025-09-09 05:34:24 | AL72: 普通订单 | AM72: 0 | AN72: 2353393836764088 | AO72: 老板周 | AP72: - | AQ72: - | AR72: 你已取消订单：商品规格/款式/数量错选 | AS72: - | AT72: - | AU72: - | AW72: 否 | AX72: 无 | AY72: 其他 | AZ72: 商品卡 | BA72: 橱窗 | BB72: - | BC72: - | BE72: 0 | BF72: 0 | BG72: 0 | BH72: 0 | BJ72: 否 | BP72: - | BQ72: - | BR72: -
A73: 6945515811466254054 | B73: 6945515811466254054 | C73: 【老板周】时髦撞色 春季新款假两件显瘦长袖打底T恤上衣 | D73: 黑色;M(100-120斤);15天内发货 | E73: 1 | F73: 3770648898645918626 | G73: Z1576-黑色-M | H73: 199 | I73: 179.25 | J73: 0 | K73: 19.75 | L73: 平台七夕消费券-19.75 | M73: - | N73: - | O73: 0 | P73: 0 | Q73: 0 | R73: 抖音月付 | S73: 0 | T73: *** | U73: *** | V73: 甘肃省 | W73: 平凉市 | X73: 静宁县 | Y73: 城区街道 | Z73: *** | AA73: 否 | AC73: 2025-08-24 22:33:07 | AD73: 灰色 | AG73: 2025-08-24 22:33:12 | AH73: 抖音极速版 | AI73: 小店自卖 | AJ73: 已关闭 | AK73: 2025-09-08 22:33:12 | AL73: 普通订单 | AM73: 0 | AN73: 0 | AP73: - | AQ73: 退款成功 | AS73: - | AT73: - | AU73: - | AW73: 否 | AX73: 无 | AY73: 其他 | AZ73: 商品卡 | BA73: 频道及活动页面 | BB73: - | BC73: - | BE73: 0 | BF73: 19.75 | BG73: 0 | BH73: 0 | BJ73: 否 | BP73: - | BQ73: - | BR73: -
A74: 6945513256170493793 | B74: 6945513256170493793 | C74: 【老板周】时髦撞色 春季新款假两件显瘦长袖打底T恤上衣 | D74: 黑色;M(100-120斤);15天内发货 | E74: 1 | F74: 3770648898645918626 | G74: Z1576-黑色-M | H74: 199 | I74: 199 | J74: 0 | K74: 0 | L74: - | M74: - | N74: - | O74: 0 | P74: 0 | Q74: 0 | R74: 抖音月付 | S74: 0 | T74: *** | U74: *** | V74: 云南省 | W74: 昭通市 | X74: 昭阳区 | Y74: 凤凰街道 | Z74: *** | AA74: 否 | AC74: 2025-08-24 20:06:58 | AD74: 灰色 | AF74: 2025-09-07 23:42:42 | AG74: 2025-08-24 20:07:04 | AH74: 抖音 | AI74: 精选联盟 | AJ74: 已完成 | AK74: 2025-09-08 20:07:04 | AL74: 普通订单 | AM74: 0 | AN74: 2353393836764088 | AO74: 老板周 | AP74: - | AQ74: - | AS74: - | AT74: - | AU74: - | AW74: 否 | AX74: 无 | AY74: 其他 | AZ74: 直播 | BA74: 商城推荐 | BB74: - | BC74: - | BD74: 2025-08-31 23:42:42 | BE74: 0 | BF74: 0 | BG74: 0 | BH74: 0 | BJ74: 否 | BP74: - | BQ74: - | BR74: -
A75: 6945504197030777878 | B75: 6945504197030777878 | C75: 【老板周】时髦撞色 春季新款假两件显瘦长袖打底T恤上衣 | D75: 黑色;S(80-100斤);15天内发货 | E75: 1 | F75: 3770648898645918626 | G75: Z1576-黑色-S | H75: 199 | I75: 199 | J75: 0 | K75: 0.84 | L75: - | M75: - | N75: - | O75: 0 | P75: 0.84 | Q75: 0 | R75: 抖音支付 | S75: 0 | T75: *** | U75: *** | V75: 四川省 | W75: 成都市 | X75: 锦江区 | Y75: 成龙路街道 | Z75: *** | AA75: 否 | AC75: 2025-08-24 17:27:14 | AD75: 灰色 | AF75: 2025-09-03 16:35:19 | AG75: 2025-08-24 17:27:30 | AH75: 抖音 | AI75: 精选联盟 | AJ75: 已完成 | AK75: 2025-09-08 17:27:31 | AL75: 普通订单 | AM75: 0 | AN75: 2353393836764088 | AO75: 老板周 | AP75: - | AQ75: - | AS75: - | AT75: - | AU75: - | AW75: 否 | AX75: 无 | AY75: 其他 | AZ75: 直播 | BA75: 直播推荐 | BB75: - | BC75: - | BD75: 2025-08-30 21:47:16 | BE75: 0 | BF75: 0 | BG75: 0 | BH75: 0 | BJ75: 否 | BP75: - | BQ75: - | BR75: -
A76: 6920902861000703125 | B76: 6920902861000703125 | C76: 【老板周】日系极简 春季新品圆领简约设计感无袖马甲 | D76: 黑色;L(120-135斤);15天内发货 | E76: 1 | F76: 3767004410471907465 | G76: Z1640-黑色-L | H76: 289 | I76: 289 | J76: 0 | K76: 0 | L76: - | M76: - | N76: - | O76: 0 | P76: 0 | Q76: 0 | R76: 支付宝 | S76: 0 | T76: *** | U76: *** | V76: 上海市 | W76: 上海市 | X76: 浦东新区 | Y76: 周浦镇 | Z76: *** | AA76: 否 | AC76: 2025-08-24 01:18:22 | AD76: 蓝色 | AE76: SF3284637255874(收） Z1640-黑色-L*1# | AG76: 2025-08-24 01:18:27 | AH76: 抖音 | AI76: 小店自卖 | AJ76: 已关闭 | AK76: 2025-09-08 01:18:28 | AL76: 普通订单 | AM76: 0 | AN76: 0 | AP76: - | AQ76: 退款成功 | AS76: - | AT76: - | AU76: - | AW76: 否 | AX76: 无 | AY76: 其他 | AZ76: 商品卡 | BA76: 购后页面 | BB76: - | BC76: - | BD76: 2025-08-31 23:39:54 | BE76: 0 | BF76: 0 | BG76: 0 | BH76: 0 | BJ76: 否 | BP76: - | BQ76: - | BR76: -
A77: 6920902023287176940 | B77: 6920902023287176940 | C77: 【老板周】日系极简 春季新品圆领简约设计感无袖马甲 | D77: 黑色;S(80-100斤);15天内发货 | E77: 1 | F77: 3767004410471907465 | G77: Z1640-黑色-S | H77: 289 | I77: 253.32 | J77: 0 | K77: 35.68 | L77: 平台七夕消费券-35.68 | M77: - | N77: - | O77: 0 | P77: 0 | Q77: 0 | R77: 抖音支付 | S77: 0 | T77: *** | U77: *** | V77: 黑龙江省 | W77: 哈尔滨市 | X77: 南岗区 | Y77: 先锋路街道 | Z77: *** | AA77: 否 | AC77: 2025-08-23 23:08:10 | AD77: 灰色 | AG77: 2025-08-23 23:08:26 | AH77: 抖音 | AI77: 精选联盟 | AJ77: 已关闭 | AK77: 2025-09-07 23:08:26 | AL77: 普通订单 | AM77: 0 | AN77: 2353393836764088 | AO77: 老板周 | AP77: - | AQ77: 退款成功 | AS77: - | AT77: - | AU77: - | AW77: 否 | AX77: 无 | AY77: 其他 | AZ77: 直播 | BA77: 搜索 | BB77: - | BC77: - | BE77: 0 | BF77: 35.68 | BG77: 0 | BH77: 0 | BJ77: 否 | BP77: - | BQ77: - | BR77: -
A78: 6920893032532966569 | B78: 6920893032532966569 | C78: 【老板周】日系极简 春季新品圆领简约设计感无袖马甲 | D78: 黑色;M(100-120斤);15天内发货 | E78: 1 | F78: 3767004410471907465 | G78: Z1640-黑色-M | H78: 289 | I78: 234 | J78: 0 | K78: 55 | L78: 金币抵扣金额-4.60;余额抵扣金额-50.40 | M78: - | N78: - | O78: 0 | P78: 0 | Q78: 0 | R78: 抖音支付 | S78: 0 | T78: *** | U78: *** | V78: 山东省 | W78: 青岛市 | X78: 市北区 | Y78: - | Z78: *** | AA78: 否 | AC78: 2025-08-23 22:21:10 | AD78: 灰色 | AG78: 2025-08-23 22:21:37 | AH78: 抖音极速版 | AI78: 精选联盟 | AJ78: 已关闭 | AK78: 2025-09-07 22:21:37 | AL78: 普通订单 | AM78: 0 | AN78: 2353393836764088 | AO78: 老板周 | AP78: - | AQ78: 退款成功 | AS78: - | AT78: - | AU78: - | AW78: 否 | AX78: 直播 | AY78: 广告 | AZ78: 直播 | BA78: 商城推荐 | BB78: - | BC78: - | BE78: 0 | BF78: 55 | BG78: 0 | BH78: 0 | BJ78: 否 | BP78: - | BQ78: - | BR78: -
A79: 6945478419003544648 | B79: 6945478419003544648 | C79: 【老板周】日系极简 春季新品圆领简约设计感无袖马甲 | D79: 黑色;M(100-120斤);15天内发货 | E79: 1 | F79: 3767004410471907465 | G79: Z1640-黑色-M | H79: 289 | I79: 289 | J79: 0 | K79: 0 | L79: - | M79: - | N79: - | O79: 0 | P79: 0 | Q79: 0 | R79: 抖音月付 | S79: 0 | T79: *** | U79: *** | V79: 江苏省 | W79: 南京市 | X79: 雨花台区 | Y79: 雨花街道 | Z79: *** | AA79: 否 | AC79: 2025-08-23 22:08:33 | AD79: 灰色 | AF79: 2025-09-09 19:52:48 | AG79: 2025-08-23 22:08:35 | AH79: 抖音 | AI79: 精选联盟 | AJ79: 已完成 | AK79: 2025-09-07 22:08:36 | AL79: 普通订单 | AM79: 0 | AN79: 2353393836764088 | AO79: 老板周 | AP79: - | AQ79: - | AS79: - | AT79: - | AU79: - | AW79: 否 | AX79: 无 | AY79: 其他 | AZ79: 直播 | BA79: 直播推荐 | BB79: - | BC79: - | BD79: 2025-09-02 19:52:48 | BE79: 0 | BF79: 0 | BG79: 0 | BH79: 0 | BJ79: 否 | BP79: - | BQ79: - | BR79: -
A80: 6920892838365920628 | B80: 6920892838365920628 | C80: 【老板周】日系极简 春季新品圆领简约设计感无袖马甲 | D80: 黑色;M(100-120斤);15天内发货 | E80: 1 | F80: 3767004410471907465 | G80: Z1640-黑色-M | H80: 289 | I80: 264.29 | J80: 0 | K80: 24.71 | L80: 平台七夕消费券-24.71 | M80: - | N80: - | O80: 0 | P80: 0 | Q80: 0 | R80: 抖音月付 | S80: 0 | T80: *** | U80: *** | V80: 内蒙古自治区 | W80: 包头市 | X80: 昆都仑区 | Y80: 白云路街道 | Z80: *** | AA80: 否 | AC80: 2025-08-23 21:48:56 | AD80: 灰色 | AG80: 2025-08-23 21:48:58 | AH80: 抖音极速版 | AI80: 精选联盟 | AJ80: 已关闭 | AK80: 2025-09-07 21:48:59 | AL80: 普通订单 | AM80: 0 | AN80: 2353393836764088 | AO80: 老板周 | AP80: - | AQ80: 退款成功 | AS80: - | AT80: - | AU80: - | AW80: 否 | AX80: 无 | AY80: 其他 | AZ80: 直播 | BA80: 频道及活动页面 | BB80: - | BC80: - | BE80: 0 | BF80: 24.71 | BG80: 0 | BH80: 0 | BJ80: 否 | BP80: - | BQ80: - | BR80: -
A81: 6918358695102807059 | B81: 6918358695102807059 | C81: 【老板周】时髦撞色 春季新款假两件显瘦长袖打底T恤上衣 | D81: 黑色;M(100-120斤);15天内发货 | E81: 1 | F81: 3770648898645918626 | G81: Z1576-黑色-M | H81: 199 | I81: 173.97 | J81: 0 | K81: 25.03 | L81: 平台七夕消费券-25.03 | M81: - | N81: - | O81: 0 | P81: 0 | Q81: 0 | R81: 抖音月付 | S81: 0 | T81: *** | U81: *** | V81: 湖南省 | W81: 常德市 | X81: 武陵区 | Y81: 德山街道 | Z81: *** | AA81: 否 | AC81: 2025-08-23 21:17:55 | AD81: 灰色 | AG81: 2025-08-23 21:17:58 | AH81: 抖音 | AI81: 精选联盟 | AJ81: 已关闭 | AK81: 2025-09-07 21:17:59 | AL81: 普通订单 | AM81: 0 | AN81: 2353393836764088 | AO81: 老板周 | AP81: - | AQ81: 退款成功 | AS81: - | AT81: - | AU81: - | AW81: 否 | AX81: 直播 | AY81: 广告 | AZ81: 直播 | BA81: 商城推荐 | BB81: - | BC81: - | BE81: 0 | BF81: 25.03 | BG81: 0 | BH81: 0 | BJ81: 否 | BP81: - | BQ81: - | BR81: -
A82: 6945467765155763766 | B82: 6945467765155763766 | C82: 【老板周】日系极简 春季新品圆领简约设计感无袖马甲 | D82: 黑色;M(100-120斤);15天内发货 | E82: 1 | F82: 3767004410471907465 | G82: Z1640-黑色-M | H82: 289 | I82: 259.05 | J82: 0 | K82: 29.95 | L82: 平台七夕消费券-29.95 | M82: - | N82: - | O82: 0 | P82: 0 | Q82: 0 | R82: 抖音月付 | S82: 0 | T82: *** | U82: *** | V82: 山东省 | W82: 济南市 | X82: 天桥区 | Y82: 北村街道 | Z82: *** | AA82: 否 | AC82: 2025-08-23 20:55:24 | AD82: 灰色 | AF82: 2025-09-09 15:25:39 | AG82: 2025-08-23 20:55:25 | AH82: 抖音 | AI82: 精选联盟 | AJ82: 已完成 | AK82: 2025-09-07 20:55:26 | AL82: 普通订单 | AM82: 0 | AN82: 2353393836764088 | AO82: 老板周 | AP82: - | AQ82: - | AS82: - | AT82: - | AU82: - | AW82: 否 | AX82: 无 | AY82: 其他 | AZ82: 直播 | BA82: 搜索 | BB82: - | BC82: - | BD82: 2025-09-02 15:25:39 | BE82: 0 | BF82: 29.95 | BG82: 0 | BH82: 0 | BJ82: 否 | BP82: - | BQ82: - | BR82: -
A83: 6920899223566450595 | B83: 6920899223566450595 | C83: 【老板周】日系极简 春季新品圆领简约设计感无袖马甲 | D83: 黑色;M(100-120斤);15天内发货 | E83: 1 | F83: 3767004410471907465 | G83: Z1640-黑色-M | H83: 289 | I83: 250.81 | J83: 0 | K83: 38.19 | L83: 平台七夕消费券-38.19 | M83: - | N83: - | O83: 0 | P83: 0 | Q83: 0 | R83: 抖音月付 | S83: 0 | T83: *** | U83: *** | V83: 吉林省 | W83: 长春市 | X83: 南关区 | Y83: 新立城镇 | Z83: *** | AA83: 否 | AC83: 2025-08-23 20:39:52 | AD83: 蓝色 | AE83: SF3237538166127(收） Z1640-黑色-M*1# | AG83: 2025-08-23 20:39:56 | AH83: 抖音 | AI83: 精选联盟 | AJ83: 已关闭 | AK83: 2025-09-07 20:39:56 | AL83: 普通订单 | AM83: 0 | AN83: 2353393836764088 | AO83: 老板周 | AP83: - | AQ83: 退款成功 | AS83: - | AT83: - | AU83: - | AW83: 否 | AX83: 无 | AY83: 其他 | AZ83: 直播 | BA83: 直播推荐 | BB83: - | BC83: - | BD83: 2025-09-01 23:14:20 | BE83: 0 | BF83: 38.19 | BG83: 0 | BH83: 0 | BJ83: 否 | BP83: - | BQ83: - | BR83: -
A84: 6945487810204669849 | B84: 6945487810204669849 | C84: 【老板周】日系极简 春季新品圆领简约设计感无袖马甲 | D84: 黑色;L(120-135斤);15天内发货 | E84: 1 | F84: 3767004410471907465 | G84: Z1640-黑色-L | H84: 289 | I84: 289 | J84: 0 | K84: 0 | L84: - | M84: - | N84: - | O84: 0 | P84: 0 | Q84: 0 | R84: 抖音月付 | S84: 0 | T84: *** | U84: *** | V84: 北京市 | W84: 北京市 | X84: 朝阳区 | Y84: 东坝地区 | Z84: *** | AA84: 否 | AC84: 2025-08-23 20:37:17 | AD84: 蓝色 | AE84: SF3237506934842(收） Z1640-黑色-L*1# | AG84: 2025-08-23 20:37:19 | AH84: 抖音 | AI84: 精选联盟 | AJ84: 已关闭 | AK84: 2025-09-07 20:37:20 | AL84: 普通订单 | AM84: 0 | AN84: 2353393836764088 | AO84: 老板周 | AP84: - | AQ84: 退款成功 | AS84: - | AT84: - | AU84: - | AW84: 否 | AX84: 无 | AY84: 其他 | AZ84: 直播 | BA84: 关注来源 | BB84: - | BC84: - | BD84: 2025-08-31 23:39:54 | BE84: 0 | BF84: 0 | BG84: 0 | BH84: 0 | BJ84: 否 | BP84: - | BQ84: - | BR84: -
A85: 6945485370033444761 | B85: 6945485370033444761 | C85: 【老板周】时髦撞色 春季新款假两件显瘦长袖打底T恤上衣 | D85: 黑色;L(120-135斤);15天内发货 | E85: 1 | F85: 3770648898645918626 | G85: Z1576-黑色-L | H85: 199 | I85: 199 | J85: 0 | K85: 0 | L85: - | M85: - | N85: - | O85: 0 | P85: 0 | Q85: 0 | R85: 抖音月付 | S85: 0 | T85: *** | U85: *** | V85: 北京市 | W85: 北京市 | X85: 朝阳区 | Y85: 东坝地区 | Z85: *** | AA85: 否 | AC85: 2025-08-23 20:37:07 | AD85: 灰色 | AG85: 2025-08-23 20:37:10 | AH85: 抖音 | AI85: 精选联盟 | AJ85: 已关闭 | AK85: 2025-09-07 20:37:11 | AL85: 普通订单 | AM85: 0 | AN85: 2353393836764088 | AO85: 老板周 | AP85: - | AQ85: 退款成功 | AS85: - | AT85: - | AU85: - | AW85: 否 | AX85: 无 | AY85: 其他 | AZ85: 直播 | BA85: 关注来源 | BB85: - | BC85: - | BE85: 0 | BF85: 0 | BG85: 0 | BH85: 0 | BJ85: 否 | BP85: - | BQ85: - | BR85: -
A86: 6945473693492254155 | B86: 6945473693492254155 | C86: 【老板周】时髦撞色 春季新款假两件显瘦长袖打底T恤上衣 | D86: 黑色;M(100-120斤);15天内发货 | E86: 1 | F86: 3770648898645918626 | G86: Z1576-黑色-M | H86: 199 | I86: 199 | J86: 0 | K86: 0 | L86: - | M86: - | N86: - | O86: 0 | P86: 0 | Q86: 0 | R86: 抖音支付 | S86: 0 | T86: *** | U86: *** | V86: 陕西省 | W86: 渭南市 | X86: 蒲城县 | Y86: 奉先街道 | Z86: *** | AA86: 否 | AC86: 2025-08-23 20:37:00 | AD86: 灰色 | AF86: 2025-09-07 23:42:42 | AG86: 2025-08-23 20:38:48 | AH86: 抖音 | AI86: 精选联盟 | AJ86: 已完成 | AK86: 2025-09-07 20:38:48 | AL86: 普通订单 | AM86: 0 | AN86: 2353393836764088 | AO86: 老板周 | AP86: - | AQ86: - | AS86: - | AT86: - | AU86: - | AW86: 否 | AX86: 无 | AY86: 其他 | AZ86: 直播 | BA86: 直播推荐 | BB86: - | BC86: - | BD86: 2025-08-31 23:42:42 | BE86: 0 | BF86: 0 | BG86: 0 | BH86: 0 | BJ86: 否 | BP86: - | BQ86: - | BR86: -
A87: 6920894543975054469 | B87: 6920894543975054469 | C87: 【老板周】日系极简 春季新品圆领简约设计感无袖马甲 | D87: 黑色;L(120-135斤);15天内发货 | E87: 1 | F87: 3767004410471907465 | G87: Z1640-黑色-L | H87: 289 | I87: 289 | J87: 0 | K87: 0 | L87: - | M87: - | N87: - | O87: 0 | P87: 0 | Q87: 0 | R87: 抖音月付 | S87: 0 | T87: *** | U87: *** | V87: 吉林省 | W87: 长春市 | X87: 宽城区 | Y87: 兴业街道 | Z87: *** | AA87: 否 | AC87: 2025-08-23 20:35:54 | AD87: 灰色 | AF87: 2025-09-07 23:39:54 | AG87: 2025-08-23 20:35:55 | AH87: 抖音 | AI87: 精选联盟 | AJ87: 已完成 | AK87: 2025-09-07 20:35:55 | AL87: 普通订单 | AM87: 0 | AN87: 2353393836764088 | AO87: 老板周 | AP87: - | AQ87: - | AS87: - | AT87: - | AU87: - | AW87: 否 | AX87: 无 | AY87: 其他 | AZ87: 直播 | BA87: 直播推荐 | BB87: - | BC87: - | BD87: 2025-08-31 23:39:54 | BE87: 0 | BF87: 0 | BG87: 0 | BH87: 0 | BJ87: 否 | BP87: - | BQ87: - | BR87: -
A88: 6945467619805763273 | B88: 6945467619805763273 | C88: 【老板周】时髦撞色 春季新款假两件显瘦长袖打底T恤上衣 | D88: 黑色;M(100-120斤);15天内发货 | E88: 1 | F88: 3770648898645918626 | G88: Z1576-黑色-M | H88: 199 | I88: 199 | J88: 0 | K88: 0 | L88: - | M88: - | N88: - | O88: 0 | P88: 0 | Q88: 0 | R88: 抖音月付 | S88: 0 | T88: *** | U88: *** | V88: 山西省 | W88: 晋中市 | X88: 平遥县 | Y88: 古陶镇 | Z88: *** | AA88: 否 | AC88: 2025-08-23 20:34:07 | AD88: 灰色 | AG88: 2025-08-23 20:34:09 | AH88: 抖音 | AI88: 精选联盟 | AJ88: 已关闭 | AK88: 2025-09-07 20:34:09 | AL88: 普通订单 | AM88: 0 | AN88: 2353393836764088 | AO88: 老板周 | AP88: - | AQ88: 退款成功 | AS88: - | AT88: - | AU88: - | AW88: 否 | AX88: 无 | AY88: 其他 | AZ88: 直播 | BA88: 直播推荐 | BB88: - | BC88: - | BE88: 0 | BF88: 0 | BG88: 0 | BH88: 0 | BJ88: 否 | BP88: - | BQ88: - | BR88: -
A89: 6920892563116359550 | B89: 6920892563116359550 | C89: 【老板周】时髦撞色 春季新款假两件显瘦长袖打底T恤上衣 | D89: 黑色;M(100-120斤);15天内发货 | E89: 1 | F89: 3770648898645918626 | G89: Z1576-黑色-M | H89: 199 | I89: 179 | J89: 0 | K89: 20 | L89: 平台专属限时优惠券-20.00 | M89: - | N89: - | O89: 0 | P89: 0 | Q89: 0 | R89: 支付宝 | S89: 0 | T89: *** | U89: *** | V89: 陕西省 | W89: 西安市 | X89: 未央区 | Y89: 未央宫街道 | Z89: *** | AA89: 否 | AC89: 2025-08-23 20:08:56 | AD89: 蓝色 | AE89: SF3239415831023(收） Z1576-黑色-M*1# | AG89: 2025-08-23 20:09:06 | AH89: 抖音 | AI89: 精选联盟 | AJ89: 已关闭 | AK89: 2025-09-07 20:09:07 | AL89: 普通订单 | AM89: 0 | AN89: 2353393836764088 | AO89: 老板周 | AP89: - | AQ89: 退款成功 | AS89: - | AT89: - | AU89: - | AW89: 否 | AX89: 直播 | AY89: 广告 | AZ89: 直播 | BA89: 其他 | BB89: - | BC89: - | BD89: 2025-08-31 23:42:42 | BE89: 0 | BF89: 20 | BG89: 0 | BH89: 0 | BJ89: 否 | BP89: - | BQ89: - | BR89: -
A90: 6945475825819719198 | B90: 6945475825819719198 | C90: 【老板周】时髦撞色 春季新款假两件显瘦长袖打底T恤上衣 | D90: 黑色;M(100-120斤);15天内发货 | E90: 1 | F90: 3770648898645918626 | G90: Z1576-黑色-M | H90: 199 | I90: 199 | J90: 0 | K90: 0 | L90: - | M90: - | N90: - | O90: 0 | P90: 0 | Q90: 0 | R90: 抖音月付 | S90: 0 | T90: *** | U90: *** | V90: 陕西省 | W90: 延安市 | X90: 宝塔区 | Y90: 桥沟街道 | Z90: *** | AA90: 否 | AC90: 2025-08-23 20:01:26 | AD90: 蓝色 | AE90: SF3284841807432(收） Z1576-黑色-M*1# | AG90: 2025-08-23 20:01:28 | AH90: 抖音 | AI90: 精选联盟 | AJ90: 已关闭 | AK90: 2025-09-07 20:01:28 | AL90: 普通订单 | AM90: 0 | AN90: 2353393836764088 | AO90: 老板周 | AP90: - | AQ90: 退款成功 | AS90: - | AT90: - | AU90: - | AW90: 否 | AX90: 无 | AY90: 其他 | AZ90: 直播 | BA90: 直播推荐 | BB90: - | BC90: - | BD90: 2025-08-31 23:42:42 | BE90: 0 | BF90: 0 | BG90: 0 | BH90: 0 | BJ90: 否 | BP90: - | BQ90: - | BR90: -
A91: 6945475928514172446 | B91: 6945475928514172446 | C91: 【老板周】日系极简 春季新品圆领简约设计感无袖马甲 | D91: 黑色;M(100-120斤);15天内发货 | E91: 1 | F91: 3767004410471907465 | G91: Z1640-黑色-M | H91: 289 | I91: 289 | J91: 0 | K91: 0 | L91: - | M91: - | N91: - | O91: 0 | P91: 0 | Q91: 0 | R91: 抖音月付 | S91: 0 | T91: *** | U91: *** | V91: 陕西省 | W91: 延安市 | X91: 宝塔区 | Y91: 桥沟街道 | Z91: *** | AA91: 否 | AC91: 2025-08-23 19:59:28 | AD91: 蓝色 | AE91: SF3284841807432(收） Z1640-黑色-M*1# | AG91: 2025-08-23 19:59:30 | AH91: 抖音 | AI91: 精选联盟 | AJ91: 已关闭 | AK91: 2025-09-07 19:59:30 | AL91: 普通订单 | AM91: 0 | AN91: 2353393836764088 | AO91: 老板周 | AP91: - | AQ91: 退款成功 | AS91: - | AT91: - | AU91: - | AW91: 否 | AX91: 无 | AY91: 其他 | AZ91: 直播 | BA91: 直播推荐 | BB91: - | BC91: - | BD91: 2025-09-01 23:14:20 | BE91: 0 | BF91: 0 | BG91: 0 | BH91: 0 | BJ91: 否 | BP91: - | BQ91: - | BR91: -
A92: 6945471889155364583 | B92: 6945471889155364583 | C92: 【老板周】日系极简 春季新品圆领简约设计感无袖马甲 | D92: 黑色;L(120-135斤);15天内发货 | E92: 1 | F92: 3767004410471907465 | G92: Z1640-黑色-L | H92: 289 | I92: 289 | J92: 0 | K92: 0 | L92: - | M92: - | N92: - | O92: 0 | P92: 0 | Q92: 0 | R92: 抖音支付 | S92: 0 | T92: *** | U92: *** | V92: 北京市 | W92: 北京市 | X92: 通州区 | Y92: 中仓街道 | Z92: *** | AA92: 否 | AC92: 2025-08-23 19:32:09 | AD92: 灰色 | AF92: 2025-09-02 18:47:11 | AG92: 2025-08-23 19:32:13 | AH92: 抖音 | AI92: 精选联盟 | AJ92: 已完成 | AK92: 2025-09-07 19:32:13 | AL92: 普通订单 | AM92: 0 | AN92: 2353393836764088 | AO92: 老板周 | AP92: - | AQ92: - | AS92: - | AT92: - | AU92: - | AW92: 否 | AX92: 无 | AY92: 其他 | AZ92: 直播 | BA92: 关注来源 | BB92: - | BC92: - | BD92: 2025-08-31 23:39:54 | BE92: 0 | BF92: 0 | BG92: 0 | BH92: 0 | BJ92: 否 | BP92: - | BQ92: - | BR92: -
A93: 6945469470994273593 | B93: 6945469470994273593 | C93: 【老板周】时髦撞色 春季新款假两件显瘦长袖打底T恤上衣 | D93: 黑色;S(80-100斤);15天内发货 | E93: 1 | F93: 3770648898645918626 | G93: Z1576-黑色-S | H93: 199 | I93: 199 | J93: 0 | K93: 0 | L93: - | M93: - | N93: - | O93: 0 | P93: 0 | Q93: 0 | R93: 抖音月付 | S93: 0 | T93: *** | U93: *** | V93: 广东省 | W93: 深圳市 | X93: 南山区 | Y93: 南山街道 | Z93: *** | AA93: 否 | AC93: 2025-08-23 19:17:36 | AD93: 灰色 | AG93: 2025-08-23 19:17:38 | AH93: 抖音 | AI93: 精选联盟 | AJ93: 已关闭 | AK93: 2025-09-07 19:17:38 | AL93: 普通订单 | AM93: 0 | AN93: 2353393836764088 | AO93: 老板周 | AP93: - | AQ93: 退款成功 | AS93: - | AT93: - | AU93: - | AW93: 否 | AX93: 无 | AY93: 其他 | AZ93: 直播 | BA93: 直播推荐 | BB93: - | BC93: - | BE93: 0 | BF93: 0 | BG93: 0 | BH93: 0 | BJ93: 否 | BP93: - | BQ93: - | BR93: -
A94: 6920896745472556170 | B94: 6920896745472556170 | C94: 【老板周】日系极简 春季新品圆领简约设计感无袖马甲 | D94: 黑色;M(100-120斤);15天内发货 | E94: 1 | F94: 3767004410471907465 | G94: Z1640-黑色-M | H94: 289 | I94: 289 | J94: 0 | K94: 0 | L94: - | M94: - | N94: - | O94: 0 | P94: 0 | Q94: 0 | R94: 抖音支付 | S94: 0 | T94: *** | U94: *** | V94: 上海市 | W94: 上海市 | X94: 黄浦区 | Y94: 打浦桥街道 | Z94: *** | AA94: 否 | AC94: 2025-08-23 19:15:08 | AD94: 蓝色 | AE94: 73570894834784(收） Z1640-黑色-M*1# | AG94: 2025-08-23 19:15:14 | AH94: 抖音 | AI94: 精选联盟 | AJ94: 已关闭 | AK94: 2025-09-07 19:15:14 | AL94: 普通订单 | AM94: 0 | AN94: 2353393836764088 | AO94: 老板周 | AP94: - | AQ94: 退款成功 | AS94: - | AT94: - | AU94: - | AW94: 否 | AX94: 无 | AY94: 其他 | AZ94: 直播 | BA94: 直播推荐 | BB94: - | BC94: - | BD94: 2025-09-01 23:14:20 | BE94: 0 | BF94: 0 | BG94: 0 | BH94: 0 | BJ94: 否 | BP94: - | BQ94: - | BR94: -
A95: 6920892429455490186 | B95: 6920892429455490186 | C95: 【老板周】时髦撞色 春季新款假两件显瘦长袖打底T恤上衣 | D95: 黑色;M(100-120斤);15天内发货 | E95: 1 | F95: 3770648898645918626 | G95: Z1576-黑色-M | H95: 199 | I95: 199 | J95: 0 | K95: 0 | L95: - | M95: - | N95: - | O95: 0 | P95: 0 | Q95: 0 | R95: 抖音支付 | S95: 0 | T95: *** | U95: *** | V95: 上海市 | W95: 上海市 | X95: 黄浦区 | Y95: 打浦桥街道 | Z95: *** | AA95: 否 | AC95: 2025-08-23 19:14:38 | AD95: 蓝色 | AE95: 73570769408190(收） Z1576-黑色-M*1# | AG95: 2025-08-23 19:14:48 | AH95: 抖音 | AI95: 精选联盟 | AJ95: 已关闭 | AK95: 2025-09-07 19:14:48 | AL95: 普通订单 | AM95: 0 | AN95: 2353393836764088 | AO95: 老板周 | AP95: - | AQ95: 退款成功 | AS95: - | AT95: - | AU95: - | AW95: 否 | AX95: 无 | AY95: 其他 | AZ95: 直播 | BA95: 直播推荐 | BB95: - | BC95: - | BD95: 2025-08-31 22:01:06 | BE95: 0 | BF95: 0 | BG95: 0 | BH95: 0 | BJ95: 否 | BP95: - | BQ95: - | BR95: -
A96: 6945480350198339381 | B96: 6945480350198339381 | C96: 【老板周】时髦撞色 春季新款假两件显瘦长袖打底T恤上衣 | D96: 黑色;M(100-120斤);15天内发货 | E96: 1 | F96: 3770648898645918626 | G96: Z1576-黑色-M | H96: 199 | I96: 199 | J96: 0 | K96: 0 | L96: - | M96: - | N96: - | O96: 0 | P96: 0 | Q96: 0 | R96: 抖音支付 | S96: 0 | T96: *** | U96: *** | V96: 陕西省 | W96: 西安市 | X96: 未央区 | Y96: 张家堡街道 | Z96: *** | AA96: 否 | AC96: 2025-08-23 18:57:42 | AD96: 灰色 | AH96: 番茄小说-抖音电商 | AI96: 精选联盟 | AJ96: 已关闭 | AK96: 2025-09-07 18:57:42 | AL96: 普通订单 | AM96: 0 | AN96: 2353393836764088 | AO96: 老板周 | AP96: - | AQ96: - | AR96: 用户超时未支付自动取消 | AS96: - | AT96: - | AU96: - | AW96: 否 | AX96: 直播 | AY96: 广告 | AZ96: 直播 | BA96: 其他 | BB96: - | BC96: - | BE96: 0 | BF96: 0 | BG96: 0 | BH96: 0 | BJ96: 否 | BP96: - | BQ96: - | BR96: -
A97: 6920901228969950691 | B97: 6920901228969950691 | C97: 【老板周】日系极简 春季新品圆领简约设计感无袖马甲 | D97: 黑色;M(100-120斤);15天内发货 | E97: 1 | F97: 3767004410471907465 | G97: Z1640-黑色-M | H97: 289 | I97: 289 | J97: 0 | K97: 0 | L97: - | M97: - | N97: - | O97: 0 | P97: 0 | Q97: 0 | R97: 抖音支付 | S97: 0 | T97: *** | U97: *** | V97: 辽宁省 | W97: 沈阳市 | X97: 苏家屯区 | Y97: 民主街道 | Z97: *** | AA97: 否 | AC97: 2025-08-23 18:22:38 | AD97: 灰色 | AG97: 2025-08-23 18:22:43 | AH97: 抖音 | AI97: 精选联盟 | AJ97: 已关闭 | AK97: 2025-09-07 18:22:44 | AL97: 普通订单 | AM97: 0 | AN97: 2353393836764088 | AO97: 老板周 | AP97: - | AQ97: 退款成功 | AS97: - | AT97: - | AU97: - | AW97: 否 | AX97: 无 | AY97: 其他 | AZ97: 直播 | BA97: 商城推荐 | BB97: - | BC97: - | BE97: 0 | BF97: 0 | BG97: 0 | BH97: 0 | BJ97: 否 | BP97: - | BQ97: - | BR97: -
A98: 6920901308765076963 | B98: 6920901308765076963 | C98: 【老板周】时髦撞色 春季新款假两件显瘦长袖打底T恤上衣 | D98: 黑色;M(100-120斤);15天内发货 | E98: 1 | F98: 3770648898645918626 | G98: Z1576-黑色-M | H98: 199 | I98: 199 | J98: 0 | K98: 0 | L98: - | M98: - | N98: - | O98: 0 | P98: 0 | Q98: 0 | R98: 抖音支付 | S98: 0 | T98: *** | U98: *** | V98: 辽宁省 | W98: 沈阳市 | X98: 苏家屯区 | Y98: 民主街道 | Z98: *** | AA98: 否 | AC98: 2025-08-23 18:22:00 | AD98: 灰色 | AG98: 2025-08-23 18:22:06 | AH98: 抖音 | AI98: 精选联盟 | AJ98: 已关闭 | AK98: 2025-09-07 18:22:06 | AL98: 普通订单 | AM98: 0 | AN98: 2353393836764088 | AO98: 老板周 | AP98: - | AQ98: 退款成功 | AS98: - | AT98: - | AU98: - | AW98: 否 | AX98: 无 | AY98: 其他 | AZ98: 直播 | BA98: 商城推荐 | BB98: - | BC98: - | BE98: 0 | BF98: 0 | BG98: 0 | BH98: 0 | BJ98: 否 | BP98: - | BQ98: - | BR98: -
A99: 6945487556598699454 | B99: 6945487556598699454 | C99: 【老板周】时髦撞色 春季新款假两件显瘦长袖打底T恤上衣 | D99: 黑色;M(100-120斤);15天内发货 | E99: 1 | F99: 3770648898645918626 | G99: Z1576-黑色-M | H99: 199 | I99: 199 | J99: 0 | K99: 0 | L99: - | M99: - | N99: - | O99: 0 | P99: 0 | Q99: 0 | R99: 抖音月付 | S99: 0 | T99: *** | U99: *** | V99: 山西省 | W99: 阳泉市 | X99: 矿区 | Y99: 平潭街街道 | Z99: *** | AA99: 否 | AC99: 2025-08-23 18:12:49 | AD99: 蓝色 | AE99: 9475620502178(收） Z1576-黑色-M*1# | AG99: 2025-08-23 18:12:51 | AH99: 抖音 | AI99: 精选联盟 | AJ99: 已关闭 | AK99: 2025-09-07 18:12:51 | AL99: 普通订单 | AM99: 0 | AN99: 2353393836764088 | AO99: 老板周 | AP99: - | AQ99: 退款成功 | AS99: - | AT99: - | AU99: - | AW99: 否 | AX99: 无 | AY99: 其他 | AZ99: 直播 | BA99: 直播推荐 | BB99: - | BC99: - | BD99: 2025-08-31 22:01:06 | BE99: 0 | BF99: 0 | BG99: 0 | BH99: 0 | BJ99: 否 | BP99: - | BQ99: - | BR99: -
A100: 6945469101898405538 | B100: 6945469101898405538 | C100: 【老板周】时髦撞色 春季新款假两件显瘦长袖打底T恤上衣 | D100: 黑色;L(120-135斤);15天内发货 | E100: 1 | F100: 3770648898645918626 | G100: Z1576-黑色-L | H100: 199 | I100: 199 | J100: 0 | K100: 0 | L100: - | M100: - | N100: - | O100: 0 | P100: 0 | Q100: 0 | R100: 支付宝 | S100: 0 | T100: *** | U100: *** | V100: 山东省 | W100: 菏泽市 | X100: 曹县 | Y100: 青菏街道 | Z100: *** | AA100: 否 | AC100: 2025-08-23 17:39:15 | AD100: 灰色 | AG100: 2025-08-23 17:39:22 | AH100: 抖音极速版 | AI100: 精选联盟 | AJ100: 已关闭 | AK100: 2025-09-07 17:39:22 | AL100: 普通订单 | AM100: 0 | AN100: 2353393836764088 | AO100: 老板周 | AP100: - | AQ100: 退款成功 | AS100: - | AT100: - | AU100: - | AW100: 否 | AX100: 直播 | AY100: 广告 | AZ100: 直播 | BA100: 搜索 | BB100: - | BC100: - | BE100: 0 | BF100: 0 | BG100: 0 | BH100: 0 | BJ100: 否 | BP100: - | BQ100: - | BR100: -
...

Sheet 抖音结算账单
R1: 结算时间 | S1: 订单号 | T1: 子订单号 | U1: 结算金额 | V1: 结算账户 | W1: 结算单类型 | X1: 有结算前退款 | Y1: 下单时间 | Z1: 商品ID | AA1: 商品名称 | AB1: 商品数量 | AC1: 达人ID | AD1: 达人名称 | AE1: 业务类型 | AF1: 订单类型 | AG1: 订单总价 | AH1: 商品总价 | AI1: 运费 | AJ1: 店铺劵 | AK1: 政府补贴商家垫资 | AL1: 结算前退款金额 | AM1: 平台补贴 | AN1: 其他平台补贴 | AO1: 政府补贴平台垫资 | AP1: 达人补贴 | AQ1: 抖音支付补贴 | AR1: 抖音月付营销补贴 | AS1: 银行补贴 | AT1: 以旧换新抵扣 | AU1: 平台补贴运费 | AV1: 用户实付 | AW1: 收入合计 | AX1: 平台服务费 | AY1: 达人佣金 | AZ1: 服务商佣金 | BA1: 渠道分成 | BB1: 招商服务费 | BC1: 站外推广费 | BD1: 其他分成 | BE1: 其他分成说明 | BF1: 支出合计 | BG1: 是否免佣 | BH1: 免佣金额 | BI1: 商户主体名称 | BJ1: 备注
A2: 年 | B2: 月 | C2: 订单号 | D2: 订单行数 | E2: 订单序位 | F2: 平台商品编码 | G2: 财务核算编码 | H2: 销售数量 | I2: 应收客户 | J2: 应收平台 | K2: 收：价外收费 | L2: 扣：平台佣金用 | M2: 扣：分销佣金 | N2: 扣：其它费用 | O2: 应到账金额 | P2: 备注1 | Q2: 备注2 | U2: 收入+支出 | AG2: 商品总价+运费 | AJ2: 包括商家发的优惠券、商品直降金额以及与平台混资补贴商家承担的金额 | AK2: 以旧换新商家先行出资，结算后商家拿着对应金额发票与政府进行金额结算。 | AL2: 退给用户的货款+运费+退补贴 | AN2: 其他平台补贴包括话费充值平台优惠金额，此部分补贴金额商家无需给平台开票 | AO2: 以旧换新政府出资补商家，跟随货款一同结算给商家，包括以旧换新政府补贴券，商家无需开票。 | AW2: 用户实付+平台补贴+达人补贴+抖音支付补贴+抖音月付补贴+银行补贴+以旧换新抵扣+平台补贴运费+政府补贴平台垫资+其他平台补贴 | AX2: '-(用户实付+平台补贴+达人补贴+平台补贴运费+政府补贴平台垫资+其他平台补贴)*费率 平台按照商品类目费率收取商家的费用 | AY2: '-(用户实付-运费+平台补贴+达人补贴+平台补贴运费+抖音支付补贴+抖音月付补贴+政府补贴平台垫资+其他平台补贴)*费率 商家支出给达人的佣金 | AZ2: 商家使用了服务商服务（例如商家招募与培训、内容制作、抖店开设与运营、达人运营等一站式服务），需要支付给对应服务商的佣金 | BA2: 仅在学浪订单场景下存在的分成，如果订单非学浪订单则不会有这个费用 | BB2: 商家支出给团长的佣金 | BC2: 推广者在抖音APP外进行商品推广，用户因推广者推广进入抖音APP进入小店平台并完成商品购买。商家商品通过精选联盟平台的推广者成交的，每笔订单商家需要向推广者支付一定比例的推广费 | BD2: 除“佣金、渠道分成、招商服务费、站外推广费”等账单中已分列展示之外的分成项目 | BF2: 平台服务费+达人佣金+服务商佣金+渠道分成+招商服务费+站外推广费+其他分成 | BG2: 订单是否命中了平台各类平台服务费减免活动，例如商品卡佣金减免等活动 | BH2: 订单结算时按照平台活动规则减免掉的金额，免佣金额不会结算或打款给商家
A3: =YEAR(R3) -> 2025 | B3: =MONTH(R3) -> 8 | C3: =S3 -> 6944909511565579469 | F3: {=IFERROR(INDEX('抖音订单-按支付日期-ABF列，要先手动清除空格'!G:G,MATCH(RIGHT(S3,LEN(S3)-1)&RIGHT(T3,LEN(T3)-1)&RIGHT(Z3,LEN(Z3)-1),'抖音订单-按支付日期-ABF列，要先手动清除空格'!A:A&'抖音订单-按支付日期-ABF列，要先手动清除空格'!B:B&'抖音订单-按支付日期-ABF列，要先手动清除空格'!F:F,0)),0)} -> 0 | G3: =IFERROR(SUBSTITUTE(CLEAN(LEFT(F3,FIND("-",F3)-1))," ",""),"") | H3: {=IFERROR(_xlfn.IFS(AND(W3="已结算",AW3>30),AB3,LEFT(W3,5)="结算后退款",-AB3,LEFT(W3,5)="保证金退款",0),0)} -> 1 | I3: =AV3-K3 -> 289 | J3: =SUM(AM3:AU3) -> 0 | K3: =AI3 -> 0 | L3: =AX3 -> -14.45 | M3: =SUM(AY3:BD3) -> 0 | O3: =SUM(I3:N3) -> 274.55 | R3: 45884.725 | S3: 6944909511565579469 | T3: '6944909511565579469 | U3: 274.55 | V3: 聚合账户 | W3: 已结算 | X3: 否 | Y3: 45872.661 | Z3: '3767004410471907465 | AA3: 【老板周】日系极简 春季新品圆领简约设计感无袖马甲 | AB3: 1 | AC3: '2353393836764088 | AD3: 老板周 | AE3: 精选联盟 | AF3: 普通订单 | AG3: 289 | AH3: 289 | AI3: 0 | AJ3: 0 | AK3: 0 | AL3: 0 | AM3: 0 | AN3: 0 | AO3: 0 | AP3: 0 | AQ3: 0 | AR3: 0 | AS3: 0 | AT3: 0 | AU3: 0 | AV3: 289 | AW3: 289 | AX3: -14.45 | AY3: 0 | AZ3: 0 | BA3: 0 | BB3: 0 | BC3: 0 | BD3: 0 | BF3: -14.45 | BH3: 0 | BI3: 广州欣煌服饰有限公司
A4: =YEAR(R4) -> 2025 | B4: =MONTH(R4) -> 8 | C4: =S4 -> '6920625548926615460 | F4: {=IFERROR(INDEX('抖音订单-按支付日期-ABF列，要先手动清除空格'!G:G,MATCH(RIGHT(S4,LEN(S4)-1)&RIGHT(T4,LEN(T4)-1)&RIGHT(Z4,LEN(Z4)-1),'抖音订单-按支付日期-ABF列，要先手动清除空格'!A:A&'抖音订单-按支付日期-ABF列，要先手动清除空格'!B:B&'抖音订单-按支付日期-ABF列，要先手动清除空格'!F:F,0)),0)} -> Z1578-黑色-S | G4: =IFERROR(SUBSTITUTE(CLEAN(LEFT(F4,FIND("-",F4)-1))," ",""),"") -> Z1578 | H4: {=IFERROR(_xlfn.IFS(AND(W4="已结算",AW4>30),AB4,LEFT(W4,5)="结算后退款",-AB4,LEFT(W4,5)="保证金退款",0),0)} -> 1 | I4: =AV4-K4 -> 289 | J4: =SUM(AM4:AU4) -> 0 | K4: =AI4 -> 0 | L4: =AX4 -> -14.45 | M4: =SUM(AY4:BD4) -> 0 | O4: =SUM(I4:N4) -> 274.55 | R4: 45885.578 | S4: '6920625548926615460 | T4: '6920625548926615460 | U4: 274.55 | V4: 聚合账户 | W4: 已结算 | X4: 否 | Y4: 45874.662 | Z4: '3767375525761384637 | AA4: 【老板周】慵懒风 新品混纱法式极简复古廓形针织上衣 | AB4: 1 | AC4: '2353393836764088 | AD4: 老板周 | AE4: 精选联盟 | AF4: 普通订单 | AG4: 289 | AH4: 289 | AI4: 0 | AJ4: 0 | AK4: 0 | AL4: 0 | AM4: 0 | AN4: 0 | AO4: 0 | AP4: 0 | AQ4: 0 | AR4: 0 | AS4: 0 | AT4: 0 | AU4: 0 | AV4: 289 | AW4: 289 | AX4: -14.45 | AY4: 0 | AZ4: 0 | BA4: 0 | BB4: 0 | BC4: 0 | BD4: 0 | BF4: -14.45 | BH4: 0 | BI4: 广州欣煌服饰有限公司
A5: =YEAR(R5) -> 2025 | B5: =MONTH(R5) -> 8 | C5: =S5 -> '6944946092181821002 | F5: {=IFERROR(INDEX('抖音订单-按支付日期-ABF列，要先手动清除空格'!G:G,MATCH(RIGHT(S5,LEN(S5)-1)&RIGHT(T5,LEN(T5)-1)&RIGHT(Z5,LEN(Z5)-1),'抖音订单-按支付日期-ABF列，要先手动清除空格'!A:A&'抖音订单-按支付日期-ABF列，要先手动清除空格'!B:B&'抖音订单-按支付日期-ABF列，要先手动清除空格'!F:F,0)),0)} -> Z1578-黑色-L | G5: =IFERROR(SUBSTITUTE(CLEAN(LEFT(F5,FIND("-",F5)-1))," ",""),"") -> Z1578 | H5: {=IFERROR(_xlfn.IFS(AND(W5="已结算",AW5>30),AB5,LEFT(W5,5)="结算后退款",-AB5,LEFT(W5,5)="保证金退款",0),0)} -> 1 | I5: =AV5-K5 -> 289 | J5: =SUM(AM5:AU5) -> 0 | K5: =AI5 -> 0 | L5: =AX5 -> -14.45 | M5: =SUM(AY5:BD5) -> 0 | O5: =SUM(I5:N5) -> 274.55 | R5: 45885.619 | S5: '6944946092181821002 | T5: '6944946092181821002 | U5: 274.55 | V5: 聚合账户 | W5: 已结算 | X5: 否 | Y5: 45874.662 | Z5: '3767375525761384637 | AA5: 【老板周】慵懒风 新品混纱法式极简复古廓形针织上衣 | AB5: 1 | AC5: '2353393836764088 | AD5: 老板周 | AE5: 精选联盟 | AF5: 普通订单 | AG5: 289 | AH5: 289 | AI5: 0 | AJ5: 0 | AK5: 0 | AL5: 0 | AM5: 0 | AN5: 0 | AO5: 0 | AP5: 0 | AQ5: 0 | AR5: 0 | AS5: 0 | AT5: 0 | AU5: 0 | AV5: 289 | AW5: 289 | AX5: -14.45 | AY5: 0 | AZ5: 0 | BA5: 0 | BB5: 0 | BC5: 0 | BD5: 0 | BF5: -14.45 | BH5: 0 | BI5: 广州欣煌服饰有限公司
A6: =YEAR(R6) -> 2025 | B6: =MONTH(R6) -> 8 | C6: =S6 -> '6920588865561066923 | F6: {=IFERROR(INDEX('抖音订单-按支付日期-ABF列，要先手动清除空格'!G:G,MATCH(RIGHT(S6,LEN(S6)-1)&RIGHT(T6,LEN(T6)-1)&RIGHT(Z6,LEN(Z6)-1),'抖音订单-按支付日期-ABF列，要先手动清除空格'!A:A&'抖音订单-按支付日期-ABF列，要先手动清除空格'!B:B&'抖音订单-按支付日期-ABF列，要先手动清除空格'!F:F,0)),0)} -> Z1640-黑色-S | G6: =IFERROR(SUBSTITUTE(CLEAN(LEFT(F6,FIND("-",F6)-1))," ",""),"") -> Z1640 | H6: {=IFERROR(_xlfn.IFS(AND(W6="已结算",AW6>30),AB6,LEFT(W6,5)="结算后退款",-AB6,LEFT(W6,5)="保证金退款",0),0)} -> 1 | I6: =AV6-K6 -> 289 | J6: =SUM(AM6:AU6) -> 0 | K6: =AI6 -> 0 | L6: =AX6 -> -14.45 | M6: =SUM(AY6:BD6) -> 0 | O6: =SUM(I6:N6) -> 274.55 | R6: 45885.692 | S6: '6920588865561066923 | T6: '6920588865561066923 | U6: 274.55 | V6: 聚合账户 | W6: 已结算 | X6: 否 | Y6: 45872.662 | Z6: '3767004410471907465 | AA6: 【老板周】日系极简 春季新品圆领简约设计感无袖马甲 | AB6: 1 | AC6: '2353393836764088 | AD6: 老板周 | AE6: 精选联盟 | AF6: 普通订单 | AG6: 289 | AH6: 289 | AI6: 0 | AJ6: 0 | AK6: 0 | AL6: 0 | AM6: 0 | AN6: 0 | AO6: 0 | AP6: 0 | AQ6: 0 | AR6: 0 | AS6: 0 | AT6: 0 | AU6: 0 | AV6: 289 | AW6: 289 | AX6: -14.45 | AY6: 0 | AZ6: 0 | BA6: 0 | BB6: 0 | BC6: 0 | BD6: 0 | BF6: -14.45 | BH6: 0 | BI6: 广州欣煌服饰有限公司
A7: =YEAR(R7) -> 2025 | B7: =MONTH(R7) -> 8 | C7: =S7 -> '6944948490935997505 | F7: {=IFERROR(INDEX('抖音订单-按支付日期-ABF列，要先手动清除空格'!G:G,MATCH(RIGHT(S7,LEN(S7)-1)&RIGHT(T7,LEN(T7)-1)&RIGHT(Z7,LEN(Z7)-1),'抖音订单-按支付日期-ABF列，要先手动清除空格'!A:A&'抖音订单-按支付日期-ABF列，要先手动清除空格'!B:B&'抖音订单-按支付日期-ABF列，要先手动清除空格'!F:F,0)),0)} -> Z1578-黑色-M | G7: =IFERROR(SUBSTITUTE(CLEAN(LEFT(F7,FIND("-",F7)-1))," ",""),"") -> Z1578 | H7: {=IFERROR(_xlfn.IFS(AND(W7="已结算",AW7>30),AB7,LEFT(W7,5)="结算后退款",-AB7,LEFT(W7,5)="保证金退款",0),0)} -> 1 | I7: =AV7-K7 -> 289 | J7: =SUM(AM7:AU7) -> 0 | K7: =AI7 -> 0 | L7: =AX7 -> -14.45 | M7: =SUM(AY7:BD7) -> 0 | O7: =SUM(I7:N7) -> 274.55 | R7: 45885.734 | S7: '6944948490935997505 | T7: '6944948490935997505 | U7: 274.55 | V7: 聚合账户 | W7: 已结算 | X7: 否 | Y7: 45874.662 | Z7: '3767375525761384637 | AA7: 【老板周】慵懒风 新品混纱法式极简复古廓形针织上衣 | AB7: 1 | AC7: '2353393836764088 | AD7: 老板周 | AE7: 精选联盟 | AF7: 普通订单 | AG7: 289 | AH7: 289 | AI7: 0 | AJ7: 0 | AK7: 0 | AL7: 0 | AM7: 0 | AN7: 0 | AO7: 0 | AP7: 0 | AQ7: 0 | AR7: 0 | AS7: 0 | AT7: 0 | AU7: 0 | AV7: 289 | AW7: 289 | AX7: -14.45 | AY7: 0 | AZ7: 0 | BA7: 0 | BB7: 0 | BC7: 0 | BD7: 0 | BF7: -14.45 | BH7: 0 | BI7: 广州欣煌服饰有限公司
A8: =YEAR(R8) -> 2025 | B8: =MONTH(R8) -> 8 | C8: =S8 -> '6945101402919081899 | F8: {=IFERROR(INDEX('抖音订单-按支付日期-ABF列，要先手动清除空格'!G:G,MATCH(RIGHT(S8,LEN(S8)-1)&RIGHT(T8,LEN(T8)-1)&RIGHT(Z8,LEN(Z8)-1),'抖音订单-按支付日期-ABF列，要先手动清除空格'!A:A&'抖音订单-按支付日期-ABF列，要先手动清除空格'!B:B&'抖音订单-按支付日期-ABF列，要先手动清除空格'!F:F,0)),0)} -> Z1688-黑色-L | G8: =IFERROR(SUBSTITUTE(CLEAN(LEFT(F8,FIND("-",F8)-1))," ",""),"") -> Z1688 | H8: {=IFERROR(_xlfn.IFS(AND(W8="已结算",AW8>30),AB8,LEFT(W8,5)="结算后退款",-AB8,LEFT(W8,5)="保证金退款",0),0)} -> 1 | I8: =AV8-K8 -> 499 | J8: =SUM(AM8:AU8) -> 0 | K8: =AI8 -> 0 | L8: =AX8 -> -24.95 | M8: =SUM(AY8:BD8) -> 0 | O8: =SUM(I8:N8) -> 474.05 | R8: 45886.573 | S8: '6945101402919081899 | T8: '6945101402919081899 | U8: 474.05 | V8: 聚合账户 | W8: 已结算 | X8: 否 | Y8: 45879.667 | Z8: '3766960333395198324 | AA8: 【老板周】复古英伦 极简设计立体剪裁无领廓形外套 | AB8: 1 | AC8: '2353393836764088 | AD8: 老板周 | AE8: 精选联盟 | AF8: 普通订单 | AG8: 499 | AH8: 499 | AI8: 0 | AJ8: 0 | AK8: 0 | AL8: 0 | AM8: 0 | AN8: 0 | AO8: 0 | AP8: 0 | AQ8: 0 | AR8: 0 | AS8: 0 | AT8: 0 | AU8: 0 | AV8: 499 | AW8: 499 | AX8: -24.95 | AY8: 0 | AZ8: 0 | BA8: 0 | BB8: 0 | BC8: 0 | BD8: 0 | BF8: -24.95 | BH8: 0 | BI8: 广州欣煌服饰有限公司
A9: =YEAR(R9) -> 2025 | B9: =MONTH(R9) -> 8 | C9: =S9 -> '6944916130719602370 | F9: {=IFERROR(INDEX('抖音订单-按支付日期-ABF列，要先手动清除空格'!G:G,MATCH(RIGHT(S9,LEN(S9)-1)&RIGHT(T9,LEN(T9)-1)&RIGHT(Z9,LEN(Z9)-1),'抖音订单-按支付日期-ABF列，要先手动清除空格'!A:A&'抖音订单-按支付日期-ABF列，要先手动清除空格'!B:B&'抖音订单-按支付日期-ABF列，要先手动清除空格'!F:F,0)),0)} -> Z2219-灰绿色-M | G9: =IFERROR(SUBSTITUTE(CLEAN(LEFT(F9,FIND("-",F9)-1))," ",""),"") -> Z2219 | H9: {=IFERROR(_xlfn.IFS(AND(W9="已结算",AW9>30),AB9,LEFT(W9,5)="结算后退款",-AB9,LEFT(W9,5)="保证金退款",0),0)} -> 1 | I9: =AV9-K9 -> 239 | J9: =SUM(AM9:AU9) -> 0 | K9: =AI9 -> 0 | L9: =AX9 -> -11.95 | M9: =SUM(AY9:BD9) -> 0 | O9: =SUM(I9:N9) -> 227.05 | R9: 45886.738 | S9: '6944916130719602370 | T9: '6944916130719602370 | U9: 227.05 | V9: 聚合账户 | W9: 已结算 | X9: 否 | Y9: 45872.874 | Z9: '3766942655402082491 | AA9: 【老板周】随性松弛 夏季自在松紧腰舒适肌理感绿豆沙阔腿裤 | AB9: 1 | AE9: 小店自卖 | AF9: 普通订单 | AG9: 239 | AH9: 239 | AI9: 0 | AJ9: 0 | AK9: 0 | AL9: 0 | AM9: 0 | AN9: 0 | AO9: 0 | AP9: 0 | AQ9: 0 | AR9: 0 | AS9: 0 | AT9: 0 | AU9: 0 | AV9: 239 | AW9: 239 | AX9: -11.95 | AY9: 0 | AZ9: 0 | BA9: 0 | BB9: 0 | BC9: 0 | BD9: 0 | BF9: -11.95 | BG9: 否 | BH9: 0 | BI9: 广州欣煌服饰有限公司
A10: =YEAR(R10) -> 2025 | B10: =MONTH(R10) -> 8 | C10: =S10 -> '6920680044383403322 | F10: {=IFERROR(INDEX('抖音订单-按支付日期-ABF列，要先手动清除空格'!G:G,MATCH(RIGHT(S10,LEN(S10)-1)&RIGHT(T10,LEN(T10)-1)&RIGHT(Z10,LEN(Z10)-1),'抖音订单-按支付日期-ABF列，要先手动清除空格'!A:A&'抖音订单-按支付日期-ABF列，要先手动清除空格'!B:B&'抖音订单-按支付日期-ABF列，要先手动清除空格'!F:F,0)),0)} -> Z1913-黑色-M | G10: =IFERROR(SUBSTITUTE(CLEAN(LEFT(F10,FIND("-",F10)-1))," ",""),"") -> Z1913 | H10: {=IFERROR(_xlfn.IFS(AND(W10="已结算",AW10>30),AB10,LEFT(W10,5)="结算后退款",-AB10,LEFT(W10,5)="保证金退款",0),0)} -> 1 | I10: =AV10-K10 -> 299 | J10: =SUM(AM10:AU10) -> 0 | K10: =AI10 -> 0 | L10: =AX10 -> -14.95 | M10: =SUM(AY10:BD10) -> 0 | O10: =SUM(I10:N10) -> 284.05 | R10: 45886.749 | S10: '6920680044383403322 | T10: '6920680044383403322 | U10: 284.05 | V10: 聚合账户 | W10: 已结算 | X10: 否 | Y10: 45879.979 | Z10: '3766958469287117220 | AA10: 【老板周】休闲立裁 夏季时髦肌理感挺括百搭九分裤 | AB10: 1 | AE10: 小店自卖 | AF10: 普通订单 | AG10: 299 | AH10: 299 | AI10: 0 | AJ10: 0 | AK10: 0 | AL10: 0 | AM10: 0 | AN10: 0 | AO10: 0 | AP10: 0 | AQ10: 0 | AR10: 0 | AS10: 0 | AT10: 0 | AU10: 0 | AV10: 299 | AW10: 299 | AX10: -14.95 | AY10: 0 | AZ10: 0 | BA10: 0 | BB10: 0 | BC10: 0 | BD10: 0 | BF10: -14.95 | BG10: 否 | BH10: 0 | BI10: 广州欣煌服饰有限公司
A11: =YEAR(R11) -> 2025 | B11: =MONTH(R11) -> 8 | C11: =S11 -> '6944918576931608501 | F11: {=IFERROR(INDEX('抖音订单-按支付日期-ABF列，要先手动清除空格'!G:G,MATCH(RIGHT(S11,LEN(S11)-1)&RIGHT(T11,LEN(T11)-1)&RIGHT(Z11,LEN(Z11)-1),'抖音订单-按支付日期-ABF列，要先手动清除空格'!A:A&'抖音订单-按支付日期-ABF列，要先手动清除空格'!B:B&'抖音订单-按支付日期-ABF列，要先手动清除空格'!F:F,0)),0)} -> Z2183-米白色-L | G11: =IFERROR(SUBSTITUTE(CLEAN(LEFT(F11,FIND("-",F11)-1))," ",""),"") -> Z2183 | H11: {=IFERROR(_xlfn.IFS(AND(W11="已结算",AW11>30),AB11,LEFT(W11,5)="结算后退款",-AB11,LEFT(W11,5)="保证金退款",0),0)} -> 1 | I11: =AV11-K11 -> 129 | J11: =SUM(AM11:AU11) -> 0 | K11: =AI11 -> 0 | L11: =AX11 -> -6.45 | M11: =SUM(AY11:BD11) -> 0 | O11: =SUM(I11:N11) -> 122.55 | R11: 45887.475 | S11: '6944918576931608501 | T11: '6944918576931608501 | U11: 122.55 | V11: 聚合账户 | W11: 已结算 | X11: 否 | Y11: 45872.913 | Z11: '3766942533029069048 | AA11: 【老板周】夏季轻盈 新品圆领气质轻薄不规则透气上衣 | AB11: 1 | AC11: '2353393836764088 | AD11: 老板周 | AE11: 精选联盟 | AF11: 普通订单 | AG11: 129 | AH11: 129 | AI11: 0 | AJ11: 0 | AK11: 0 | AL11: 0 | AM11: 0 | AN11: 0 | AO11: 0 | AP11: 0 | AQ11: 0 | AR11: 0 | AS11: 0 | AT11: 0 | AU11: 0 | AV11: 129 | AW11: 129 | AX11: -6.45 | AY11: 0 | AZ11: 0 | BA11: 0 | BB11: 0 | BC11: 0 | BD11: 0 | BF11: -6.45 | BH11: 0 | BI11: 广州欣煌服饰有限公司
A12: =YEAR(R12) -> 2025 | B12: =MONTH(R12) -> 8 | C12: =S12 -> '6944902956203382263 | F12: {=IFERROR(INDEX('抖音订单-按支付日期-ABF列，要先手动清除空格'!G:G,MATCH(RIGHT(S12,LEN(S12)-1)&RIGHT(T12,LEN(T12)-1)&RIGHT(Z12,LEN(Z12)-1),'抖音订单-按支付日期-ABF列，要先手动清除空格'!A:A&'抖音订单-按支付日期-ABF列，要先手动清除空格'!B:B&'抖音订单-按支付日期-ABF列，要先手动清除空格'!F:F,0)),0)} -> Z1640-黑色-L | G12: =IFERROR(SUBSTITUTE(CLEAN(LEFT(F12,FIND("-",F12)-1))," ",""),"") -> Z1640 | H12: {=IFERROR(_xlfn.IFS(AND(W12="已结算",AW12>30),AB12,LEFT(W12,5)="结算后退款",-AB12,LEFT(W12,5)="保证金退款",0),0)} -> 1 | I12: =AV12-K12 -> 289 | J12: =SUM(AM12:AU12) -> 0 | K12: =AI12 -> 0 | L12: =AX12 -> -14.45 | M12: =SUM(AY12:BD12) -> 0 | O12: =SUM(I12:N12) -> 274.55 | R12: 45887.475 | S12: '6944902956203382263 | T12: '6944902956203382263 | U12: 274.55 | V12: 聚合账户 | W12: 已结算 | X12: 否 | Y12: 45872.661 | Z12: '3767004410471907465 | AA12: 【老板周】日系极简 春季新品圆领简约设计感无袖马甲 | AB12: 1 | AC12: '2353393836764088 | AD12: 老板周 | AE12: 精选联盟 | AF12: 普通订单 | AG12: 289 | AH12: 289 | AI12: 0 | AJ12: 0 | AK12: 0 | AL12: 0 | AM12: 0 | AN12: 0 | AO12: 0 | AP12: 0 | AQ12: 0 | AR12: 0 | AS12: 0 | AT12: 0 | AU12: 0 | AV12: 289 | AW12: 289 | AX12: -14.45 | AY12: 0 | AZ12: 0 | BA12: 0 | BB12: 0 | BC12: 0 | BD12: 0 | BF12: -14.45 | BH12: 0 | BI12: 广州欣煌服饰有限公司
A13: =YEAR(R13) -> 2025 | B13: =MONTH(R13) -> 8 | C13: =S13 -> '6944898532312946567 | F13: {=IFERROR(INDEX('抖音订单-按支付日期-ABF列，要先手动清除空格'!G:G,MATCH(RIGHT(S13,LEN(S13)-1)&RIGHT(T13,LEN(T13)-1)&RIGHT(Z13,LEN(Z13)-1),'抖音订单-按支付日期-ABF列，要先手动清除空格'!A:A&'抖音订单-按支付日期-ABF列，要先手动清除空格'!B:B&'抖音订单-按支付日期-ABF列，要先手动清除空格'!F:F,0)),0)} -> Z1640-黑色-M | G13: =IFERROR(SUBSTITUTE(CLEAN(LEFT(F13,FIND("-",F13)-1))," ",""),"") -> Z1640 | H13: {=IFERROR(_xlfn.IFS(AND(W13="已结算",AW13>30),AB13,LEFT(W13,5)="结算后退款",-AB13,LEFT(W13,5)="保证金退款",0),0)} -> 1 | I13: =AV13-K13 -> 289 | J13: =SUM(AM13:AU13) -> 0 | K13: =AI13 -> 0 | L13: =AX13 -> -14.45 | M13: =SUM(AY13:BD13) -> 0 | O13: =SUM(I13:N13) -> 274.55 | R13: 45889.174 | S13: '6944898532312946567 | T13: '6944898532312946567 | U13: 274.55 | V13: 聚合账户 | W13: 已结算 | X13: 否 | Y13: 45872.661 | Z13: '3767004410471907465 | AA13: 【老板周】日系极简 春季新品圆领简约设计感无袖马甲 | AB13: 1 | AC13: '2353393836764088 | AD13: 老板周 | AE13: 精选联盟 | AF13: 普通订单 | AG13: 289 | AH13: 289 | AI13: 0 | AJ13: 0 | AK13: 0 | AL13: 0 | AM13: 0 | AN13: 0 | AO13: 0 | AP13: 0 | AQ13: 0 | AR13: 0 | AS13: 0 | AT13: 0 | AU13: 0 | AV13: 289 | AW13: 289 | AX13: -14.45 | AY13: 0 | AZ13: 0 | BA13: 0 | BB13: 0 | BC13: 0 | BD13: 0 | BF13: -14.45 | BH13: 0 | BI13: 广州欣煌服饰有限公司
A14: =YEAR(R14) -> 2025 | B14: =MONTH(R14) -> 8 | C14: =S14 -> '6944889464345662958 | F14: {=IFERROR(INDEX('抖音订单-按支付日期-ABF列，要先手动清除空格'!G:G,MATCH(RIGHT(S14,LEN(S14)-1)&RIGHT(T14,LEN(T14)-1)&RIGHT(Z14,LEN(Z14)-1),'抖音订单-按支付日期-ABF列，要先手动清除空格'!A:A&'抖音订单-按支付日期-ABF列，要先手动清除空格'!B:B&'抖音订单-按支付日期-ABF列，要先手动清除空格'!F:F,0)),0)} -> Z1640-黑色-M | G14: =IFERROR(SUBSTITUTE(CLEAN(LEFT(F14,FIND("-",F14)-1))," ",""),"") -> Z1640 | H14: {=IFERROR(_xlfn.IFS(AND(W14="已结算",AW14>30),AB14,LEFT(W14,5)="结算后退款",-AB14,LEFT(W14,5)="保证金退款",0),0)} -> 1 | I14: =AV14-K14 -> 289 | J14: =SUM(AM14:AU14) -> 0 | K14: =AI14 -> 0 | L14: =AX14 -> -14.45 | M14: =SUM(AY14:BD14) -> 0 | O14: =SUM(I14:N14) -> 274.55 | R14: 45889.508 | S14: '6944889464345662958 | T14: '6944889464345662958 | U14: 274.55 | V14: 聚合账户 | W14: 已结算 | X14: 否 | Y14: 45872.662 | Z14: '3767004410471907465 | AA14: 【老板周】日系极简 春季新品圆领简约设计感无袖马甲 | AB14: 1 | AC14: '2353393836764088 | AD14: 老板周 | AE14: 精选联盟 | AF14: 普通订单 | AG14: 289 | AH14: 289 | AI14: 0 | AJ14: 0 | AK14: 0 | AL14: 0 | AM14: 0 | AN14: 0 | AO14: 0 | AP14: 0 | AQ14: 0 | AR14: 0 | AS14: 0 | AT14: 0 | AU14: 0 | AV14: 289 | AW14: 289 | AX14: -14.45 | AY14: 0 | AZ14: 0 | BA14: 0 | BB14: 0 | BC14: 0 | BD14: 0 | BF14: -14.45 | BH14: 0 | BI14: 广州欣煌服饰有限公司
A15: =YEAR(R15) -> 2025 | B15: =MONTH(R15) -> 8 | C15: =S15 -> '6920588758294560314 | F15: {=IFERROR(INDEX('抖音订单-按支付日期-ABF列，要先手动清除空格'!G:G,MATCH(RIGHT(S15,LEN(S15)-1)&RIGHT(T15,LEN(T15)-1)&RIGHT(Z15,LEN(Z15)-1),'抖音订单-按支付日期-ABF列，要先手动清除空格'!A:A&'抖音订单-按支付日期-ABF列，要先手动清除空格'!B:B&'抖音订单-按支付日期-ABF列，要先手动清除空格'!F:F,0)),0)} -> Z1640-黑色-L | G15: =IFERROR(SUBSTITUTE(CLEAN(LEFT(F15,FIND("-",F15)-1))," ",""),"") -> Z1640 | H15: {=IFERROR(_xlfn.IFS(AND(W15="已结算",AW15>30),AB15,LEFT(W15,5)="结算后退款",-AB15,LEFT(W15,5)="保证金退款",0),0)} -> 1 | I15: =AV15-K15 -> 289 | J15: =SUM(AM15:AU15) -> 0 | K15: =AI15 -> 0 | L15: =AX15 -> -14.45 | M15: =SUM(AY15:BD15) -> 0 | O15: =SUM(I15:N15) -> 274.55 | R15: 45889.508 | S15: '6920588758294560314 | T15: '6920588758294560314 | U15: 274.55 | V15: 聚合账户 | W15: 已结算 | X15: 否 | Y15: 45872.661 | Z15: '3767004410471907465 | AA15: 【老板周】日系极简 春季新品圆领简约设计感无袖马甲 | AB15: 1 | AC15: '2353393836764088 | AD15: 老板周 | AE15: 精选联盟 | AF15: 普通订单 | AG15: 289 | AH15: 289 | AI15: 0 | AJ15: 0 | AK15: 0 | AL15: 0 | AM15: 0 | AN15: 0 | AO15: 0 | AP15: 0 | AQ15: 0 | AR15: 0 | AS15: 0 | AT15: 0 | AU15: 0 | AV15: 289 | AW15: 289 | AX15: -14.45 | AY15: 0 | AZ15: 0 | BA15: 0 | BB15: 0 | BC15: 0 | BD15: 0 | BF15: -14.45 | BH15: 0 | BI15: 广州欣煌服饰有限公司
A16: =YEAR(R16) -> 2025 | B16: =MONTH(R16) -> 8 | C16: =S16 -> '6944900882349627297 | F16: {=IFERROR(INDEX('抖音订单-按支付日期-ABF列，要先手动清除空格'!G:G,MATCH(RIGHT(S16,LEN(S16)-1)&RIGHT(T16,LEN(T16)-1)&RIGHT(Z16,LEN(Z16)-1),'抖音订单-按支付日期-ABF列，要先手动清除空格'!A:A&'抖音订单-按支付日期-ABF列，要先手动清除空格'!B:B&'抖音订单-按支付日期-ABF列，要先手动清除空格'!F:F,0)),0)} -> Z1640-黑色-L | G16: =IFERROR(SUBSTITUTE(CLEAN(LEFT(F16,FIND("-",F16)-1))," ",""),"") -> Z1640 | H16: {=IFERROR(_xlfn.IFS(AND(W16="已结算",AW16>30),AB16,LEFT(W16,5)="结算后退款",-AB16,LEFT(W16,5)="保证金退款",0),0)} -> 1 | I16: =AV16-K16 -> 289 | J16: =SUM(AM16:AU16) -> 0 | K16: =AI16 -> 0 | L16: =AX16 -> -14.45 | M16: =SUM(AY16:BD16) -> 0 | O16: =SUM(I16:N16) -> 274.55 | R16: 45889.534 | S16: '6944900882349627297 | T16: '6944900882349627297 | U16: 274.55 | V16: 聚合账户 | W16: 已结算 | X16: 否 | Y16: 45872.661 | Z16: '3767004410471907465 | AA16: 【老板周】日系极简 春季新品圆领简约设计感无袖马甲 | AB16: 1 | AC16: '2353393836764088 | AD16: 老板周 | AE16: 精选联盟 | AF16: 普通订单 | AG16: 289 | AH16: 289 | AI16: 0 | AJ16: 0 | AK16: 0 | AL16: 0 | AM16: 0 | AN16: 0 | AO16: 0 | AP16: 0 | AQ16: 0 | AR16: 0 | AS16: 0 | AT16: 0 | AU16: 0 | AV16: 289 | AW16: 289 | AX16: -14.45 | AY16: 0 | AZ16: 0 | BA16: 0 | BB16: 0 | BC16: 0 | BD16: 0 | BF16: -14.45 | BH16: 0 | BI16: 广州欣煌服饰有限公司
A17: =YEAR(R17) -> 2025 | B17: =MONTH(R17) -> 8 | C17: =S17 -> '6920588768434027755 | F17: {=IFERROR(INDEX('抖音订单-按支付日期-ABF列，要先手动清除空格'!G:G,MATCH(RIGHT(S17,LEN(S17)-1)&RIGHT(T17,LEN(T17)-1)&RIGHT(Z17,LEN(Z17)-1),'抖音订单-按支付日期-ABF列，要先手动清除空格'!A:A&'抖音订单-按支付日期-ABF列，要先手动清除空格'!B:B&'抖音订单-按支付日期-ABF列，要先手动清除空格'!F:F,0)),0)} -> Z1640-黑色-M | G17: =IFERROR(SUBSTITUTE(CLEAN(LEFT(F17,FIND("-",F17)-1))," ",""),"") -> Z1640 | H17: {=IFERROR(_xlfn.IFS(AND(W17="已结算",AW17>30),AB17,LEFT(W17,5)="结算后退款",-AB17,LEFT(W17,5)="保证金退款",0),0)} -> 1 | I17: =AV17-K17 -> 289 | J17: =SUM(AM17:AU17) -> 0 | K17: =AI17 -> 0 | L17: =AX17 -> -14.45 | M17: =SUM(AY17:BD17) -> 0 | O17: =SUM(I17:N17) -> 274.55 | R17: 45889.567 | S17: '6920588768434027755 | T17: '6920588768434027755 | U17: 274.55 | V17: 聚合账户 | W17: 已结算 | X17: 否 | Y17: 45872.661 | Z17: '3767004410471907465 | AA17: 【老板周】日系极简 春季新品圆领简约设计感无袖马甲 | AB17: 1 | AC17: '2353393836764088 | AD17: 老板周 | AE17: 精选联盟 | AF17: 普通订单 | AG17: 289 | AH17: 289 | AI17: 0 | AJ17: 0 | AK17: 0 | AL17: 0 | AM17: 0 | AN17: 0 | AO17: 0 | AP17: 0 | AQ17: 0 | AR17: 0 | AS17: 0 | AT17: 0 | AU17: 0 | AV17: 289 | AW17: 289 | AX17: -14.45 | AY17: 0 | AZ17: 0 | BA17: 0 | BB17: 0 | BC17: 0 | BD17: 0 | BF17: -14.45 | BH17: 0 | BI17: 广州欣煌服饰有限公司
A18: =YEAR(R18) -> 2025 | B18: =MONTH(R18) -> 8 | C18: =S18 -> '6920591103095635580 | F18: {=IFERROR(INDEX('抖音订单-按支付日期-ABF列，要先手动清除空格'!G:G,MATCH(RIGHT(S18,LEN(S18)-1)&RIGHT(T18,LEN(T18)-1)&RIGHT(Z18,LEN(Z18)-1),'抖音订单-按支付日期-ABF列，要先手动清除空格'!A:A&'抖音订单-按支付日期-ABF列，要先手动清除空格'!B:B&'抖音订单-按支付日期-ABF列，要先手动清除空格'!F:F,0)),0)} -> Z1640-黑色-S | G18: =IFERROR(SUBSTITUTE(CLEAN(LEFT(F18,FIND("-",F18)-1))," ",""),"") -> Z1640 | H18: {=IFERROR(_xlfn.IFS(AND(W18="已结算",AW18>30),AB18,LEFT(W18,5)="结算后退款",-AB18,LEFT(W18,5)="保证金退款",0),0)} -> 1 | I18: =AV18-K18 -> 289 | J18: =SUM(AM18:AU18) -> 0 | K18: =AI18 -> 0 | L18: =AX18 -> -14.45 | M18: =SUM(AY18:BD18) -> 0 | O18: =SUM(I18:N18) -> 274.55 | R18: 45889.588 | S18: '6920591103095635580 | T18: '6920591103095635580 | U18: 274.55 | V18: 聚合账户 | W18: 已结算 | X18: 否 | Y18: 45872.661 | Z18: '3767004410471907465 | AA18: 【老板周】日系极简 春季新品圆领简约设计感无袖马甲 | AB18: 1 | AC18: '2353393836764088 | AD18: 老板周 | AE18: 精选联盟 | AF18: 普通订单 | AG18: 289 | AH18: 289 | AI18: 0 | AJ18: 0 | AK18: 0 | AL18: 0 | AM18: 0 | AN18: 0 | AO18: 0 | AP18: 0 | AQ18: 0 | AR18: 0 | AS18: 0 | AT18: 0 | AU18: 0 | AV18: 289 | AW18: 289 | AX18: -14.45 | AY18: 0 | AZ18: 0 | BA18: 0 | BB18: 0 | BC18: 0 | BD18: 0 | BF18: -14.45 | BH18: 0 | BI18: 广州欣煌服饰有限公司
A19: =YEAR(R19) -> 2025 | B19: =MONTH(R19) -> 8 | C19: =S19 -> '6944894013550499428 | F19: {=IFERROR(INDEX('抖音订单-按支付日期-ABF列，要先手动清除空格'!G:G,MATCH(RIGHT(S19,LEN(S19)-1)&RIGHT(T19,LEN(T19)-1)&RIGHT(Z19,LEN(Z19)-1),'抖音订单-按支付日期-ABF列，要先手动清除空格'!A:A&'抖音订单-按支付日期-ABF列，要先手动清除空格'!B:B&'抖音订单-按支付日期-ABF列，要先手动清除空格'!F:F,0)),0)} -> Z1640-黑色-M | G19: =IFERROR(SUBSTITUTE(CLEAN(LEFT(F19,FIND("-",F19)-1))," ",""),"") -> Z1640 | H19: {=IFERROR(_xlfn.IFS(AND(W19="已结算",AW19>30),AB19,LEFT(W19,5)="结算后退款",-AB19,LEFT(W19,5)="保证金退款",0),0)} -> 1 | I19: =AV19-K19 -> 289 | J19: =SUM(AM19:AU19) -> 0 | K19: =AI19 -> 0 | L19: =AX19 -> -14.45 | M19: =SUM(AY19:BD19) -> 0 | O19: =SUM(I19:N19) -> 274.55 | R19: 45889.588 | S19: '6944894013550499428 | T19: '6944894013550499428 | U19: 274.55 | V19: 聚合账户 | W19: 已结算 | X19: 否 | Y19: 45872.661 | Z19: '3767004410471907465 | AA19: 【老板周】日系极简 春季新品圆领简约设计感无袖马甲 | AB19: 1 | AC19: '2353393836764088 | AD19: 老板周 | AE19: 精选联盟 | AF19: 普通订单 | AG19: 289 | AH19: 289 | AI19: 0 | AJ19: 0 | AK19: 0 | AL19: 0 | AM19: 0 | AN19: 0 | AO19: 0 | AP19: 0 | AQ19: 0 | AR19: 0 | AS19: 0 | AT19: 0 | AU19: 0 | AV19: 289 | AW19: 289 | AX19: -14.45 | AY19: 0 | AZ19: 0 | BA19: 0 | BB19: 0 | BC19: 0 | BD19: 0 | BF19: -14.45 | BH19: 0 | BI19: 广州欣煌服饰有限公司
A20: =YEAR(R20) -> 2025 | B20: =MONTH(R20) -> 8 | C20: =S20 -> '6944889432733980469 | F20: {=IFERROR(INDEX('抖音订单-按支付日期-ABF列，要先手动清除空格'!G:G,MATCH(RIGHT(S20,LEN(S20)-1)&RIGHT(T20,LEN(T20)-1)&RIGHT(Z20,LEN(Z20)-1),'抖音订单-按支付日期-ABF列，要先手动清除空格'!A:A&'抖音订单-按支付日期-ABF列，要先手动清除空格'!B:B&'抖音订单-按支付日期-ABF列，要先手动清除空格'!F:F,0)),0)} -> Z1640-黑色-S | G20: =IFERROR(SUBSTITUTE(CLEAN(LEFT(F20,FIND("-",F20)-1))," ",""),"") -> Z1640 | H20: {=IFERROR(_xlfn.IFS(AND(W20="已结算",AW20>30),AB20,LEFT(W20,5)="结算后退款",-AB20,LEFT(W20,5)="保证金退款",0),0)} -> 1 | I20: =AV20-K20 -> 289 | J20: =SUM(AM20:AU20) -> 0 | K20: =AI20 -> 0 | L20: =AX20 -> -14.45 | M20: =SUM(AY20:BD20) -> 0 | O20: =SUM(I20:N20) -> 274.55 | R20: 45889.588 | S20: '6944889432733980469 | T20: '6944889432733980469 | U20: 274.55 | V20: 聚合账户 | W20: 已结算 | X20: 否 | Y20: 45872.662 | Z20: '3767004410471907465 | AA20: 【老板周】日系极简 春季新品圆领简约设计感无袖马甲 | AB20: 1 | AC20: '2353393836764088 | AD20: 老板周 | AE20: 精选联盟 | AF20: 普通订单 | AG20: 289 | AH20: 289 | AI20: 0 | AJ20: 0 | AK20: 0 | AL20: 0 | AM20: 0 | AN20: 0 | AO20: 0 | AP20: 0 | AQ20: 0 | AR20: 0 | AS20: 0 | AT20: 0 | AU20: 0 | AV20: 289 | AW20: 289 | AX20: -14.45 | AY20: 0 | AZ20: 0 | BA20: 0 | BB20: 0 | BC20: 0 | BD20: 0 | BF20: -14.45 | BH20: 0 | BI20: 广州欣煌服饰有限公司
A21: =YEAR(R21) -> 2025 | B21: =MONTH(R21) -> 8 | C21: =S21 -> '6920595763321732711 | F21: {=IFERROR(INDEX('抖音订单-按支付日期-ABF列，要先手动清除空格'!G:G,MATCH(RIGHT(S21,LEN(S21)-1)&RIGHT(T21,LEN(T21)-1)&RIGHT(Z21,LEN(Z21)-1),'抖音订单-按支付日期-ABF列，要先手动清除空格'!A:A&'抖音订单-按支付日期-ABF列，要先手动清除空格'!B:B&'抖音订单-按支付日期-ABF列，要先手动清除空格'!F:F,0)),0)} -> Z1640-黑色-L | G21: =IFERROR(SUBSTITUTE(CLEAN(LEFT(F21,FIND("-",F21)-1))," ",""),"") -> Z1640 | H21: {=IFERROR(_xlfn.IFS(AND(W21="已结算",AW21>30),AB21,LEFT(W21,5)="结算后退款",-AB21,LEFT(W21,5)="保证金退款",0),0)} -> 1 | I21: =AV21-K21 -> 289 | J21: =SUM(AM21:AU21) -> 0 | K21: =AI21 -> 0 | L21: =AX21 -> -14.45 | M21: =SUM(AY21:BD21) -> 0 | O21: =SUM(I21:N21) -> 274.55 | R21: 45889.696 | S21: '6920595763321732711 | T21: '6920595763321732711 | U21: 274.55 | V21: 聚合账户 | W21: 已结算 | X21: 否 | Y21: 45872.662 | Z21: '3767004410471907465 | AA21: 【老板周】日系极简 春季新品圆领简约设计感无袖马甲 | AB21: 1 | AC21: '2353393836764088 | AD21: 老板周 | AE21: 精选联盟 | AF21: 普通订单 | AG21: 289 | AH21: 289 | AI21: 0 | AJ21: 0 | AK21: 0 | AL21: 0 | AM21: 0 | AN21: 0 | AO21: 0 | AP21: 0 | AQ21: 0 | AR21: 0 | AS21: 0 | AT21: 0 | AU21: 0 | AV21: 289 | AW21: 289 | AX21: -14.45 | AY21: 0 | AZ21: 0 | BA21: 0 | BB21: 0 | BC21: 0 | BD21: 0 | BF21: -14.45 | BH21: 0 | BI21: 广州欣煌服饰有限公司
A22: =YEAR(R22) -> 2025 | B22: =MONTH(R22) -> 8 | C22: =S22 -> '6944909565032862834 | F22: {=IFERROR(INDEX('抖音订单-按支付日期-ABF列，要先手动清除空格'!G:G,MATCH(RIGHT(S22,LEN(S22)-1)&RIGHT(T22,LEN(T22)-1)&RIGHT(Z22,LEN(Z22)-1),'抖音订单-按支付日期-ABF列，要先手动清除空格'!A:A&'抖音订单-按支付日期-ABF列，要先手动清除空格'!B:B&'抖音订单-按支付日期-ABF列，要先手动清除空格'!F:F,0)),0)} -> Z1640-黑色-M | G22: =IFERROR(SUBSTITUTE(CLEAN(LEFT(F22,FIND("-",F22)-1))," ",""),"") -> Z1640 | H22: {=IFERROR(_xlfn.IFS(AND(W22="已结算",AW22>30),AB22,LEFT(W22,5)="结算后退款",-AB22,LEFT(W22,5)="保证金退款",0),0)} -> 1 | I22: =AV22-K22 -> 289 | J22: =SUM(AM22:AU22) -> 0 | K22: =AI22 -> 0 | L22: =AX22 -> -14.45 | M22: =SUM(AY22:BD22) -> 0 | O22: =SUM(I22:N22) -> 274.55 | R22: 45889.711 | S22: '6944909565032862834 | T22: '6944909565032862834 | U22: 274.55 | V22: 聚合账户 | W22: 已结算 | X22: 否 | Y22: 45872.661 | Z22: '3767004410471907465 | AA22: 【老板周】日系极简 春季新品圆领简约设计感无袖马甲 | AB22: 1 | AC22: '2353393836764088 | AD22: 老板周 | AE22: 精选联盟 | AF22: 普通订单 | AG22: 289 | AH22: 289 | AI22: 0 | AJ22: 0 | AK22: 0 | AL22: 0 | AM22: 0 | AN22: 0 | AO22: 0 | AP22: 0 | AQ22: 0 | AR22: 0 | AS22: 0 | AT22: 0 | AU22: 0 | AV22: 289 | AW22: 289 | AX22: -14.45 | AY22: 0 | AZ22: 0 | BA22: 0 | BB22: 0 | BC22: 0 | BD22: 0 | BF22: -14.45 | BH22: 0 | BI22: 广州欣煌服饰有限公司
... A33: =YEAR(R33) -> 2025 | B33: =MONTH(R33) -> 8 | C33: =S33 -> '6945119329413174815 | F33: {=IFERROR(INDEX('抖音订单-按支付日期-ABF列，要先手动清除空格'!G:G,MATCH(RIGHT(S33,LEN(S33)-1)&RIGHT(T33,LEN(T33)-1)&RIGHT(Z33,LEN(Z33)-1),'抖音订单-按支付日期-ABF列，要先手动清除空格'!A:A&'抖音订单-按支付日期-ABF列，要先手动清除空格'!B:B&'抖音订单-按支付日期-ABF列，要先手动清除空格'!F:F,0)),0)} -> Z476-灰色-L | G33: =IFERROR(SUBSTITUTE(CLEAN(LEFT(F33,FIND("-",F33)-1))," ",""),"") -> Z476 | H33: {=IFERROR(_xlfn.IFS(AND(W33="已结算",AW33>30),AB33,LEFT(W33,5)="结算后退款",-AB33,LEFT(W33,5)="保证金退款",0),0)} -> 1 | I33: =AV33-K33 -> 180 | J33: =SUM(AM33:AU33) -> 0 | K33: =AI33 -> 0 | L33: =AX33 -> -9 | M33: =SUM(AY33:BD33) -> 0 | O33: =SUM(I33:N33) -> 171 | R33: 45892.354 | S33: '6945119329413174815 | T33: '6945119329413174815 | U33: 171 | V33: 聚合账户 | W33: 已结算 | X33: 否 | Y33: 45879.771 | Z33: '3766240353087259102 | AA33: 【老板周】春夏经典时髦 简约基础款拉长比例短上衣 | AB33: 1 | AC33: '2353393836764088 | AD33: 老板周 | AE33: 精选联盟 | AF33: 普通订单 | AG33: 180 | AH33: 180 | AI33: 0 | AJ33: 0 | AK33: 0 | AL33: 0 | AM33: 0 | AN33: 0 | AO33: 0 | AP33: 0 | AQ33: 0 | AR33: 0 | AS33: 0 | AT33: 0 | AU33: 0 | AV33: 180 | AW33: 180 | AX33: -9 | AY33: 0 | AZ33: 0 | BA33: 0 | BB33: 0 | BC33: 0 | BD33: 0 | BF33: -9 | BH33: 0 | BI33: 广州欣煌服饰有限公司
A34: =YEAR(R34) -> 2025 | B34: =MONTH(R34) -> 8 | C34: =S34 -> '6920600395440946785 | F34: {=IFERROR(INDEX('抖音订单-按支付日期-ABF列，要先手动清除空格'!G:G,MATCH(RIGHT(S34,LEN(S34)-1)&RIGHT(T34,LEN(T34)-1)&RIGHT(Z34,LEN(Z34)-1),'抖音订单-按支付日期-ABF列，要先手动清除空格'!A:A&'抖音订单-按支付日期-ABF列，要先手动清除空格'!B:B&'抖音订单-按支付日期-ABF列，要先手动清除空格'!F:F,0)),0)} -> Z2256-粉色-XL | G34: =IFERROR(SUBSTITUTE(CLEAN(LEFT(F34,FIND("-",F34)-1))," ",""),"") -> Z2256 | H34: {=IFERROR(_xlfn.IFS(AND(W34="已结算",AW34>30),AB34,LEFT(W34,5)="结算后退款",-AB34,LEFT(W34,5)="保证金退款",0),0)} -> 1 | I34: =AV34-K34 -> 299 | J34: =SUM(AM34:AU34) -> 0 | K34: =AI34 -> 0 | L34: =AX34 -> -14.95 | M34: =SUM(AY34:BD34) -> 0 | O34: =SUM(I34:N34) -> 284.05 | R34: 45892.544 | S34: '6920600395440946785 | T34: '6920600395441012321 | U34: 284.05 | V34: 聚合账户 | W34: 已结算 | X34: 否 | Y34: 45873.513 | Z34: '3766943280328212883 | AA34: 【老板周】法式气质 夏季新款重工斜裁开衩松紧腰半裙 | AB34: 1 | AE34: 小店自卖 | AF34: 普通订单 | AG34: 299 | AH34: 299 | AI34: 0 | AJ34: 0 | AK34: 0 | AL34: 0 | AM34: 0 | AN34: 0 | AO34: 0 | AP34: 0 | AQ34: 0 | AR34: 0 | AS34: 0 | AT34: 0 | AU34: 0 | AV34: 299 | AW34: 299 | AX34: -14.95 | AY34: 0 | AZ34: 0 | BA34: 0 | BB34: 0 | BC34: 0 | BD34: 0 | BF34: -14.95 | BG34: 否 | BH34: 0 | BI34: 广州欣煌服饰有限公司
A35: =YEAR(R35) -> 2025 | B35: =MONTH(R35) -> 8 | C35: =S35 -> '6920600395440946785 | F35: {=IFERROR(INDEX('抖音订单-按支付日期-ABF列，要先手动清除空格'!G:G,MATCH(RIGHT(S35,LEN(S35)-1)&RIGHT(T35,LEN(T35)-1)&RIGHT(Z35,LEN(Z35)-1),'抖音订单-按支付日期-ABF列，要先手动清除空格'!A:A&'抖音订单-按支付日期-ABF列，要先手动清除空格'!B:B&'抖音订单-按支付日期-ABF列，要先手动清除空格'!F:F,0)),0)} -> Z2183-米白色-XL | G35: =IFERROR(SUBSTITUTE(CLEAN(LEFT(F35,FIND("-",F35)-1))," ",""),"") -> Z2183 | H35: {=IFERROR(_xlfn.IFS(AND(W35="已结算",AW35>30),AB35,LEFT(W35,5)="结算后退款",-AB35,LEFT(W35,5)="保证金退款",0),0)} -> 1 | I35: =AV35-K35 -> 129 | J35: =SUM(AM35:AU35) -> 0 | K35: =AI35 -> 0 | L35: =AX35 -> -6.45 | M35: =SUM(AY35:BD35) -> 0 | O35: =SUM(I35:N35) -> 122.55 | R35: 45892.642 | S35: '6920600395440946785 | T35: '6920600395440946785 | U35: 122.55 | V35: 聚合账户 | W35: 已结算 | X35: 否 | Y35: 45873.513 | Z35: '3766942533029069048 | AA35: 【老板周】夏季轻盈 新品圆领气质轻薄不规则透气上衣 | AB35: 1 | AC35: '2353393836764088 | AD35: 老板周 | AE35: 精选联盟 | AF35: 普通订单 | AG35: 129 | AH35: 129 | AI35: 0 | AJ35: 0 | AK35: 0 | AL35: 0 | AM35: 0 | AN35: 0 | AO35: 0 | AP35: 0 | AQ35: 0 | AR35: 0 | AS35: 0 | AT35: 0 | AU35: 0 | AV35: 129 | AW35: 129 | AX35: -6.45 | AY35: 0 | AZ35: 0 | BA35: 0 | BB35: 0 | BC35: 0 | BD35: 0 | BF35: -6.45 | BG35: 否 | BH35: 0 | BI35: 广州欣煌服饰有限公司
A36: =YEAR(R36) -> 2025 | B36: =MONTH(R36) -> 8 | C36: =S36 -> '6944950932732318859 | F36: {=IFERROR(INDEX('抖音订单-按支付日期-ABF列，要先手动清除空格'!G:G,MATCH(RIGHT(S36,LEN(S36)-1)&RIGHT(T36,LEN(T36)-1)&RIGHT(Z36,LEN(Z36)-1),'抖音订单-按支付日期-ABF列，要先手动清除空格'!A:A&'抖音订单-按支付日期-ABF列，要先手动清除空格'!B:B&'抖音订单-按支付日期-ABF列，要先手动清除空格'!F:F,0)),0)} -> Z1640-黑色-L | G36: =IFERROR(SUBSTITUTE(CLEAN(LEFT(F36,FIND("-",F36)-1))," ",""),"") -> Z1640 | H36: {=IFERROR(_xlfn.IFS(AND(W36="已结算",AW36>30),AB36,LEFT(W36,5)="结算后退款",-AB36,LEFT(W36,5)="保证金退款",0),0)} -> 1 | I36: =AV36-K36 -> 289 | J36: =SUM(AM36:AU36) -> 0 | K36: =AI36 -> 0 | L36: =AX36 -> -14.45 | M36: =SUM(AY36:BD36) -> 0 | O36: =SUM(I36:N36) -> 274.55 | R36: 45892.697 | S36: '6944950932732318859 | T36: '6944950932732318859 | U36: 274.55 | V36: 聚合账户 | W36: 已结算 | X36: 否 | Y36: 45874.677 | Z36: '3767004410471907465 | AA36: 【老板周】日系极简 春季新品圆领简约设计感无袖马甲 | AB36: 1 | AC36: '2353393836764088 | AD36: 老板周 | AE36: 精选联盟 | AF36: 普通订单 | AG36: 289 | AH36: 289 | AI36: 0 | AJ36: 0 | AK36: 0 | AL36: 0 | AM36: 0 | AN36: 0 | AO36: 0 | AP36: 0 | AQ36: 0 | AR36: 0 | AS36: 0 | AT36: 0 | AU36: 0 | AV36: 289 | AW36: 289 | AX36: -14.45 | AY36: 0 | AZ36: 0 | BA36: 0 | BB36: 0 | BC36: 0 | BD36: 0 | BF36: -14.45 | BH36: 0 | BI36: 广州欣煌服饰有限公司
A37: =YEAR(R37) -> 2025 | B37: =MONTH(R37) -> 8 | C37: =S37 -> '6945097200975353681 | F37: {=IFERROR(INDEX('抖音订单-按支付日期-ABF列，要先手动清除空格'!G:G,MATCH(RIGHT(S37,LEN(S37)-1)&RIGHT(T37,LEN(T37)-1)&RIGHT(Z37,LEN(Z37)-1),'抖音订单-按支付日期-ABF列，要先手动清除空格'!A:A&'抖音订单-按支付日期-ABF列，要先手动清除空格'!B:B&'抖音订单-按支付日期-ABF列，要先手动清除空格'!F:F,0)),0)} -> Z1688-黑色-M | G37: =IFERROR(SUBSTITUTE(CLEAN(LEFT(F37,FIND("-",F37)-1))," ",""),"") -> Z1688 | H37: {=IFERROR(_xlfn.IFS(AND(W37="已结算",AW37>30),AB37,LEFT(W37,5)="结算后退款",-AB37,LEFT(W37,5)="保证金退款",0),0)} -> 1 | I37: =AV37-K37 -> 499 | J37: =SUM(AM37:AU37) -> 0 | K37: =AI37 -> 0 | L37: =AX37 -> -24.95 | M37: =SUM(AY37:BD37) -> 0 | O37: =SUM(I37:N37) -> 474.05 | R37: 45893.518 | S37: '6945097200975353681 | T37: '6945097200975353681 | U37: 474.05 | V37: 聚合账户 | W37: 已结算 | X37: 否 | Y37: 45879.863 | Z37: '3766960333395198324 | AA37: 【老板周】复古英伦 极简设计立体剪裁无领廓形外套 | AB37: 1 | AC37: '2353393836764088 | AD37: 老板周 | AE37: 精选联盟 | AF37: 普通订单 | AG37: 499 | AH37: 499 | AI37: 0 | AJ37: 0 | AK37: 0 | AL37: 0 | AM37: 0 | AN37: 0 | AO37: 0 | AP37: 0 | AQ37: 0 | AR37: 0 | AS37: 0 | AT37: 0 | AU37: 0 | AV37: 499 | AW37: 499 | AX37: -24.95 | AY37: 0 | AZ37: 0 | BA37: 0 | BB37: 0 | BC37: 0 | BD37: 0 | BF37: -24.95 | BH37: 0 | BI37: 广州欣煌服饰有限公司
A38: =YEAR(R38) -> 2025 | B38: =MONTH(R38) -> 8 | C38: =S38 -> '6944913823821207524 | F38: {=IFERROR(INDEX('抖音订单-按支付日期-ABF列，要先手动清除空格'!G:G,MATCH(RIGHT(S38,LEN(S38)-1)&RIGHT(T38,LEN(T38)-1)&RIGHT(Z38,LEN(Z38)-1),'抖音订单-按支付日期-ABF列，要先手动清除空格'!A:A&'抖音订单-按支付日期-ABF列，要先手动清除空格'!B:B&'抖音订单-按支付日期-ABF列，要先手动清除空格'!F:F,0)),0)} -> Z1640-黑色-M | G38: =IFERROR(SUBSTITUTE(CLEAN(LEFT(F38,FIND("-",F38)-1))," ",""),"") -> Z1640 | H38: {=IFERROR(_xlfn.IFS(AND(W38="已结算",AW38>30),AB38,LEFT(W38,5)="结算后退款",-AB38,LEFT(W38,5)="保证金退款",0),0)} -> 1 | I38: =AV38-K38 -> 289 | J38: =SUM(AM38:AU38) -> 0 | K38: =AI38 -> 0 | L38: =AX38 -> -14.45 | M38: =SUM(AY38:BD38) -> 0 | O38: =SUM(I38:N38) -> 274.55 | R38: 45893.518 | S38: '6944913823821207524 | T38: '6944913823821207524 | U38: 274.55 | V38: 聚合账户 | W38: 已结算 | X38: 否 | Y38: 45872.672 | Z38: '3767004410471907465 | AA38: 【老板周】日系极简 春季新品圆领简约设计感无袖马甲 | AB38: 1 | AC38: '2353393836764088 | AD38: 老板周 | AE38: 精选联盟 | AF38: 普通订单 | AG38: 289 | AH38: 289 | AI38: 0 | AJ38: 0 | AK38: 0 | AL38: 0 | AM38: 0 | AN38: 0 | AO38: 0 | AP38: 0 | AQ38: 0 | AR38: 0 | AS38: 0 | AT38: 0 | AU38: 0 | AV38: 289 | AW38: 289 | AX38: -14.45 | AY38: 0 | AZ38: 0 | BA38: 0 | BB38: 0 | BC38: 0 | BD38: 0 | BF38: -14.45 | BH38: 0 | BI38: 广州欣煌服饰有限公司
A39: =YEAR(R39) -> 2025 | B39: =MONTH(R39) -> 8 | C39: =S39 -> '6944953285442541377 | F39: {=IFERROR(INDEX('抖音订单-按支付日期-ABF列，要先手动清除空格'!G:G,MATCH(RIGHT(S39,LEN(S39)-1)&RIGHT(T39,LEN(T39)-1)&RIGHT(Z39,LEN(Z39)-1),'抖音订单-按支付日期-ABF列，要先手动清除空格'!A:A&'抖音订单-按支付日期-ABF列，要先手动清除空格'!B:B&'抖音订单-按支付日期-ABF列，要先手动清除空格'!F:F,0)),0)} -> Z2183-黑色-M | G39: =IFERROR(SUBSTITUTE(CLEAN(LEFT(F39,FIND("-",F39)-1))," ",""),"") -> Z2183 | H39: {=IFERROR(_xlfn.IFS(AND(W39="已结算",AW39>30),AB39,LEFT(W39,5)="结算后退款",-AB39,LEFT(W39,5)="保证金退款",0),0)} -> 1 | I39: =AV39-K39 -> 129 | J39: =SUM(AM39:AU39) -> 0 | K39: =AI39 -> 0 | L39: =AX39 -> -6.45 | M39: =SUM(AY39:BD39) -> 0 | O39: =SUM(I39:N39) -> 122.55 | R39: 45893.621 | S39: '6944953285442541377 | T39: '6944953285442541377 | U39: 122.55 | V39: 聚合账户 | W39: 已结算 | X39: 否 | Y39: 45874.935 | Z39: '3766942533029069048 | AA39: 【老板周】夏季轻盈 新品圆领气质轻薄不规则透气上衣 | AB39: 1 | AC39: '2353393836764088 | AD39: 老板周 | AE39: 精选联盟 | AF39: 普通订单 | AG39: 129 | AH39: 129 | AI39: 0 | AJ39: 0 | AK39: 0 | AL39: 0 | AM39: 0 | AN39: 0 | AO39: 0 | AP39: 0 | AQ39: 0 | AR39: 0 | AS39: 0 | AT39: 0 | AU39: 0 | AV39: 129 | AW39: 129 | AX39: -6.45 | AY39: 0 | AZ39: 0 | BA39: 0 | BB39: 0 | BC39: 0 | BD39: 0 | BF39: -6.45 | BH39: 0 | BI39: 广州欣煌服饰有限公司
A40: =YEAR(R40) -> 2025 | B40: =MONTH(R40) -> 8 | C40: =S40 -> '6920679374368898969 | F40: {=IFERROR(INDEX('抖音订单-按支付日期-ABF列，要先手动清除空格'!G:G,MATCH(RIGHT(S40,LEN(S40)-1)&RIGHT(T40,LEN(T40)-1)&RIGHT(Z40,LEN(Z40)-1),'抖音订单-按支付日期-ABF列，要先手动清除空格'!A:A&'抖音订单-按支付日期-ABF列，要先手动清除空格'!B:B&'抖音订单-按支付日期-ABF列，要先手动清除空格'!F:F,0)),0)} -> Z482-黑色-M | G40: =IFERROR(SUBSTITUTE(CLEAN(LEFT(F40,FIND("-",F40)-1))," ",""),"") -> Z482 | H40: {=IFERROR(_xlfn.IFS(AND(W40="已结算",AW40>30),AB40,LEFT(W40,5)="结算后退款",-AB40,LEFT(W40,5)="保证金退款",0),0)} -> 1 | I40: =AV40-K40 -> 289 | J40: =SUM(AM40:AU40) -> 0 | K40: =AI40 -> 0 | L40: =AX40 -> -14.45 | M40: =SUM(AY40:BD40) -> 0 | O40: =SUM(I40:N40) -> 274.55 | R40: 45894.507 | S40: '6920679374368898969 | T40: '6920679374368898969 | U40: 274.55 | V40: 聚合账户 | W40: 已结算 | X40: 否 | Y40: 45879.769 | Z40: '3766240945658527845 | AA40: 【老板周】老钱风 简约休闲圆领后背扣子时髦马甲 | AB40: 1 | AC40: '2353393836764088 | AD40: 老板周 | AE40: 精选联盟 | AF40: 普通订单 | AG40: 289 | AH40: 289 | AI40: 0 | AJ40: 0 | AK40: 0 | AL40: 0 | AM40: 0 | AN40: 0 | AO40: 0 | AP40: 0 | AQ40: 0 | AR40: 0 | AS40: 0 | AT40: 0 | AU40: 0 | AV40: 289 | AW40: 289 | AX40: -14.45 | AY40: 0 | AZ40: 0 | BA40: 0 | BB40: 0 | BC40: 0 | BD40: 0 | BF40: -14.45 | BH40: 0 | BI40: 广州欣煌服饰有限公司
A41: =YEAR(R41) -> 2025 | B41: =MONTH(R41) -> 8 | C41: =S41 -> '6920688272115924197 | F41: {=IFERROR(INDEX('抖音订单-按支付日期-ABF列，要先手动清除空格'!G:G,MATCH(RIGHT(S41,LEN(S41)-1)&RIGHT(T41,LEN(T41)-1)&RIGHT(Z41,LEN(Z41)-1),'抖音订单-按支付日期-ABF列，要先手动清除空格'!A:A&'抖音订单-按支付日期-ABF列，要先手动清除空格'!B:B&'抖音订单-按支付日期-ABF列，要先手动清除空格'!F:F,0)),0)} -> Z482-黑色-L | G41: =IFERROR(SUBSTITUTE(CLEAN(LEFT(F41,FIND("-",F41)-1))," ",""),"") -> Z482 | H41: {=IFERROR(_xlfn.IFS(AND(W41="已结算",AW41>30),AB41,LEFT(W41,5)="结算后退款",-AB41,LEFT(W41,5)="保证金退款",0),0)} -> 1 | I41: =AV41-K41 -> 289 | J41: =SUM(AM41:AU41) -> 0 | K41: =AI41 -> 0 | L41: =AX41 -> -14.45 | M41: =SUM(AY41:BD41) -> 0 | O41: =SUM(I41:N41) -> 274.55 | R41: 45894.519 | S41: '6920688272115924197 | T41: '6920688272115924197 | U41: 274.55 | V41: 聚合账户 | W41: 已结算 | X41: 否 | Y41: 45879.813 | Z41: '3766240945658527845 | AA41: 【老板周】老钱风 简约休闲圆领后背扣子时髦马甲 | AB41: 1 | AC41: '2353393836764088 | AD41: 老板周 | AE41: 精选联盟 | AF41: 普通订单 | AG41: 289 | AH41: 289 | AI41: 0 | AJ41: 0 | AK41: 0 | AL41: 0 | AM41: 0 | AN41: 0 | AO41: 0 | AP41: 0 | AQ41: 0 | AR41: 0 | AS41: 0 | AT41: 0 | AU41: 0 | AV41: 289 | AW41: 289 | AX41: -14.45 | AY41: 0 | AZ41: 0 | BA41: 0 | BB41: 0 | BC41: 0 | BD41: 0 | BF41: -14.45 | BH41: 0 | BI41: 广州欣煌服饰有限公司
A42: =YEAR(R42) -> 2025 | B42: =MONTH(R42) -> 8 | C42: =S42 -> '6945123623644894425 | F42: {=IFERROR(INDEX('抖音订单-按支付日期-ABF列，要先手动清除空格'!G:G,MATCH(RIGHT(S42,LEN(S42)-1)&RIGHT(T42,LEN(T42)-1)&RIGHT(Z42,LEN(Z42)-1),'抖音订单-按支付日期-ABF列，要先手动清除空格'!A:A&'抖音订单-按支付日期-ABF列，要先手动清除空格'!B:B&'抖音订单-按支付日期-ABF列，要先手动清除空格'!F:F,0)),0)} -> Z482-黑色-S | G42: =IFERROR(SUBSTITUTE(CLEAN(LEFT(F42,FIND("-",F42)-1))," ",""),"") -> Z482 | H42: {=IFERROR(_xlfn.IFS(AND(W42="已结算",AW42>30),AB42,LEFT(W42,5)="结算后退款",-AB42,LEFT(W42,5)="保证金退款",0),0)} -> 1 | I42: =AV42-K42 -> 289 | J42: =SUM(AM42:AU42) -> 0 | K42: =AI42 -> 0 | L42: =AX42 -> -14.45 | M42: =SUM(AY42:BD42) -> 0 | O42: =SUM(I42:N42) -> 274.55 | R42: 45894.519 | S42: '6945123623644894425 | T42: '6945123623644894425 | U42: 274.55 | V42: 聚合账户 | W42: 已结算 | X42: 否 | Y42: 45879.772 | Z42: '3766240945658527845 | AA42: 【老板周】老钱风 简约休闲圆领后背扣子时髦马甲 | AB42: 1 | AC42: '2353393836764088 | AD42: 老板周 | AE42: 精选联盟 | AF42: 普通订单 | AG42: 289 | AH42: 289 | AI42: 0 | AJ42: 0 | AK42: 0 | AL42: 0 | AM42: 0 | AN42: 0 | AO42: 0 | AP42: 0 | AQ42: 0 | AR42: 0 | AS42: 0 | AT42: 0 | AU42: 0 | AV42: 289 | AW42: 289 | AX42: -14.45 | AY42: 0 | AZ42: 0 | BA42: 0 | BB42: 0 | BC42: 0 | BD42: 0 | BF42: -14.45 | BH42: 0 | BI42: 广州欣煌服饰有限公司
A43: =YEAR(R43) -> 2025 | B43: =MONTH(R43) -> 8 | C43: =S43 -> '6945117197164287538 | F43: {=IFERROR(INDEX('抖音订单-按支付日期-ABF列，要先手动清除空格'!G:G,MATCH(RIGHT(S43,LEN(S43)-1)&RIGHT(T43,LEN(T43)-1)&RIGHT(Z43,LEN(Z43)-1),'抖音订单-按支付日期-ABF列，要先手动清除空格'!A:A&'抖音订单-按支付日期-ABF列，要先手动清除空格'!B:B&'抖音订单-按支付日期-ABF列，要先手动清除空格'!F:F,0)),0)} -> Z482-黑色-S | G43: =IFERROR(SUBSTITUTE(CLEAN(LEFT(F43,FIND("-",F43)-1))," ",""),"") -> Z482 | H43: {=IFERROR(_xlfn.IFS(AND(W43="已结算",AW43>30),AB43,LEFT(W43,5)="结算后退款",-AB43,LEFT(W43,5)="保证金退款",0),0)} -> 1 | I43: =AV43-K43 -> 289 | J43: =SUM(AM43:AU43) -> 0 | K43: =AI43 -> 0 | L43: =AX43 -> -14.45 | M43: =SUM(AY43:BD43) -> 0 | O43: =SUM(I43:N43) -> 274.55 | R43: 45894.659 | S43: '6945117197164287538 | T43: '6945117197164287538 | U43: 274.55 | V43: 聚合账户 | W43: 已结算 | X43: 否 | Y43: 45879.769 | Z43: '3766240945658527845 | AA43: 【老板周】老钱风 简约休闲圆领后背扣子时髦马甲 | AB43: 1 | AC43: '2353393836764088 | AD43: 老板周 | AE43: 精选联盟 | AF43: 普通订单 | AG43: 289 | AH43: 289 | AI43: 0 | AJ43: 0 | AK43: 0 | AL43: 0 | AM43: 0 | AN43: 0 | AO43: 0 | AP43: 0 | AQ43: 0 | AR43: 0 | AS43: 0 | AT43: 0 | AU43: 0 | AV43: 289 | AW43: 289 | AX43: -14.45 | AY43: 0 | AZ43: 0 | BA43: 0 | BB43: 0 | BC43: 0 | BD43: 0 | BF43: -14.45 | BH43: 0 | BI43: 广州欣煌服饰有限公司
