Workbook

Sheet 订单明细
A1: 订单号 | B1: 订单状态 | C1: 售后状态 | D1: 订单类型 | E1: 订单标记 | F1: 收件人姓名 | G1: 收件人电话 | H1: 收件人地址 | I1: 省 | J1: 市 | K1: 区 | L1: 区域编码 | M1: 小红书编码 | N1: 条形码 | O1: 规格ID | P1: 达人ID | Q1: 达人名称 | R1: SKU名称 | S1: SKU规格 | T1: SKU件数 | U1: 是否为赠品 | V1: 发票/Invoice | W1: 商品总价(元) | X1: 用户应付金额(元) | Y1: 平台优惠(元) | Z1: 店铺优惠(元) | AA1: 支付渠道优惠(元) | AB1: SKU商家改价(元) | AC1: 商家应收金额(元)（支付金额） | AD1: 支付方式 | AE1: 支付渠道订单号 | AF1: 支付期数 | AG1: 利息费用 | AH1: 手续费承担方 | AI1: 支付时间 | AJ1: sku净重(kg) | AK1: 包裹总净重(kg) | AL1: 包裹总运费(元) | AM1: 快递公司 | AN1: 快递单号 | AO1: 大头笔/Paint Marker | AP1: 集包地/Express Extend 1 | AQ1: 三段码/Express Extend 2 | AR1: 订购人身份证姓名/ID Name | AS1: 订购人身份证号/ID Number | AT1: 收件人身份证姓名 | AU1: 收件人身份证号 | AV1: 订单创建时间 | AW1: 预售订单开始发货时间 | AX1: 预售订单截止发货时间 | AY1: 承诺发货时间 | AZ1: 订单发货时间 | BA1: 订单完成时间 | BB1: 发货仓库 | BC1: 确认收货类型 | BD1: 是否延迟收货 | BE1: 用户备注 | BF1: 包裹备注标记 | BG1: 包裹备注信息 | BH1: 异常原因 | BI1: 店铺名称 | BJ1: 用户编号 | BK1: 运费模版名称 | BL1: 物流方案名称 | BM1: 第三方机构订单号 | BN1: 国补模式 | BO1: 供应商id | BP1: 供应商名称 | BQ1: 商家编码 | BR1: 商品ID | BS1: 商品名称
A2: P771683143371443691 | B2: 已完成 | C2: 无售后 | D2: 预售订单 | F2: 陆* | G2: 199****2821 | H2: 上海 上海市 宝山区 *** | I2: 上海 | J2: 上海市 | K2: 宝山区 | L2: 310113111000 | M2: 6894ac11aa1e7b001555658f | N2: XHS-3IRER6T45U68 | O2: 6894ac11aa1e7b001555658e | R2: 【老板周】复古老钱 新品小众宽松时髦腰果花松紧腰休闲裤 花色 M（100-120斤） | S2: 花色 M（100-120斤） | T2: 1 | W2: 249.00 | X2: 249.00 | Y2: 0.00 | Z2: 0.00 | AB2: 0.00 | AC2: 249.00 | AD2: 微信 | AE2: 4350802247202508259221136879 | AI2: 2025-08-25 22:12:30 | AK2: 0.000 | AL2: 0.00 | AM2: 中通速递 | AN2: 73569586895536 | AV2: 2025-08-25 22:12:23 | AY2: 2025-09-09 22:12:30 | AZ2: 2025-08-25 22:56:08 | BA2: 2025-08-27 16:51:27 | BB2: 第三方平台卖家电子库存 | BC2: 用户确认收货 | BD2: 否 | BI2: LAO BAN ZHOU的店 | BJ2: 5661009c5e87e718219897ac | BK2: 公司店运费模版 | BL2: 小红书公司 | BQ2: Z2338-花色-M | BR2: 6894ac11aa1e7b001555658b | BS2: 【老板周】复古老钱 新品小众宽松时髦腰果花松紧腰休闲裤
A3: P771601056297099071 | B3: 已关闭 | C3: 售后完成 | D3: 预售订单 | F3: 史* | G3: 135****5235 | H3: 广东省 江门市 江海区 *** | I3: 广东省 | J3: 江门市 | K3: 江海区 | L3: 440704001 | M3: 6894b76bf735ce00153807e6 | N3: XHS-3I9QHHLHJ400 | O3: 6894b76bf735ce00153807e5 | R3: 【老板周】慵懒慵 秋冬新款复古撞色条纹松弛感毛衣 条纹 S（80-100斤） | S3: 条纹 S（80-100斤） | T3: 1 | W3: 289.00 | X3: 289.00 | Y3: 0.00 | Z3: 0.00 | AB3: 0.00 | AC3: 289.00 | AD3: 微信 | AE3: 4302302286202508243205233952 | AI3: 2025-08-24 23:24:26 | AK3: 0.000 | AL3: 0.00 | AM3: 中通速递 | AN3: 73569436349866 | AV3: 2025-08-24 23:24:16 | AY3: 2025-09-08 23:24:26 | AZ3: 2025-08-24 23:44:31 | BB3: 第三方平台卖家电子库存 | BD3: 否 | BF3: 蓝旗 | BG3: ;SF3230026344337(收） Z2271-条纹-S*1# | BI3: LAO BAN ZHOU的店 | BJ3: 67603dc70000000018015c4e | BK3: 公司店运费模版 | BL3: 小红书公司 | BQ3: Z2271-条纹-S | BR3: 6894b76bf735ce00153807e4 | BS3: 【老板周】慵懒慵 秋冬新款复古撞色条纹松弛感毛衣
A4: P771077302074017641 | B4: 已完成 | C4: 无售后 | D4: 预售订单 | E4: 物流异常 | F4: 周* | G4: 150****4975 | H4: 内蒙古自治区 鄂尔多斯市 康巴什区 *** | I4: 内蒙古自治区 | J4: 鄂尔多斯市 | K4: 康巴什区 | L4: 150603 | M4: 6896fe0c6d08080015500893 | N4: XHS-3EHYVMD8SZR4 | O4: 6896fe0c6d08080015500892 | P4: 650d6e9f000000001603a6ac | Q4: 老板周. | R4: 【老板周】夏季轻盈 新品圆领气质轻薄不规则透气上衣 黑色 M（80-100斤） | S4: 黑色 M（80-100斤） | T4: 1 | W4: 129.00 | X4: 129.00 | Y4: 0.00 | Z4: 0.00 | AB4: 0.00 | AC4: 129.00 | AD4: 微信 | AE4: 4337602246202508189619352845 | AI4: 2025-08-18 21:55:09 | AK4: 0.000 | AL4: 0.00 | AM4: 中通速递 | AN4: 73568731918406 | AV4: 2025-08-18 21:55:02 | AY4: 2025-09-02 21:55:09 | AZ4: 2025-08-19 22:18:12 | BA4: 2025-08-26 22:18:12 | BB4: 第三方平台卖家电子库存 | BC4: 系统自动收货 | BD4: 否 | BF4: 蓝旗 | BG4: 拦截;73568592691278(收） Z2183-米白色-M*1# | BI4: LAO BAN ZHOU的店 | BJ4: 5f8e45b90000000001001f97 | BK4: 公司店运费模版 | BL4: 小红书公司 | BQ4: Z2183-黑色-M | BR4: 6896fe0c6d08080015500891 | BS4: 【老板周】夏季轻盈 新品圆领气质轻薄不规则透气上衣
A5: P771077302074017641 | B5: 已完成 | C5: 售后完成 | D5: 预售订单 | E5: 物流异常 | F5: 周* | G5: 150****4975 | H5: 内蒙古自治区 鄂尔多斯市 康巴什区 *** | I5: 内蒙古自治区 | J5: 鄂尔多斯市 | K5: 康巴什区 | L5: 150603 | M5: 6896fe0c6d08080015500899 | N5: XHS-3EHYVMDNSDTS | O5: 6896fe0c6d08080015500898 | P5: 650d6e9f000000001603a6ac | Q5: 老板周. | R5: 【老板周】夏季轻盈 新品圆领气质轻薄不规则透气上衣 米白色 M（80-100斤） | S5: 米白色 M（80-100斤） | T5: 1 | W5: 129.00 | X5: 129.00 | Y5: 0.00 | Z5: 0.00 | AB5: 0.00 | AC5: 129.00 | AD5: 微信 | AE5: 4337602246202508189619352845 | AI5: 2025-08-18 21:55:09 | AK5: 0.000 | AL5: 0.00 | AM5: 中通速递 | AN5: 73568592691278 | AV5: 2025-08-18 21:55:02 | AY5: 2025-09-02 21:55:09 | AZ5: 2025-08-18 22:55:40 | BB5: 第三方平台卖家电子库存 | BD5: 否 | BF5: 蓝旗 | BG5: 拦截;73568592691278(收） Z2183-米白色-M*1# | BI5: LAO BAN ZHOU的店 | BJ5: 5f8e45b90000000001001f97 | BK5: 公司店运费模版 | BL5: 小红书公司 | BQ5: Z2183-米白色-M | BR5: 6896fe0c6d08080015500891 | BS5: 【老板周】夏季轻盈 新品圆领气质轻薄不规则透气上衣
A6: P770990197404134041 | B6: 已关闭 | C6: 售后完成 | D6: 预售订单 | F6: 陈** | G6: 138****3883 | H6: 上海 上海市 长宁区 *** | I6: 上海 | J6: 上海市 | K6: 长宁区 | L6: 310105011000 | M6: 68949ffbc34eef001610ef47 | N6: XHS-3HO32A90HCZK | O6: 68949ffbc34eef001610ef46 | P6: 650d6e9f000000001603a6ac | Q6: 老板周. | R6: 【老板周】夏季新款 小众轻盈空气感重工泡泡绉小飞袖上衣 黑色 M（100-120斤） | S6: 黑色 M（100-120斤） | T6: 1 | W6: 339.00 | X6: 339.00 | Y6: 0.00 | Z6: 0.00 | AB6: 0.00 | AC6: 339.00 | AD6: 微信 | AE6: 4307502582202508176171663706 | AI6: 2025-08-17 21:43:23 | AK6: 0.000 | AL6: 0.00 | AM6: 中通速递 | AN6: 73568587025232 | AV6: 2025-08-17 21:43:17 | AY6: 2025-09-01 21:43:23 | AZ6: 2025-08-18 21:23:31 | BA6: 2025-08-25 21:23:33 | BB6: 第三方平台卖家电子库存 | BC6: 系统自动收货 | BD6: 否 | BF6: 蓝旗 | BG6: ;SF3230107717291(收） Z2308-黑色-M*1# | BI6: LAO BAN ZHOU的店 | BJ6: 5ef987090000000001001e3d | BK6: 公司店运费模版 | BL6: 小红书公司 | BQ6: Z2308-黑色-M | BR6: 68949ffbc34eef001610ef43 | BS6: 【老板周】夏季新款 小众轻盈空气感重工泡泡绉小飞袖上衣
A7: P770990615215304131 | B7: 已关闭 | C7: 售后完成 | D7: 预售订单 | F7: 何* | G7: 189****1661 | H7: 湖南省 长沙市 雨花区 *** | I7: 湖南省 | J7: 长沙市 | K7: 雨花区 | L7: 430111 | M7: 6896e3fdd48cf90015433efb | N7: XHS-3G6Z6JI0FO5C | O7: 6896e3fdd48cf90015433efa | P7: 650d6e9f000000001603a6ac | Q7: 老板周. | R7: 【老板周】休闲腔调 夏季薄款圆领口袋设计百搭三角T恤 黄绿色 S（80-100斤） | S7: 黄绿色 S（80-100斤） | T7: 1 | W7: 269.00 | X7: 269.00 | Y7: 0.00 | Z7: 0.00 | AB7: 0.00 | AC7: 269.00 | AD7: 支付宝 | AE7: 2025081722001438351419440818 | AI7: 2025-08-17 21:50:20 | AK7: 0.000 | AL7: 0.00 | AM7: 中通速递 | AN7: 73568444482820 | AV7: 2025-08-17 21:50:15 | AY7: 2025-09-01 21:50:20 | AZ7: 2025-08-17 22:55:10 | BA7: 2025-08-24 22:55:11 | BB7: 第三方平台卖家电子库存 | BC7: 系统自动收货 | BD7: 否 | BF7: 蓝旗 | BG7: 肩膀勾线;SF3230325430957(收） Z2233-黄绿色-S*1# | BI7: LAO BAN ZHOU的店 | BJ7: 5bde6c50d9463d00012dd3b7 | BK7: 公司店运费模版 | BL7: 小红书公司 | BQ7: Z2233-黄绿色-S | BR7: 6896e3fdd48cf90015433eed | BS7: 【老板周】休闲腔调 夏季薄款圆领口袋设计百搭三角T恤
A8: P770986869946371481 | B8: 已关闭 | C8: 售后完成 | D8: 预售订单 | F8: 刘** | G8: 158****3237 | H8: 陕西省 西安市 新城区 *** | I8: 陕西省 | J8: 西安市 | K8: 新城区 | L8: 610102007 | M8: 689704bae53c1000157cfa9f | N8: XHS-3FAGCOT1V85C | O8: 689704bae53c1000157cfa9e | P8: 650d6e9f000000001603a6ac | Q8: 老板周. | R8: 【老板周】法式随性 夏季时髦叠门襟无袖设计感开叉马甲 黑色 M（100-120斤） | S8: 黑色 M（100-120斤） | T8: 1 | W8: 229.00 | X8: 229.00 | Y8: 0.00 | Z8: 0.00 | AB8: 0.00 | AC8: 229.00 | AD8: 微信 | AE8: 4306702271202508170222076938 | AI8: 2025-08-17 20:47:56 | AK8: 0.000 | AL8: 0.00 | AM8: 中通速递 | AN8: 73568441965438 | AV8: 2025-08-17 20:47:50 | AY8: 2025-09-01 20:47:56 | AZ8: 2025-08-17 21:32:26 | BA8: 2025-08-24 21:32:26 | BB8: 第三方平台卖家电子库存 | BC8: 系统自动收货 | BD8: 否 | BF8: 蓝旗 | BG8: ;SF3289318820600(收） Z2218-黑色-S*1 Z2218-黑色-M*1# | BI8: LAO BAN ZHOU的店 | BJ8: 5c793a590000000010012874 | BK8: 公司店运费模版 | BL8: 小红书公司 | BQ8: Z2218-黑色-M | BR8: 689704bae53c1000157cfa9b | BS8: 【老板周】法式随性 夏季时髦叠门襟无袖设计感开叉马甲
A9: P770986869946371481 | B9: 已关闭 | C9: 售后完成 | D9: 预售订单 | F9: 刘** | G9: 158****3237 | H9: 陕西省 西安市 新城区 *** | I9: 陕西省 | J9: 西安市 | K9: 新城区 | L9: 610102007 | M9: 689704bae53c1000157cfa9d | N9: XHS-3FAGCOSWVFGG | O9: 689704bae53c1000157cfa9c | P9: 650d6e9f000000001603a6ac | Q9: 老板周. | R9: 【老板周】法式随性 夏季时髦叠门襟无袖设计感开叉马甲 黑色 S（80-100斤） | S9: 黑色 S（80-100斤） | T9: 1 | W9: 229.00 | X9: 229.00 | Y9: 0.00 | Z9: 0.00 | AB9: 0.00 | AC9: 229.00 | AD9: 微信 | AE9: 4306702271202508170222076938 | AI9: 2025-08-17 20:47:56 | AK9: 0.000 | AL9: 0.00 | AM9: 中通速递 | AN9: 73568576683034 | AV9: 2025-08-17 20:47:50 | AY9: 2025-09-01 20:47:56 | AZ9: 2025-08-18 19:43:07 | BA9: 2025-08-25 19:43:08 | BB9: 第三方平台卖家电子库存 | BC9: 系统自动收货 | BD9: 否 | BF9: 蓝旗 | BG9: ;SF3289318820600(收） Z2218-黑色-S*1 Z2218-黑色-M*1# | BI9: LAO BAN ZHOU的店 | BJ9: 5c793a590000000010012874 | BK9: 公司店运费模版 | BL9: 小红书公司 | BQ9: Z2218-黑色-S | BR9: 689704bae53c1000157cfa9b | BS9: 【老板周】法式随性 夏季时髦叠门襟无袖设计感开叉马甲
A10: P770986580251454261 | B10: 已关闭 | C10: 售后完成 | D10: 预售订单 | F10: 王** | G10: 157****7660 | H10: 甘肃省 兰州市 安宁区 *** | I10: 甘肃省 | J10: 兰州市 | K10: 安宁区 | L10: 620105 | M10: 689704bae53c1000157cfa9d | N10: XHS-3FAGCOSWVFGG | O10: 689704bae53c1000157cfa9c | P10: 650d6e9f000000001603a6ac | Q10: 老板周. | R10: 【老板周】法式随性 夏季时髦叠门襟无袖设计感开叉马甲 黑色 S（80-100斤） | S10: 黑色 S（80-100斤） | T10: 1 | W10: 229.00 | X10: 229.00 | Y10: 0.00 | Z10: 0.00 | AB10: 0.00 | AC10: 229.00 | AD10: 微信 | AE10: 4336802247202508170250305747 | AI10: 2025-08-17 20:43:06 | AK10: 0.000 | AL10: 0.00 | AM10: 中通速递 | AN10: 73568556568537 | AV10: 2025-08-17 20:43:00 | AY10: 2025-09-01 20:43:06 | AZ10: 2025-08-18 17:29:30 | BA10: 2025-08-25 17:29:30 | BB10: 第三方平台卖家电子库存 | BC10: 系统自动收货 | BD10: 否 | BF10: 蓝旗 | BG10: ;JDX042496871681(收） Z2218-黑色-S*1# | BI10: LAO BAN ZHOU的店 | BJ10: 5a966dd7e8ac2b762a5a6e20 | BK10: 公司店运费模版 | BL10: 小红书公司 | BQ10: Z2218-黑色-S | BR10: 689704bae53c1000157cfa9b | BS10: 【老板周】法式随性 夏季时髦叠门襟无袖设计感开叉马甲
A11: P770984511919250241 | B11: 已关闭 | C11: 售后完成 | D11: 预售订单 | F11: 玉** | G11: 139****3111 | H11: 辽宁省 沈阳市 浑南区 *** | I11: 辽宁省 | J11: 沈阳市 | K11: 浑南区 | L11: 210112 | M11: 689704bae53c1000157cfaa1 | N11: XHS-3FAGCOT6V0U8 | O11: 689704bae53c1000157cfaa0 | P11: 650d6e9f000000001603a6ac | Q11: 老板周. | R11: 【老板周】法式随性 夏季时髦叠门襟无袖设计感开叉马甲 黑色 L（120-135斤） | S11: 黑色 L（120-135斤） | T11: 1 | W11: 229.00 | X11: 229.00 | Y11: 0.00 | Z11: 0.00 | AB11: 0.00 | AC11: 229.00 | AD11: 银联 | AE11: 432508172008322427418 | AI11: 2025-08-17 20:08:37 | AK11: 0.000 | AL11: 0.00 | AM11: 中通速递 | AN11: 73568436568058 | AV11: 2025-08-17 20:08:32 | AY11: 2025-09-01 20:08:37 | AZ11: 2025-08-17 20:35:14 | BA11: 2025-08-24 20:35:14 | BB11: 第三方平台卖家电子库存 | BC11: 系统自动收货 | BD11: 否 | BF11: 蓝旗 | BG11: ;73569281821300(收） Z2218-黑色-L*1# | BI11: LAO BAN ZHOU的店 | BJ11: 5abc9bade8ac2b23030f3e59 | BK11: 公司店运费模版 | BL11: 小红书公司 | BQ11: Z2218-黑色-L | BR11: 689704bae53c1000157cfa9b | BS11: 【老板周】法式随性 夏季时髦叠门襟无袖设计感开叉马甲
A12: P770983921263440451 | B12: 已完成 | C12: 售后完成 | D12: 预售订单 | F12: 王** | G12: 186****8688 | H12: 内蒙古自治区 呼伦贝尔市 海拉尔区 *** | I12: 内蒙古自治区 | J12: 呼伦贝尔市 | K12: 海拉尔区 | L12: 150702101000 | M12: 689704bae53c1000157cfaa1 | N12: XHS-3FAGCOT6V0U8 | O12: 689704bae53c1000157cfaa0 | P12: 650d6e9f000000001603a6ac | Q12: 老板周. | R12: 【老板周】法式随性 夏季时髦叠门襟无袖设计感开叉马甲 黑色 L（120-135斤） | S12: 黑色 L（120-135斤） | T12: 1 | W12: 229.00 | X12: 229.00 | Y12: 0.00 | Z12: 0.00 | AB12: 0.00 | AC12: 229.00 | AD12: 支付宝 | AE12: 2025081722001445001452299017 | AI12: 2025-08-17 19:58:48 | AK12: 0.000 | AL12: 0.00 | AM12: 中通速递 | AN12: 73568436950563 | AV12: 2025-08-17 19:58:41 | AY12: 2025-09-01 19:58:48 | AZ12: 2025-08-17 20:35:14 | BA12: 2025-08-24 20:35:14 | BB12: 第三方平台卖家电子库存 | BC12: 系统自动收货 | BD12: 否 | BF12: 蓝旗 | BG12: ;SF3280467567718(收） Z2218-黑色-L*1# | BI12: LAO BAN ZHOU的店 | BJ12: 5a2552fd4eacab6a98c94bb1 | BK12: 公司店运费模版 | BL12: 小红书公司 | BQ12: Z2218-黑色-L | BR12: 689704bae53c1000157cfa9b | BS12: 【老板周】法式随性 夏季时髦叠门襟无袖设计感开叉马甲
A13: P770822898182284051 | B13: 已关闭 | C13: 售后完成 | D13: 预售订单 | F13: 何 | G13: 135****0291 | H13: 湖南省 长沙市 岳麓区 *** | I13: 湖南省 | J13: 长沙市 | K13: 岳麓区 | L13: 430104005 | M13: 689dee3bbc668f00150ae4a2 | N13: XHS-3JY88WA16VWG | O13: 689dee3bbc668f00150ae4a1 | P13: 650d6e9f000000001603a6ac | Q13: 老板周. | R13: 【老板周】经典慵懒 秋季经典撞色条纹镂空针织上衣 黑白条纹 M（100-135斤） | S13: 黑白条纹 M（100-135斤） | T13: 1 | W13: 219.00 | X13: 219.00 | Y13: 0.00 | Z13: 0.00 | AB13: 0.00 | AC13: 219.00 | AD13: 支付宝 | AE13: 2025081522001457781456456422 | AI13: 2025-08-15 23:15:05 | AK13: 0.000 | AL13: 0.00 | AM13: 中通速递 | AN13: 73568875427704 | AV13: 2025-08-15 23:14:58 | AY13: 2025-08-30 23:15:05 | AZ13: 2025-08-21 00:20:35 | BB13: 第三方平台卖家电子库存 | BD13: 否 | BF13: 蓝旗 | BG13: ;SF3289575962710(收） Z2376-黑白条纹-M*1# | BI13: LAO BAN ZHOU的店 | BJ13: 5c1a271e000000000703e641 | BK13: 公司店运费模版 | BL13: 小红书公司 | BQ13: Z2376-黑白条纹-M | BR13: 689dee3bbc668f00150ae49e | BS13: 【老板周】经典慵懒 秋季经典撞色条纹镂空针织上衣
A14: P770821520016218311 | B14: 已完成 | C14: 无售后 | D14: 预售订单 | F14: 王* | G14: 138****7966 | H14: 福建省 三明市 沙县区 *** | I14: 福建省 | J14: 三明市 | K14: 沙县区 | L14: 350405 | M14: 689dee5baa1e7b00156ae7c1 | N14: XHS-3JY9LAG89YPS | O14: 689dee5baa1e7b00156ae7c0 | P14: 650d6e9f000000001603a6ac | Q14: 老板周. | R14: LAO BAN ZHOU 【老板周】极简主义 秋冬新款复古卷边前短后长针织上衣 灰色 S（80-100斤） | S14: 灰色 S（80-100斤） | T14: 1 | W14: 219.00 | X14: 219.00 | Y14: 0.00 | Z14: 0.00 | AB14: 0.00 | AC14: 219.00 | AD14: 微信先用后付 | AI14: 2025-08-15 22:52:00 | AK14: 0.000 | AL14: 0.00 | AM14: 中通速递 | AN14: 73569287102336 | AV14: 2025-08-15 22:52:00 | AY14: 2025-08-30 22:52:00 | AZ14: 2025-08-25 19:55:00 | BA14: 2025-08-27 17:10:53 | BB14: 第三方平台卖家电子库存 | BC14: 用户确认收货 | BD14: 否 | BI14: LAO BAN ZHOU的店 | BJ14: 573725d782ec392b7aac36a5 | BK14: 公司店运费模版 | BL14: 小红书公司 | BQ14: Z2365-灰色-S | BR14: 689dee5baa1e7b00156ae7bb | BS14: 【老板周】极简主义 秋冬新款复古卷边前短后长针织上衣
A15: P770818894631507761 | B15: 已完成 | C15: 无售后 | D15: 预售订单 | F15: 毛 | G15: 188****0712 | H15: 上海 上海市 杨浦区 *** | I15: 上海 | J15: 上海市 | K15: 杨浦区 | L15: 310110006 | M15: 689dee541ea4cb00155e6f97 | N15: XHS-3JY9BQCVPTDS | O15: 689dee541ea4cb00155e6f96 | P15: 650d6e9f000000001603a6ac | Q15: 老板周. | R15: LAO BAN ZHOU 【老板周】百搭气质 秋冬新款百搭造型感气质三角巾 藏青色 | S15: 藏青色 | T15: 1 | W15: 199.00 | X15: 199.00 | Y15: 0.00 | Z15: 0.00 | AB15: 0.00 | AC15: 199.00 | AD15: 支付宝免密 | AE15: 2025081522001459511443799810 | AI15: 2025-08-15 22:08:16 | AK15: 0.000 | AL15: 0.00 | AM15: 中通速递 | AN15: 73569428130248 | AV15: 2025-08-15 22:08:14 | AY15: 2025-08-30 22:08:16 | AZ15: 2025-08-24 21:27:21 | BA15: 2025-08-27 08:52:15 | BB15: 第三方平台卖家电子库存 | BC15: 用户确认收货 | BD15: 否 | BI15: LAO BAN ZHOU的店 | BJ15: 5aaaf92e4eacab0922af9f62 | BK15: 公司店运费模版 | BL15: 小红书公司 | BQ15: Z2380-藏青色 | BR15: 689dee541ea4cb00155e6f93 | BS15: 【老板周】百搭气质 秋冬新款百搭造型感气质三角巾
A16: P770818846205191671 | B16: 已完成 | C16: 无售后 | D16: 预售订单 | F16: 方* | G16: 199****7277 | H16: 山东省 日照市 东港区 *** | I16: 山东省 | J16: 日照市 | K16: 东港区 | L16: 371102008000 | M16: 6896fe48057f570015d29245 | N16: XHS-2Z0D3J1YAL8G | O16: 6896fe48057f570015d29244 | P16: 650d6e9f000000001603a6ac | Q16: 老板周. | R16: 【老板周】时髦撞色 春季新款假两件显瘦长袖打底T恤上衣 黑色 M（100-120斤） | S16: 黑色 M（100-120斤） | T16: 1 | W16: 199.00 | X16: 199.00 | Y16: 0.00 | Z16: 0.00 | AB16: 0.00 | AC16: 199.00 | AD16: 支付宝 | AE16: 2025081522001446921455566706 | AI16: 2025-08-15 22:07:36 | AK16: 0.000 | AL16: 0.00 | AM16: 中通速递 | AN16: 73569429601749 | AV16: 2025-08-15 22:07:26 | AY16: 2025-08-30 22:07:36 | AZ16: 2025-08-24 21:24:18 | BA16: 2025-08-27 16:15:17 | BB16: 第三方平台卖家电子库存 | BC16: 用户确认收货 | BD16: 否 | BI16: LAO BAN ZHOU的店 | BJ16: 5b219a89e8ac2b2d65a2a890 | BK16: 公司店运费模版 | BL16: 小红书公司 | BQ16: Z1576-黑色-M | BR16: 6896fe48057f570015d29241 | BS16: 【老板周】时髦撞色 春季新款假两件显瘦长袖打底T恤上衣
A17: P770817653033321541 | B17: 已关闭 | C17: 售后完成 | D17: 预售订单 | F17: 铁 | G17: 188****9286 | H17: 浙江省 绍兴市 诸暨市 *** | I17: 浙江省 | J17: 绍兴市 | K17: 诸暨市 | L17: 330681005000 | M17: 6896fe67c165480015b3eb01 | N17: XHS-2Z4TJTXW55OG | O17: 6896fe67c165480015b3eb00 | R17: 【老板周】舒适休闲 极简短版腰头抽绳设计宽松半身裙 黑色 S（80-100斤） | S17: 黑色 S（80-100斤） | T17: 1 | W17: 189.00 | X17: 189.00 | Y17: 0.00 | Z17: 0.00 | AB17: 0.00 | AC17: 189.00 | AD17: 支付宝 | AE17: 2025081522001420121433136963 | AI17: 2025-08-15 21:48:31 | AK17: 0.000 | AL17: 0.00 | AM17: 中通速递 | AN17: 73569255709053 | AV17: 2025-08-15 21:47:33 | AY17: 2025-08-30 21:48:31 | AZ17: 2025-08-23 17:27:48 | BB17: 第三方平台卖家电子库存 | BD17: 否 | BF17: 蓝旗 | BG17: ;78934215260877(收） Z1645-黑色-S*1# | BI17: LAO BAN ZHOU的店 | BJ17: 5b5c85dbe8ac2b5d1dc7f406 | BK17: 公司店运费模版 | BL17: 小红书公司 | BQ17: Z1645-黑色-S | BR17: 6896fe67c165480015b3eaff | BS17: 【老板周】舒适休闲 极简短版腰头抽绳设计宽松半身裙
A18: P770815073365177321 | B18: 已关闭 | C18: 售后完成 | D18: 预售订单 | F18: 朱** | G18: 133****6756 | H18: 江苏省 常州市 钟楼区 *** | I18: 江苏省 | J18: 常州市 | K18: 钟楼区 | L18: 320404002 | M18: 689dee45c34eef00157e1208 | N18: XHS-3JY8RM3UZL6O | O18: 689dee45c34eef00157e1207 | P18: 650d6e9f000000001603a6ac | Q18: 老板周. | R18: 【老板周】小众日系 秋冬叠穿时髦下摆不规则宽松马甲 灰色 S（80-100斤） | S18: 灰色 S（80-100斤） | T18: 1 | W18: 179.00 | X18: 179.00 | Y18: 0.00 | Z18: 0.00 | AB18: 0.00 | AC18: 179.00 | AD18: 微信 | AE18: 4347802469202508151936939245 | AI18: 2025-08-15 21:04:40 | AK18: 0.000 | AL18: 0.00 | AM18: 中通速递 | AN18: 73569144709848 | AV18: 2025-08-15 21:04:33 | AY18: 2025-08-30 21:04:40 | AZ18: 2025-08-22 21:16:10 | BB18: 第三方平台卖家电子库存 | BD18: 否 | BF18: 蓝旗 | BG18: ;JDX042510841197(收） Z2378-灰色-S*1# | BI18: LAO BAN ZHOU的店 | BJ18: 5ae3fc4211be1062fa142bc7 | BK18: 公司店运费模版 | BL18: 小红书公司 | BQ18: Z2378-灰色-S | BR18: 689dee45c34eef00157e11fa | BS18: 【老板周】小众日系 秋冬叠穿时髦下摆不规则宽松马甲
A19: P770813889954234671 | B19: 已关闭 | C19: 售后完成 | D19: 预售订单 | F19: 仇** | G19: 139****2227 | H19: 天津 天津市 滨海新区 *** | I19: 天津 | J19: 天津市 | K19: 滨海新区 | L19: 120116 | M19: 689dee5baa1e7b00156ae7bd | N19: XHS-3JY9LAG0S9OG | O19: 689dee5baa1e7b00156ae7bc | P19: 650d6e9f000000001603a6ac | Q19: 老板周. | R19: LAO BAN ZHOU 【老板周】极简主义 秋冬新款复古卷边前短后长针织上衣 黑色 S（80-100斤） | S19: 黑色 S（80-100斤） | T19: 1 | W19: 219.00 | X19: 219.00 | Y19: 0.00 | Z19: 0.00 | AB19: 0.00 | AC19: 219.00 | AD19: 支付宝 | AE19: 2025081522001400711430980476 | AI19: 2025-08-15 20:44:57 | AK19: 0.000 | AL19: 0.00 | AM19: 中通速递 | AN19: 73569144710903 | AV19: 2025-08-15 20:44:50 | AY19: 2025-08-30 20:44:57 | AZ19: 2025-08-22 21:11:54 | BB19: 第三方平台卖家电子库存 | BD19: 否 | BF19: 蓝旗 | BG19: ;JDX042517220056(收） Z2365-黑色-S*1# | BI19: LAO BAN ZHOU的店 | BJ19: 5dac2bc6000000000100347a | BK19: 公司店运费模版 | BL19: 小红书公司 | BQ19: Z2365-黑色-S | BR19: 689dee5baa1e7b00156ae7bb | BS19: 【老板周】极简主义 秋冬新款复古卷边前短后长针织上衣
A20: P770811839659457301 | B20: 已完成 | C20: 无售后 | D20: 预售订单 | F20: 赵** | G20: 138****7478 | H20: 广东省 佛山市 顺德区 *** | I20: 广东省 | J20: 佛山市 | K20: 顺德区 | L20: 440606006000 | M20: 689dee541ea4cb00155e6f97 | N20: XHS-3JY9BQCVPTDS | O20: 689dee541ea4cb00155e6f96 | P20: 650d6e9f000000001603a6ac | Q20: 老板周. | R20: LAO BAN ZHOU 【老板周】百搭气质 秋冬新款百搭造型感气质三角巾 藏青色 | S20: 藏青色 | T20: 1 | W20: 199.00 | X20: 199.00 | Y20: 0.00 | Z20: 0.00 | AB20: 0.00 | AC20: 199.00 | AD20: 微信 | AE20: 4350102250202508157176301480 | AI20: 2025-08-15 20:10:46 | AK20: 0.000 | AL20: 0.00 | AM20: 中通速递 | AN20: 73569424315508 | AV20: 2025-08-15 20:10:39 | AY20: 2025-08-30 20:10:46 | AZ20: 2025-08-24 20:19:50 | BA20: 2025-08-26 22:28:56 | BB20: 第三方平台卖家电子库存 | BC20: 用户确认收货 | BD20: 否 | BI20: LAO BAN ZHOU的店 | BJ20: 6290506300000000210294b2 | BK20: 公司店运费模版 | BL20: 小红书公司 | BQ20: Z2380-藏青色 | BR20: 689dee541ea4cb00155e6f93 | BS20: 【老板周】百搭气质 秋冬新款百搭造型感气质三角巾
A21: P770809432946213601 | B21: 已关闭 | C21: 售后完成 | D21: 预售订单 | F21: 王* | G21: 180****1869 | H21: 安徽省 合肥市 蜀山区 *** | I21: 安徽省 | J21: 合肥市 | K21: 蜀山区 | L21: 340104 | M21: 689dee5baa1e7b00156ae7c3 | N21: XHS-3JY9LAGFRNR4 | O21: 689dee5baa1e7b00156ae7c2 | P21: 650d6e9f000000001603a6ac | Q21: 老板周. | R21: LAO BAN ZHOU 【老板周】极简主义 秋冬新款复古卷边前短后长针织上衣 灰色 M（100-135斤） | S21: 灰色 M（100-135斤） | T21: 1 | W21: 219.00 | X21: 219.00 | Y21: 0.00 | Z21: 0.00 | AB21: 0.00 | AC21: 219.00 | AD21: 微信 | AE21: 4326602241202508159115746828 | AI21: 2025-08-15 19:30:40 | AK21: 0.000 | AL21: 0.00 | AM21: 中通速递 | AN21: 73568592670460 | AV21: 2025-08-15 19:30:33 | AY21: 2025-08-30 19:30:40 | AZ21: 2025-08-18 22:35:44 | BA21: 2025-08-25 22:35:44 | BB21: 第三方平台卖家电子库存 | BC21: 系统自动收货 | BD21: 否 | BF21: 蓝旗 | BG21: ;JDX042534359284(收） Z2365-灰色-M*1# | BI21: LAO BAN ZHOU的店 | BJ21: 5b15fe3ff7e8b96ea4ab300b | BK21: 公司店运费模版 | BL21: 小红书公司 | BQ21: Z2365-灰色-M | BR21: 689dee5baa1e7b00156ae7bb | BS21: 【老板周】极简主义 秋冬新款复古卷边前短后长针织上衣
A22: P770807071130358401 | B22: 已完成 | C22: 无售后 | D22: 预售订单 | F22: 邹* | G22: 182****1061 | H22: 江苏省 南京市 建邺区 *** | I22: 江苏省 | J22: 南京市 | K22: 建邺区 | L22: 320105001000 | M22: 689dee541ea4cb00155e6f95 | N22: XHS-3JY9BQCQQ0OW | O22: 689dee541ea4cb00155e6f94 | P22: 650d6e9f000000001603a6ac | Q22: 老板周. | R22: 【老板周】百搭气质 秋冬新款百搭造型感气质三角巾 黑色 | S22: 黑色 | T22: 1 | W22: 199.00 | X22: 199.00 | Y22: 0.00 | Z22: 0.00 | AB22: 0.00 | AC22: 199.00 | AD22: 微信 | AE22: 4327402459202508152067557130 | AI22: 2025-08-15 18:51:19 | AK22: 0.000 | AL22: 0.00 | AM22: 中通速递 | AN22: 73568735152201 | AV22: 2025-08-15 18:51:11 | AY22: 2025-08-30 18:51:19 | AZ22: 2025-08-19 23:52:01 | BA22: 2025-08-26 23:52:01 | BB22: 第三方平台卖家电子库存 | BC22: 系统自动收货 | BD22: 否 | BI22: LAO BAN ZHOU的店 | BJ22: 64a58eea000000001003691c | BK22: 公司店运费模版 | BL22: 小红书公司 | BQ22: Z2380-黑色 | BR22: 689dee541ea4cb00155e6f93 | BS22: 【老板周】百搭气质 秋冬新款百搭造型感气质三角巾
A23: P770802455479324851 | B23: 已完成 | C23: 无售后 | D23: 预售订单 | F23: 童 | G23: 186****5600 | H23: 浙江省 杭州市 萧山区 *** | I23: 浙江省 | J23: 杭州市 | K23: 萧山区 | L23: 330109110 | M23: XHS-3JFVUELM3W8W | N23: XHS-3JFVUELM3W8W | O23: 689720eeb6005400015a679b | P23: 650d6e9f000000001603a6ac | Q23: 老板周. | R23: 【老板周】气质经典 秋冬无缝一体半高领显瘦打底针织 黑色 L（100-120斤） | S23: 黑色 L（100-120斤） | T23: 1 | W23: 219.00 | X23: 219.00 | Y23: 0.00 | Z23: 0.00 | AB23: 0.00 | AC23: 219.00 | AD23: 微信 | AE23: 4329902477202508151518076766 | AI23: 2025-08-15 17:34:25 | AK23: 0.000 | AL23: 0.00 | AM23: 中通速递 | AN23: 73569144711713 | AV23: 2025-08-15 17:34:15 | AY23: 2025-08-30 17:34:25 | AZ23: 2025-08-22 20:56:19 | BA23: 2025-08-27 08:17:40 | BB23: 第三方平台卖家电子库存 | BC23: 用户确认收货 | BD23: 否 | BI23: LAO BAN ZHOU的店 | BJ23: 5d6148d8000000000100aeb9 | BK23: 公司店运费模版 | BL23: 小红书公司 | BQ23: Z2351-黑色-L | BR23: 689720eeb6005400015a6797 | BS23: 【老板周】气质经典 秋冬无缝一体半高领显瘦打底针织
A24: P770802417453059131 | B24: 已完成 | C24: 无售后 | D24: 预售订单 | F24: 党* | G24: 139****6606 | H24: 新疆维吾尔自治区 乌鲁木齐市 天山区 *** | I24: 新疆维吾尔自治区 | J24: 乌鲁木齐市 | K24: 天山区 | L24: 650102012 | M24: XHS-3JFVUELM3W8W | N24: XHS-3JFVUELM3W8W | O24: 689720eeb6005400015a679b | P24: 650d6e9f000000001603a6ac | Q24: 老板周. | R24: 【老板周】气质经典 秋冬无缝一体半高领显瘦打底针织 黑色 L（100-120斤） | S24: 黑色 L（100-120斤） | T24: 1 | W24: 219.00 | X24: 229.00 | Y24: 0.00 | Z24: 0.00 | AB24: 0.00 | AC24: 229.00 | AD24: 支付宝 | AE24: 2025081522001452271435125494 | AI24: 2025-08-15 17:35:16 | AK24: 0.000 | AL24: 10.00 | AM24: 中通速递 | AN24: 73569144711826 | AV24: 2025-08-15 17:33:37 | AY24: 2025-08-30 17:35:16 | AZ24: 2025-08-22 20:56:19 | BA24: 2025-08-26 22:26:55 | BB24: 第三方平台卖家电子库存 | BC24: 用户确认收货 | BD24: 否 | BI24: LAO BAN ZHOU的店 | BJ24: 5a221f7fdb2e6047a150b1e7 | BK24: 公司店运费模版 | BL24: 小红书公司 | BQ24: Z2351-黑色-L | BR24: 689720eeb6005400015a6797 | BS24: 【老板周】气质经典 秋冬无缝一体半高领显瘦打底针织
A25: P770801203180185471 | B25: 已完成 | C25: 无售后 | D25: 预售订单 | F25: 四*** | G25: 181****6065 | H25: 广东省 深圳市 宝安区 *** | I25: 广东省 | J25: 深圳市 | K25: 宝安区 | L25: 440306021000 | M25: 689dee65ae962f0015895c5e | N25: XHS-3JY9YVCTEBR4 | O25: 689dee65ae962f0015895c5d | P25: 650d6e9f000000001603a6ac | Q25: 老板周. | R25: LAO BAN ZHOU 【老板周】复古休闲 秋冬细腻柔软连帽单排扣针织上衣 灰色 S（80-100斤） | S25: 灰色 S（80-100斤） | T25: 1 | W25: 299.00 | X25: 299.00 | Y25: 0.00 | Z25: 0.00 | AB25: 0.00 | AC25: 299.00 | AD25: 支付宝 | AE25: 2025081523001435931400346554 | AI25: 2025-08-15 17:13:32 | AK25: 0.000 | AL25: 0.00 | AM25: 中通速递 | AN25: 73568731901762 | AV25: 2025-08-15 17:13:23 | AY25: 2025-08-30 17:13:32 | AZ25: 2025-08-19 22:39:49 | BA25: 2025-08-26 22:39:49 | BB25: 第三方平台卖家电子库存 | BC25: 系统自动收货 | BD25: 否 | BI25: LAO BAN ZHOU的店 | BJ25: 5c37daa6000000000502f411 | BK25: 公司店运费模版 | BL25: 小红书公司 | BQ25: Z2366-灰色-S | BR25: 689dee65ae962f0015895c58 | BS25: 【老板周】复古休闲 秋冬细腻柔软连帽单排扣针织上衣
A26: P770800342402378981 | B26: 已完成 | C26: 无售后 | D26: 预售订单 | F26: 法******** | G26: 183****4792 | H26: 广东省 惠州市 惠阳区 *** | I26: 广东省 | J26: 惠州市 | K26: 惠阳区 | L26: 441303008000 | M26: 689dee335cb635001516ec70 | N26: XHS-3JY7U8WB1P1C | O26: 689dee335cb635001516ec6f | P26: 650d6e9f000000001603a6ac | Q26: 老板周. | R26: LAO BAN ZHOU 【老板周】复古调性 秋冬新款百搭松紧腰分割线廓形九分裤 深藏青色 L（110-125斤） | S26: 深藏青色 L（110-125斤） | T26: 1 | W26: 299.00 | X26: 299.00 | Y26: 0.00 | Z26: 0.00 | AB26: 0.00 | AC26: 299.00 | AD26: 支付宝 | AE26: 2025081522001412281457345278 | AI26: 2025-08-15 16:59:08 | AK26: 0.000 | AL26: 0.00 | AM26: 中通速递 | AN26: 73568735152148 | AV26: 2025-08-15 16:59:02 | AY26: 2025-08-30 16:59:08 | AZ26: 2025-08-19 23:53:31 | BA26: 2025-08-26 23:53:32 | BB26: 第三方平台卖家电子库存 | BC26: 系统自动收货 | BD26: 否 | BI26: LAO BAN ZHOU的店 | BJ26: 5d0a54ca0000000011027781 | BK26: 公司店运费模版 | BL26: 小红书公司 | BQ26: Z2375-深藏青色-L | BR26: 689dee335cb635001516ec6a | BS26: 【老板周】复古调性 秋冬新款百搭松紧腰分割线廓形九分裤
A27: P770800341884471531 | B27: 已完成 | C27: 无售后 | D27: 预售订单 | F27: 飛* | G27: 189****4299 | H27: 福建省 厦门市 思明区 *** | I27: 福建省 | J27: 厦门市 | K27: 思明区 | L27: 350203008 | M27: 689dee335cb635001516ec72 | N27: XHS-3JY7U8WG1HQ8 | O27: 689dee335cb635001516ec71 | P27: 650d6e9f000000001603a6ac | Q27: 老板周. | R27: LAO BAN ZHOU 【老板周】复古调性 秋冬新款百搭松紧腰分割线廓形九分裤 深藏青色 XL（125-140斤） | S27: 深藏青色 XL（125-140斤） | T27: 1 | W27: 299.00 | X27: 299.00 | Y27: 0.00 | Z27: 0.00 | AB27: 0.00 | AC27: 299.00 | AD27: 支付宝 | AE27: 2025081522001420281447898668 | AI27: 2025-08-15 16:59:17 | AK27: 0.000 | AL27: 0.00 | AM27: 中通速递 | AN27: 73568735151749 | AV27: 2025-08-15 16:59:02 | AY27: 2025-08-30 16:59:17 | AZ27: 2025-08-19 23:50:59 | BA27: 2025-08-26 23:51:00 | BB27: 第三方平台卖家电子库存 | BC27: 系统自动收货 | BD27: 否 | BI27: LAO BAN ZHOU的店 | BJ27: 5b56f65411be1079cb320859 | BK27: 公司店运费模版 | BL27: 小红书公司 | BQ27: Z2375-黑色-XL | BR27: 689dee335cb635001516ec6a | BS27: 【老板周】复古调性 秋冬新款百搭松紧腰分割线廓形九分裤
A28: P770800349964423951 | B28: 已完成 | C28: 无售后 | D28: 预售订单 | F28: 洛********** | G28: 138****7815 | H28: 上海 上海市 松江区 *** | I28: 上海 | J28: 上海市 | K28: 松江区 | L28: 310117102 | M28: 689dee335cb635001516ec70 | N28: XHS-3JY7U8WB1P1C | O28: 689dee335cb635001516ec6f | P28: 650d6e9f000000001603a6ac | Q28: 老板周. | R28: LAO BAN ZHOU 【老板周】复古调性 秋冬新款百搭松紧腰分割线廓形九分裤 深藏青色 L（110-125斤） | S28: 深藏青色 L（110-125斤） | T28: 1 | W28: 299.00 | X28: 299.00 | Y28: 0.00 | Z28: 0.00 | AB28: 0.00 | AC28: 299.00 | AD28: 微信 | AE28: 4331702257202508151255946117 | AI28: 2025-08-15 16:59:17 | AK28: 0.000 | AL28: 0.00 | AM28: 中通速递 | AN28: 73568735152467 | AV28: 2025-08-15 16:59:10 | AY28: 2025-08-30 16:59:17 | AZ28: 2025-08-19 23:53:31 | BA28: 2025-08-26 23:53:32 | BB28: 第三方平台卖家电子库存 | BC28: 系统自动收货 | BD28: 否 | BI28: LAO BAN ZHOU的店 | BJ28: 59c7427f51783a624bf0c129 | BK28: 公司店运费模版 | BL28: 小红书公司 | BQ28: Z2375-深藏青色-L | BR28: 689dee335cb635001516ec6a | BS28: 【老板周】复古调性 秋冬新款百搭松紧腰分割线廓形九分裤
A29: P770800340656114071 | B29: 已完成 | C29: 无售后 | D29: 预售订单 | F29: 天******** | G29: 151****5145 | H29: 上海 上海市 青浦区 *** | I29: 上海 | J29: 上海市 | K29: 青浦区 | L29: 310118110 | M29: 689dee335cb635001516ec76 | N29: XHS-3JY7U8WQ1340 | O29: 689dee335cb635001516ec75 | P29: 650d6e9f000000001603a6ac | Q29: 老板周. | R29: LAO BAN ZHOU 【老板周】复古调性 秋冬新款百搭松紧腰分割线廓形九分裤 杏色 M（95-110斤） | S29: 杏色 M（95-110斤） | T29: 1 | W29: 299.00 | X29: 299.00 | Y29: 0.00 | Z29: 0.00 | AB29: 0.00 | AC29: 299.00 | AD29: 支付宝 | AE29: 2025081522001407191429949693 | AI29: 2025-08-15 16:59:07 | AK29: 0.000 | AL29: 0.00 | AM29: 中通速递 | AN29: 73568735151897 | AV29: 2025-08-15 16:59:00 | AY29: 2025-08-30 16:59:07 | AZ29: 2025-08-19 23:51:25 | BA29: 2025-08-26 23:51:25 | BB29: 第三方平台卖家电子库存 | BC29: 系统自动收货 | BD29: 否 | BI29: LAO BAN ZHOU的店 | BJ29: 5cf2ea8a0000000012014485 | BK29: 公司店运费模版 | BL29: 小红书公司 | BQ29: Z2375-杏色-M | BR29: 689dee335cb635001516ec6a | BS29: 【老板周】复古调性 秋冬新款百搭松紧腰分割线廓形九分裤
A30: P770800341731245681 | B30: 已完成 | C30: 无售后 | D30: 预售订单 | F30: 娜* | G30: 186****6007 | H30: 浙江省 宁波市 海曙区 *** | I30: 浙江省 | J30: 宁波市 | K30: 海曙区 | L30: 330203008 | M30: 689dee335cb635001516ec6e | N30: XHS-3JY7U8W8JSOW | O30: 689dee335cb635001516ec6d | P30: 650d6e9f000000001603a6ac | Q30: 老板周. | R30: LAO BAN ZHOU 【老板周】复古调性 秋冬新款百搭松紧腰分割线廓形九分裤 深藏青色 M（95-110斤） | S30: 深藏青色 M（95-110斤） | T30: 1 | W30: 299.00 | X30: 299.00 | Y30: 0.00 | Z30: 0.00 | AB30: 0.00 | AC30: 299.00 | AD30: 支付宝 | AE30: 2025081522001404551429034447 | AI30: 2025-08-15 16:59:10 | AK30: 0.000 | AL30: 0.00 | AM30: 中通速递 | AN30: 73568735152189 | AV30: 2025-08-15 16:59:01 | AY30: 2025-08-30 16:59:10 | AZ30: 2025-08-19 23:54:36 | BA30: 2025-08-26 23:54:36 | BB30: 第三方平台卖家电子库存 | BC30: 系统自动收货 | BD30: 否 | BI30: LAO BAN ZHOU的店 | BJ30: 575f9c7982ec395b0b158782 | BK30: 公司店运费模版 | BL30: 小红书公司 | BQ30: Z2375-深藏青色-M | BR30: 689dee335cb635001516ec6a | BS30: 【老板周】复古调性 秋冬新款百搭松紧腰分割线廓形九分裤
A31: P770800350927090411 | B31: 已完成 | C31: 无售后 | D31: 预售订单 | F31: 朱** | G31: 138****2102 | H31: 安徽省 宣城市 宣州区 *** | I31: 安徽省 | J31: 宣城市 | K31: 宣州区 | L31: 341802002 | M31: 689dee335cb635001516ec6e | N31: XHS-3JY7U8W8JSOW | O31: 689dee335cb635001516ec6d | P31: 650d6e9f000000001603a6ac | Q31: 老板周. | R31: LAO BAN ZHOU 【老板周】复古调性 秋冬新款百搭松紧腰分割线廓形九分裤 深藏青色 M（95-110斤） | S31: 深藏青色 M（95-110斤） | T31: 1 | W31: 299.00 | X31: 299.00 | Y31: 0.00 | Z31: 0.00 | AB31: 0.00 | AC31: 299.00 | AD31: 微信 | AE31: 4334302258202508158131147276 | AI31: 2025-08-15 16:59:15 | AK31: 0.000 | AL31: 0.00 | AM31: 中通速递 | AN31: 73568735152388 | AV31: 2025-08-15 16:59:11 | AY31: 2025-08-30 16:59:15 | AZ31: 2025-08-19 23:54:36 | BA31: 2025-08-26 23:54:36 | BB31: 第三方平台卖家电子库存 | BC31: 系统自动收货 | BD31: 否 | BI31: LAO BAN ZHOU的店 | BJ31: 57f103df50c4b44080876d63 | BK31: 公司店运费模版 | BL31: 小红书公司 | BQ31: Z2375-深藏青色-M | BR31: 689dee335cb635001516ec6a | BS31: 【老板周】复古调性 秋冬新款百搭松紧腰分割线廓形九分裤
A32: P770800347247449271 | B32: 已完成 | C32: 无售后 | D32: 预售订单 | F32: 1**** | G32: 186****0711 | H32: 广东省 深圳市 宝安区 *** | I32: 广东省 | J32: 深圳市 | K32: 宝安区 | L32: 440306003 | M32: 689dee335cb635001516ec6e | N32: XHS-3JY7U8W8JSOW | O32: 689dee335cb635001516ec6d | P32: 650d6e9f000000001603a6ac | Q32: 老板周. | R32: LAO BAN ZHOU 【老板周】复古调性 秋冬新款百搭松紧腰分割线廓形九分裤 深藏青色 M（95-110斤） | S32: 深藏青色 M（95-110斤） | T32: 1 | W32: 299.00 | X32: 299.00 | Y32: 0.00 | Z32: 0.00 | AB32: 0.00 | AC32: 299.00 | AD32: 微信先用后付 | AI32: 2025-08-15 16:59:08 | AK32: 0.000 | AL32: 0.00 | AM32: 中通速递 | AN32: 73568735152069 | AV32: 2025-08-15 16:59:07 | AY32: 2025-08-30 16:59:08 | AZ32: 2025-08-19 23:54:36 | BA32: 2025-08-26 23:54:36 | BB32: 第三方平台卖家电子库存 | BC32: 系统自动收货 | BD32: 否 | BI32: LAO BAN ZHOU的店 | BJ32: 5bd8468373bdbf0001982456 | BK32: 公司店运费模版 | BL32: 小红书公司 | BQ32: Z2375-深藏青色-M | BR32: 689dee335cb635001516ec6a | BS32: 【老板周】复古调性 秋冬新款百搭松紧腰分割线廓形九分裤
A33: P770800356297378821 | B33: 已完成 | C33: 无售后 | D33: 预售订单 | F33: 法******** | G33: 183****4792 | H33: 广东省 惠州市 惠阳区 *** | I33: 广东省 | J33: 惠州市 | K33: 惠阳区 | L33: 441303008000 | M33: 689dee335cb635001516ec78 | N33: XHS-3JY7U8WV0VSW | O33: 689dee335cb635001516ec77 | P33: 650d6e9f000000001603a6ac | Q33: 老板周. | R33: LAO BAN ZHOU 【老板周】复古调性 秋冬新款百搭松紧腰分割线廓形九分裤 杏色 L（110-125斤） | S33: 杏色 L（110-125斤） | T33: 1 | W33: 299.00 | X33: 299.00 | Y33: 0.00 | Z33: 0.00 | AB33: 0.00 | AC33: 299.00 | AD33: 支付宝 | AE33: 2025081523001412281458634745 | AI33: 2025-08-15 16:59:22 | AK33: 0.000 | AL33: 0.00 | AM33: 中通速递 | AN33: 73568735151922 | AV33: 2025-08-15 16:59:16 | AY33: 2025-08-30 16:59:22 | AZ33: 2025-08-19 23:55:20 | BA33: 2025-08-26 23:55:20 | BB33: 第三方平台卖家电子库存 | BC33: 系统自动收货 | BD33: 否 | BI33: LAO BAN ZHOU的店 | BJ33: 5d0a54ca0000000011027781 | BK33: 公司店运费模版 | BL33: 小红书公司 | BQ33: Z2375-杏色-L | BR33: 689dee335cb635001516ec6a | BS33: 【老板周】复古调性 秋冬新款百搭松紧腰分割线廓形九分裤
A34: P770799979667284611 | B34: 已关闭 | C34: 售后完成 | D34: 预售订单 | F34: 何 | G34: 135****0291 | H34: 湖南省 长沙市 岳麓区 *** | I34: 湖南省 | J34: 长沙市 | K34: 岳麓区 | L34: 430104005 | M34: 689dee541ea4cb00155e6f97 | N34: XHS-3JY9BQCVPTDS | O34: 689dee541ea4cb00155e6f96 | P34: 650d6e9f000000001603a6ac | Q34: 老板周. | R34: LAO BAN ZHOU 【老板周】百搭气质 秋冬新款百搭造型感气质三角巾 藏青色 | S34: 藏青色 | T34: 1 | W34: 199.00 | X34: 199.00 | Y34: 0.00 | Z34: 0.00 | AB34: 0.00 | AC34: 199.00 | AD34: 支付宝 | AE34: 2025081522001457781456515826 | AI34: 2025-08-15 16:53:07 | AK34: 0.000 | AL34: 0.00 | AM34: 中通速递 | AN34: 73568592670776 | AV34: 2025-08-15 16:52:59 | AY34: 2025-08-30 16:53:07 | AZ34: 2025-08-18 22:30:28 | BA34: 2025-08-25 22:30:29 | BB34: 第三方平台卖家电子库存 | BC34: 系统自动收货 | BD34: 否 | BF34: 蓝旗 | BG34: ;SF3289575962710(收） Z2380-藏青色*1# | BI34: LAO BAN ZHOU的店 | BJ34: 5c1a271e000000000703e641 | BK34: 公司店运费模版 | BL34: 小红书公司 | BQ34: Z2380-藏青色 | BR34: 689dee541ea4cb00155e6f93 | BS34: 【老板周】百搭气质 秋冬新款百搭造型感气质三角巾
A35: P770800038248138451 | B35: 已关闭 | C35: 售后完成 | D35: 预售订单 | F35: l** | G35: 183****6177 | H35: 四川省 绵阳市 涪城区 *** | I35: 四川省 | J35: 绵阳市 | K35: 涪城区 | L35: 510703 | M35: 689dee541ea4cb00155e6f95 | N35: XHS-3JY9BQCQQ0OW | O35: 689dee541ea4cb00155e6f94 | P35: 650d6e9f000000001603a6ac | Q35: 老板周. | R35: 【老板周】百搭气质 秋冬新款百搭造型感气质三角巾 黑色 | S35: 黑色 | T35: 1 | W35: 199.00 | X35: 199.00 | Y35: 0.00 | Z35: 0.00 | AB35: 0.00 | AC35: 199.00 | AD35: 微信 | AE35: 4309702285202508159958080728 | AI35: 2025-08-15 16:54:04 | AK35: 0.000 | AL35: 0.00 | AM35: 中通速递 | AN35: 73568592688365 | AV35: 2025-08-15 16:53:58 | AY35: 2025-08-30 16:54:04 | AZ35: 2025-08-18 22:31:19 | BA35: 2025-08-25 22:31:19 | BB35: 第三方平台卖家电子库存 | BC35: 系统自动收货 | BD35: 否 | BF35: 蓝旗 | BG35: ;SF3289877149275(收） Z2380-藏青色*1 Z2380-黑色*1# | BI35: LAO BAN ZHOU的店 | BJ35: 6067c578000000000100a225 | BK35: 公司店运费模版 | BL35: 小红书公司 | BQ35: Z2380-黑色 | BR35: 689dee541ea4cb00155e6f93 | BS35: 【老板周】百搭气质 秋冬新款百搭造型感气质三角巾
A36: P770800038248138451 | B36: 已关闭 | C36: 售后完成 | D36: 预售订单 | F36: l** | G36: 183****6177 | H36: 四川省 绵阳市 涪城区 *** | I36: 四川省 | J36: 绵阳市 | K36: 涪城区 | L36: 510703 | M36: 689dee541ea4cb00155e6f97 | N36: XHS-3JY9BQCVPTDS | O36: 689dee541ea4cb00155e6f96 | P36: 650d6e9f000000001603a6ac | Q36: 老板周. | R36: LAO BAN ZHOU 【老板周】百搭气质 秋冬新款百搭造型感气质三角巾 藏青色 | S36: 藏青色 | T36: 1 | W36: 199.00 | X36: 199.00 | Y36: 0.00 | Z36: 0.00 | AB36: 0.00 | AC36: 199.00 | AD36: 微信 | AE36: 4309702285202508159958080728 | AI36: 2025-08-15 16:54:04 | AK36: 0.000 | AL36: 0.00 | AM36: 中通速递 | AN36: 73568864925966 | AV36: 2025-08-15 16:53:58 | AY36: 2025-08-30 16:54:04 | AZ36: 2025-08-20 20:48:44 | BB36: 第三方平台卖家电子库存 | BD36: 否 | BF36: 蓝旗 | BG36: ;SF3289877149275(收） Z2380-藏青色*1 Z2380-黑色*1# | BI36: LAO BAN ZHOU的店 | BJ36: 6067c578000000000100a225 | BK36: 公司店运费模版 | BL36: 小红书公司 | BQ36: Z2380-藏青色 | BR36: 689dee541ea4cb00155e6f93 | BS36: 【老板周】百搭气质 秋冬新款百搭造型感气质三角巾
A37: P770799964547510201 | B37: 已完成 | C37: 售后完成 | D37: 预售订单 | F37: 段** | G37: 136****6258 | H37: 福建省 三明市 三元区 *** | I37: 福建省 | J37: 三明市 | K37: 三元区 | L37: 350403001 | M37: 689dee541ea4cb00155e6f95 | N37: XHS-3JY9BQCQQ0OW | O37: 689dee541ea4cb00155e6f94 | P37: 650d6e9f000000001603a6ac | Q37: 老板周. | R37: 【老板周】百搭气质 秋冬新款百搭造型感气质三角巾 黑色 | S37: 黑色 | T37: 1 | W37: 199.00 | X37: 199.00 | Y37: 0.00 | Z37: 0.00 | AB37: 0.00 | AC37: 199.00 | AD37: 支付宝 | AE37: 2025081522001439961455318841 | AI37: 2025-08-15 16:52:50 | AK37: 0.000 | AL37: 0.00 | AM37: 中通速递 | AN37: 73568592670842 | AV37: 2025-08-15 16:52:44 | AY37: 2025-08-30 16:52:50 | AZ37: 2025-08-18 22:31:19 | BA37: 2025-08-25 22:31:19 | BB37: 第三方平台卖家电子库存 | BC37: 系统自动收货 | BD37: 否 | BF37: 蓝旗 | BG37: ;SF3230365475335(收） Z2380-黑色*1# | BI37: LAO BAN ZHOU的店 | BJ37: 5bed014017885e0001f01556 | BK37: 公司店运费模版 | BL37: 小红书公司 | BQ37: Z2380-黑色 | BR37: 689dee541ea4cb00155e6f93 | BS37: 【老板周】百搭气质 秋冬新款百搭造型感气质三角巾
A38: P770798353781374661 | B38: 已关闭 | C38: 售后完成 | D38: 预售订单 | F38: 曹** | G38: 187****3097 | H38: 安徽省 合肥市 蜀山区 *** | I38: 安徽省 | J38: 合肥市 | K38: 蜀山区 | L38: 340104 | M38: 689dee45c34eef00157e1208 | N38: XHS-3JY8RM3UZL6O | O38: 689dee45c34eef00157e1207 | P38: 650d6e9f000000001603a6ac | Q38: 老板周. | R38: 【老板周】小众日系 秋冬叠穿时髦下摆不规则宽松马甲 灰色 S（80-100斤） | S38: 灰色 S（80-100斤） | T38: 1 | W38: 179.00 | X38: 179.00 | Y38: 0.00 | Z38: 0.00 | AB38: 0.00 | AC38: 179.00 | AD38: 微信 | AE38: 4316902246202508157348165609 | AI38: 2025-08-15 16:26:01 | AK38: 0.000 | AL38: 0.00 | AM38: 中通速递 | AN38: 73568735151828 | AV38: 2025-08-15 16:25:54 | AY38: 2025-08-30 16:26:01 | AZ38: 2025-08-19 23:36:17 | BA38: 2025-08-26 23:36:18 | BB38: 第三方平台卖家电子库存 | BC38: 系统自动收货 | BD38: 否 | BF38: 蓝旗 | BG38: ;JDX042487675994(收） Z2378-灰色-S*1# | BI38: LAO BAN ZHOU的店 | BJ38: 5a03262d4eacab7812d21919 | BK38: 公司店运费模版 | BL38: 小红书公司 | BQ38: Z2378-灰色-S | BR38: 689dee45c34eef00157e11fa | BS38: 【老板周】小众日系 秋冬叠穿时髦下摆不规则宽松马甲
A39: P770798387983284011 | B39: 已关闭 | C39: 售后完成 | D39: 预售订单 | F39: 何 | G39: 135****0291 | H39: 湖南省 长沙市 岳麓区 *** | I39: 湖南省 | J39: 长沙市 | K39: 岳麓区 | L39: 430104005 | M39: 689d92c8956aac0015f36639 | N39: XHS-2PMHDZ8YH728 | O39: 689d92c8956aac0015f36638 | P39: 650d6e9f000000001603a6ac | Q39: 老板周. | R39: 【老板周】舒适经典 新款柔软细腻无缝一体半高领打底衫 黑色 M（100-120斤） | S39: 黑色 M（100-120斤） | T39: 1 | W39: 199.00 | X39: 199.00 | Y39: 0.00 | Z39: 0.00 | AB39: 0.00 | AC39: 199.00 | AD39: 支付宝 | AE39: 2025081522001457781454758034 | AI39: 2025-08-15 16:26:34 | AK39: 0.000 | AL39: 0.00 | AM39: 中通速递 | AN39: 73568864925675 | AV39: 2025-08-15 16:26:28 | AY39: 2025-08-30 16:26:34 | AZ39: 2025-08-20 20:38:35 | BB39: 第三方平台卖家电子库存 | BD39: 否 | BF39: 蓝旗 | BG39: ;SF3289575962710(收） Z1248-黑色-M*1# | BI39: LAO BAN ZHOU的店 | BJ39: 5c1a271e000000000703e641 | BK39: 公司店运费模版 | BL39: 小红书公司 | BQ39: Z1248-黑色-M | BR39: 689d92c8956aac0015f3662f | BS39: 【老板周】舒适经典 新款柔软细腻无缝一体半高领打底衫
A40: P770798754835129721 | B40: 已完成 | C40: 无售后 | D40: 预售订单 | F40: 三* | G40: 177****6716 | H40: 宁夏回族自治区 银川市 兴庆区 *** | I40: 宁夏回族自治区 | J40: 银川市 | K40: 兴庆区 | L40: 640104 | M40: 689d92c8956aac0015f3663b | N40: XHS-2PMHE0F2J5DS | O40: 689d92c8956aac0015f3663a | P40: 650d6e9f000000001603a6ac | Q40: 老板周. | R40: 【老板周】舒适经典 新款柔软细腻无缝一体半高领打底衫 黑色 L（120-135斤） | S40: 黑色 L（120-135斤） | T40: 1 | W40: 199.00 | X40: 199.00 | Y40: 0.00 | Z40: 0.00 | AB40: 0.00 | AC40: 199.00 | AD40: 微信 | AE40: 4334002477202508159661676431 | AI40: 2025-08-15 16:32:40 | AK40: 0.000 | AL40: 0.00 | AM40: 中通速递 | AN40: 73568874677198 | AV40: 2025-08-15 16:32:35 | AY40: 2025-08-30 16:32:40 | AZ40: 2025-08-20 23:54:30 | BA40: 2025-08-27 10:54:57 | BB40: 第三方平台卖家电子库存 | BC40: 用户确认收货 | BD40: 否 | BI40: LAO BAN ZHOU的店 | BJ40: 5eb402c90000000001002da9 | BK40: 公司店运费模版 | BL40: 小红书公司 | BQ40: Z1248-黑色-L | BR40: 689d92c8956aac0015f3662f | BS40: 【老板周】舒适经典 新款柔软细腻无缝一体半高领打底衫
A41: P770798117968454421 | B41: 已关闭 | C41: 售后完成 | D41: 预售订单 | F41: 王** | G41: 157****7660 | H41: 甘肃省 兰州市 安宁区 *** | I41: 甘肃省 | J41: 兰州市 | K41: 安宁区 | L41: 620105 | M41: 689dee5baa1e7b00156ae7c1 | N41: XHS-3JY9LAG89YPS | O41: 689dee5baa1e7b00156ae7c0 | P41: 650d6e9f000000001603a6ac | Q41: 老板周. | R41: LAO BAN ZHOU 【老板周】极简主义 秋冬新款复古卷边前短后长针织上衣 灰色 S（80-100斤） | S41: 灰色 S（80-100斤） | T41: 1 | W41: 219.00 | X41: 219.00 | Y41: 0.00 | Z41: 0.00 | AB41: 0.00 | AC41: 219.00 | AD41: 支付宝 | AE41: 2025081522001422071432990777 | AI41: 2025-08-15 16:22:27 | AK41: 0.000 | AL41: 0.00 | AM41: 中通速递 | AN41: 73568586201255 | AV41: 2025-08-15 16:21:58 | AY41: 2025-08-30 16:22:27 | AZ41: 2025-08-18 21:15:14 | BA41: 2025-08-25 21:15:15 | BB41: 第三方平台卖家电子库存 | BC41: 系统自动收货 | BD41: 否 | BF41: 蓝旗 | BG41: ;JDX042496871681(收） Z2365-灰色-S*1# | BI41: LAO BAN ZHOU的店 | BJ41: 5a966dd7e8ac2b762a5a6e20 | BK41: 公司店运费模版 | BL41: 小红书公司 | BQ41: Z2365-灰色-S | BR41: 689dee5baa1e7b00156ae7bb | BS41: 【老板周】极简主义 秋冬新款复古卷边前短后长针织上衣
A42: P770798337207284891 | B42: 已关闭 | C42: 售后完成 | D42: 预售订单 | F42: 何 | G42: 135****0291 | H42: 湖南省 长沙市 岳麓区 *** | I42: 湖南省 | J42: 长沙市 | K42: 岳麓区 | L42: 430104005 | M42: 689dee45c34eef00157e11fe | N42: XHS-3JY8RM360LQ8 | O42: 689dee45c34eef00157e11fd | P42: 650d6e9f000000001603a6ac | Q42: 老板周. | R42: 【老板周】小众日系 秋冬叠穿时髦下摆不规则宽松马甲 花纱色 M（100-135斤） | S42: 花纱色 M（100-135斤） | T42: 1 | W42: 179.00 | X42: 179.00 | Y42: 0.00 | Z42: 0.00 | AB42: 0.00 | AC42: 179.00 | AD42: 支付宝 | AE42: 2025081522001457781456530401 | AI42: 2025-08-15 16:25:44 | AK42: 0.000 | AL42: 0.00 | AM42: 中通速递 | AN42: 73569148403912 | AV42: 2025-08-15 16:25:37 | AY42: 2025-08-30 16:25:44 | AZ42: 2025-08-22 21:57:29 | BB42: 第三方平台卖家电子库存 | BD42: 否 | BF42: 蓝旗 | BG42: ;SF3289575962710(收） Z2378-花纱色-M*1# | BI42: LAO BAN ZHOU的店 | BJ42: 5c1a271e000000000703e641 | BK42: 公司店运费模版 | BL42: 小红书公司 | BQ42: Z2378-花纱色-M | BR42: 689dee45c34eef00157e11fa | BS42: 【老板周】小众日系 秋冬叠穿时髦下摆不规则宽松马甲
A43: P770797478381146081 | B43: 已完成 | C43: 无售后 | D43: 预售订单 | F43: 赵** | G43: 139****3693 | H43: 上海 上海市 青浦区 *** | I43: 上海 | J43: 上海市 | K43: 青浦区 | L43: 310118106000 | M43: 689dee2db292580015c1974c | N43: XHS-3JY78059ZB40 | O43: 689dee2db292580015c1974b | P43: 650d6e9f000000001603a6ac | Q43: 老板周. | R43: 【老板周】通勤质感 秋冬重磅新品半松紧腰垂感口袋西裤 灰色 M（100-120斤） | S43: 灰色 M（100-120斤） | T43: 1 | W43: 359.00 | X43: 359.00 | Y43: 0.00 | Z43: 0.00 | AB43: 0.00 | AC43: 359.00 | AD43: 微信 | AE43: 4330002578202508159124990143 | AI43: 2025-08-15 16:11:24 | AK43: 0.000 | AL43: 0.00 | AM43: 中通速递 | AN43: 73569589599965 | AV43: 2025-08-15 16:11:18 | AY43: 2025-08-30 16:11:24 | AZ43: 2025-08-25 23:34:04 | BA43: 2025-08-27 11:01:59 | BB43: 第三方平台卖家电子库存 | BC43: 用户确认收货 | BD43: 否 | BI43: LAO BAN ZHOU的店 | BJ43: 5cf22c5300000000170337ba | BK43: 公司店运费模版 | BL43: 小红书公司 | BQ43: Z2363-灰色-M | BR43: 689dee2db292580015c19742 | BS43: 【老板周】通勤质感 秋冬重磅新品半松紧腰垂感口袋西裤
A44: P770797313602194761 | B44: 已关闭 | C44: 售后完成 | D44: 预售订单 | F44: 张** | G44: 186****1435 | H44: 北京 北京市 通州区 *** | I44: 北京 | J44: 北京市 | K44: 通州区 | L44: 110112003 | M44: 689d98fa3b9d470015b74589 | N44: XHS-33LDRKJ82328 | O44: 689d98fa3b9d470015b74588 | P44: 650d6e9f000000001603a6ac | Q44: 老板周. | R44: 【老板周】小众休闲 春季单口袋翻领设计感廓形百搭衬衫 黑色 L（120-135斤） | S44: 黑色 L（120-135斤） | T44: 1 | W44: 289.00 | X44: 289.00 | Y44: 0.00 | Z44: 0.00 | AB44: 0.00 | AC44: 289.00 | AD44: 支付宝 | AE44: 2025081522001403541431507443 | AI44: 2025-08-15 16:08:42 | AK44: 0.000 | AL44: 0.00 | AM44: 中通速递 | AN44: 73568731901642 | AV44: 2025-08-15 16:08:33 | AY44: 2025-08-30 16:08:42 | AZ44: 2025-08-19 22:20:09 | BA44: 2025-08-26 22:20:09 | BB44: 第三方平台卖家电子库存 | BC44: 系统自动收货 | BD44: 否 | BF44: 蓝旗 | BG44: ;SF3230664726480(收） Z1744-黑色-L*1# | BI44: LAO BAN ZHOU的店 | BJ44: 55edb487e4b1cf15d5cde665 | BK44: 公司店运费模版 | BL44: 小红书公司 | BQ44: Z1744-黑色-L | BR44: 689d98fa3b9d470015b74583 | BS44: 【老板周】小众休闲 春季单口袋翻领设计感廓形百搭衬衫
A45: P770796465763337081 | B45: 已完成 | C45: 无售后 | D45: 预售订单 | F45: 陈** | G45: 138****2801 | H45: 上海 上海市 浦东新区 *** | I45: 上海 | J45: 上海市 | K45: 浦东新区 | L45: 310115 | M45: XHS-3JXERVVVBFUO | N45: XHS-3JXERVVVBFUO | O45: 689d9a9c731333000196a4cd | P45: 650d6e9f000000001603a6ac | Q45: 老板周. | R45: 【老板周】舒适经典 新款柔软细腻无缝一体半高领打底衫 杏色 M（100-120斤） | S45: 杏色 M（100-120斤） | T45: 1 | W45: 199.00 | X45: 199.00 | Y45: 0.00 | Z45: 0.00 | AB45: 0.00 | AC45: 199.00 | AD45: 支付宝 | AE45: 2025081523001470641401813146 | AI45: 2025-08-15 15:54:30 | AK45: 0.000 | AL45: 0.00 | AM45: 中通速递 | AN45: 73568875428093 | AV45: 2025-08-15 15:54:26 | AY45: 2025-08-30 15:54:30 | AZ45: 2025-08-21 00:14:51 | BA45: 2025-08-27 11:14:15 | BB45: 第三方平台卖家电子库存 | BC45: 用户确认收货 | BD45: 否 | BI45: LAO BAN ZHOU的店 | BJ45: 5485cc1fd6e4a92d747bfb90 | BK45: 公司店运费模版 | BL45: 小红书公司 | BQ45: Z1248-杏色-M | BR45: 689d92c8956aac0015f3662f | BS45: 【老板周】舒适经典 新款柔软细腻无缝一体半高领打底衫
A46: P770796470293501151 | B46: 已关闭 | C46: 售后完成 | D46: 预售订单 | F46: 庄* | G46: 187****1622 | H46: 黑龙江省 哈尔滨市 道里区 *** | I46: 黑龙江省 | J46: 哈尔滨市 | K46: 道里区 | L46: 230102 | M46: 689d92c8956aac0015f3663b | N46: XHS-2PMHE0F2J5DS | O46: 689d92c8956aac0015f3663a | P46: 650d6e9f000000001603a6ac | Q46: 老板周. | R46: 【老板周】舒适经典 新款柔软细腻无缝一体半高领打底衫 黑色 L（120-135斤） | S46: 黑色 L（120-135斤） | T46: 1 | W46: 199.00 | X46: 199.00 | Y46: 0.00 | Z46: 0.00 | AB46: 0.00 | AC46: 199.00 | AD46: 微信 | AE46: 4349902483202508153516961941 | AI46: 2025-08-15 15:54:44 | AK46: 0.000 | AL46: 0.00 | AM46: 中通速递 | AN46: 73568871669615 | AV46: 2025-08-15 15:54:30 | AY46: 2025-08-30 15:54:44 | AZ46: 2025-08-20 22:29:50 | BB46: 第三方平台卖家电子库存 | BD46: 否 | BF46: 蓝旗 | BG46: ;772046902829039(收） Z1248-黑色-L*1# | BI46: LAO BAN ZHOU的店 | BJ46: 584821d16a6a6950c491bd8f | BK46: 公司店运费模版 | BL46: 小红书公司 | BQ46: Z1248-黑色-L | BR46: 689d92c8956aac0015f3662f | BS46: 【老板周】舒适经典 新款柔软细腻无缝一体半高领打底衫
A47: P770796096694064811 | B47: 已完成 | C47: 无售后 | D47: 预售订单 | F47: I********* | G47: 191****8044 | H47: 广东省 东莞市 樟木头镇 *** | I47: 广东省 | J47: 东莞市 | K47: 樟木头镇 | L47: 441900112000 | M47: 689dee45c34eef00157e120a | N47: XHS-3JY8RM3ZZDVK | O47: 689dee45c34eef00157e1209 | P47: 650d6e9f000000001603a6ac | Q47: 老板周. | R47: 【老板周】小众日系 秋冬叠穿时髦下摆不规则宽松马甲 灰色 M（100-135斤） | S47: 灰色 M（100-135斤） | T47: 1 | W47: 179.00 | X47: 179.00 | Y47: 0.00 | Z47: 0.00 | AB47: 0.00 | AC47: 179.00 | AD47: 支付宝 | AE47: 2025081522001434691415547577 | AI47: 2025-08-15 15:48:26 | AK47: 0.000 | AL47: 0.00 | AM47: 中通速递 | AN47: 73568735151338 | AV47: 2025-08-15 15:48:16 | AY47: 2025-08-30 15:48:26 | AZ47: 2025-08-19 23:36:42 | BA47: 2025-08-26 23:36:42 | BB47: 第三方平台卖家电子库存 | BC47: 系统自动收货 | BD47: 否 | BI47: LAO BAN ZHOU的店 | BJ47: 5f4db7270000000001001385 | BK47: 公司店运费模版 | BL47: 小红书公司 | BQ47: Z2378-灰色-M | BR47: 689dee45c34eef00157e11fa | BS47: 【老板周】小众日系 秋冬叠穿时髦下摆不规则宽松马甲
A48: P770796110033183261 | B48: 已关闭 | C48: 售后完成 | D48: 预售订单 | F48: 张** | G48: 134****2812 | H48: 广东省 深圳市 福田区 *** | I48: 广东省 | J48: 深圳市 | K48: 福田区 | L48: 440304007 | M48: 689dee45c34eef00157e11fc | N48: XHS-3JY8RM310T1C | O48: 689dee45c34eef00157e11fb | P48: 650d6e9f000000001603a6ac | Q48: 老板周. | R48: 【老板周】小众日系 秋冬叠穿时髦下摆不规则宽松马甲 花纱色 S（80-100斤） | S48: 花纱色 S（80-100斤） | T48: 1 | W48: 179.00 | X48: 179.00 | Y48: 0.00 | Z48: 0.00 | AB48: 0.00 | AC48: 179.00 | AD48: 支付宝 | AE48: 2025081522001482941453653204 | AI48: 2025-08-15 15:48:36 | AK48: 0.000 | AL48: 0.00 | AM48: 中通速递 | AN48: 73569411582317 | AV48: 2025-08-15 15:48:30 | AY48: 2025-08-30 15:48:36 | AZ48: 2025-08-24 19:20:35 | BB48: 第三方平台卖家电子库存 | BD48: 否 | BF48: 蓝旗 | BG48: ;SF3230032965181(收） Z2378-花纱色-S*1# | BI48: LAO BAN ZHOU的店 | BJ48: 56f1f9f784edcd70cdc3da52 | BK48: 公司店运费模版 | BL48: 小红书公司 | BQ48: Z2378-花纱色-S | BR48: 689dee45c34eef00157e11fa | BS48: 【老板周】小众日系 秋冬叠穿时髦下摆不规则宽松马甲
A49: P770796097446414361 | B49: 已关闭 | C49: 售后完成 | D49: 预售订单 | F49: 方** | G49: 152****0022 | H49: 天津 天津市 武清区 *** | I49: 天津 | J49: 天津市 | K49: 武清区 | L49: 120114115000 | M49: 689dee45c34eef00157e11fc | N49: XHS-3JY8RM310T1C | O49: 689dee45c34eef00157e11fb | P49: 650d6e9f000000001603a6ac | Q49: 老板周. | R49: 【老板周】小众日系 秋冬叠穿时髦下摆不规则宽松马甲 花纱色 S（80-100斤） | S49: 花纱色 S（80-100斤） | T49: 1 | W49: 179.00 | X49: 179.00 | Y49: 0.00 | Z49: 0.00 | AB49: 0.00 | AC49: 179.00 | AD49: 支付宝 | AE49: 2025081522001449701411814067 | AI49: 2025-08-15 15:48:27 | AK49: 0.000 | AL49: 0.00 | AM49: 中通速递 | AN49: 73569144710214 | AV49: 2025-08-15 15:48:17 | AY49: 2025-08-30 15:48:27 | AZ49: 2025-08-22 21:27:46 | BB49: 第三方平台卖家电子库存 | BD49: 否 | BF49: 蓝旗 | BG49: ;JDX042539808890(收） Z2378-花纱色-S*1# | BI49: LAO BAN ZHOU的店 | BJ49: 5e46a01d0000000001008d31 | BK49: 公司店运费模版 | BL49: 小红书公司 | BQ49: Z2378-花纱色-S | BR49: 689dee45c34eef00157e11fa | BS49: 【老板周】小众日系 秋冬叠穿时髦下摆不规则宽松马甲
A50: P770796111496158521 | B50: 已完成 | C50: 无售后 | D50: 预售订单 | F50: 李* | G50: 176****0421 | H50: 陕西省 西安市 未央区 *** | I50: 陕西省 | J50: 西安市 | K50: 未央区 | L50: 610112001 | M50: 689dee45c34eef00157e1208 | N50: XHS-3JY8RM3UZL6O | O50: 689dee45c34eef00157e1207 | P50: 650d6e9f000000001603a6ac | Q50: 老板周. | R50: 【老板周】小众日系 秋冬叠穿时髦下摆不规则宽松马甲 灰色 S（80-100斤） | S50: 灰色 S（80-100斤） | T50: 1 | W50: 179.00 | X50: 179.00 | Y50: 0.00 | Z50: 0.00 | AB50: 0.00 | AC50: 179.00 | AD50: 支付宝 | AE50: 2025081522001465651424501445 | AI50: 2025-08-15 15:48:35 | AK50: 0.000 | AL50: 0.00 | AM50: 中通速递 | AN50: 73568735151432 | AV50: 2025-08-15 15:48:31 | AY50: 2025-08-30 15:48:35 | AZ50: 2025-08-19 23:36:17 | BA50: 2025-08-26 23:36:18 | BB50: 第三方平台卖家电子库存 | BC50: 系统自动收货 | BD50: 否 | BI50: LAO BAN ZHOU的店 | BJ50: 5fd34cc20000000001003bc8 | BK50: 公司店运费模版 | BL50: 小红书公司 | BQ50: Z2378-灰色-S | BR50: 689dee45c34eef00157e11fa | BS50: 【老板周】小众日系 秋冬叠穿时髦下摆不规则宽松马甲
A51: P770795108315278051 | B51: 已完成 | C51: 售后完成 | D51: 预售订单 | F51: 王** | G51: 136****7066 | H51: 北京 北京市 西城区 *** | I51: 北京 | J51: 北京市 | K51: 西城区 | L51: 110102017000 | M51: 689dee2db292580015c19746 | N51: XHS-3JY7804XHTDS | O51: 689dee2db292580015c19745 | P51: 650d6e9f000000001603a6ac | Q51: 老板周. | R51: 【老板周】通勤质感 秋冬重磅新品半松紧腰垂感口袋西裤 黑色 M（100-120斤） | S51: 黑色 M（100-120斤） | T51: 1 | W51: 359.00 | X51: 359.00 | Y51: 0.00 | Z51: 0.00 | AB51: 0.00 | AC51: 359.00 | AD51: 支付宝 | AE51: 2025081522001492241418896447 | AI51: 2025-08-15 15:31:56 | AK51: 0.000 | AL51: 0.00 | AM51: 中通速递 | AN51: 73569432293407 | AV51: 2025-08-15 15:31:48 | AY51: 2025-08-30 15:31:56 | AZ51: 2025-08-24 22:12:09 | BA51: 2025-08-27 11:49:06 | BB51: 第三方平台卖家电子库存 | BC51: 用户确认收货 | BD51: 否 | BF51: 蓝旗 | BG51: ;JDX042584202698(收） Z2363-黑色-M*1# | BI51: LAO BAN ZHOU的店 | BJ51: 5ebe9831000000000101ef7f | BK51: 公司店运费模版 | BL51: 小红书公司 | BQ51: Z2363-黑色-M | BR51: 689dee2db292580015c19742 | BS51: 【老板周】通勤质感 秋冬重磅新品半松紧腰垂感口袋西裤
A52: P770795407221086221 | B52: 已完成 | C52: 无售后 | D52: 预售订单 | E52: 催发货 | F52: 李* | G52: 192****0049 | H52: 辽宁省 沈阳市 沈河区 *** | I52: 辽宁省 | J52: 沈阳市 | K52: 沈河区 | L52: 210103 | M52: 689dee2db292580015c1974c | N52: XHS-3JY78059ZB40 | O52: 689dee2db292580015c1974b | P52: 650d6e9f000000001603a6ac | Q52: 老板周. | R52: 【老板周】通勤质感 秋冬重磅新品半松紧腰垂感口袋西裤 灰色 M（100-120斤） | S52: 灰色 M（100-120斤） | T52: 1 | W52: 359.00 | X52: 359.00 | Y52: 0.00 | Z52: 0.00 | AB52: 0.00 | AC52: 359.00 | AD52: 微信 | AE52: 4336702239202508150999383593 | AI52: 2025-08-15 15:36:55 | AK52: 0.000 | AL52: 0.00 | AM52: 中通速递 | AN52: 73569432293369 | AV52: 2025-08-15 15:36:47 | AY52: 2025-08-30 15:36:55 | AZ52: 2025-08-24 22:08:23 | BA52: 2025-08-27 17:23:23 | BB52: 第三方平台卖家电子库存 | BC52: 用户确认收货 | BD52: 否 | BI52: LAO BAN ZHOU的店 | BJ52: 5c8ca9040000000012030379 | BK52: 公司店运费模版 | BL52: 小红书公司 | BQ52: Z2363-灰色-M | BR52: 689dee2db292580015c19742 | BS52: 【老板周】通勤质感 秋冬重磅新品半松紧腰垂感口袋西裤
A53: P770795400699278151 | B53: 已完成 | C53: 售后完成 | D53: 预售订单 | F53: 王** | G53: 136****7066 | H53: 北京 北京市 西城区 *** | I53: 北京 | J53: 北京市 | K53: 西城区 | L53: 110102017000 | M53: 689dee2db292580015c1974c | N53: XHS-3JY78059ZB40 | O53: 689dee2db292580015c1974b | P53: 650d6e9f000000001603a6ac | Q53: 老板周. | R53: 【老板周】通勤质感 秋冬重磅新品半松紧腰垂感口袋西裤 灰色 M（100-120斤） | S53: 灰色 M（100-120斤） | T53: 1 | W53: 359.00 | X53: 359.00 | Y53: 0.00 | Z53: 0.00 | AB53: 0.00 | AC53: 359.00 | AD53: 支付宝 | AE53: 2025081523001492241419507831 | AI53: 2025-08-15 15:36:48 | AK53: 0.000 | AL53: 0.00 | AM53: 中通速递 | AN53: 73569432293009 | AV53: 2025-08-15 15:36:40 | AY53: 2025-08-30 15:36:48 | AZ53: 2025-08-24 22:08:23 | BA53: 2025-08-27 11:48:59 | BB53: 第三方平台卖家电子库存 | BC53: 用户确认收货 | BD53: 否 | BF53: 蓝旗 | BG53: ;JDX042584202698(收） Z2363-灰色-M*1# | BI53: LAO BAN ZHOU的店 | BJ53: 5ebe9831000000000101ef7f | BK53: 公司店运费模版 | BL53: 小红书公司 | BQ53: Z2363-灰色-M | BR53: 689dee2db292580015c19742 | BS53: 【老板周】通勤质感 秋冬重磅新品半松紧腰垂感口袋西裤
A54: P770795092998457951 | B54: 已完成 | C54: 无售后 | D54: 预售订单 | F54: 曹* | G54: 159****0903 | H54: 北京 北京市 大兴区 *** | I54: 北京 | J54: 北京市 | K54: 大兴区 | L54: 110115 | M54: 689dee2db292580015c19746 | N54: XHS-3JY7804XHTDS | O54: 689dee2db292580015c19745 | P54: 650d6e9f000000001603a6ac | Q54: 老板周. | R54: 【老板周】通勤质感 秋冬重磅新品半松紧腰垂感口袋西裤 黑色 M（100-120斤） | S54: 黑色 M（100-120斤） | T54: 1 | W54: 359.00 | X54: 359.00 | Y54: 0.00 | Z54: 0.00 | AB54: 0.00 | AC54: 359.00 | AD54: 支付宝 | AE54: 2025081522001491851430393327 | AI54: 2025-08-15 15:31:45 | AK54: 0.000 | AL54: 0.00 | AM54: 中通速递 | AN54: 73569378742529 | AV54: 2025-08-15 15:31:33 | AY54: 2025-08-30 15:31:45 | AZ54: 2025-08-24 14:31:36 | BA54: 2025-08-26 22:44:43 | BB54: 第三方平台卖家电子库存 | BC54: 用户确认收货 | BD54: 否 | BI54: LAO BAN ZHOU的店 | BJ54: 5af8be4211be105a03654a46 | BK54: 公司店运费模版 | BL54: 小红书公司 | BQ54: Z2363-黑色-M | BR54: 689dee2db292580015c19742 | BS54: 【老板周】通勤质感 秋冬重磅新品半松紧腰垂感口袋西裤
A55: P770795098086034121 | B55: 已完成 | C55: 售后完成 | D55: 预售订单 | F55: 张* | G55: 173****9346 | H55: 上海 上海市 浦东新区 *** | I55: 上海 | J55: 上海市 | K55: 浦东新区 | L55: 310115105 | M55: 689dee2db292580015c19748 | N55: XHS-3JY78052HM2O | O55: 689dee2db292580015c19747 | P55: 650d6e9f000000001603a6ac | Q55: 老板周. | R55: 【老板周】通勤质感 秋冬重磅新品半松紧腰垂感口袋西裤 黑色 L（120-135斤） | S55: 黑色 L（120-135斤） | T55: 1 | W55: 359.00 | X55: 359.00 | Y55: 0.00 | Z55: 0.00 | AB55: 0.00 | AC55: 359.00 | AD55: 支付宝 | AE55: 2025081522001450481431049812 | AI55: 2025-08-15 15:31:50 | AK55: 0.000 | AL55: 0.00 | AM55: 中通速递 | AN55: 73569590703128 | AV55: 2025-08-15 15:31:38 | AY55: 2025-08-30 15:31:50 | AZ55: 2025-08-26 00:10:35 | BA55: 2025-08-27 17:06:35 | BB55: 第三方平台卖家电子库存 | BC55: 用户确认收货 | BD55: 否 | BF55: 蓝旗 | BG55: ;SF3280485190011(收） Z2363-黑色-L*1# | BI55: LAO BAN ZHOU的店 | BJ55: 6626194c0000000003033a71 | BK55: 公司店运费模版 | BL55: 小红书公司 | BQ55: Z2363-黑色-L | BR55: 689dee2db292580015c19742 | BS55: 【老板周】通勤质感 秋冬重磅新品半松紧腰垂感口袋西裤
A56: P770795099673396171 | B56: 已完成 | C56: 售后完成 | D56: 预售订单 | F56: 涂** | G56: 138****0622 | H56: 四川省 成都市 双流区 *** | I56: 四川省 | J56: 成都市 | K56: 双流区 | L56: 510116003000 | M56: 689dee2db292580015c1974c | N56: XHS-3JY78059ZB40 | O56: 689dee2db292580015c1974b | P56: 650d6e9f000000001603a6ac | Q56: 老板周. | R56: 【老板周】通勤质感 秋冬重磅新品半松紧腰垂感口袋西裤 灰色 M（100-120斤） | S56: 灰色 M（100-120斤） | T56: 1 | W56: 359.00 | X56: 359.00 | Y56: 0.00 | Z56: 0.00 | AB56: 0.00 | AC56: 359.00 | AD56: 微信 | AE56: 4316002575202508152432784547 | AI56: 2025-08-15 15:31:46 | AK56: 0.000 | AL56: 0.00 | AM56: 中通速递 | AN56: 73569294175907 | AV56: 2025-08-15 15:31:39 | AY56: 2025-08-30 15:31:46 | AZ56: 2025-08-23 23:21:46 | BA56: 2025-08-27 14:42:54 | BB56: 第三方平台卖家电子库存 | BC56: 用户确认收货 | BD56: 否 | BF56: 蓝旗 | BG56: ;SF3239924337345(收） Z2363-灰色-M*1# | BI56: LAO BAN ZHOU的店 | BJ56: 594b18b95e87e7271006d25a | BK56: 公司店运费模版 | BL56: 小红书公司 | BQ56: Z2363-灰色-M | BR56: 689dee2db292580015c19742 | BS56: 【老板周】通勤质感 秋冬重磅新品半松紧腰垂感口袋西裤
A57: P770795098672334381 | B57: 已完成 | C57: 无售后 | D57: 预售订单 | F57: 许** | G57: 186****0536 | H57: 陕西省 榆林市 横山区 *** | I57: 陕西省 | J57: 榆林市 | K57: 横山区 | L57: 610803 | M57: 689dee2db292580015c1974e | N57: XHS-3JY7805CH7GG | O57: 689dee2db292580015c1974d | P57: 650d6e9f000000001603a6ac | Q57: 老板周. | R57: 【老板周】通勤质感 秋冬重磅新品半松紧腰垂感口袋西裤 灰色 L（120-135斤） | S57: 灰色 L（120-135斤） | T57: 1 | W57: 359.00 | X57: 359.00 | Y57: 0.00 | Z57: 0.00 | AB57: 0.00 | AC57: 359.00 | AD57: 微信先用后付 | AI57: 2025-08-15 15:31:39 | AK57: 0.000 | AL57: 0.00 | AM57: 中通速递 | AN57: 73569432293621 | AV57: 2025-08-15 15:31:38 | AY57: 2025-08-30 15:31:39 | AZ57: 2025-08-24 22:07:19 | BA57: 2025-08-27 14:52:25 | BB57: 第三方平台卖家电子库存 | BC57: 用户确认收货 | BD57: 否 | BI57: LAO BAN ZHOU的店 | BJ57: 5af3cae811be1017e37263a1 | BK57: 公司店运费模版 | BL57: 小红书公司 | BQ57: Z2363-灰色-L | BR57: 689dee2db292580015c19742 | BS57: 【老板周】通勤质感 秋冬重磅新品半松紧腰垂感口袋西裤
A58: P770795096898414161 | B58: 已关闭 | C58: 售后完成 | D58: 预售订单 | F58: 张** | G58: 133****8131 | H58: 上海 上海市 闵行区 *** | I58: 上海 | J58: 上海市 | K58: 闵行区 | L58: 310112103000 | M58: 689dee2db292580015c1974c | N58: XHS-3JY78059ZB40 | O58: 689dee2db292580015c1974b | P58: 650d6e9f000000001603a6ac | Q58: 老板周. | R58: 【老板周】通勤质感 秋冬重磅新品半松紧腰垂感口袋西裤 灰色 M（100-120斤） | S58: 灰色 M（100-120斤） | T58: 1 | W58: 359.00 | X58: 359.00 | Y58: 0.00 | Z58: 0.00 | AB58: 0.00 | AC58: 359.00 | AD58: 微信 | AE58: 4307802469202508157342709693 | AI58: 2025-08-15 15:31:41 | AK58: 0.000 | AL58: 0.00 | AM58: 中通速递 | AN58: 73569287102422 | AV58: 2025-08-15 15:31:37 | AY58: 2025-08-30 15:31:41 | AZ58: 2025-08-23 20:57:59 | BB58: 第三方平台卖家电子库存 | BD58: 否 | BF58: 蓝旗 | BG58: ;SF1522073487212(收） Z2363-灰色-M*1# | BI58: LAO BAN ZHOU的店 | BJ58: 5e57b71f000000000100b1ef | BK58: 公司店运费模版 | BL58: 小红书公司 | BQ58: Z2363-灰色-M | BR58: 689dee2db292580015c19742 | BS58: 【老板周】通勤质感 秋冬重磅新品半松紧腰垂感口袋西裤
A59: P770795097742070261 | B59: 已关闭 | C59: 售后完成 | D59: 预售订单 | E59: 物流异常 | F59: 丛** | G59: 135****8332 | H59: 吉林省 长春市 南关区 *** | I59: 吉林省 | J59: 长春市 | K59: 南关区 | L59: 220102 | M59: 689dee2db292580015c1974a | N59: XHS-3JY78054ZIF4 | O59: 689dee2db292580015c19749 | P59: 650d6e9f000000001603a6ac | Q59: 老板周. | R59: 【老板周】通勤质感 秋冬重磅新品半松紧腰垂感口袋西裤 灰色 S（80-100斤） | S59: 灰色 S（80-100斤） | T59: 1 | W59: 359.00 | X59: 359.00 | Y59: 0.00 | Z59: 0.00 | AB59: 0.00 | AC59: 359.00 | AD59: 微信 | AE59: 4326602467202508159812340740 | AI59: 2025-08-15 15:31:43 | AK59: 0.000 | AL59: 0.00 | AM59: 中通速递 | AN59: 73569432292163 | AV59: 2025-08-15 15:31:37 | AY59: 2025-08-30 15:31:43 | AZ59: 2025-08-24 22:08:57 | BB59: 第三方平台卖家电子库存 | BD59: 否 | BF59: 蓝旗 | BG59: 加急 拦截;73569432292163(收） Z2363-灰色-S*1# | BI59: LAO BAN ZHOU的店 | BJ59: 590d488150c4b43cbb96e939 | BK59: 公司店运费模版 | BL59: 小红书公司 | BQ59: Z2363-灰色-S | BR59: 689dee2db292580015c19742 | BS59: 【老板周】通勤质感 秋冬重磅新品半松紧腰垂感口袋西裤
A60: P770794938906198011 | B60: 已完成 | C60: 无售后 | D60: 预售订单 | F60: 等* | G60: 159****5950 | H60: 重庆 重庆市 万州区 *** | I60: 重庆 | J60: 重庆市 | K60: 万州区 | L60: 500101018000 | M60: 689dee2db292580015c1974a | N60: XHS-3JY78054ZIF4 | O60: 689dee2db292580015c19749 | P60: 650d6e9f000000001603a6ac | Q60: 老板周. | R60: 【老板周】通勤质感 秋冬重磅新品半松紧腰垂感口袋西裤 灰色 S（80-100斤） | S60: 灰色 S（80-100斤） | T60: 1 | W60: 359.00 | X60: 359.00 | Y60: 0.00 | Z60: 0.00 | AB60: 0.00 | AC60: 359.00 | AD60: 微信 | AE60: 4311002265202508153944380222 | AI60: 2025-08-15 15:29:08 | AK60: 0.000 | AL60: 0.00 | AM60: 中通速递 | AN60: 73569432292321 | AV60: 2025-08-15 15:28:59 | AY60: 2025-08-30 15:29:08 | AZ60: 2025-08-24 22:08:57 | BA60: 2025-08-27 10:43:58 | BB60: 第三方平台卖家电子库存 | BC60: 用户确认收货 | BD60: 否 | BI60: LAO BAN ZHOU的店 | BJ60: 5c615f07000000001b013f8e | BK60: 公司店运费模版 | BL60: 小红书公司 | BQ60: Z2363-灰色-S | BR60: 689dee2db292580015c19742 | BS60: 【老板周】通勤质感 秋冬重磅新品半松紧腰垂感口袋西裤
A61: P770794934880461651 | B61: 已完成 | C61: 无售后 | D61: 预售订单 | F61: 郭** | G61: 135****2037 | H61: 广东省 广州市 番禺区 *** | I61: 广东省 | J61: 广州市 | K61: 番禺区 | L61: 440113012 | M61: 689dee2db292580015c1974c | N61: XHS-3JY78059ZB40 | O61: 689dee2db292580015c1974b | P61: 650d6e9f000000001603a6ac | Q61: 老板周. | R61: 【老板周】通勤质感 秋冬重磅新品半松紧腰垂感口袋西裤 灰色 M（100-120斤） | S61: 灰色 M（100-120斤） | T61: 1 | W61: 359.00 | X61: 359.00 | Y61: 0.00 | Z61: 0.00 | AB61: 0.00 | AC61: 359.00 | AD61: 支付宝 | AE61: 2025081522001403291453515521 | AI61: 2025-08-15 15:29:03 | AK61: 0.000 | AL61: 0.00 | AM61: 中通速递 | AN61: 73569287101396 | AV61: 2025-08-15 15:28:55 | AY61: 2025-08-30 15:29:03 | AZ61: 2025-08-23 20:57:59 | BA61: 2025-08-26 22:58:44 | BB61: 第三方平台卖家电子库存 | BC61: 用户确认收货 | BD61: 否 | BI61: LAO BAN ZHOU的店 | BJ61: 571a4b9a4775a74ab677dd1c | BK61: 公司店运费模版 | BL61: 小红书公司 | BQ61: Z2363-灰色-M | BR61: 689dee2db292580015c19742 | BS61: 【老板周】通勤质感 秋冬重磅新品半松紧腰垂感口袋西裤
A62: P770794618887352631 | B62: 已完成 | C62: 无售后 | D62: 预售订单 | F62: 王* | G62: 159****5120 | H62: 北京 北京市 西城区 *** | I62: 北京 | J62: 北京市 | K62: 西城区 | L62: 110102 | M62: 689d92c8956aac0015f36637 | N62: XHS-2PMHDY7HMXHC | O62: 689d92c8956aac0015f36636 | P62: 650d6e9f000000001603a6ac | Q62: 老板周. | R62: 【老板周】舒适经典 新款柔软细腻无缝一体半高领打底衫 黑色 S（80-100斤） | S62: 黑色 S（80-100斤） | T62: 1 | W62: 199.00 | X62: 199.00 | Y62: 0.00 | Z62: 0.00 | AB62: 0.00 | AC62: 199.00 | AD62: 微信 | AE62: 4314902586202508158568930623 | AI62: 2025-08-15 15:23:44 | AK62: 0.000 | AL62: 0.00 | AM62: 中通速递 | AN62: 73568871667396 | AV62: 2025-08-15 15:23:39 | AY62: 2025-08-30 15:23:44 | AZ62: 2025-08-20 22:31:23 | BA62: 2025-08-27 10:33:20 | BB62: 第三方平台卖家电子库存 | BC62: 用户确认收货 | BD62: 否 | BI62: LAO BAN ZHOU的店 | BJ62: 5627508c447608016830a2bf | BK62: 公司店运费模版 | BL62: 小红书公司 | BQ62: Z1248-黑色-S | BR62: 689d92c8956aac0015f3662f | BS62: 【老板周】舒适经典 新款柔软细腻无缝一体半高领打底衫
A63: P770794262760472121 | B63: 已关闭 | C63: 售后完成 | D63: 预售订单 | F63: 米* | G63: 138****1008 | H63: 江苏省 苏州市 太仓市 *** | I63: 江苏省 | J63: 苏州市 | K63: 太仓市 | L63: 320585403000 | M63: 689d92c8956aac0015f36637 | N63: XHS-2PMHDY7HMXHC | O63: 689d92c8956aac0015f36636 | P63: 650d6e9f000000001603a6ac | Q63: 老板周. | R63: 【老板周】舒适经典 新款柔软细腻无缝一体半高领打底衫 黑色 S（80-100斤） | S63: 黑色 S（80-100斤） | T63: 1 | W63: 199.00 | X63: 199.00 | Y63: 0.00 | Z63: 0.00 | AB63: 0.00 | AC63: 199.00 | AD63: 微信 | AE63: 4319502252202508152954273060 | AI63: 2025-08-15 15:17:47 | AK63: 0.000 | AL63: 0.00 | AM63: 中通速递 | AN63: 73568871666050 | AV63: 2025-08-15 15:17:43 | AY63: 2025-08-30 15:17:47 | AZ63: 2025-08-20 22:31:23 | BB63: 第三方平台卖家电子库存 | BD63: 否 | BF63: 蓝旗 | BG63: ;JDX042520199702(收） Z1248-黑色-S*1# | BI63: LAO BAN ZHOU的店 | BJ63: 58a2e1dc69aa52071ba94c00 | BK63: 公司店运费模版 | BL63: 小红书公司 | BQ63: Z1248-黑色-S | BR63: 689d92c8956aac0015f3662f | BS63: 【老板周】舒适经典 新款柔软细腻无缝一体半高领打底衫
A64: P770794525672392531 | B64: 已完成 | C64: 无售后 | D64: 预售订单 | F64: 吴** | G64: 188****1225 | H64: 广东省 珠海市 香洲区 *** | I64: 广东省 | J64: 珠海市 | K64: 香洲区 | L64: 440402102000 | M64: 689dee45c34eef00157e1208 | N64: XHS-3JY8RM3UZL6O | O64: 689dee45c34eef00157e1207 | P64: 650d6e9f000000001603a6ac | Q64: 老板周. | R64: 【老板周】小众日系 秋冬叠穿时髦下摆不规则宽松马甲 灰色 S（80-100斤） | S64: 灰色 S（80-100斤） | T64: 1 | W64: 179.00 | X64: 179.00 | Y64: 0.00 | Z64: 0.00 | AB64: 0.00 | AC64: 179.00 | AD64: 支付宝 | AE64: 2025081523001435301455746655 | AI64: 2025-08-15 15:22:16 | AK64: 0.000 | AL64: 0.00 | AM64: 中通速递 | AN64: 73568735150528 | AV64: 2025-08-15 15:22:05 | AY64: 2025-08-30 15:22:16 | AZ64: 2025-08-19 23:36:17 | BA64: 2025-08-26 23:36:18 | BB64: 第三方平台卖家电子库存 | BC64: 系统自动收货 | BD64: 否 | BI64: LAO BAN ZHOU的店 | BJ64: 5dd08c5f0000000001004592 | BK64: 公司店运费模版 | BL64: 小红书公司 | BQ64: Z2378-灰色-S | BR64: 689dee45c34eef00157e11fa | BS64: 【老板周】小众日系 秋冬叠穿时髦下摆不规则宽松马甲
A65: P770794257861206101 | B65: 已完成 | C65: 无售后 | D65: 预售订单 | F65: 方** | G65: 181****8680 | H65: 上海 上海市 宝山区 *** | I65: 上海 | J65: 上海市 | K65: 宝山区 | L65: 310113103000 | M65: 689d92c8956aac0015f3663b | N65: XHS-2PMHE0F2J5DS | O65: 689d92c8956aac0015f3663a | P65: 650d6e9f000000001603a6ac | Q65: 老板周. | R65: 【老板周】舒适经典 新款柔软细腻无缝一体半高领打底衫 黑色 L（120-135斤） | S65: 黑色 L（120-135斤） | T65: 1 | W65: 199.00 | X65: 199.00 | Y65: 0.00 | Z65: 0.00 | AB65: 0.00 | AC65: 199.00 | AD65: 微信 | AE65: 4313502286202508158189547016 | AI65: 2025-08-15 15:17:45 | AK65: 0.000 | AL65: 0.00 | AM65: 中通速递 | AN65: 73568871665081 | AV65: 2025-08-15 15:17:38 | AY65: 2025-08-30 15:17:45 | AZ65: 2025-08-20 22:29:50 | BA65: 2025-08-27 09:37:58 | BB65: 第三方平台卖家电子库存 | BC65: 用户确认收货 | BD65: 否 | BF65: 红旗 | BG65: Z1248小礼物;补发(6127889)#;补发73569574884104 | BI65: LAO BAN ZHOU的店 | BJ65: 5a589de34eacab61267bc6ae | BK65: 公司店运费模版 | BL65: 小红书公司 | BQ65: Z1248-黑色-L | BR65: 689d92c8956aac0015f3662f | BS65: 【老板周】舒适经典 新款柔软细腻无缝一体半高领打底衫
A66: P770794446611478281 | B66: 已关闭 | C66: 售后完成 | D66: 预售订单 | F66: 郝** | G66: 150****1320 | H66: 内蒙古自治区 呼和浩特市 回民区 *** | I66: 内蒙古自治区 | J66: 呼和浩特市 | K66: 回民区 | L66: 150103 | M66: 689dee45c34eef00157e11fc | N66: XHS-3JY8RM310T1C | O66: 689dee45c34eef00157e11fb | P66: 650d6e9f000000001603a6ac | Q66: 老板周. | R66: 【老板周】小众日系 秋冬叠穿时髦下摆不规则宽松马甲 花纱色 S（80-100斤） | S66: 花纱色 S（80-100斤） | T66: 1 | W66: 179.00 | X66: 179.00 | Y66: 0.00 | Z66: 0.00 | AB66: 0.00 | AC66: 179.00 | AD66: 支付宝 | AE66: 2025081522001419551423053635 | AI66: 2025-08-15 15:20:56 | AK66: 0.000 | AL66: 0.00 | AM66: 中通速递 | AN66: 73568875428052 | AV66: 2025-08-15 15:20:46 | AY66: 2025-08-30 15:20:56 | AZ66: 2025-08-21 00:20:35 | BB66: 第三方平台卖家电子库存 | BD66: 否 | BF66: 蓝旗 | BG66: ;73569356446260(收） Z2378-花纱色-S*1# | BI66: LAO BAN ZHOU的店 | BJ66: 5da81c91000000000100a656 | BK66: 公司店运费模版 | BL66: 小红书公司 | BQ66: Z2378-花纱色-S | BR66: 689dee45c34eef00157e11fa | BS66: 【老板周】小众日系 秋冬叠穿时髦下摆不规则宽松马甲
A67: P770794260083193631 | B67: 已完成 | C67: 无售后 | D67: 预售订单 | F67: 7** | G67: 136****1561 | H67: 广西壮族自治区 柳州市 城中区 *** | I67: 广西壮族自治区 | J67: 柳州市 | K67: 城中区 | L67: 450202005000 | M67: 689d92c8956aac0015f3663b | N67: XHS-2PMHE0F2J5DS | O67: 689d92c8956aac0015f3663a | P67: 650d6e9f000000001603a6ac | Q67: 老板周. | R67: 【老板周】舒适经典 新款柔软细腻无缝一体半高领打底衫 黑色 L（120-135斤） | S67: 黑色 L（120-135斤） | T67: 1 | W67: 199.00 | X67: 199.00 | Y67: 0.00 | Z67: 0.00 | AB67: 0.00 | AC67: 199.00 | AD67: 微信 | AE67: 4332402475202508159443479448 | AI67: 2025-08-15 15:17:47 | AK67: 0.000 | AL67: 0.00 | AM67: 中通速递 | AN67: 73568871666182 | AV67: 2025-08-15 15:17:40 | AY67: 2025-08-30 15:17:47 | AZ67: 2025-08-20 22:29:50 | BA67: 2025-08-27 12:31:45 | BB67: 第三方平台卖家电子库存 | BC67: 用户确认收货 | BD67: 是 | BF67: 红旗 | BG67: Z1248小礼物;补发(6127893)#;补发73569574884385 | BI67: LAO BAN ZHOU的店 | BJ67: 5ace005b4eacab4013550665 | BK67: 公司店运费模版 | BL67: 小红书公司 | BQ67: Z1248-黑色-L | BR67: 689d92c8956aac0015f3662f | BS67: 【老板周】舒适经典 新款柔软细腻无缝一体半高领打底衫
A68: P770794613000337021 | B68: 已完成 | C68: 无售后 | D68: 预售订单 | F68: 陈** | G68: 138****2801 | H68: 上海 上海市 浦东新区 *** | I68: 上海 | J68: 上海市 | K68: 浦东新区 | L68: 310115 | M68: 689d92c8956aac0015f36639 | N68: XHS-2PMHDZ8YH728 | O68: 689d92c8956aac0015f36638 | P68: 650d6e9f000000001603a6ac | Q68: 老板周. | R68: 【老板周】舒适经典 新款柔软细腻无缝一体半高领打底衫 黑色 M（100-120斤） | S68: 黑色 M（100-120斤） | T68: 1 | W68: 199.00 | X68: 199.00 | Y68: 0.00 | Z68: 0.00 | AB68: 0.00 | AC68: 199.00 | AD68: 支付宝 | AE68: 2025081522001470641402028241 | AI68: 2025-08-15 15:23:40 | AK68: 0.000 | AL68: 0.00 | AM68: 中通速递 | AN68: 73568864925236 | AV68: 2025-08-15 15:23:33 | AY68: 2025-08-30 15:23:40 | AZ68: 2025-08-20 20:38:35 | BA68: 2025-08-27 11:14:53 | BB68: 第三方平台卖家电子库存 | BC68: 用户确认收货 | BD68: 否 | BI68: LAO BAN ZHOU的店 | BJ68: 5485cc1fd6e4a92d747bfb90 | BK68: 公司店运费模版 | BL68: 小红书公司 | BQ68: Z1248-黑色-M | BR68: 689d92c8956aac0015f3662f | BS68: 【老板周】舒适经典 新款柔软细腻无缝一体半高领打底衫
A69: P770794057829472761 | B69: 已关闭 | C69: 售后完成 | D69: 预售订单 | F69: 米* | G69: 138****1008 | H69: 江苏省 苏州市 太仓市 *** | I69: 江苏省 | J69: 苏州市 | K69: 太仓市 | L69: 320585403000 | M69: 689dee45c34eef00157e11fc | N69: XHS-3JY8RM310T1C | O69: 689dee45c34eef00157e11fb | P69: 650d6e9f000000001603a6ac | Q69: 老板周. | R69: 【老板周】小众日系 秋冬叠穿时髦下摆不规则宽松马甲 花纱色 S（80-100斤） | S69: 花纱色 S（80-100斤） | T69: 1 | W69: 179.00 | X69: 179.00 | Y69: 0.00 | Z69: 0.00 | AB69: 0.00 | AC69: 179.00 | AD69: 微信 | AE69: 4303302579202508152843431070 | AI69: 2025-08-15 15:14:23 | AK69: 0.000 | AL69: 0.00 | AM69: 中通速递 | AN69: 73568874677040 | AV69: 2025-08-15 15:14:18 | AY69: 2025-08-30 15:14:23 | AZ69: 2025-08-20 23:49:17 | BB69: 第三方平台卖家电子库存 | BD69: 否 | BF69: 蓝旗 | BG69: ;JDX042520199702(收） Z2378-花纱色-S*1# | BI69: LAO BAN ZHOU的店 | BJ69: 58a2e1dc69aa52071ba94c00 | BK69: 公司店运费模版 | BL69: 小红书公司 | BQ69: Z2378-花纱色-S | BR69: 689dee45c34eef00157e11fa | BS69: 【老板周】小众日系 秋冬叠穿时髦下摆不规则宽松马甲
A70: P770794027175352691 | B70: 已完成 | C70: 无售后 | D70: 预售订单 | F70: 王* | G70: 159****5120 | H70: 北京 北京市 西城区 *** | I70: 北京 | J70: 北京市 | K70: 西城区 | L70: 110102 | M70: 689dee45c34eef00157e11fc | N70: XHS-3JY8RM310T1C | O70: 689dee45c34eef00157e11fb | P70: 650d6e9f000000001603a6ac | Q70: 老板周. | R70: 【老板周】小众日系 秋冬叠穿时髦下摆不规则宽松马甲 花纱色 S（80-100斤） | S70: 花纱色 S（80-100斤） | T70: 1 | W70: 179.00 | X70: 179.00 | Y70: 0.00 | Z70: 0.00 | AB70: 0.00 | AC70: 179.00 | AD70: 微信 | AE70: 4313702240202508155196574523 | AI70: 2025-08-15 15:13:53 | AK70: 0.000 | AL70: 0.00 | AM70: 中通速递 | AN70: 73568874677514 | AV70: 2025-08-15 15:13:47 | AY70: 2025-08-30 15:13:53 | AZ70: 2025-08-20 23:49:17 | BA70: 2025-08-27 10:33:35 | BB70: 第三方平台卖家电子库存 | BC70: 用户确认收货 | BD70: 否 | BI70: LAO BAN ZHOU的店 | BJ70: 5627508c447608016830a2bf | BK70: 公司店运费模版 | BL70: 小红书公司 | BQ70: Z2378-花纱色-S | BR70: 689dee45c34eef00157e11fa | BS70: 【老板周】小众日系 秋冬叠穿时髦下摆不规则宽松马甲
A71: P770794042509304891 | B71: 已完成 | C71: 售后完成 | D71: 预售订单 | F71: 刘** | G71: 138****6762 | H71: 新疆维吾尔自治区 乌鲁木齐市 水磨沟区 *** | I71: 新疆维吾尔自治区 | J71: 乌鲁木齐市 | K71: 水磨沟区 | L71: 650105 | M71: 689dee45c34eef00157e11fe | N71: XHS-3JY8RM360LQ8 | O71: 689dee45c34eef00157e11fd | P71: 650d6e9f000000001603a6ac | Q71: 老板周. | R71: 【老板周】小众日系 秋冬叠穿时髦下摆不规则宽松马甲 花纱色 M（100-135斤） | S71: 花纱色 M（100-135斤） | T71: 1 | W71: 179.00 | X71: 189.00 | Y71: 0.00 | Z71: 0.00 | AB71: 0.00 | AC71: 189.00 | AD71: 微信 | AE71: 4330102235202508158090006582 | AI71: 2025-08-15 15:14:10 | AK71: 0.000 | AL71: 10.00 | AM71: 中通速递 | AN71: 73568871665896 | AV71: 2025-08-15 15:14:02 | AY71: 2025-08-30 15:14:10 | AZ71: 2025-08-20 22:37:00 | BA71: 2025-08-25 00:10:29 | BB71: 第三方平台卖家电子库存 | BC71: 用户确认收货 | BD71: 否 | BF71: 蓝旗 | BG71: ;SF3230042266135(收） Z2378-花纱色-M*1# | BI71: LAO BAN ZHOU的店 | BJ71: 5cde3dda00000000050330bd | BK71: 公司店运费模版 | BL71: 小红书公司 | BQ71: Z2378-花纱色-M | BR71: 689dee45c34eef00157e11fa | BS71: 【老板周】小众日系 秋冬叠穿时髦下摆不规则宽松马甲
A72: P770794022057206671 | B72: 已完成 | C72: 无售后 | D72: 预售订单 | F72: 纪** | G72: 180****2785 | H72: 重庆 重庆市 沙坪坝区 *** | I72: 重庆 | J72: 重庆市 | K72: 沙坪坝区 | L72: 500106016000 | M72: 689dee45c34eef00157e11fe | N72: XHS-3JY8RM360LQ8 | O72: 689dee45c34eef00157e11fd | P72: 650d6e9f000000001603a6ac | Q72: 老板周. | R72: 【老板周】小众日系 秋冬叠穿时髦下摆不规则宽松马甲 花纱色 M（100-135斤） | S72: 花纱色 M（100-135斤） | T72: 1 | W72: 179.00 | X72: 179.00 | Y72: 0.00 | Z72: 0.00 | AB72: 0.00 | AC72: 179.00 | AD72: 支付宝 | AE72: 2025081522001420241411120796 | AI72: 2025-08-15 15:13:50 | AK72: 0.000 | AL72: 0.00 | AM72: 中通速递 | AN72: 73568735151062 | AV72: 2025-08-15 15:13:42 | AY72: 2025-08-30 15:13:50 | AZ72: 2025-08-19 23:25:35 | BA72: 2025-08-26 23:25:35 | BB72: 第三方平台卖家电子库存 | BC72: 系统自动收货 | BD72: 否 | BI72: LAO BAN ZHOU的店 | BJ72: 567cb8f4e00dd861900f2723 | BK72: 公司店运费模版 | BL72: 小红书公司 | BQ72: Z2378-花纱色-M | BR72: 689dee45c34eef00157e11fa | BS72: 【老板周】小众日系 秋冬叠穿时髦下摆不规则宽松马甲
A73: P770794018572034931 | B73: 已完成 | C73: 无售后 | D73: 预售订单 | F73: 胖* | G73: 158****0396 | H73: 浙江省 温州市 苍南县 *** | I73: 浙江省 | J73: 温州市 | K73: 苍南县 | L73: 330327100000 | M73: 689dee45c34eef00157e11fc | N73: XHS-3JY8RM310T1C | O73: 689dee45c34eef00157e11fb | P73: 650d6e9f000000001603a6ac | Q73: 老板周. | R73: 【老板周】小众日系 秋冬叠穿时髦下摆不规则宽松马甲 花纱色 S（80-100斤） | S73: 花纱色 S（80-100斤） | T73: 1 | W73: 179.00 | X73: 179.00 | Y73: 0.00 | Z73: 0.00 | AB73: 0.00 | AC73: 179.00 | AD73: 微信 | AE73: 4348502245202508159628346390 | AI73: 2025-08-15 15:13:44 | AK73: 0.000 | AL73: 0.00 | AM73: 中通速递 | AN73: 73568735151312 | AV73: 2025-08-15 15:13:38 | AY73: 2025-08-30 15:13:44 | AZ73: 2025-08-19 23:37:09 | BA73: 2025-08-26 23:37:09 | BB73: 第三方平台卖家电子库存 | BC73: 系统自动收货 | BD73: 否 | BI73: LAO BAN ZHOU的店 | BJ73: 62788d0c0000000010005c63 | BK73: 公司店运费模版 | BL73: 小红书公司 | BQ73: Z2378-花纱色-S | BR73: 689dee45c34eef00157e11fa | BS73: 【老板周】小众日系 秋冬叠穿时髦下摆不规则宽松马甲
A74: P770794019971106161 | B74: 已完成 | C74: 无售后 | D74: 预售订单 | F74: 何* | G74: 138****0996 | H74: 上海 上海市 浦东新区 *** | I74: 上海 | J74: 上海市 | K74: 浦东新区 | L74: 310115 | M74: 689dee45c34eef00157e11fe | N74: XHS-3JY8RM360LQ8 | O74: 689dee45c34eef00157e11fd | P74: 650d6e9f000000001603a6ac | Q74: 老板周. | R74: 【老板周】小众日系 秋冬叠穿时髦下摆不规则宽松马甲 花纱色 M（100-135斤） | S74: 花纱色 M（100-135斤） | T74: 1 | W74: 179.00 | X74: 179.00 | Y74: 0.00 | Z74: 0.00 | AB74: 0.00 | AC74: 179.00 | AD74: 微信 | AE74: 4343402237202508155774463952 | AI74: 2025-08-15 15:13:46 | AK74: 0.000 | AL74: 0.00 | AM74: 中通速递 | AN74: 73568735151287 | AV74: 2025-08-15 15:13:40 | AY74: 2025-08-30 15:13:46 | AZ74: 2025-08-19 23:25:35 | BA74: 2025-08-26 23:25:35 | BB74: 第三方平台卖家电子库存 | BC74: 系统自动收货 | BD74: 否 | BI74: LAO BAN ZHOU的店 | BJ74: 5a791d6ddb2e6075f46e5388 | BK74: 公司店运费模版 | BL74: 小红书公司 | BQ74: Z2378-花纱色-M | BR74: 689dee45c34eef00157e11fa | BS74: 【老板周】小众日系 秋冬叠穿时髦下摆不规则宽松马甲
A75: P770794020008329151 | B75: 已关闭 | C75: 售后完成 | D75: 预售订单 | F75: 杨** | G75: 152****7878 | H75: 山东省 滨州市 沾化区 *** | I75: 山东省 | J75: 滨州市 | K75: 沾化区 | L75: 371603001000 | M75: 689dee45c34eef00157e11fe | N75: XHS-3JY8RM360LQ8 | O75: 689dee45c34eef00157e11fd | P75: 650d6e9f000000001603a6ac | Q75: 老板周. | R75: 【老板周】小众日系 秋冬叠穿时髦下摆不规则宽松马甲 花纱色 M（100-135斤） | S75: 花纱色 M（100-135斤） | T75: 1 | W75: 179.00 | X75: 179.00 | Y75: 0.00 | Z75: 0.00 | AB75: 0.00 | AC75: 179.00 | AD75: 支付宝 | AE75: 2025081523001498651431776212 | AI75: 2025-08-15 15:14:06 | AK75: 0.000 | AL75: 0.00 | AM75: 中通速递 | AN75: 73568874677726 | AV75: 2025-08-15 15:13:40 | AY75: 2025-08-30 15:14:06 | AZ75: 2025-08-20 23:49:17 | BB75: 第三方平台卖家电子库存 | BD75: 否 | BF75: 蓝旗 | BG75: ;JDX042515159145(收） Z2378-花纱色-S*1# | BI75: LAO BAN ZHOU的店 | BJ75: 5a9517cc4eacab5b758a2332 | BK75: 公司店运费模版 | BL75: 小红书公司 | BQ75: Z2378-花纱色-M | BR75: 689dee45c34eef00157e11fa | BS75: 【老板周】小众日系 秋冬叠穿时髦下摆不规则宽松马甲
A76: P770793869532382601 | B76: 已完成 | C76: 售后完成 | D76: 预售订单 | F76: 陈** | G76: 180****1532 | H76: 上海 上海市 普陀区 *** | I76: 上海 | J76: 上海市 | K76: 普陀区 | L76: 310107 | M76: 689dee45c34eef00157e120a | N76: XHS-3JY8RM3ZZDVK | O76: 689dee45c34eef00157e1209 | P76: 650d6e9f000000001603a6ac | Q76: 老板周. | R76: 【老板周】小众日系 秋冬叠穿时髦下摆不规则宽松马甲 灰色 M（100-135斤） | S76: 灰色 M（100-135斤） | T76: 1 | W76: 179.00 | X76: 179.00 | Y76: 0.00 | Z76: 0.00 | AB76: 0.00 | AC76: 179.00 | AD76: 微信 | AE76: 4339602479202508159867562177 | AI76: 2025-08-15 15:11:16 | AK76: 0.000 | AL76: 0.00 | AM76: 中通速递 | AN76: 73568735150543 | AV76: 2025-08-15 15:11:09 | AY76: 2025-08-30 15:11:16 | AZ76: 2025-08-19 23:36:42 | BA76: 2025-08-26 23:36:42 | BB76: 第三方平台卖家电子库存 | BC76: 系统自动收货 | BD76: 否 | BF76: 蓝旗 | BG76: ;SF3230865560918(收） Z2378-灰色-M*1# | BI76: LAO BAN ZHOU的店 | BJ76: 5b2e5e756b58b75a69c5fce8 | BK76: 公司店运费模版 | BL76: 小红书公司 | BQ76: Z2378-灰色-M | BR76: 689dee45c34eef00157e11fa | BS76: 【老板周】小众日系 秋冬叠穿时髦下摆不规则宽松马甲
A77: P770794020316255331 | B77: 已完成 | C77: 无售后 | D77: 预售订单 | F77: 9***** | G77: 180****7809 | H77: 广东省 中山市 板芙镇 *** | I77: 广东省 | J77: 中山市 | K77: 板芙镇 | L77: 442000115000 | M77: 689dee45c34eef00157e11fe | N77: XHS-3JY8RM360LQ8 | O77: 689dee45c34eef00157e11fd | P77: 650d6e9f000000001603a6ac | Q77: 老板周. | R77: 【老板周】小众日系 秋冬叠穿时髦下摆不规则宽松马甲 花纱色 M（100-135斤） | S77: 花纱色 M（100-135斤） | T77: 1 | W77: 179.00 | X77: 179.00 | Y77: 0.00 | Z77: 0.00 | AB77: 0.00 | AC77: 179.00 | AD77: 微信 | AE77: 4319602253202508154825309425 | AI77: 2025-08-15 15:13:46 | AK77: 0.000 | AL77: 0.00 | AM77: 中通速递 | AN77: 73568735151141 | AV77: 2025-08-15 15:13:40 | AY77: 2025-08-30 15:13:46 | AZ77: 2025-08-19 23:25:35 | BA77: 2025-08-26 23:25:35 | BB77: 第三方平台卖家电子库存 | BC77: 系统自动收货 | BD77: 否 | BI77: LAO BAN ZHOU的店 | BJ77: 5c27b7140000000005039e8f | BK77: 公司店运费模版 | BL77: 小红书公司 | BQ77: Z2378-花纱色-M | BR77: 689dee45c34eef00157e11fa | BS77: 【老板周】小众日系 秋冬叠穿时髦下摆不规则宽松马甲
A78: P770794018587272501 | B78: 已关闭 | C78: 售后完成 | D78: 预售订单 | F78: 张** | G78: 139****7729 | H78: 浙江省 嘉兴市 南湖区 *** | I78: 浙江省 | J78: 嘉兴市 | K78: 南湖区 | L78: 330402014 | M78: 689dee45c34eef00157e11fe | N78: XHS-3JY8RM360LQ8 | O78: 689dee45c34eef00157e11fd | P78: 650d6e9f000000001603a6ac | Q78: 老板周. | R78: 【老板周】小众日系 秋冬叠穿时髦下摆不规则宽松马甲 花纱色 M（100-135斤） | S78: 花纱色 M（100-135斤） | T78: 1 | W78: 179.00 | X78: 179.00 | Y78: 0.00 | Z78: 0.00 | AB78: 0.00 | AC78: 179.00 | AD78: 支付宝 | AE78: 2025081522001401441437615721 | AI78: 2025-08-15 15:13:46 | AK78: 0.000 | AL78: 0.00 | AM78: 中通速递 | AN78: 73568735151019 | AV78: 2025-08-15 15:13:38 | AY78: 2025-08-30 15:13:46 | AZ78: 2025-08-19 23:25:35 | BA78: 2025-08-26 23:25:35 | BB78: 第三方平台卖家电子库存 | BC78: 系统自动收货 | BD78: 否 | BF78: 蓝旗 | BG78: ;773373691988931(收） Z2378-花纱色-M*1# | BI78: LAO BAN ZHOU的店 | BJ78: 5d1dcd5f0000000016022c66 | BK78: 公司店运费模版 | BL78: 小红书公司 | BQ78: Z2378-花纱色-M | BR78: 689dee45c34eef00157e11fa | BS78: 【老板周】小众日系 秋冬叠穿时髦下摆不规则宽松马甲
A79: P770794019357298741 | B79: 已完成 | C79: 无售后 | D79: 预售订单 | F79: 黄** | G79: 138****8611 | H79: 江苏省 泰州市 靖江市 *** | I79: 江苏省 | J79: 泰州市 | K79: 靖江市 | L79: 321282 | M79: 689dee45c34eef00157e11fe | N79: XHS-3JY8RM360LQ8 | O79: 689dee45c34eef00157e11fd | P79: 650d6e9f000000001603a6ac | Q79: 老板周. | R79: 【老板周】小众日系 秋冬叠穿时髦下摆不规则宽松马甲 花纱色 M（100-135斤） | S79: 花纱色 M（100-135斤） | T79: 1 | W79: 179.00 | X79: 179.00 | Y79: 0.00 | Z79: 0.00 | AB79: 0.00 | AC79: 179.00 | AD79: 支付宝 | AE79: 2025081522001418651441975041 | AI79: 2025-08-15 15:13:45 | AK79: 0.000 | AL79: 0.00 | AM79: 中通速递 | AN79: 73568735150252 | AV79: 2025-08-15 15:13:39 | AY79: 2025-08-30 15:13:45 | AZ79: 2025-08-19 23:25:35 | BA79: 2025-08-26 23:25:35 | BB79: 第三方平台卖家电子库存 | BC79: 系统自动收货 | BD79: 否 | BI79: LAO BAN ZHOU的店 | BJ79: 5bae3990dc55cf000120d032 | BK79: 公司店运费模版 | BL79: 小红书公司 | BQ79: Z2378-花纱色-M | BR79: 689dee45c34eef00157e11fa | BS79: 【老板周】小众日系 秋冬叠穿时髦下摆不规则宽松马甲
A80: P770794018286221631 | B80: 已完成 | C80: 无售后 | D80: 预售订单 | F80: 陈** | G80: 137****8275 | H80: 广东省 广州市 番禺区 *** | I80: 广东省 | J80: 广州市 | K80: 番禺区 | L80: 440113015000 | M80: 689dee45c34eef00157e11fc | N80: XHS-3JY8RM310T1C | O80: 689dee45c34eef00157e11fb | P80: 650d6e9f000000001603a6ac | Q80: 老板周. | R80: 【老板周】小众日系 秋冬叠穿时髦下摆不规则宽松马甲 花纱色 S（80-100斤） | S80: 花纱色 S（80-100斤） | T80: 1 | W80: 179.00 | X80: 179.00 | Y80: 0.00 | Z80: 0.00 | AB80: 0.00 | AC80: 179.00 | AD80: 支付宝 | AE80: 2025081523001422461431672573 | AI80: 2025-08-15 15:13:48 | AK80: 0.000 | AL80: 0.00 | AM80: 中通速递 | AN80: 73568735150648 | AV80: 2025-08-15 15:13:38 | AY80: 2025-08-30 15:13:48 | AZ80: 2025-08-19 23:37:09 | BA80: 2025-08-26 23:37:09 | BB80: 第三方平台卖家电子库存 | BC80: 系统自动收货 | BD80: 否 | BI80: LAO BAN ZHOU的店 | BJ80: 5f8ad074000000000101c803 | BK80: 公司店运费模版 | BL80: 小红书公司 | BQ80: Z2378-花纱色-S | BR80: 689dee45c34eef00157e11fa | BS80: 【老板周】小众日系 秋冬叠穿时髦下摆不规则宽松马甲
A81: P770794020469428631 | B81: 已完成 | C81: 无售后 | D81: 预售订单 | F81: s*** | G81: 136****8881 | H81: 四川省 成都市 郫都区 *** | I81: 四川省 | J81: 成都市 | K81: 郫都区 | L81: 510124108 | M81: 689dee45c34eef00157e11fe | N81: XHS-3JY8RM360LQ8 | O81: 689dee45c34eef00157e11fd | P81: 650d6e9f000000001603a6ac | Q81: 老板周. | R81: 【老板周】小众日系 秋冬叠穿时髦下摆不规则宽松马甲 花纱色 M（100-135斤） | S81: 花纱色 M（100-135斤） | T81: 1 | W81: 179.00 | X81: 179.00 | Y81: 0.00 | Z81: 0.00 | AB81: 0.00 | AC81: 179.00 | AD81: 支付宝 | AE81: 2025081522001444341440753302 | AI81: 2025-08-15 15:13:47 | AK81: 0.000 | AL81: 0.00 | AM81: 中通速递 | AN81: 73568735150081 | AV81: 2025-08-15 15:13:40 | AY81: 2025-08-30 15:13:47 | AZ81: 2025-08-19 23:25:35 | BA81: 2025-08-26 23:25:35 | BB81: 第三方平台卖家电子库存 | BC81: 系统自动收货 | BD81: 否 | BI81: LAO BAN ZHOU的店 | BJ81: 5481bc0cd6e4a968faed64db | BK81: 公司店运费模版 | BL81: 小红书公司 | BQ81: Z2378-花纱色-M | BR81: 689dee45c34eef00157e11fa | BS81: 【老板周】小众日系 秋冬叠穿时髦下摆不规则宽松马甲
A82: P770794019497300331 | B82: 已完成 | C82: 无售后 | D82: 预售订单 | F82: 丁** | G82: 137****8267 | H82: 上海 上海市 宝山区 *** | I82: 上海 | J82: 上海市 | K82: 宝山区 | L82: 310113109000 | M82: 689dee45c34eef00157e11fe | N82: XHS-3JY8RM360LQ8 | O82: 689dee45c34eef00157e11fd | P82: 650d6e9f000000001603a6ac | Q82: 老板周. | R82: 【老板周】小众日系 秋冬叠穿时髦下摆不规则宽松马甲 花纱色 M（100-135斤） | S82: 花纱色 M（100-135斤） | T82: 1 | W82: 179.00 | X82: 179.00 | Y82: 0.00 | Z82: 0.00 | AB82: 0.00 | AC82: 179.00 | AD82: 微信 | AE82: 4350902465202508157181310652 | AI82: 2025-08-15 15:13:45 | AK82: 0.000 | AL82: 0.00 | AM82: 中通速递 | AN82: 73568735150597 | AV82: 2025-08-15 15:13:39 | AY82: 2025-08-30 15:13:45 | AZ82: 2025-08-19 23:25:35 | BA82: 2025-08-26 23:25:35 | BB82: 第三方平台卖家电子库存 | BC82: 系统自动收货 | BD82: 否 | BI82: LAO BAN ZHOU的店 | BJ82: 5558a9d167bc653fc2f3e4ab | BK82: 公司店运费模版 | BL82: 小红书公司 | BQ82: Z2378-花纱色-M | BR82: 689dee45c34eef00157e11fa | BS82: 【老板周】小众日系 秋冬叠穿时髦下摆不规则宽松马甲
A83: P770794019068036511 | B83: 已完成 | C83: 无售后 | D83: 预售订单 | F83: 张 | G83: 157****8966 | H83: 内蒙古自治区 鄂尔多斯市 伊金霍洛旗 *** | I83: 内蒙古自治区 | J83: 鄂尔多斯市 | K83: 伊金霍洛旗 | L83: 150627 | M83: 689dee45c34eef00157e11fe | N83: XHS-3JY8RM360LQ8 | O83: 689dee45c34eef00157e11fd | P83: 650d6e9f000000001603a6ac | Q83: 老板周. | R83: 【老板周】小众日系 秋冬叠穿时髦下摆不规则宽松马甲 花纱色 M（100-135斤） | S83: 花纱色 M（100-135斤） | T83: 1 | W83: 179.00 | X83: 179.00 | Y83: 0.00 | Z83: 0.00 | AB83: 0.00 | AC83: 179.00 | AD83: 支付宝 | AE83: 2025081523001418451412697964 | AI83: 2025-08-15 15:13:50 | AK83: 0.000 | AL83: 0.00 | AM83: 中通速递 | AN83: 73568735150939 | AV83: 2025-08-15 15:13:39 | AY83: 2025-08-30 15:13:50 | AZ83: 2025-08-19 23:25:35 | BA83: 2025-08-26 23:25:35 | BB83: 第三方平台卖家电子库存 | BC83: 系统自动收货 | BD83: 否 | BI83: LAO BAN ZHOU的店 | BJ83: 59dcb65fde5fb43d22d6e00f | BK83: 公司店运费模版 | BL83: 小红书公司 | BQ83: Z2378-花纱色-M | BR83: 689dee45c34eef00157e11fa | BS83: 【老板周】小众日系 秋冬叠穿时髦下摆不规则宽松马甲
A84: P770794018206458841 | B84: 已关闭 | C84: 售后完成 | D84: 预售订单 | F84: 阎** | G84: 139****3167 | H84: 甘肃省 兰州市 城关区 *** | I84: 甘肃省 | J84: 兰州市 | K84: 城关区 | L84: 620102 | M84: 689dee45c34eef00157e11fe | N84: XHS-3JY8RM360LQ8 | O84: 689dee45c34eef00157e11fd | P84: 650d6e9f000000001603a6ac | Q84: 老板周. | R84: 【老板周】小众日系 秋冬叠穿时髦下摆不规则宽松马甲 花纱色 M（100-135斤） | S84: 花纱色 M（100-135斤） | T84: 1 | W84: 179.00 | X84: 179.00 | Y84: 0.00 | Z84: 0.00 | AB84: 0.00 | AC84: 179.00 | AD84: 支付宝 | AE84: 2025081522001415121422827257 | AI84: 2025-08-15 15:13:45 | AK84: 0.000 | AL84: 0.00 | AM84: 中通速递 | AN84: 73568735151466 | AV84: 2025-08-15 15:13:38 | AY84: 2025-08-30 15:13:45 | AZ84: 2025-08-19 23:25:35 | BA84: 2025-08-26 23:25:35 | BB84: 第三方平台卖家电子库存 | BC84: 系统自动收货 | BD84: 否 | BF84: 蓝旗 | BG84: ;JDX042497264569(收） Z2378-花纱色-M*1# | BI84: LAO BAN ZHOU的店 | BJ84: 5b601fae4eacab6cf4db9917 | BK84: 公司店运费模版 | BL84: 小红书公司 | BQ84: Z2378-花纱色-M | BR84: 689dee45c34eef00157e11fa | BS84: 【老板周】小众日系 秋冬叠穿时髦下摆不规则宽松马甲
A85: P770794017000112911 | B85: 已完成 | C85: 无售后 | D85: 预售订单 | F85: 小** | G85: 138****1113 | H85: 江苏省 苏州市 姑苏区 *** | I85: 江苏省 | J85: 苏州市 | K85: 姑苏区 | L85: 320508024000 | M85: 689dee45c34eef00157e11fc | N85: XHS-3JY8RM310T1C | O85: 689dee45c34eef00157e11fb | P85: 650d6e9f000000001603a6ac | Q85: 老板周. | R85: 【老板周】小众日系 秋冬叠穿时髦下摆不规则宽松马甲 花纱色 S（80-100斤） | S85: 花纱色 S（80-100斤） | T85: 1 | W85: 179.00 | X85: 179.00 | Y85: 0.00 | Z85: 0.00 | AB85: 0.00 | AC85: 179.00 | AD85: 支付宝 | AE85: 2025081522001401121429359236 | AI85: 2025-08-15 15:13:45 | AK85: 0.000 | AL85: 0.00 | AM85: 中通速递 | AN85: 73568735151417 | AV85: 2025-08-15 15:13:37 | AY85: 2025-08-30 15:13:45 | AZ85: 2025-08-19 23:37:09 | BA85: 2025-08-26 23:37:09 | BB85: 第三方平台卖家电子库存 | BC85: 系统自动收货 | BD85: 否 | BI85: LAO BAN ZHOU的店 | BJ85: 560a02243397db0e6720e25a | BK85: 公司店运费模版 | BL85: 小红书公司 | BQ85: Z2378-花纱色-S | BR85: 689dee45c34eef00157e11fa | BS85: 【老板周】小众日系 秋冬叠穿时髦下摆不规则宽松马甲
A86: P770643835711413521 | B86: 已关闭 | C86: 售后完成 | D86: 预售订单 | F86: 张** | G86: 181****5302 | H86: 河南省 郑州市 郑州经济技术开发区 *** | I86: 河南省 | J86: 郑州市 | K86: 郑州经济技术开发区 | L86: 410171561000 | M86: 6896fe67c165480015b3eb01 | N86: XHS-2Z4TJTXW55OG | O86: 6896fe67c165480015b3eb00 | R86: 【老板周】舒适休闲 极简短版腰头抽绳设计宽松半身裙 黑色 S（80-100斤） | S86: 黑色 S（80-100斤） | T86: 1 | W86: 189.00 | X86: 189.00 | Y86: 0.00 | Z86: 0.00 | AB86: 0.00 | AC86: 189.00 | AD86: 支付宝 | AE86: 2025081322001479671408881982 | AI86: 2025-08-13 21:30:46 | AK86: 0.000 | AL86: 0.00 | AM86: 中通速递 | AN86: 73568874685735 | AV86: 2025-08-13 21:30:36 | AY86: 2025-08-28 21:30:46 | AZ86: 2025-08-20 23:50:55 | BB86: 第三方平台卖家电子库存 | BD86: 否 | BF86: 蓝旗 | BG86: ;SF3289570487093(收） Z1576-黑色-S*1 Z1645-黑色-S*1# | BI86: LAO BAN ZHOU的店 | BJ86: 58c5584c5e87e743058ba819 | BK86: 公司店运费模版 | BL86: 小红书公司 | BQ86: Z1645-黑色-S | BR86: 6896fe67c165480015b3eaff | BS86: 【老板周】舒适休闲 极简短版腰头抽绳设计宽松半身裙
A87: P770643835711413521 | B87: 已关闭 | C87: 售后完成 | D87: 预售订单 | F87: 张** | G87: 181****5302 | H87: 河南省 郑州市 郑州经济技术开发区 *** | I87: 河南省 | J87: 郑州市 | K87: 郑州经济技术开发区 | L87: 410171561000 | M87: 6896fe48057f570015d29243 | N87: XHS-2Z0D3IBQCYKG | O87: 6896fe48057f570015d29242 | P87: 650d6e9f000000001603a6ac | Q87: 老板周. | R87: 【老板周】时髦撞色 春季新款假两件显瘦长袖打底T恤上衣 黑色 S（80-100斤） | S87: 黑色 S（80-100斤） | T87: 1 | W87: 199.00 | X87: 199.00 | Y87: 0.00 | Z87: 0.00 | AB87: 0.00 | AC87: 199.00 | AD87: 支付宝 | AE87: 2025081322001479671408881982 | AI87: 2025-08-13 21:30:46 | AK87: 0.000 | AL87: 0.00 | AM87: 中通速递 | AN87: 73569012203279 | AV87: 2025-08-13 21:30:36 | AY87: 2025-08-28 21:30:46 | AZ87: 2025-08-21 23:19:25 | BB87: 第三方平台卖家电子库存 | BD87: 否 | BF87: 蓝旗 | BG87: ;SF3289570487093(收） Z1576-黑色-S*1 Z1645-黑色-S*1# | BI87: LAO BAN ZHOU的店 | BJ87: 58c5584c5e87e743058ba819 | BK87: 公司店运费模版 | BL87: 小红书公司 | BQ87: Z1576-黑色-S | BR87: 6896fe48057f570015d29241 | BS87: 【老板周】时髦撞色 春季新款假两件显瘦长袖打底T恤上衣
A88: P770643835711413521 | B88: 已关闭 | C88: 售后完成 | D88: 预售订单 | F88: 张** | G88: 181****5302 | H88: 河南省 郑州市 郑州经济技术开发区 *** | I88: 河南省 | J88: 郑州市 | K88: 郑州经济技术开发区 | L88: 410171561000 | M88: 6896fe5c3b9d47001590a857 | N88: XHS-31AJPPHCTL34 | O88: 6896fe5c3b9d47001590a856 | P88: 650d6e9f000000001603a6ac | Q88: 老板周. | R88: 【老板周】日系极简 春季新品圆领简约设计感无袖马甲 黑色 S（80-100斤） | S88: 黑色 S（80-100斤） | T88: 1 | W88: 289.00 | X88: 289.00 | Y88: 0.00 | Z88: 0.00 | AB88: 0.00 | AC88: 289.00 | AD88: 支付宝 | AE88: 2025081322001479671408881982 | AI88: 2025-08-13 21:30:46 | AK88: 0.000 | AL88: 0.00 | AV88: 2025-08-13 21:30:36 | AY88: 2025-08-28 21:30:46 | BB88: 第三方平台卖家电子库存 | BD88: 否 | BF88: 蓝旗 | BG88: ;SF3289570487093(收） Z1576-黑色-S*1 Z1645-黑色-S*1# | BI88: LAO BAN ZHOU的店 | BJ88: 58c5584c5e87e743058ba819 | BK88: 公司店运费模版 | BL88: 小红书公司 | BQ88: Z1640-黑色-S | BR88: 6896fe5c3b9d47001590a855 | BS88: 【老板周】日系极简 春季新品圆领简约设计感无袖马甲
A89: P770645825682316701 | B89: 已完成 | C89: 无售后 | D89: 预售订单 | F89: 罗 | G89: 139****6727 | H89: 上海 上海市 松江区 *** | I89: 上海 | J89: 上海市 | K89: 松江区 | L89: 310117105000 | M89: 6896fe48057f570015d29245 | N89: XHS-2Z0D3J1YAL8G | O89: 6896fe48057f570015d29244 | P89: 650d6e9f000000001603a6ac | Q89: 老板周. | R89: 【老板周】时髦撞色 春季新款假两件显瘦长袖打底T恤上衣 黑色 M（100-120斤） | S89: 黑色 M（100-120斤） | T89: 1 | W89: 199.00 | X89: 199.00 | Y89: 0.00 | Z89: 0.00 | AB89: 0.00 | AC89: 199.00 | AD89: 微信 | AE89: 4303502284202508134947847381 | AI89: 2025-08-13 22:03:51 | AK89: 0.000 | AL89: 0.00 | AM89: 中通速递 | AN89: 73569012203440 | AV89: 2025-08-13 22:03:45 | AY89: 2025-08-28 22:03:51 | AZ89: 2025-08-21 23:19:25 | BA89: 2025-08-27 06:17:55 | BB89: 第三方平台卖家电子库存 | BC89: 用户确认收货 | BD89: 否 | BI89: LAO BAN ZHOU的店 | BJ89: 5e940fa200000000010067c3 | BK89: 公司店运费模版 | BL89: 小红书公司 | BQ89: Z1576-黑色-M | BR89: 6896fe48057f570015d29241 | BS89: 【老板周】时髦撞色 春季新款假两件显瘦长袖打底T恤上衣
A90: P770645880641023381 | B90: 已关闭 | C90: 售后完成 | D90: 预售订单 | F90: 陈* | G90: 177****1409 | H90: 重庆 重庆市 江津区 *** | I90: 重庆 | J90: 重庆市 | K90: 江津区 | L90: 500116006 | M90: 6896fe48057f570015d29245 | N90: XHS-2Z0D3J1YAL8G | O90: 6896fe48057f570015d29244 | P90: 650d6e9f000000001603a6ac | Q90: 老板周. | R90: 【老板周】时髦撞色 春季新款假两件显瘦长袖打底T恤上衣 黑色 M（100-120斤） | S90: 黑色 M（100-120斤） | T90: 1 | W90: 199.00 | X90: 199.00 | Y90: 0.00 | Z90: 0.00 | AB90: 0.00 | AC90: 199.00 | AD90: 微信 | AE90: 4348702586202508138748925665 | AI90: 2025-08-13 22:04:56 | AK90: 0.000 | AL90: 0.00 | AM90: 中通速递 | AN90: 73569012202336 | AV90: 2025-08-13 22:04:40 | AY90: 2025-08-28 22:04:56 | AZ90: 2025-08-21 23:19:26 | BB90: 第三方平台卖家电子库存 | BD90: 否 | BF90: 蓝旗 | BG90: ;JDX042521186517(收） Z1576-黑色-M*1# | BI90: LAO BAN ZHOU的店 | BJ90: 618892ca0000000010007c31 | BK90: 公司店运费模版 | BL90: 小红书公司 | BQ90: Z1576-黑色-M | BR90: 6896fe48057f570015d29241 | BS90: 【老板周】时髦撞色 春季新款假两件显瘦长袖打底T恤上衣
A91: P770638780093456882 | B91: 已完成 | C91: 无售后 | D91: 预售订单 | F91: 张* | G91: 181****8041 | H91: 广东省 深圳市 宝安区 *** | I91: 广东省 | J91: 深圳市 | K91: 宝安区 | L91: 440306004 | M91: 6896fe335cb63500154f597a | N91: XHS-2Z0FTLHATY4G | O91: 6896fe335cb63500154f5979 | P91: 650d6e9f000000001603a6ac | Q91: 老板周. | R91: 【老板周】松弛感 春夏新款简约休闲宽松阔腿弯刀私服裤 黑色 M（100-120斤） | S91: 黑色 M（100-120斤） | T91: 1 | W91: 289.00 | X91: 289.00 | Y91: 0.00 | Z91: 0.00 | AB91: 0.00 | AC91: 289.00 | AD91: 支付宝 | AI91: 2025-08-13 20:06:25 | AK91: 0.000 | AL91: 0.00 | AM91: 中通速递 | AN91: 73568731902560 | AV91: 2025-08-13 20:06:20 | AY91: 2025-08-28 20:06:25 | AZ91: 2025-08-19 22:48:51 | BA91: 2025-08-26 22:48:51 | BB91: 第三方平台卖家电子库存 | BC91: 系统自动收货 | BD91: 否 | BI91: LAO BAN ZHOU的店 | BJ91: 5ad200f54eacab2e0d3580f1 | BK91: 公司店运费模版 | BL91: 小红书公司 | BQ91: Z1581-黑色-M | BR91: 6896fe335cb63500154f5970 | BS91: 【老板周】松弛感 春夏新款简约休闲宽松阔腿弯刀私服裤
A92: P770637065043122801 | B92: 已完成 | C92: 无售后 | D92: 预售订单 | F92: 橘* | G92: 188****3517 | H92: 广西壮族自治区 南宁市 青秀区 *** | I92: 广西壮族自治区 | J92: 南宁市 | K92: 青秀区 | L92: 450103 | M92: 6896fe335cb63500154f5974 | N92: XHS-2Z0FTJ3XWUM8 | O92: 6896fe335cb63500154f5973 | P92: 650d6e9f000000001603a6ac | Q92: 老板周. | R92: 【老板周】松弛感 春夏新款简约休闲宽松阔腿弯刀私服裤 白色 M（100-120斤） | S92: 白色 M（100-120斤） | T92: 1 | W92: 289.00 | X92: 289.00 | Y92: 0.00 | Z92: 0.00 | AB92: 0.00 | AC92: 289.00 | AD92: 微信 | AE92: 4350602266202508138211126988 | AI92: 2025-08-13 19:38:00 | AK92: 0.000 | AL92: 0.00 | AM92: 中通速递 | AN92: 73568731902440 | AV92: 2025-08-13 19:37:45 | AY92: 2025-08-28 19:38:00 | AZ92: 2025-08-19 22:29:58 | BA92: 2025-08-26 22:29:58 | BB92: 第三方平台卖家电子库存 | BC92: 系统自动收货 | BD92: 否 | BI92: LAO BAN ZHOU的店 | BJ92: 57629b8f50c4b43c0b5f0f18 | BK92: 公司店运费模版 | BL92: 小红书公司 | BQ92: Z1581-白色-M | BR92: 6896fe335cb63500154f5970 | BS92: 【老板周】松弛感 春夏新款简约休闲宽松阔腿弯刀私服裤
A93: P770629227939064881 | B93: 已完成 | C93: 无售后 | D93: 预售订单 | F93: 冯** | G93: 156****4106 | H93: 北京 北京市 平谷区 *** | I93: 北京 | J93: 北京市 | K93: 平谷区 | L93: 110117005000 | M93: 6894abfd581ea2001544ce83 | N93: XHS-3IRG3JNKD98G | O93: 6894abfd581ea2001544ce82 | P93: 650d6e9f000000001603a6ac | Q93: 老板周. | R93: 【老板周】法式复古 秋冬新品不规则纹理白天鹅针织上衣 米白色 L（120-135斤） | S93: 米白色 L（120-135斤） | T93: 1 | W93: 169.00 | X93: 169.00 | Y93: 0.00 | Z93: 0.00 | AB93: 0.00 | AC93: 169.00 | AD93: 微信先用后付 | AI93: 2025-08-13 17:27:09 | AK93: 0.000 | AL93: 0.00 | AM93: 中通速递 | AN93: 73569291685753 | AV93: 2025-08-13 17:27:08 | AY93: 2025-08-28 17:27:09 | AZ93: 2025-08-23 22:17:49 | BA93: 2025-08-27 07:04:23 | BB93: 第三方平台卖家电子库存 | BC93: 用户确认收货 | BD93: 否 | BI93: LAO BAN ZHOU的店 | BJ93: 60364dbb0000000001000844 | BK93: 公司店运费模版 | BL93: 小红书公司 | BQ93: Z2333-米白色-L | BR93: 6894abfd581ea2001544ce7d | BS93: 【老板周】法式复古 秋冬新品不规则纹理白天鹅针织上衣
A94: P770633097859472931 | B94: 已关闭 | C94: 售后完成 | D94: 预售订单 | F94: 文** | G94: 138****5050 | H94: 辽宁省 沈阳市 苏家屯区 *** | I94: 辽宁省 | J94: 沈阳市 | K94: 苏家屯区 | L94: 210111 | M94: 6896fe335cb63500154f597c | N94: XHS-2Z0FTM8FFZEO | O94: 6896fe335cb63500154f597b | P94: 650d6e9f000000001603a6ac | Q94: 老板周. | R94: 【老板周】松弛感 春夏新款简约休闲宽松阔腿弯刀私服裤 黑色 L（120-135斤） | S94: 黑色 L（120-135斤） | T94: 1 | W94: 289.00 | X94: 289.00 | Y94: 0.00 | Z94: 0.00 | AB94: 0.00 | AC94: 289.00 | AD94: 支付宝 | AE94: 2025081322001471731419169749 | AI94: 2025-08-13 18:31:44 | AK94: 0.000 | AL94: 0.00 | AM94: 中通速递 | AN94: 73568731902281 | AV94: 2025-08-13 18:31:38 | AY94: 2025-08-28 18:31:44 | AZ94: 2025-08-19 22:17:32 | BA94: 2025-08-26 22:17:33 | BB94: 第三方平台卖家电子库存 | BC94: 系统自动收货 | BD94: 否 | BF94: 蓝旗 | BG94: ;772046773695972(收） Z1581-黑色-L*1# | BI94: LAO BAN ZHOU的店 | BJ94: 5c2cd2ef0000000007037223 | BK94: 公司店运费模版 | BL94: 小红书公司 | BQ94: Z1581-黑色-L | BR94: 6896fe335cb63500154f5970 | BS94: 【老板周】松弛感 春夏新款简约休闲宽松阔腿弯刀私服裤
A95: P770628663394212021 | B95: 已关闭 | C95: 售后完成 | D95: 预售订单 | F95: 风* | G95: 182****6980 | H95: 河南省 南阳市 唐河县 *** | I95: 河南省 | J95: 南阳市 | K95: 唐河县 | L95: 411328101000 | M95: 6894abfd581ea2001544ce81 | N95: XHS-3IRG3JNFDGJK | O95: 6894abfd581ea2001544ce80 | P95: 650d6e9f000000001603a6ac | Q95: 老板周. | R95: 【老板周】法式复古 秋冬新品不规则纹理白天鹅针织上衣 米白色 M（100-120斤） | S95: 米白色 M（100-120斤） | T95: 1 | W95: 169.00 | X95: 169.00 | Y95: 0.00 | Z95: 0.00 | AB95: 0.00 | AC95: 169.00 | AD95: 支付宝 | AE95: 2025081322001411221414995144 | AI95: 2025-08-13 17:17:55 | AK95: 0.000 | AL95: 0.00 | AM95: 中通速递 | AN95: 73569291686316 | AV95: 2025-08-13 17:17:43 | AY95: 2025-08-28 17:17:55 | AZ95: 2025-08-23 22:19:03 | BB95: 第三方平台卖家电子库存 | BD95: 否 | BF95: 蓝旗 | BG95: ;SF3230189229018(收） Z2333-米白色-M*1# | BI95: LAO BAN ZHOU的店 | BJ95: 5fc21a700000000001005077 | BK95: 公司店运费模版 | BL95: 小红书公司 | BQ95: Z2333-米白色-M | BR95: 6894abfd581ea2001544ce7d | BS95: 【老板周】法式复古 秋冬新品不规则纹理白天鹅针织上衣
A96: P770625887719453891 | B96: 已完成 | C96: 售后完成 | D96: 预售订单 | F96: 张** | G96: 138****1310 | H96: 天津 天津市 河西区 *** | I96: 天津 | J96: 天津市 | K96: 河西区 | L96: 120103003 | M96: 689b434256a70c0015776468 | N96: XHS-3JR16LNXWRGG | O96: 689b434256a70c0015776467 | P96: 650d6e9f000000001603a6ac | Q96: 老板周. | R96: LAO BAN ZHOU 【老板周】休闲经典 秋冬新品时髦百搭牛仔破洞背带裤 牛仔蓝色 L（120-135斤） | S96: 牛仔蓝色 L（120-135斤） | T96: 1 | W96: 399.00 | X96: 399.00 | Y96: 0.00 | Z96: 0.00 | AB96: 0.00 | AC96: 399.00 | AD96: 支付宝 | AE96: 2025081322001463681445754321 | AI96: 2025-08-13 16:31:38 | AK96: 0.000 | AL96: 0.00 | AM96: 中通速递 | AN96: 73568436949837 | AV96: 2025-08-13 16:31:27 | AY96: 2025-08-28 16:31:38 | AZ96: 2025-08-17 20:43:59 | BA96: 2025-08-24 20:43:59 | BB96: 第三方平台卖家电子库存 | BC96: 系统自动收货 | BD96: 否 | BF96: 蓝旗 | BG96: ;JDX042558273617(收） Z2284-牛仔蓝色-L*1# | BI96: LAO BAN ZHOU的店 | BJ96: 574a54625e87e71443ed2da8 | BK96: 公司店运费模版 | BL96: 小红书公司 | BQ96: Z2284-牛仔蓝色-L | BR96: 689b434256a70c0015776462 | BS96: 【老板周】休闲经典 秋冬新品时髦百搭牛仔破洞背带裤
A97: P770388218319370581 | B97: 已完成 | C97: 无售后 | D97: 预售订单 | F97: 唐** | G97: 138****6293 | H97: 浙江省 绍兴市 越城区 *** | I97: 浙江省 | J97: 绍兴市 | K97: 越城区 | L97: 330602006000 | M97: 6894abfd581ea2001544ce7f | N97: XHS-3IRG3JNADNUO | O97: 6894abfd581ea2001544ce7e | P97: 650d6e9f000000001603a6ac | Q97: 老板周. | R97: 【老板周】法式复古 秋冬新品不规则纹理白天鹅针织上衣 米白色 S（80-100斤） | S97: 米白色 S（80-100斤） | T97: 1 | W97: 169.00 | X97: 169.00 | Y97: 0.00 | Z97: 0.00 | AB97: 0.00 | AC97: 169.00 | AD97: 微信 | AE97: 4304702266202508100505551309 | AI97: 2025-08-10 22:30:26 | AK97: 0.000 | AL97: 0.00 | AM97: 中通速递 | AN97: 73568735150240 | AV97: 2025-08-10 22:30:18 | AY97: 2025-08-25 22:30:26 | AZ97: 2025-08-19 23:24:11 | BA97: 2025-08-26 23:24:11 | BB97: 第三方平台卖家电子库存 | BC97: 系统自动收货 | BD97: 否 | BI97: LAO BAN ZHOU的店 | BJ97: 5890a2d76a6a690a36528a3e | BK97: 公司店运费模版 | BL97: 小红书公司 | BQ97: Z2333-米白色-S | BR97: 6894abfd581ea2001544ce7d | BS97: 【老板周】法式复古 秋冬新品不规则纹理白天鹅针织上衣
A98: P770388132291000981 | B98: 已完成 | C98: 无售后 | D98: 预售订单 | F98: J****** | G98: 150****6385 | H98: 辽宁省 沈阳市 和平区 *** | I98: 辽宁省 | J98: 沈阳市 | K98: 和平区 | L98: 210102 | M98: 6894abfd581ea2001544ce7f | N98: XHS-3IRG3JNADNUO | O98: 6894abfd581ea2001544ce7e | P98: 650d6e9f000000001603a6ac | Q98: 老板周. | R98: 【老板周】法式复古 秋冬新品不规则纹理白天鹅针织上衣 米白色 S（80-100斤） | S98: 米白色 S（80-100斤） | T98: 1 | W98: 169.00 | X98: 169.00 | Y98: 0.00 | Z98: 0.00 | AB98: 0.00 | AC98: 169.00 | AD98: 支付宝 | AE98: 2025081022001411621442949422 | AI98: 2025-08-10 22:28:58 | AK98: 0.000 | AL98: 0.00 | AM98: 中通速递 | AN98: 73568735151325 | AV98: 2025-08-10 22:28:52 | AY98: 2025-08-25 22:28:58 | AZ98: 2025-08-19 23:24:06 | BA98: 2025-08-26 23:24:06 | BB98: 第三方平台卖家电子库存 | BC98: 系统自动收货 | BD98: 否 | BI98: LAO BAN ZHOU的店 | BJ98: 5759b61150c4b432a713734c | BK98: 公司店运费模版 | BL98: 小红书公司 | BQ98: Z2333-米白色-S | BR98: 6894abfd581ea2001544ce7d | BS98: 【老板周】法式复古 秋冬新品不规则纹理白天鹅针织上衣
A99: P770381824712038751 | B99: 已关闭 | C99: 售后完成 | D99: 预售订单 | E99: 已改地址 | F99: 贺* | G99: 136****5810 | H99: 山东省 青岛市 市北区 *** | I99: 山东省 | J99: 青岛市 | K99: 市北区 | L99: 370203035000 | M99: 68970ccdfe39ac0015b91516 | N99: XHS-31Z6WPZ8ZG1S | O99: 68970ccdfe39ac0015b91515 | P99: 650d6e9f000000001603a6ac | Q99: 老板周. | R99: 【老板周】复古英伦 极简设计立体剪裁无领廓形外套 黑色 L（120-135斤） | S99: 黑色 L（120-135斤） | T99: 1 | W99: 499.00 | X99: 499.00 | Y99: 0.00 | Z99: 0.00 | AB99: 0.00 | AC99: 499.00 | AD99: 微信 | AE99: 4324602291202508101380702260 | AI99: 2025-08-10 20:43:53 | AK99: 0.000 | AL99: 0.00 | AM99: 中通速递 | AN99: 73568444479401 | AV99: 2025-08-10 20:43:44 | AY99: 2025-08-25 20:43:53 | AZ99: 2025-08-17 22:17:32 | BA99: 2025-08-24 22:17:32 | BB99: 第三方平台卖家电子库存 | BC99: 系统自动收货 | BD99: 否 | BF99: 蓝旗 | BG99: ;JDX042514972942(收） Z1688-黑色-L*1# | BI99: LAO BAN ZHOU的店 | BJ99: 598eec1f5e87e77b1b9d8e14 | BK99: 公司店运费模版 | BL99: 小红书公司 | BQ99: Z1688-黑色-L | BR99: 68970ccdfe39ac0015b91510 | BS99: 【老板周】复古英伦 极简设计立体剪裁无领廓形外套
A100: P770450992956407491 | B100: 已完成 | C100: 售后完成 | D100: 预售订单 | F100: 令* | G100: 139****0198 | H100: 江苏省 南京市 鼓楼区 *** | I100: 江苏省 | J100: 南京市 | K100: 鼓楼区 | L100: 320106004000 | M100: 6896fe0c6d08080015500897 | N100: XHS-3EHYVMDISL4W | O100: 6896fe0c6d08080015500896 | P100: 650d6e9f000000001603a6ac | Q100: 老板周. | R100: 【老板周】夏季轻盈 新品圆领气质轻薄不规则透气上衣 黑色 XL（120-135斤） | S100: 黑色 XL（120-135斤） | T100: 1 | W100: 129.00 | X100: 129.00 | Y100: 0.00 | Z100: 0.00 | AB100: 0.00 | AC100: 129.00 | AD100: 微信 | AE100: 4350202571202508117674522708 | AI100: 2025-08-11 15:56:40 | AK100: 0.000 | AL100: 0.00 | AM100: 中通速递 | AN100: 73568587024805 | AV100: 2025-08-11 15:56:33 | AY100: 2025-08-26 15:56:40 | AZ100: 2025-08-18 21:22:40 | BA100: 2025-08-25 21:22:40 | BB100: 第三方平台卖家电子库存 | BC100: 系统自动收货 | BD100: 否 | BF100: 蓝旗 | BG100: ;JDX042627226783(收） Z2183-黑色-XL*1# | BI100: LAO BAN ZHOU的店 | BJ100: 590833fb6a6a692fae5bf779 | BK100: 公司店运费模版 | BL100: 小红书公司 | BQ100: Z2183-黑色-XL | BR100: 6896fe0c6d08080015500891 | BS100: 【老板周】夏季轻盈 新品圆领气质轻薄不规则透气上衣
...

Sheet 结算明细
A1: 年 | B1: 月 | C1: 订单号 | D1: 订单行数 | E1: 订单序位 | F1: 商家编码 | G1: 财务核算编码 | H1: 销售数量 | I1: 应收客户 | J1: 应收平台 | K1: 收：价外收费 | L1: 扣：平台佣金用 | M1: 扣：分销佣金 | N1: 扣其它费用 | O1: 应到账金额 | P1: 备注1 | Q1: 备注2 | R1: 订单号 | S1: 售后单号 | T1: 下单时间 | U1: 完成时间 | V1: 结算时间 | W1: 交易类型 | X1: 结算账户 | Y1: 动账金额 | Z1: 商品名称 | AA1: 类目 | AB1: SKU条码 | AC1: 规格ID | AD1: 商品数量 | AE1: 计佣基数 | AF1: 商品实付/实退 | AG1: 优惠类型 | AH1: 商家优惠 | AI1: 平台优惠补贴 | AJ1: 平台运费补贴 | AK1: 佣金率 | AL1: 返利率 | AM1: 佣金总额 | AN1: 计税价格(含税) | AO1: 计税价格(未税) | AP1: 税率 | AQ1: 跨境税代缴 | AR1: 商品税金 | AS1: 卖家CPS佣金率 | AT1: 分销佣金 | AU1: _x0008__x0008_推广_x0008_达人ID | AV1: 达人昵称 | AW1: 带货类型 | AX1: 代运营服务商佣金 | AY1: 代开发服务商佣金 | AZ1: 运费 | BA1: 运费税金 | BB1: 支付渠道费 | BC1: 花呗分期手续费 | BD1: 国补订单毛保金额 | BE1: 备注
A2: =YEAR(V2) -> 2025 | B2: =MONTH(V2) -> 8 | C2: =R2 -> P770450992956407491 | D2: =COUNTIF(R:R,R2) -> 2 | E2: =COUNTIF($R$2:R2,R2) -> 1 | F2: {=INDEX(订单明细!BQ:BQ,MATCH(R2&AC2,订单明细!A:A&订单明细!O:O,0))} -> Z2183-黑色-XL | G2: =LEFT(F2,FIND("-",F2)-1) -> Z2183 | H2: {=_xlfn.IFS(C2=0,"",I2>0,AD2,AND(I2<0,I2>-30),0,I2<=-30,-1)} -> -1 | I2: =AF2 -> -129 | J2: =AI2+AJ2 -> 0 | K2: =IF(AZ2<=0,AZ2,AZ2/COUNTIFS(R:R,R2,AZ:AZ,">0")) -> 0 | L2: =AM2 -> 6.45 | M2: =AT2 -> 0.77 | O2: =SUM(I2:N2) -> -121.78 | R2: P770450992956407491 | S2: R5640749128652672 | T2: 2025-08-11 15:56:33 | U2: 2025-08-31 14:13:53 | V2: 2025-08-31 22:10:26 | W2: 退款 | X2: 店铺余额 | Y2: -121.78 | Z2: 【老板周】夏季轻盈 新品 · 【老板周】夏季轻盈 新品圆领气质轻薄不规则透气上衣 黑色 XL（120-135斤） | AA2: 女装/女士精品>T恤 | AB2: XHS-3EHYVMDISL4W | AC2: 6896fe0c6d08080015500896 | AD2: 0 | AE2: -129 | AF2: -129 | AG2: 0 | AH2: 0 | AI2: 0 | AJ2: 0 | AK2: 0 | AL2: 0 | AM2: 6.45 | AN2: 0 | AO2: 0 | AP2: 0 | AQ2: 否 | AR2: 0 | AS2: 0 | AT2: 0.77 | AU2: 650d6e9f000000001603a6ac | AV2: 老板周. | AW2: 达人带货 | AZ2: 0 | BA2: 0 | BB2: 0 | BC2: 0 | BD2: 0
A3: =YEAR(V3) -> 2025 | B3: =MONTH(V3) -> 8 | C3: =R3 -> P770450992956407491 | D3: =COUNTIF(R:R,R3) -> 2 | E3: =COUNTIF($R$2:R3,R3) -> 2 | F3: {=INDEX(订单明细!BQ:BQ,MATCH(R3&AC3,订单明细!A:A&订单明细!O:O,0))} -> Z2183-黑色-XL | G3: =LEFT(F3,FIND("-",F3)-1) -> Z2183 | H3: {=_xlfn.IFS(C3=0,"",I3>0,AD3,AND(I3<0,I3>-30),0,I3<=-30,-1)} -> 1 | I3: =AF3 -> 129 | J3: =AI3+AJ3 -> 0 | K3: =IF(AZ3<=0,AZ3,AZ3/COUNTIFS(R:R,R3,AZ:AZ,">0")) -> 0 | L3: =AM3 -> -6.45 | M3: =AT3 -> -0.77 | O3: =SUM(I3:N3) -> 121.78 | R3: P770450992956407491 | T3: 2025-08-11 15:56:33 | U3: 2025-08-25 21:22:41 | V3: 2025-08-31 22:10:26 | W3: 结算入账 | X3: 店铺余额 | Y3: 121.78 | Z3: 【老板周】夏季轻盈 新品 · 【老板周】夏季轻盈 新品圆领气质轻薄不规则透气上衣 黑色 XL（120-135斤） | AA3: 女装/女士精品>T恤 | AB3: XHS-3EHYVMDISL4W | AC3: 6896fe0c6d08080015500896 | AD3: 1 | AE3: 129 | AF3: 129 | AH3: 0 | AI3: 0 | AJ3: 0 | AK3: 0.05 | AL3: 0 | AM3: -6.45 | AN3: 129 | AO3: 129 | AP3: 0 | AQ3: 否 | AR3: 0 | AS3: 0.006 | AT3: -0.77 | AU3: 650d6e9f000000001603a6ac | AV3: 老板周. | AW3: 达人带货 | AZ3: 0 | BA3: 0 | BB3: 0 | BC3: 0 | BD3: 0
A4: =YEAR(V4) -> 2025 | B4: =MONTH(V4) -> 8 | C4: =R4 -> P770795407221086221 | D4: =COUNTIF(R:R,R4) -> 1 | E4: =COUNTIF($R$2:R4,R4) -> 1 | F4: {=INDEX(订单明细!BQ:BQ,MATCH(R4&AC4,订单明细!A:A&订单明细!O:O,0))} -> Z2363-灰色-M | G4: =LEFT(F4,FIND("-",F4)-1) -> Z2363 | H4: {=_xlfn.IFS(C4=0,"",I4>0,AD4,AND(I4<0,I4>-30),0,I4<=-30,-1)} -> 1 | I4: =AF4 -> 359 | J4: =AI4+AJ4 -> 0 | K4: =IF(AZ4<=0,AZ4,AZ4/COUNTIFS(R:R,R4,AZ:AZ,">0")) -> 0 | L4: =AM4 -> -17.95 | M4: =AT4 -> -2.15 | O4: =SUM(I4:N4) -> 338.9 | R4: P770795407221086221 | T4: 2025-08-15 15:36:47 | U4: 2025-08-27 17:23:23 | V4: 2025-08-31 17:54:09 | W4: 结算入账 | X4: 店铺余额 | Y4: 338.9 | Z4: 【老板周】通勤质感 秋冬 · 【老板周】通勤质感 秋冬重磅新品半松紧腰垂感口袋西裤 灰色 M（100-120斤） | AA4: 女装/女士精品>裤子>西装裤/正装裤 | AB4: XHS-3JY78059ZB40 | AC4: 689dee2db292580015c1974b | AD4: 1 | AE4: 359 | AF4: 359 | AH4: 0 | AI4: 0 | AJ4: 0 | AK4: 0.05 | AL4: 0 | AM4: -17.95 | AN4: 359 | AO4: 359 | AP4: 0 | AQ4: 否 | AR4: 0 | AS4: 0.006 | AT4: -2.15 | AU4: 650d6e9f000000001603a6ac | AV4: 老板周. | AW4: 达人带货 | AZ4: 0 | BA4: 0 | BB4: 0 | BC4: 0 | BD4: 0
A5: =YEAR(V5) -> 2025 | B5: =MONTH(V5) -> 8 | C5: =R5 -> P770821520016218311 | D5: =COUNTIF(R:R,R5) -> 1 | E5: =COUNTIF($R$2:R5,R5) -> 1 | F5: {=INDEX(订单明细!BQ:BQ,MATCH(R5&AC5,订单明细!A:A&订单明细!O:O,0))} -> Z2365-灰色-S | G5: =LEFT(F5,FIND("-",F5)-1) -> Z2365 | H5: {=_xlfn.IFS(C5=0,"",I5>0,AD5,AND(I5<0,I5>-30),0,I5<=-30,-1)} -> 1 | I5: =AF5 -> 219 | J5: =AI5+AJ5 -> 0 | K5: =IF(AZ5<=0,AZ5,AZ5/COUNTIFS(R:R,R5,AZ:AZ,">0")) -> 0 | L5: =AM5 -> -10.95 | M5: =AT5 -> -1.31 | O5: =SUM(I5:N5) -> 206.74 | R5: P770821520016218311 | T5: 2025-08-15 22:52:00 | U5: 2025-08-27 17:10:53 | V5: 2025-08-31 17:40:23 | W5: 结算入账 | X5: 店铺余额 | Y5: 206.74 | Z5: 【老板周】极简主义 秋冬 · 【老板周】极简主义 秋冬新款复古卷边前短后长针织上衣 灰色 S（80-100斤） | AA5: 女装/女士精品>毛针织衫 | AB5: XHS-3JY9LAG89YPS | AC5: 689dee5baa1e7b00156ae7c0 | AD5: 1 | AE5: 219 | AF5: 219 | AH5: 0 | AI5: 0 | AJ5: 0 | AK5: 0.05 | AL5: 0 | AM5: -10.95 | AN5: 219 | AO5: 219 | AP5: 0 | AQ5: 否 | AR5: 0 | AS5: 0.006 | AT5: -1.31 | AU5: 650d6e9f000000001603a6ac | AV5: 老板周. | AW5: 达人带货 | AZ5: 0 | BA5: 0 | BB5: 0 | BC5: 0 | BD5: 0
A6: =YEAR(V6) -> 2025 | B6: =MONTH(V6) -> 8 | C6: =R6 -> P771683143371443691 | D6: =COUNTIF(R:R,R6) -> 1 | E6: =COUNTIF($R$2:R6,R6) -> 1 | F6: {=INDEX(订单明细!BQ:BQ,MATCH(R6&AC6,订单明细!A:A&订单明细!O:O,0))} -> Z2338-花色-M | G6: =LEFT(F6,FIND("-",F6)-1) -> Z2338 | H6: {=_xlfn.IFS(C6=0,"",I6>0,AD6,AND(I6<0,I6>-30),0,I6<=-30,-1)} -> 1 | I6: =AF6 -> 249 | J6: =AI6+AJ6 -> 0 | K6: =IF(AZ6<=0,AZ6,AZ6/COUNTIFS(R:R,R6,AZ:AZ,">0")) -> 0 | L6: =AM6 -> -12.45 | M6: =AT6 -> 0 | O6: =SUM(I6:N6) -> 236.55 | R6: P771683143371443691 | T6: 2025-08-25 22:12:23 | U6: 2025-08-27 16:51:27 | V6: 2025-08-31 17:24:56 | W6: 结算入账 | X6: 店铺余额 | Y6: 236.55 | Z6: 【老板周】复古老钱 新品 · 【老板周】复古老钱 新品小众宽松时髦腰果花松紧腰休闲裤 花色 M（100-120斤） | AA6: 女装/女士精品>裤子>休闲裤 | AB6: XHS-3IRER6T45U68 | AC6: 6894ac11aa1e7b001555658e | AD6: 1 | AE6: 249 | AF6: 249 | AH6: 0 | AI6: 0 | AJ6: 0 | AK6: 0.05 | AL6: 0 | AM6: -12.45 | AN6: 249 | AO6: 249 | AP6: 0 | AQ6: 否 | AR6: 0 | AS6: 0 | AT6: 0 | AZ6: 0 | BA6: 0 | BB6: 0 | BC6: 0 | BD6: 0
A7: =YEAR(V7) -> 2025 | B7: =MONTH(V7) -> 8 | C7: =R7 -> P770795098086034121 | D7: =COUNTIF(R:R,R7) -> 2 | E7: =COUNTIF($R$2:R7,R7) -> 1 | F7: {=INDEX(订单明细!BQ:BQ,MATCH(R7&AC7,订单明细!A:A&订单明细!O:O,0))} -> Z2363-黑色-L | G7: =LEFT(F7,FIND("-",F7)-1) -> Z2363 | H7: {=_xlfn.IFS(C7=0,"",I7>0,AD7,AND(I7<0,I7>-30),0,I7<=-30,-1)} -> -1 | I7: =AF7 -> -359 | J7: =AI7+AJ7 -> 0 | K7: =IF(AZ7<=0,AZ7,AZ7/COUNTIFS(R:R,R7,AZ:AZ,">0")) -> 0 | L7: =AM7 -> 17.95 | M7: =AT7 -> 2.15 | O7: =SUM(I7:N7) -> -338.9 | R7: P770795098086034121 | S7: R8603412185555555 | T7: 2025-08-15 15:31:38 | U7: 2025-08-27 18:38:57 | V7: 2025-08-31 17:18:01 | W7: 退款 | X7: 店铺余额 | Y7: -338.9 | Z7: 【老板周】通勤质感 秋冬 · 【老板周】通勤质感 秋冬重磅新品半松紧腰垂感口袋西裤 黑色 L（120-135斤） | AA7: 女装/女士精品>裤子>西装裤/正装裤 | AB7: XHS-3JY78052HM2O | AC7: 689dee2db292580015c19747 | AD7: 0 | AE7: -359 | AF7: -359 | AG7: 0 | AH7: 0 | AI7: 0 | AJ7: 0 | AK7: 0 | AL7: 0 | AM7: 17.95 | AN7: 0 | AO7: 0 | AP7: 0 | AQ7: 否 | AR7: 0 | AS7: 0 | AT7: 2.15 | AU7: 650d6e9f000000001603a6ac | AV7: 老板周. | AW7: 达人带货 | AZ7: 0 | BA7: 0 | BB7: 0 | BC7: 0 | BD7: 0
A8: =YEAR(V8) -> 2025 | B8: =MONTH(V8) -> 8 | C8: =R8 -> P770984511919250241 | D8: =COUNTIF(R:R,R8) -> 2 | E8: =COUNTIF($R$2:R8,R8) -> 1 | F8: {=INDEX(订单明细!BQ:BQ,MATCH(R8&AC8,订单明细!A:A&订单明细!O:O,0))} -> Z2218-黑色-L | G8: =LEFT(F8,FIND("-",F8)-1) -> Z2218 | H8: {=_xlfn.IFS(C8=0,"",I8>0,AD8,AND(I8<0,I8>-30),0,I8<=-30,-1)} -> -1 | I8: =AF8 -> -229 | J8: =AI8+AJ8 -> 0 | K8: =IF(AZ8<=0,AZ8,AZ8/COUNTIFS(R:R,R8,AZ:AZ,">0")) -> 0 | L8: =AM8 -> 11.45 | M8: =AT8 -> 1.37 | O8: =SUM(I8:N8) -> -216.18 | R8: P770984511919250241 | S8: R1925024178435962 | T8: 2025-08-17 20:08:31 | U8: 2025-08-27 17:06:50 | V8: 2025-08-31 17:18:01 | W8: 退款 | X8: 店铺余额 | Y8: -216.18 | Z8: 【老板周】法式随性 夏季 · 【老板周】法式随性 夏季时髦叠门襟无袖设计感开叉马甲 黑色 L（120-135斤） | AA8: 女装/女士精品>马夹 | AB8: XHS-3FAGCOT6V0U8 | AC8: 689704bae53c1000157cfaa0 | AD8: 0 | AE8: -229 | AF8: -229 | AG8: 0 | AH8: 0 | AI8: 0 | AJ8: 0 | AK8: 0 | AL8: 0 | AM8: 11.45 | AN8: 0 | AO8: 0 | AP8: 0 | AQ8: 否 | AR8: 0 | AS8: 0 | AT8: 1.37 | AU8: 650d6e9f000000001603a6ac | AV8: 老板周. | AW8: 达人带货 | AZ8: 0 | BA8: 0 | BB8: 0 | BC8: 0 | BD8: 0
A9: =YEAR(V9) -> 2025 | B9: =MONTH(V9) -> 8 | C9: =R9 -> P770984511919250241 | D9: =COUNTIF(R:R,R9) -> 2 | E9: =COUNTIF($R$2:R9,R9) -> 2 | F9: {=INDEX(订单明细!BQ:BQ,MATCH(R9&AC9,订单明细!A:A&订单明细!O:O,0))} -> Z2218-黑色-L | G9: =LEFT(F9,FIND("-",F9)-1) -> Z2218 | H9: {=_xlfn.IFS(C9=0,"",I9>0,AD9,AND(I9<0,I9>-30),0,I9<=-30,-1)} -> 1 | I9: =AF9 -> 229 | J9: =AI9+AJ9 -> 0 | K9: =IF(AZ9<=0,AZ9,AZ9/COUNTIFS(R:R,R9,AZ:AZ,">0")) -> 0 | L9: =AM9 -> -11.45 | M9: =AT9 -> -1.37 | O9: =SUM(I9:N9) -> 216.18 | R9: P770984511919250241 | T9: 2025-08-17 20:08:31 | U9: 2025-08-27 17:06:50 | V9: 2025-08-31 17:18:01 | W9: 结算入账 | X9: 店铺余额 | Y9: 216.18 | Z9: 【老板周】法式随性 夏季 · 【老板周】法式随性 夏季时髦叠门襟无袖设计感开叉马甲 黑色 L（120-135斤） | AA9: 女装/女士精品>马夹 | AB9: XHS-3FAGCOT6V0U8 | AC9: 689704bae53c1000157cfaa0 | AD9: 1 | AE9: 229 | AF9: 229 | AH9: 0 | AI9: 0 | AJ9: 0 | AK9: 0.05 | AL9: 0 | AM9: -11.45 | AN9: 229 | AO9: 229 | AP9: 0 | AQ9: 否 | AR9: 0 | AS9: 0.006 | AT9: -1.37 | AU9: 650d6e9f000000001603a6ac | AV9: 老板周. | AW9: 达人带货 | AZ9: 0 | BA9: 0 | BB9: 0 | BC9: 0 | BD9: 0
A10: =YEAR(V10) -> 2025 | B10: =MONTH(V10) -> 8 | C10: =R10 -> P770795098086034121 | D10: =COUNTIF(R:R,R10) -> 2 | E10: =COUNTIF($R$2:R10,R10) -> 2 | F10: {=INDEX(订单明细!BQ:BQ,MATCH(R10&AC10,订单明细!A:A&订单明细!O:O,0))} -> Z2363-黑色-L | G10: =LEFT(F10,FIND("-",F10)-1) -> Z2363 | H10: {=_xlfn.IFS(C10=0,"",I10>0,AD10,AND(I10<0,I10>-30),0,I10<=-30,-1)} -> 1 | I10: =AF10 -> 359 | J10: =AI10+AJ10 -> 0 | K10: =IF(AZ10<=0,AZ10,AZ10/COUNTIFS(R:R,R10,AZ:AZ,">0")) -> 0 | L10: =AM10 -> -17.95 | M10: =AT10 -> -2.15 | O10: =SUM(I10:N10) -> 338.9 | R10: P770795098086034121 | T10: 2025-08-15 15:31:38 | U10: 2025-08-27 17:06:35 | V10: 2025-08-31 17:18:01 | W10: 结算入账 | X10: 店铺余额 | Y10: 338.9 | Z10: 【老板周】通勤质感 秋冬 · 【老板周】通勤质感 秋冬重磅新品半松紧腰垂感口袋西裤 黑色 L（120-135斤） | AA10: 女装/女士精品>裤子>西装裤/正装裤 | AB10: XHS-3JY78052HM2O | AC10: 689dee2db292580015c19747 | AD10: 1 | AE10: 359 | AF10: 359 | AH10: 0 | AI10: 0 | AJ10: 0 | AK10: 0.05 | AL10: 0 | AM10: -17.95 | AN10: 359 | AO10: 359 | AP10: 0 | AQ10: 否 | AR10: 0 | AS10: 0.006 | AT10: -2.15 | AU10: 650d6e9f000000001603a6ac | AV10: 老板周. | AW10: 达人带货 | AZ10: 0 | BA10: 0 | BB10: 0 | BC10: 0 | BD10: 0
A11: =YEAR(V11) -> 2025 | B11: =MONTH(V11) -> 8 | C11: =R11 -> P770381824712038751 | D11: =COUNTIF(R:R,R11) -> 2 | E11: =COUNTIF($R$2:R11,R11) -> 1 | F11: {=INDEX(订单明细!BQ:BQ,MATCH(R11&AC11,订单明细!A:A&订单明细!O:O,0))} -> Z1688-黑色-L | G11: =LEFT(F11,FIND("-",F11)-1) -> Z1688 | H11: {=_xlfn.IFS(C11=0,"",I11>0,AD11,AND(I11<0,I11>-30),0,I11<=-30,-1)} -> -1 | I11: =AF11 -> -499 | J11: =AI11+AJ11 -> 0 | K11: =IF(AZ11<=0,AZ11,AZ11/COUNTIFS(R:R,R11,AZ:AZ,">0")) -> 0 | L11: =AM11 -> 24.95 | M11: =AT11 -> 2.99 | O11: =SUM(I11:N11) -> -471.06 | R11: P770381824712038751 | S11: R1203875175623359 | T11: 2025-08-10 20:43:44 | U11: 2025-08-24 20:11:22 | V11: 2025-08-31 17:08:33 | W11: 退款 | X11: 店铺余额 | Y11: -471.06 | Z11: 【老板周】复古英伦 极简 · 【老板周】复古英伦 极简设计立体剪裁无领廓形外套 黑色 L（120-135斤） | AA11: 女装/女士精品>短外套 | AB11: XHS-31Z6WPZ8ZG1S | AC11: 68970ccdfe39ac0015b91515 | AD11: 0 | AE11: -499 | AF11: -499 | AG11: 0 | AH11: 0 | AI11: 0 | AJ11: 0 | AK11: 0 | AL11: 0 | AM11: 24.95 | AN11: 0 | AO11: 0 | AP11: 0 | AQ11: 否 | AR11: 0 | AS11: 0 | AT11: 2.99 | AU11: 650d6e9f000000001603a6ac | AV11: 老板周. | AW11: 达人带货 | AZ11: 0 | BA11: 0 | BB11: 0 | BC11: 0 | BD11: 0
A12: =YEAR(V12) -> 2025 | B12: =MONTH(V12) -> 8 | C12: =R12 -> P770381824712038751 | D12: =COUNTIF(R:R,R12) -> 2 | E12: =COUNTIF($R$2:R12,R12) -> 2 | F12: {=INDEX(订单明细!BQ:BQ,MATCH(R12&AC12,订单明细!A:A&订单明细!O:O,0))} -> Z1688-黑色-L | G12: =LEFT(F12,FIND("-",F12)-1) -> Z1688 | H12: {=_xlfn.IFS(C12=0,"",I12>0,AD12,AND(I12<0,I12>-30),0,I12<=-30,-1)} -> 1 | I12: =AF12 -> 499 | J12: =AI12+AJ12 -> 0 | K12: =IF(AZ12<=0,AZ12,AZ12/COUNTIFS(R:R,R12,AZ:AZ,">0")) -> 0 | L12: =AM12 -> -24.95 | M12: =AT12 -> -2.99 | O12: =SUM(I12:N12) -> 471.06 | R12: P770381824712038751 | T12: 2025-08-10 20:43:44 | U12: 2025-08-27 16:58:50 | V12: 2025-08-31 17:08:33 | W12: 结算入账 | X12: 店铺余额 | Y12: 471.06 | Z12: 【老板周】复古英伦 极简 · 【老板周】复古英伦 极简设计立体剪裁无领廓形外套 黑色 L（120-135斤） | AA12: 女装/女士精品>短外套 | AB12: XHS-31Z6WPZ8ZG1S | AC12: 68970ccdfe39ac0015b91515 | AD12: 1 | AE12: 499 | AF12: 499 | AH12: 0 | AI12: 0 | AJ12: 0 | AK12: 0.05 | AL12: 0 | AM12: -24.95 | AN12: 499 | AO12: 499 | AP12: 0 | AQ12: 否 | AR12: 0 | AS12: 0.006 | AT12: -2.99 | AU12: 650d6e9f000000001603a6ac | AV12: 老板周. | AW12: 达人带货 | AZ12: 0 | BA12: 0 | BB12: 0 | BC12: 0 | BD12: 0
A13: =YEAR(V13) -> 2025 | B13: =MONTH(V13) -> 8 | C13: =R13 -> P770818846205191671 | D13: =COUNTIF(R:R,R13) -> 1 | E13: =COUNTIF($R$2:R13,R13) -> 1 | F13: {=INDEX(订单明细!BQ:BQ,MATCH(R13&AC13,订单明细!A:A&订单明细!O:O,0))} -> Z1576-黑色-M | G13: =LEFT(F13,FIND("-",F13)-1) -> Z1576 | H13: {=_xlfn.IFS(C13=0,"",I13>0,AD13,AND(I13<0,I13>-30),0,I13<=-30,-1)} -> 1 | I13: =AF13 -> 199 | J13: =AI13+AJ13 -> 0 | K13: =IF(AZ13<=0,AZ13,AZ13/COUNTIFS(R:R,R13,AZ:AZ,">0")) -> 0 | L13: =AM13 -> -9.95 | M13: =AT13 -> -1.19 | O13: =SUM(I13:N13) -> 187.86 | R13: P770818846205191671 | T13: 2025-08-15 22:07:26 | U13: 2025-08-27 16:15:17 | V13: 2025-08-31 16:46:31 | W13: 结算入账 | X13: 店铺余额 | Y13: 187.86 | Z13: 【老板周】时髦撞色 春季 · 【老板周】时髦撞色 春季新款假两件显瘦长袖打底T恤上衣 黑色 M（100-120斤） | AA13: 女装/女士精品>T恤 | AB13: XHS-2Z0D3J1YAL8G | AC13: 6896fe48057f570015d29244 | AD13: 1 | AE13: 199 | AF13: 199 | AH13: 0 | AI13: 0 | AJ13: 0 | AK13: 0.05 | AL13: 0 | AM13: -9.95 | AN13: 199 | AO13: 199 | AP13: 0 | AQ13: 否 | AR13: 0 | AS13: 0.006 | AT13: -1.19 | AU13: 650d6e9f000000001603a6ac | AV13: 老板周. | AW13: 达人带货 | AZ13: 0 | BA13: 0 | BB13: 0 | BC13: 0 | BD13: 0
A14: =YEAR(V14) -> 2025 | B14: =MONTH(V14) -> 8 | C14: =R14 -> P770798117968454421 | D14: =COUNTIF(R:R,R14) -> 2 | E14: =COUNTIF($R$2:R14,R14) -> 1 | F14: {=INDEX(订单明细!BQ:BQ,MATCH(R14&AC14,订单明细!A:A&订单明细!O:O,0))} -> Z2365-灰色-S | G14: =LEFT(F14,FIND("-",F14)-1) -> Z2365 | H14: {=_xlfn.IFS(C14=0,"",I14>0,AD14,AND(I14<0,I14>-30),0,I14<=-30,-1)} -> -1 | I14: =AF14 -> -219 | J14: =AI14+AJ14 -> 0 | K14: =IF(AZ14<=0,AZ14,AZ14/COUNTIFS(R:R,R14,AZ:AZ,">0")) -> 0 | L14: =AM14 -> 10.95 | M14: =AT14 -> 1.31 | O14: =SUM(I14:N14) -> -206.74 | R14: P770798117968454421 | S14: R6845442155679510 | T14: 2025-08-15 16:21:58 | U14: 2025-08-24 10:33:34 | V14: 2025-08-31 16:38:40 | W14: 退款 | X14: 店铺余额 | Y14: -206.74 | Z14: 【老板周】极简主义 秋冬 · 【老板周】极简主义 秋冬新款复古卷边前短后长针织上衣 灰色 S（80-100斤） | AA14: 女装/女士精品>毛针织衫 | AB14: XHS-3JY9LAG89YPS | AC14: 689dee5baa1e7b00156ae7c0 | AD14: 0 | AE14: -219 | AF14: -219 | AG14: 0 | AH14: 0 | AI14: 0 | AJ14: 0 | AK14: 0 | AL14: 0 | AM14: 10.95 | AN14: 0 | AO14: 0 | AP14: 0 | AQ14: 否 | AR14: 0 | AS14: 0 | AT14: 1.31 | AU14: 650d6e9f000000001603a6ac | AV14: 老板周. | AW14: 达人带货 | AZ14: 0 | BA14: 0 | BB14: 0 | BC14: 0 | BD14: 0
A15: =YEAR(V15) -> 2025 | B15: =MONTH(V15) -> 8 | C15: =R15 -> P770986580251454261 | D15: =COUNTIF(R:R,R15) -> 2 | E15: =COUNTIF($R$2:R15,R15) -> 1 | F15: {=INDEX(订单明细!BQ:BQ,MATCH(R15&AC15,订单明细!A:A&订单明细!O:O,0))} -> Z2218-黑色-S | G15: =LEFT(F15,FIND("-",F15)-1) -> Z2218 | H15: {=_xlfn.IFS(C15=0,"",I15>0,AD15,AND(I15<0,I15>-30),0,I15<=-30,-1)} -> -1 | I15: =AF15 -> -229 | J15: =AI15+AJ15 -> 0 | K15: =IF(AZ15<=0,AZ15,AZ15/COUNTIFS(R:R,R15,AZ:AZ,">0")) -> 0 | L15: =AM15 -> 11.45 | M15: =AT15 -> 1.37 | O15: =SUM(I15:N15) -> -216.18 | R15: P770986580251454261 | S15: R5145426155617207 | T15: 2025-08-17 20:43:00 | U15: 2025-08-24 10:33:44 | V15: 2025-08-31 16:38:40 | W15: 退款 | X15: 店铺余额 | Y15: -216.18 | Z15: 【老板周】法式随性 夏季 · 【老板周】法式随性 夏季时髦叠门襟无袖设计感开叉马甲 黑色 S（80-100斤） | AA15: 女装/女士精品>马夹 | AB15: XHS-3FAGCOSWVFGG | AC15: 689704bae53c1000157cfa9c | AD15: 0 | AE15: -229 | AF15: -229 | AG15: 0 | AH15: 0 | AI15: 0 | AJ15: 0 | AK15: 0 | AL15: 0 | AM15: 11.45 | AN15: 0 | AO15: 0 | AP15: 0 | AQ15: 否 | AR15: 0 | AS15: 0 | AT15: 1.37 | AU15: 650d6e9f000000001603a6ac | AV15: 老板周. | AW15: 达人带货 | AZ15: 0 | BA15: 0 | BB15: 0 | BC15: 0 | BD15: 0
A16: =YEAR(V16) -> 2025 | B16: =MONTH(V16) -> 8 | C16: =R16 -> P770986580251454261 | D16: =COUNTIF(R:R,R16) -> 2 | E16: =COUNTIF($R$2:R16,R16) -> 2 | F16: {=INDEX(订单明细!BQ:BQ,MATCH(R16&AC16,订单明细!A:A&订单明细!O:O,0))} -> Z2218-黑色-S | G16: =LEFT(F16,FIND("-",F16)-1) -> Z2218 | H16: {=_xlfn.IFS(C16=0,"",I16>0,AD16,AND(I16<0,I16>-30),0,I16<=-30,-1)} -> 1 | I16: =AF16 -> 229 | J16: =AI16+AJ16 -> 0 | K16: =IF(AZ16<=0,AZ16,AZ16/COUNTIFS(R:R,R16,AZ:AZ,">0")) -> 0 | L16: =AM16 -> -11.45 | M16: =AT16 -> -1.37 | O16: =SUM(I16:N16) -> 216.18 | R16: P770986580251454261 | T16: 2025-08-17 20:43:00 | U16: 2025-08-27 16:24:28 | V16: 2025-08-31 16:38:40 | W16: 结算入账 | X16: 店铺余额 | Y16: 216.18 | Z16: 【老板周】法式随性 夏季 · 【老板周】法式随性 夏季时髦叠门襟无袖设计感开叉马甲 黑色 S（80-100斤） | AA16: 女装/女士精品>马夹 | AB16: XHS-3FAGCOSWVFGG | AC16: 689704bae53c1000157cfa9c | AD16: 1 | AE16: 229 | AF16: 229 | AH16: 0 | AI16: 0 | AJ16: 0 | AK16: 0.05 | AL16: 0 | AM16: -11.45 | AN16: 229 | AO16: 229 | AP16: 0 | AQ16: 否 | AR16: 0 | AS16: 0.006 | AT16: -1.37 | AU16: 650d6e9f000000001603a6ac | AV16: 老板周. | AW16: 达人带货 | AZ16: 0 | BA16: 0 | BB16: 0 | BC16: 0 | BD16: 0
A17: =YEAR(V17) -> 2025 | B17: =MONTH(V17) -> 8 | C17: =R17 -> P770798117968454421 | D17: =COUNTIF(R:R,R17) -> 2 | E17: =COUNTIF($R$2:R17,R17) -> 2 | F17: {=INDEX(订单明细!BQ:BQ,MATCH(R17&AC17,订单明细!A:A&订单明细!O:O,0))} -> Z2365-灰色-S | G17: =LEFT(F17,FIND("-",F17)-1) -> Z2365 | H17: {=_xlfn.IFS(C17=0,"",I17>0,AD17,AND(I17<0,I17>-30),0,I17<=-30,-1)} -> 1 | I17: =AF17 -> 219 | J17: =AI17+AJ17 -> 0 | K17: =IF(AZ17<=0,AZ17,AZ17/COUNTIFS(R:R,R17,AZ:AZ,">0")) -> 0 | L17: =AM17 -> -10.95 | M17: =AT17 -> -1.31 | O17: =SUM(I17:N17) -> 206.74 | R17: P770798117968454421 | T17: 2025-08-15 16:21:58 | U17: 2025-08-27 16:24:29 | V17: 2025-08-31 16:38:40 | W17: 结算入账 | X17: 店铺余额 | Y17: 206.74 | Z17: 【老板周】极简主义 秋冬 · 【老板周】极简主义 秋冬新款复古卷边前短后长针织上衣 灰色 S（80-100斤） | AA17: 女装/女士精品>毛针织衫 | AB17: XHS-3JY9LAG89YPS | AC17: 689dee5baa1e7b00156ae7c0 | AD17: 1 | AE17: 219 | AF17: 219 | AH17: 0 | AI17: 0 | AJ17: 0 | AK17: 0.05 | AL17: 0 | AM17: -10.95 | AN17: 219 | AO17: 219 | AP17: 0 | AQ17: 否 | AR17: 0 | AS17: 0.006 | AT17: -1.31 | AU17: 650d6e9f000000001603a6ac | AV17: 老板周. | AW17: 达人带货 | AZ17: 0 | BA17: 0 | BB17: 0 | BC17: 0 | BD17: 0
A18: =YEAR(V18) -> 2025 | B18: =MONTH(V18) -> 8 | C18: =R18 -> P770813889954234671 | D18: =COUNTIF(R:R,R18) -> 2 | E18: =COUNTIF($R$2:R18,R18) -> 1 | F18: {=INDEX(订单明细!BQ:BQ,MATCH(R18&AC18,订单明细!A:A&订单明细!O:O,0))} -> Z2365-黑色-S | G18: =LEFT(F18,FIND("-",F18)-1) -> Z2365 | H18: {=_xlfn.IFS(C18=0,"",I18>0,AD18,AND(I18<0,I18>-30),0,I18<=-30,-1)} -> -1 | I18: =AF18 -> -219 | J18: =AI18+AJ18 -> 0 | K18: =IF(AZ18<=0,AZ18,AZ18/COUNTIFS(R:R,R18,AZ:AZ,">0")) -> 0 | L18: =AM18 -> 10.95 | M18: =AT18 -> 1.31 | O18: =SUM(I18:N18) -> -206.74 | R18: P770813889954234671 | S18: R5423467132482381 | T18: 2025-08-15 20:44:49 | U18: 2025-08-25 17:13:43 | V18: 2025-08-31 16:38:36 | W18: 退款 | X18: 店铺余额 | Y18: -206.74 | Z18: 【老板周】极简主义 秋冬 · 【老板周】极简主义 秋冬新款复古卷边前短后长针织上衣 黑色 S（80-100斤） | AA18: 女装/女士精品>毛针织衫 | AB18: XHS-3JY9LAG0S9OG | AC18: 689dee5baa1e7b00156ae7bc | AD18: 0 | AE18: -219 | AF18: -219 | AG18: 0 | AH18: 0 | AI18: 0 | AJ18: 0 | AK18: 0 | AL18: 0 | AM18: 10.95 | AN18: 0 | AO18: 0 | AP18: 0 | AQ18: 否 | AR18: 0 | AS18: 0 | AT18: 1.31 | AU18: 650d6e9f000000001603a6ac | AV18: 老板周. | AW18: 达人带货 | AZ18: 0 | BA18: 0 | BB18: 0 | BC18: 0 | BD18: 0
A19: =YEAR(V19) -> 2025 | B19: =MONTH(V19) -> 8 | C19: =R19 -> P770813889954234671 | D19: =COUNTIF(R:R,R19) -> 2 | E19: =COUNTIF($R$2:R19,R19) -> 2 | F19: {=INDEX(订单明细!BQ:BQ,MATCH(R19&AC19,订单明细!A:A&订单明细!O:O,0))} -> Z2365-黑色-S | G19: =LEFT(F19,FIND("-",F19)-1) -> Z2365 | H19: {=_xlfn.IFS(C19=0,"",I19>0,AD19,AND(I19<0,I19>-30),0,I19<=-30,-1)} -> 1 | I19: =AF19 -> 219 | J19: =AI19+AJ19 -> 0 | K19: =IF(AZ19<=0,AZ19,AZ19/COUNTIFS(R:R,R19,AZ:AZ,">0")) -> 0 | L19: =AM19 -> -10.95 | M19: =AT19 -> -1.31 | O19: =SUM(I19:N19) -> 206.74 | R19: P770813889954234671 | T19: 2025-08-15 20:44:49 | U19: 2025-08-27 16:20:07 | V19: 2025-08-31 16:38:36 | W19: 结算入账 | X19: 店铺余额 | Y19: 206.74 | Z19: 【老板周】极简主义 秋冬 · 【老板周】极简主义 秋冬新款复古卷边前短后长针织上衣 黑色 S（80-100斤） | AA19: 女装/女士精品>毛针织衫 | AB19: XHS-3JY9LAG0S9OG | AC19: 689dee5baa1e7b00156ae7bc | AD19: 1 | AE19: 219 | AF19: 219 | AH19: 0 | AI19: 0 | AJ19: 0 | AK19: 0.05 | AL19: 0 | AM19: -10.95 | AN19: 219 | AO19: 219 | AP19: 0 | AQ19: 否 | AR19: 0 | AS19: 0.006 | AT19: -1.31 | AU19: 650d6e9f000000001603a6ac | AV19: 老板周. | AW19: 达人带货 | AZ19: 0 | BA19: 0 | BB19: 0 | BC19: 0 | BD19: 0
A20: =YEAR(V20) -> 2025 | B20: =MONTH(V20) -> 8 | C20: =R20 -> P770794018206458841 | D20: =COUNTIF(R:R,R20) -> 2 | E20: =COUNTIF($R$2:R20,R20) -> 1 | F20: {=INDEX(订单明细!BQ:BQ,MATCH(R20&AC20,订单明细!A:A&订单明细!O:O,0))} -> Z2378-花纱色-M | G20: =LEFT(F20,FIND("-",F20)-1) -> Z2378 | H20: {=_xlfn.IFS(C20=0,"",I20>0,AD20,AND(I20<0,I20>-30),0,I20<=-30,-1)} -> -1 | I20: =AF20 -> -179 | J20: =AI20+AJ20 -> 0 | K20: =IF(AZ20<=0,AZ20,AZ20/COUNTIFS(R:R,R20,AZ:AZ,">0")) -> 0 | L20: =AM20 -> 8.95 | M20: =AT20 -> 1.07 | O20: =SUM(I20:N20) -> -168.98 | R20: P770794018206458841 | S20: R0645884157385706 | T20: 2025-08-15 15:13:38 | U20: 2025-08-24 10:56:35 | V20: 2025-08-31 16:28:41 | W20: 退款 | X20: 店铺余额 | Y20: -168.98 | Z20: 【老板周】小众日系 秋冬 · 【老板周】小众日系 秋冬叠穿时髦下摆不规则宽松马甲 花纱色 M（100-135斤） | AA20: 女装/女士精品>马夹 | AB20: XHS-3JY8RM360LQ8 | AC20: 689dee45c34eef00157e11fd | AD20: 0 | AE20: -179 | AF20: -179 | AG20: 0 | AH20: 0 | AI20: 0 | AJ20: 0 | AK20: 0 | AL20: 0 | AM20: 8.95 | AN20: 0 | AO20: 0 | AP20: 0 | AQ20: 否 | AR20: 0 | AS20: 0 | AT20: 1.07 | AU20: 650d6e9f000000001603a6ac | AV20: 老板周. | AW20: 达人带货 | AZ20: 0 | BA20: 0 | BB20: 0 | BC20: 0 | BD20: 0
A21: =YEAR(V21) -> 2025 | B21: =MONTH(V21) -> 8 | C21: =R21 -> P770794018206458841 | D21: =COUNTIF(R:R,R21) -> 2 | E21: =COUNTIF($R$2:R21,R21) -> 2 | F21: {=INDEX(订单明细!BQ:BQ,MATCH(R21&AC21,订单明细!A:A&订单明细!O:O,0))} -> Z2378-花纱色-M | G21: =LEFT(F21,FIND("-",F21)-1) -> Z2378 | H21: {=_xlfn.IFS(C21=0,"",I21>0,AD21,AND(I21<0,I21>-30),0,I21<=-30,-1)} -> 1 | I21: =AF21 -> 179 | J21: =AI21+AJ21 -> 0 | K21: =IF(AZ21<=0,AZ21,AZ21/COUNTIFS(R:R,R21,AZ:AZ,">0")) -> 0 | L21: =AM21 -> -8.95 | M21: =AT21 -> -1.07 | O21: =SUM(I21:N21) -> 168.98 | R21: P770794018206458841 | T21: 2025-08-15 15:13:38 | U21: 2025-08-27 16:18:15 | V21: 2025-08-31 16:28:41 | W21: 结算入账 | X21: 店铺余额 | Y21: 168.98 | Z21: 【老板周】小众日系 秋冬 · 【老板周】小众日系 秋冬叠穿时髦下摆不规则宽松马甲 花纱色 M（100-135斤） | AA21: 女装/女士精品>马夹 | AB21: XHS-3JY8RM360LQ8 | AC21: 689dee45c34eef00157e11fd | AD21: 1 | AE21: 179 | AF21: 179 | AH21: 0 | AI21: 0 | AJ21: 0 | AK21: 0.05 | AL21: 0 | AM21: -8.95 | AN21: 179 | AO21: 179 | AP21: 0 | AQ21: 否 | AR21: 0 | AS21: 0.006 | AT21: -1.07 | AU21: 650d6e9f000000001603a6ac | AV21: 老板周. | AW21: 达人带货 | AZ21: 0 | BA21: 0 | BB21: 0 | BC21: 0 | BD21: 0
A22: =YEAR(V22) -> 2025 | B22: =MONTH(V22) -> 8 | C22: =R22 -> P770793869532382601 | D22: =COUNTIF(R:R,R22) -> 2 | E22: =COUNTIF($R$2:R22,R22) -> 1 | F22: {=INDEX(订单明细!BQ:BQ,MATCH(R22&AC22,订单明细!A:A&订单明细!O:O,0))} -> Z2378-灰色-M | G22: =LEFT(F22,FIND("-",F22)-1) -> Z2378 | H22: {=_xlfn.IFS(C22=0,"",I22>0,AD22,AND(I22<0,I22>-30),0,I22<=-30,-1)} -> -1 | I22: =AF22 -> -179 | J22: =AI22+AJ22 -> 0 | K22: =IF(AZ22<=0,AZ22,AZ22/COUNTIFS(R:R,R22,AZ:AZ,">0")) -> 0 | L22: =AM22 -> 8.95 | M22: =AT22 -> 1.07 | O22: =SUM(I22:N22) -> -168.98 | R22: P770793869532382601 | S22: R3238260190940580 | T22: 2025-08-15 15:11:09 | U22: 2025-08-29 10:31:02 | V22: 2025-08-31 16:18:01 | W22: 退款 | X22: 店铺余额 | Y22: -168.98 | Z22: 【老板周】小众日系 秋冬 · 【老板周】小众日系 秋冬叠穿时髦下摆不规则宽松马甲 灰色 M（100-135斤） | AA22: 女装/女士精品>马夹 | AB22: XHS-3JY8RM3ZZDVK | AC22: 689dee45c34eef00157e1209 | AD22: 0 | AE22: -179 | AF22: -179 | AG22: 0 | AH22: 0 | AI22: 0 | AJ22: 0 | AK22: 0 | AL22: 0 | AM22: 8.95 | AN22: 0 | AO22: 0 | AP22: 0 | AQ22: 否 | AR22: 0 | AS22: 0 | AT22: 1.07 | AU22: 650d6e9f000000001603a6ac | AV22: 老板周. | AW22: 达人带货 | AZ22: 0 | BA22: 0 | BB22: 0 | BC22: 0 | BD22: 0
A23: =YEAR(V23) -> 2025 | B23: =MONTH(V23) -> 8 | C23: =R23 -> P770796097446414361 | D23: =COUNTIF(R:R,R23) -> 2 | E23: =COUNTIF($R$2:R23,R23) -> 1 | F23: {=INDEX(订单明细!BQ:BQ,MATCH(R23&AC23,订单明细!A:A&订单明细!O:O,0))} -> Z2378-花纱色-S | G23: =LEFT(F23,FIND("-",F23)-1) -> Z2378 | H23: {=_xlfn.IFS(C23=0,"",I23>0,AD23,AND(I23<0,I23>-30),0,I23<=-30,-1)} -> -1 | I23: =AF23 -> -179 | J23: =AI23+AJ23 -> 0 | K23: =IF(AZ23<=0,AZ23,AZ23/COUNTIFS(R:R,R23,AZ:AZ,">0")) -> 0 | L23: =AM23 -> 8.95 | M23: =AT23 -> 1.07 | O23: =SUM(I23:N23) -> -168.98 | R23: P770796097446414361 | S23: R4641436114866881 | T23: 2025-08-15 15:48:17 | U23: 2025-08-25 17:52:36 | V23: 2025-08-31 16:18:01 | W23: 退款 | X23: 店铺余额 | Y23: -168.98 | Z23: 【老板周】小众日系 秋冬 · 【老板周】小众日系 秋冬叠穿时髦下摆不规则宽松马甲 花纱色 S（80-100斤） | AA23: 女装/女士精品>马夹 | AB23: XHS-3JY8RM310T1C | AC23: 689dee45c34eef00157e11fb | AD23: 0 | AE23: -179 | AF23: -179 | AG23: 0 | AH23: 0 | AI23: 0 | AJ23: 0 | AK23: 0 | AL23: 0 | AM23: 8.95 | AN23: 0 | AO23: 0 | AP23: 0 | AQ23: 否 | AR23: 0 | AS23: 0 | AT23: 1.07 | AU23: 650d6e9f000000001603a6ac | AV23: 老板周. | AW23: 达人带货 | AZ23: 0 | BA23: 0 | BB23: 0 | BC23: 0 | BD23: 0
A24: =YEAR(V24) -> 2025 | B24: =MONTH(V24) -> 8 | C24: =R24 -> P770794042509304891 | D24: =COUNTIF(R:R,R24) -> 2 | E24: =COUNTIF($R$2:R24,R24) -> 1 | F24: {=INDEX(订单明细!BQ:BQ,MATCH(R24&AC24,订单明细!A:A&订单明细!O:O,0))} -> Z2378-花纱色-M | G24: =LEFT(F24,FIND("-",F24)-1) -> Z2378 | H24: {=_xlfn.IFS(C24=0,"",I24>0,AD24,AND(I24<0,I24>-30),0,I24<=-30,-1)} -> -1 | I24: =AF24 -> -179 | J24: =AI24+AJ24 -> 0 | K24: =IF(AZ24<=0,AZ24,AZ24/COUNTIFS(R:R,R24,AZ:AZ,">0")) -> -10 | L24: =AM24 -> 8.95 | M24: =AT24 -> 1.07 | O24: =SUM(I24:N24) -> -178.98 | R24: P770794042509304891 | S24: R0930489179160166 | T24: 2025-08-15 15:14:02 | U24: 2025-08-26 12:45:50 | V24: 2025-08-31 16:18:01 | W24: 退款 | X24: 店铺余额 | Y24: -178.98 | Z24: 【老板周】小众日系 秋冬 · 【老板周】小众日系 秋冬叠穿时髦下摆不规则宽松马甲 花纱色 M（100-135斤） | AA24: 女装/女士精品>马夹 | AB24: XHS-3JY8RM360LQ8 | AC24: 689dee45c34eef00157e11fd | AD24: 0 | AE24: -179 | AF24: -179 | AG24: 0 | AH24: 0 | AI24: 0 | AJ24: 0 | AK24: 0 | AL24: 0 | AM24: 8.95 | AN24: 0 | AO24: 0 | AP24: 0 | AQ24: 否 | AR24: 0 | AS24: 0 | AT24: 1.07 | AU24: 650d6e9f000000001603a6ac | AV24: 老板周. | AW24: 达人带货 | AZ24: -10 | BA24: 0 | BB24: 0 | BC24: 0 | BD24: 0
A25: =YEAR(V25) -> 2025 | B25: =MONTH(V25) -> 8 | C25: =R25 -> P770796097446414361 | D25: =COUNTIF(R:R,R25) -> 2 | E25: =COUNTIF($R$2:R25,R25) -> 2 | F25: {=INDEX(订单明细!BQ:BQ,MATCH(R25&AC25,订单明细!A:A&订单明细!O:O,0))} -> Z2378-花纱色-S | G25: =LEFT(F25,FIND("-",F25)-1) -> Z2378 | H25: {=_xlfn.IFS(C25=0,"",I25>0,AD25,AND(I25<0,I25>-30),0,I25<=-30,-1)} -> 1 | I25: =AF25 -> 179 | J25: =AI25+AJ25 -> 0 | K25: =IF(AZ25<=0,AZ25,AZ25/COUNTIFS(R:R,R25,AZ:AZ,">0")) -> 0 | L25: =AM25 -> -8.95 | M25: =AT25 -> -1.07 | O25: =SUM(I25:N25) -> 168.98 | R25: P770796097446414361 | T25: 2025-08-15 15:48:17 | U25: 2025-08-27 16:07:44 | V25: 2025-08-31 16:18:01 | W25: 结算入账 | X25: 店铺余额 | Y25: 168.98 | Z25: 【老板周】小众日系 秋冬 · 【老板周】小众日系 秋冬叠穿时髦下摆不规则宽松马甲 花纱色 S（80-100斤） | AA25: 女装/女士精品>马夹 | AB25: XHS-3JY8RM310T1C | AC25: 689dee45c34eef00157e11fb | AD25: 1 | AE25: 179 | AF25: 179 | AH25: 0 | AI25: 0 | AJ25: 0 | AK25: 0.05 | AL25: 0 | AM25: -8.95 | AN25: 179 | AO25: 179 | AP25: 0 | AQ25: 否 | AR25: 0 | AS25: 0.006 | AT25: -1.07 | AU25: 650d6e9f000000001603a6ac | AV25: 老板周. | AW25: 达人带货 | AZ25: 0 | BA25: 0 | BB25: 0 | BC25: 0 | BD25: 0
A26: =YEAR(V26) -> 2025 | B26: =MONTH(V26) -> 8 | C26: =R26 -> P770794042509304891 | D26: =COUNTIF(R:R,R26) -> 2 | E26: =COUNTIF($R$2:R26,R26) -> 2 | F26: {=INDEX(订单明细!BQ:BQ,MATCH(R26&AC26,订单明细!A:A&订单明细!O:O,0))} -> Z2378-花纱色-M | G26: =LEFT(F26,FIND("-",F26)-1) -> Z2378 | H26: {=_xlfn.IFS(C26=0,"",I26>0,AD26,AND(I26<0,I26>-30),0,I26<=-30,-1)} -> 1 | I26: =AF26 -> 179 | J26: =AI26+AJ26 -> 0 | K26: =IF(AZ26<=0,AZ26,AZ26/COUNTIFS(R:R,R26,AZ:AZ,">0")) -> 10 | L26: =AM26 -> -8.95 | M26: =AT26 -> -1.07 | O26: =SUM(I26:N26) -> 178.98 | R26: P770794042509304891 | T26: 2025-08-15 15:14:02 | U26: 2025-08-25 00:10:29 | V26: 2025-08-31 16:18:01 | W26: 结算入账 | X26: 店铺余额 | Y26: 178.98 | Z26: 【老板周】小众日系 秋冬 · 【老板周】小众日系 秋冬叠穿时髦下摆不规则宽松马甲 花纱色 M（100-135斤） | AA26: 女装/女士精品>马夹 | AB26: XHS-3JY8RM360LQ8 | AC26: 689dee45c34eef00157e11fd | AD26: 1 | AE26: 179 | AF26: 179 | AH26: 0 | AI26: 0 | AJ26: 0 | AK26: 0.05 | AL26: 0 | AM26: -8.95 | AN26: 179 | AO26: 179 | AP26: 0 | AQ26: 否 | AR26: 0 | AS26: 0.006 | AT26: -1.07 | AU26: 650d6e9f000000001603a6ac | AV26: 老板周. | AW26: 达人带货 | AZ26: 10 | BA26: 0 | BB26: 0 | BC26: 0 | BD26: 0
A27: =YEAR(V27) -> 2025 | B27: =MONTH(V27) -> 8 | C27: =R27 -> P770793869532382601 | D27: =COUNTIF(R:R,R27) -> 2 | E27: =COUNTIF($R$2:R27,R27) -> 2 | F27: {=INDEX(订单明细!BQ:BQ,MATCH(R27&AC27,订单明细!A:A&订单明细!O:O,0))} -> Z2378-灰色-M | G27: =LEFT(F27,FIND("-",F27)-1) -> Z2378 | H27: {=_xlfn.IFS(C27=0,"",I27>0,AD27,AND(I27<0,I27>-30),0,I27<=-30,-1)} -> 1 | I27: =AF27 -> 179 | J27: =AI27+AJ27 -> 0 | K27: =IF(AZ27<=0,AZ27,AZ27/COUNTIFS(R:R,R27,AZ:AZ,">0")) -> 0 | L27: =AM27 -> -8.95 | M27: =AT27 -> -1.07 | O27: =SUM(I27:N27) -> 168.98 | R27: P770793869532382601 | T27: 2025-08-15 15:11:09 | U27: 2025-08-26 23:36:42 | V27: 2025-08-31 16:18:01 | W27: 结算入账 | X27: 店铺余额 | Y27: 168.98 | Z27: 【老板周】小众日系 秋冬 · 【老板周】小众日系 秋冬叠穿时髦下摆不规则宽松马甲 灰色 M（100-135斤） | AA27: 女装/女士精品>马夹 | AB27: XHS-3JY8RM3ZZDVK | AC27: 689dee45c34eef00157e1209 | AD27: 1 | AE27: 179 | AF27: 179 | AH27: 0 | AI27: 0 | AJ27: 0 | AK27: 0.05 | AL27: 0 | AM27: -8.95 | AN27: 179 | AO27: 179 | AP27: 0 | AQ27: 否 | AR27: 0 | AS27: 0.006 | AT27: -1.07 | AU27: 650d6e9f000000001603a6ac | AV27: 老板周. | AW27: 达人带货 | AZ27: 0 | BA27: 0 | BB27: 0 | BC27: 0 | BD27: 0
A28: =YEAR(V28) -> 2025 | B28: =MONTH(V28) -> 8 | C28: =R28 -> P770794020008329151 | D28: =COUNTIF(R:R,R28) -> 2 | E28: =COUNTIF($R$2:R28,R28) -> 1 | F28: {=INDEX(订单明细!BQ:BQ,MATCH(R28&AC28,订单明细!A:A&订单明细!O:O,0))} -> Z2378-花纱色-M | G28: =LEFT(F28,FIND("-",F28)-1) -> Z2378 | H28: {=_xlfn.IFS(C28=0,"",I28>0,AD28,AND(I28<0,I28>-30),0,I28<=-30,-1)} -> -1 | I28: =AF28 -> -179 | J28: =AI28+AJ28 -> 0 | K28: =IF(AZ28<=0,AZ28,AZ28/COUNTIFS(R:R,R28,AZ:AZ,">0")) -> 0 | L28: =AM28 -> 8.95 | M28: =AT28 -> 1.07 | O28: =SUM(I28:N28) -> -168.98 | R28: P770794020008329151 | S28: R0832915122860985 | T28: 2025-08-15 15:13:40 | U28: 2025-08-24 17:52:27 | V28: 2025-08-31 16:18:00 | W28: 退款 | X28: 店铺余额 | Y28: -168.98 | Z28: 【老板周】小众日系 秋冬 · 【老板周】小众日系 秋冬叠穿时髦下摆不规则宽松马甲 花纱色 M（100-135斤） | AA28: 女装/女士精品>马夹 | AB28: XHS-3JY8RM360LQ8 | AC28: 689dee45c34eef00157e11fd | AD28: 0 | AE28: -179 | AF28: -179 | AG28: 0 | AH28: 0 | AI28: 0 | AJ28: 0 | AK28: 0 | AL28: 0 | AM28: 8.95 | AN28: 0 | AO28: 0 | AP28: 0 | AQ28: 否 | AR28: 0 | AS28: 0 | AT28: 1.07 | AU28: 650d6e9f000000001603a6ac | AV28: 老板周. | AW28: 达人带货 | AZ28: 0 | BA28: 0 | BB28: 0 | BC28: 0 | BD28: 0
A29: =YEAR(V29) -> 2025 | B29: =MONTH(V29) -> 8 | C29: =R29 -> P770794020008329151 | D29: =COUNTIF(R:R,R29) -> 2 | E29: =COUNTIF($R$2:R29,R29) -> 2 | F29: {=INDEX(订单明细!BQ:BQ,MATCH(R29&AC29,订单明细!A:A&订单明细!O:O,0))} -> Z2378-花纱色-M | G29: =LEFT(F29,FIND("-",F29)-1) -> Z2378 | H29: {=_xlfn.IFS(C29=0,"",I29>0,AD29,AND(I29<0,I29>-30),0,I29<=-30,-1)} -> 1 | I29: =AF29 -> 179 | J29: =AI29+AJ29 -> 0 | K29: =IF(AZ29<=0,AZ29,AZ29/COUNTIFS(R:R,R29,AZ:AZ,">0")) -> 0 | L29: =AM29 -> -8.95 | M29: =AT29 -> -1.07 | O29: =SUM(I29:N29) -> 168.98 | R29: P770794020008329151 | T29: 2025-08-15 15:13:40 | U29: 2025-08-27 16:05:05 | V29: 2025-08-31 16:18:00 | W29: 结算入账 | X29: 店铺余额 | Y29: 168.98 | Z29: 【老板周】小众日系 秋冬 · 【老板周】小众日系 秋冬叠穿时髦下摆不规则宽松马甲 花纱色 M（100-135斤） | AA29: 女装/女士精品>马夹 | AB29: XHS-3JY8RM360LQ8 | AC29: 689dee45c34eef00157e11fd | AD29: 1 | AE29: 179 | AF29: 179 | AH29: 0 | AI29: 0 | AJ29: 0 | AK29: 0.05 | AL29: 0 | AM29: -8.95 | AN29: 179 | AO29: 179 | AP29: 0 | AQ29: 否 | AR29: 0 | AS29: 0.006 | AT29: -1.07 | AU29: 650d6e9f000000001603a6ac | AV29: 老板周. | AW29: 达人带货 | AZ29: 0 | BA29: 0 | BB29: 0 | BC29: 0 | BD29: 0
A30: =YEAR(V30) -> 2025 | B30: =MONTH(V30) -> 8 | C30: =R30 -> P770376704723157681 | D30: =COUNTIF(R:R,R30) -> 2 | E30: =COUNTIF($R$2:R30,R30) -> 1 | F30: {=INDEX(订单明细!BQ:BQ,MATCH(R30&AC30,订单明细!A:A&订单明细!O:O,0))} -> Z1640-黑色-L | G30: =LEFT(F30,FIND("-",F30)-1) -> Z1640 | H30: {=_xlfn.IFS(C30=0,"",I30>0,AD30,AND(I30<0,I30>-30),0,I30<=-30,-1)} -> -1 | I30: =AF30 -> -289 | J30: =AI30+AJ30 -> 0 | K30: =IF(AZ30<=0,AZ30,AZ30/COUNTIFS(R:R,R30,AZ:AZ,">0")) -> 0 | L30: =AM30 -> 14.45 | M30: =AT30 -> 1.73 | O30: =SUM(I30:N30) -> -272.82 | R30: P770376704723157681 | S30: R2315768193245155 | T30: 2025-08-10 19:18:24 | U30: 2025-08-27 15:44:52 | V30: 2025-08-31 15:58:32 | W30: 退款 | X30: 店铺余额 | Y30: -272.82 | Z30: 【老板周】日系极简 春季 · 【老板周】日系极简 春季新品圆领简约设计感无袖马甲 黑色 L（120-135斤） | AA30: 女装/女士精品>马夹 | AB30: XHS-31AJPPHPB2TC | AC30: 6896fe5c3b9d47001590a85a | AD30: 0 | AE30: -289 | AF30: -289 | AG30: 0 | AH30: 0 | AI30: 0 | AJ30: 0 | AK30: 0 | AL30: 0 | AM30: 14.45 | AN30: 0 | AO30: 0 | AP30: 0 | AQ30: 否 | AR30: 0 | AS30: 0 | AT30: 1.73 | AU30: 650d6e9f000000001603a6ac | AV30: 老板周. | AW30: 达人带货 | AZ30: 0 | BA30: 0 | BB30: 0 | BC30: 0 | BD30: 0
A31: =YEAR(V31) -> 2025 | B31: =MONTH(V31) -> 8 | C31: =R31 -> P770376704723157681 | D31: =COUNTIF(R:R,R31) -> 2 | E31: =COUNTIF($R$2:R31,R31) -> 2 | F31: {=INDEX(订单明细!BQ:BQ,MATCH(R31&AC31,订单明细!A:A&订单明细!O:O,0))} -> Z1640-黑色-L | G31: =LEFT(F31,FIND("-",F31)-1) -> Z1640 | H31: {=_xlfn.IFS(C31=0,"",I31>0,AD31,AND(I31<0,I31>-30),0,I31<=-30,-1)} -> 1 | I31: =AF31 -> 289 | J31: =AI31+AJ31 -> 0 | K31: =IF(AZ31<=0,AZ31,AZ31/COUNTIFS(R:R,R31,AZ:AZ,">0")) -> 0 | L31: =AM31 -> -14.45 | M31: =AT31 -> -1.73 | O31: =SUM(I31:N31) -> 272.82 | R31: P770376704723157681 | T31: 2025-08-10 19:18:24 | U31: 2025-08-27 15:44:50 | V31: 2025-08-31 15:58:32 | W31: 结算入账 | X31: 店铺余额 | Y31: 272.82 | Z31: 【老板周】日系极简 春季 · 【老板周】日系极简 春季新品圆领简约设计感无袖马甲 黑色 L（120-135斤） | AA31: 女装/女士精品>马夹 | AB31: XHS-31AJPPHPB2TC | AC31: 6896fe5c3b9d47001590a85a | AD31: 1 | AE31: 289 | AF31: 289 | AH31: 0 | AI31: 0 | AJ31: 0 | AK31: 0.05 | AL31: 0 | AM31: -14.45 | AN31: 289 | AO31: 289 | AP31: 0 | AQ31: 否 | AR31: 0 | AS31: 0.006 | AT31: -1.73 | AU31: 650d6e9f000000001603a6ac | AV31: 老板周. | AW31: 达人带货 | AZ31: 0 | BA31: 0 | BB31: 0 | BC31: 0 | BD31: 0
A32: =YEAR(V32) -> 2025 | B32: =MONTH(V32) -> 8 | C32: =R32 -> P771601056297099071 | D32: =COUNTIF(R:R,R32) -> 2 | E32: =COUNTIF($R$2:R32,R32) -> 1 | F32: {=INDEX(订单明细!BQ:BQ,MATCH(R32&AC32,订单明细!A:A&订单明细!O:O,0))} -> Z2271-条纹-S | G32: =LEFT(F32,FIND("-",F32)-1) -> Z2271 | H32: {=_xlfn.IFS(C32=0,"",I32>0,AD32,AND(I32<0,I32>-30),0,I32<=-30,-1)} -> -1 | I32: =AF32 -> -289 | J32: =AI32+AJ32 -> 0 | K32: =IF(AZ32<=0,AZ32,AZ32/COUNTIFS(R:R,R32,AZ:AZ,">0")) -> 0 | L32: =AM32 -> 14.45 | M32: =AT32 -> 0 | O32: =SUM(I32:N32) -> -274.55 | R32: P771601056297099071 | S32: R9709907173119522 | T32: 2025-08-24 23:24:16 | U32: 2025-08-26 11:51:51 | V32: 2025-08-31 15:47:53 | W32: 退款 | X32: 店铺余额 | Y32: -274.55 | Z32: 【老板周】慵懒风 秋冬新 · 【老板周】慵懒风 秋冬新款复古撞色条纹松弛感毛衣 条纹 S（80-100斤） | AA32: 女装/女士精品>毛衣 | AB32: XHS-3I9QHHLHJ400 | AC32: 6894b76bf735ce00153807e5 | AD32: 0 | AE32: -289 | AF32: -289 | AG32: 0 | AH32: 0 | AI32: 0 | AJ32: 0 | AK32: 0 | AL32: 0 | AM32: 14.45 | AN32: 0 | AO32: 0 | AP32: 0 | AQ32: 否 | AR32: 0 | AS32: 0 | AT32: 0 | AZ32: 0 | BA32: 0 | BB32: 0 | BC32: 0 | BD32: 0
A33: =YEAR(V33) -> 2025 | B33: =MONTH(V33) -> 8 | C33: =R33 -> P771601056297099071 | D33: =COUNTIF(R:R,R33) -> 2 | E33: =COUNTIF($R$2:R33,R33) -> 2 | F33: {=INDEX(订单明细!BQ:BQ,MATCH(R33&AC33,订单明细!A:A&订单明细!O:O,0))} -> Z2271-条纹-S | G33: =LEFT(F33,FIND("-",F33)-1) -> Z2271 | H33: {=_xlfn.IFS(C33=0,"",I33>0,AD33,AND(I33<0,I33>-30),0,I33<=-30,-1)} -> 1 | I33: =AF33 -> 289 | J33: =AI33+AJ33 -> 0 | K33: =IF(AZ33<=0,AZ33,AZ33/COUNTIFS(R:R,R33,AZ:AZ,">0")) -> 0 | L33: =AM33 -> -14.45 | M33: =AT33 -> 0 | O33: =SUM(I33:N33) -> 274.55 | R33: P771601056297099071 | T33: 2025-08-24 23:24:16 | U33: 2025-08-27 15:33:25 | V33: 2025-08-31 15:47:53 | W33: 结算入账 | X33: 店铺余额 | Y33: 274.55 | Z33: 【老板周】慵懒风 秋冬新 · 【老板周】慵懒风 秋冬新款复古撞色条纹松弛感毛衣 条纹 S（80-100斤） | AA33: 女装/女士精品>毛衣 | AB33: XHS-3I9QHHLHJ400 | AC33: 6894b76bf735ce00153807e5 | AD33: 1 | AE33: 289 | AF33: 289 | AH33: 0 | AI33: 0 | AJ33: 0 | AK33: 0.05 | AL33: 0 | AM33: -14.45 | AN33: 289 | AO33: 289 | AP33: 0 | AQ33: 否 | AR33: 0 | AS33: 0 | AT33: 0 | AZ33: 0 | BA33: 0 | BB33: 0 | BC33: 0 | BD33: 0
A34: =YEAR(V34) -> 2025 | B34: =MONTH(V34) -> 8 | C34: =R34 -> P770794057829472761 | D34: =COUNTIF(R:R,R34) -> 2 | E34: =COUNTIF($R$2:R34,R34) -> 1 | F34: {=INDEX(订单明细!BQ:BQ,MATCH(R34&AC34,订单明细!A:A&订单明细!O:O,0))} -> Z2378-花纱色-S | G34: =LEFT(F34,FIND("-",F34)-1) -> Z2378 | H34: {=_xlfn.IFS(C34=0,"",I34>0,AD34,AND(I34<0,I34>-30),0,I34<=-30,-1)} -> -1 | I34: =AF34 -> -179 | J34: =AI34+AJ34 -> 0 | K34: =IF(AZ34<=0,AZ34,AZ34/COUNTIFS(R:R,R34,AZ:AZ,">0")) -> 0 | L34: =AM34 -> 8.95 | M34: =AT34 -> 1.07 | O34: =SUM(I34:N34) -> -168.98 | R34: P770794057829472761 | S34: R2947276140633243 | T34: 2025-08-15 15:14:17 | U34: 2025-08-25 11:49:57 | V34: 2025-08-31 15:38:21 | W34: 退款 | X34: 店铺余额 | Y34: -168.98 | Z34: 【老板周】小众日系 秋冬 · 【老板周】小众日系 秋冬叠穿时髦下摆不规则宽松马甲 花纱色 S（80-100斤） | AA34: 女装/女士精品>马夹 | AB34: XHS-3JY8RM310T1C | AC34: 689dee45c34eef00157e11fb | AD34: 0 | AE34: -179 | AF34: -179 | AG34: 0 | AH34: 0 | AI34: 0 | AJ34: 0 | AK34: 0 | AL34: 0 | AM34: 8.95 | AN34: 0 | AO34: 0 | AP34: 0 | AQ34: 否 | AR34: 0 | AS34: 0 | AT34: 1.07 | AU34: 650d6e9f000000001603a6ac | AV34: 老板周. | AW34: 达人带货 | AZ34: 0 | BA34: 0 | BB34: 0 | BC34: 0 | BD34: 0
A35: =YEAR(V35) -> 2025 | B35: =MONTH(V35) -> 8 | C35: =R35 -> P770794262760472121 | D35: =COUNTIF(R:R,R35) -> 2 | E35: =COUNTIF($R$2:R35,R35) -> 1 | F35: {=INDEX(订单明细!BQ:BQ,MATCH(R35&AC35,订单明细!A:A&订单明细!O:O,0))} -> Z1248-黑色-S | G35: =LEFT(F35,FIND("-",F35)-1) -> Z1248 | H35: {=_xlfn.IFS(C35=0,"",I35>0,AD35,AND(I35<0,I35>-30),0,I35<=-30,-1)} -> -1 | I35: =AF35 -> -199 | J35: =AI35+AJ35 -> 0 | K35: =IF(AZ35<=0,AZ35,AZ35/COUNTIFS(R:R,R35,AZ:AZ,">0")) -> 0 | L35: =AM35 -> 9.95 | M35: =AT35 -> 1.19 | O35: =SUM(I35:N35) -> -187.86 | R35: P770794262760472121 | S35: R6047212140616203 | T35: 2025-08-15 15:17:42 | U35: 2025-08-25 11:49:57 | V35: 2025-08-31 15:38:21 | W35: 退款 | X35: 店铺余额 | Y35: -187.86 | Z35: 【老板周】舒适经典 新款 · 【老板周】舒适经典 新款柔软细腻无缝一体半高领打底衫 黑色 S（80-100斤） | AA35: 女士内衣/男士内衣/家居服>打底衣 | AB35: XHS-2PMHDY7HMXHC | AC35: 689d92c8956aac0015f36636 | AD35: 0 | AE35: -199 | AF35: -199 | AG35: 0 | AH35: 0 | AI35: 0 | AJ35: 0 | AK35: 0 | AL35: 0 | AM35: 9.95 | AN35: 0 | AO35: 0 | AP35: 0 | AQ35: 否 | AR35: 0 | AS35: 0 | AT35: 1.19 | AU35: 650d6e9f000000001603a6ac | AV35: 老板周. | AW35: 达人带货 | AZ35: 0 | BA35: 0 | BB35: 0 | BC35: 0 | BD35: 0
A36: =YEAR(V36) -> 2025 | B36: =MONTH(V36) -> 8 | C36: =R36 -> P770794262760472121 | D36: =COUNTIF(R:R,R36) -> 2 | E36: =COUNTIF($R$2:R36,R36) -> 2 | F36: {=INDEX(订单明细!BQ:BQ,MATCH(R36&AC36,订单明细!A:A&订单明细!O:O,0))} -> Z1248-黑色-S | G36: =LEFT(F36,FIND("-",F36)-1) -> Z1248 | H36: {=_xlfn.IFS(C36=0,"",I36>0,AD36,AND(I36<0,I36>-30),0,I36<=-30,-1)} -> 1 | I36: =AF36 -> 199 | J36: =AI36+AJ36 -> 0 | K36: =IF(AZ36<=0,AZ36,AZ36/COUNTIFS(R:R,R36,AZ:AZ,">0")) -> 0 | L36: =AM36 -> -9.95 | M36: =AT36 -> -1.19 | O36: =SUM(I36:N36) -> 187.86 | R36: P770794262760472121 | T36: 2025-08-15 15:17:42 | U36: 2025-08-27 15:28:03 | V36: 2025-08-31 15:38:21 | W36: 结算入账 | X36: 店铺余额 | Y36: 187.86 | Z36: 【老板周】舒适经典 新款 · 【老板周】舒适经典 新款柔软细腻无缝一体半高领打底衫 黑色 S（80-100斤） | AA36: 女士内衣/男士内衣/家居服>打底衣 | AB36: XHS-2PMHDY7HMXHC | AC36: 689d92c8956aac0015f36636 | AD36: 1 | AE36: 199 | AF36: 199 | AH36: 0 | AI36: 0 | AJ36: 0 | AK36: 0.05 | AL36: 0 | AM36: -9.95 | AN36: 199 | AO36: 199 | AP36: 0 | AQ36: 否 | AR36: 0 | AS36: 0.006 | AT36: -1.19 | AU36: 650d6e9f000000001603a6ac | AV36: 老板周. | AW36: 达人带货 | AZ36: 0 | BA36: 0 | BB36: 0 | BC36: 0 | BD36: 0
A37: =YEAR(V37) -> 2025 | B37: =MONTH(V37) -> 8 | C37: =R37 -> P770794057829472761 | D37: =COUNTIF(R:R,R37) -> 2 | E37: =COUNTIF($R$2:R37,R37) -> 2 | F37: {=INDEX(订单明细!BQ:BQ,MATCH(R37&AC37,订单明细!A:A&订单明细!O:O,0))} -> Z2378-花纱色-S | G37: =LEFT(F37,FIND("-",F37)-1) -> Z2378 | H37: {=_xlfn.IFS(C37=0,"",I37>0,AD37,AND(I37<0,I37>-30),0,I37<=-30,-1)} -> 1 | I37: =AF37 -> 179 | J37: =AI37+AJ37 -> 0 | K37: =IF(AZ37<=0,AZ37,AZ37/COUNTIFS(R:R,R37,AZ:AZ,">0")) -> 0 | L37: =AM37 -> -8.95 | M37: =AT37 -> -1.07 | O37: =SUM(I37:N37) -> 168.98 | R37: P770794057829472761 | T37: 2025-08-15 15:14:17 | U37: 2025-08-27 15:28:03 | V37: 2025-08-31 15:38:21 | W37: 结算入账 | X37: 店铺余额 | Y37: 168.98 | Z37: 【老板周】小众日系 秋冬 · 【老板周】小众日系 秋冬叠穿时髦下摆不规则宽松马甲 花纱色 S（80-100斤） | AA37: 女装/女士精品>马夹 | AB37: XHS-3JY8RM310T1C | AC37: 689dee45c34eef00157e11fb | AD37: 1 | AE37: 179 | AF37: 179 | AH37: 0 | AI37: 0 | AJ37: 0 | AK37: 0.05 | AL37: 0 | AM37: -8.95 | AN37: 179 | AO37: 179 | AP37: 0 | AQ37: 否 | AR37: 0 | AS37: 0.006 | AT37: -1.07 | AU37: 650d6e9f000000001603a6ac | AV37: 老板周. | AW37: 达人带货 | AZ37: 0 | BA37: 0 | BB37: 0 | BC37: 0 | BD37: 0
A38: =YEAR(V38) -> 2025 | B38: =MONTH(V38) -> 8 | C38: =R38 -> P770795098672334381 | D38: =COUNTIF(R:R,R38) -> 1 | E38: =COUNTIF($R$2:R38,R38) -> 1 | F38: {=INDEX(订单明细!BQ:BQ,MATCH(R38&AC38,订单明细!A:A&订单明细!O:O,0))} -> Z2363-灰色-L | G38: =LEFT(F38,FIND("-",F38)-1) -> Z2363 | H38: {=_xlfn.IFS(C38=0,"",I38>0,AD38,AND(I38<0,I38>-30),0,I38<=-30,-1)} -> 1 | I38: =AF38 -> 359 | J38: =AI38+AJ38 -> 0 | K38: =IF(AZ38<=0,AZ38,AZ38/COUNTIFS(R:R,R38,AZ:AZ,">0")) -> 0 | L38: =AM38 -> -17.95 | M38: =AT38 -> -2.15 | O38: =SUM(I38:N38) -> 338.9 | R38: P770795098672334381 | T38: 2025-08-15 15:31:38 | U38: 2025-08-27 14:52:25 | V38: 2025-08-31 15:25:56 | W38: 结算入账 | X38: 店铺余额 | Y38: 338.9 | Z38: 【老板周】通勤质感 秋冬 · 【老板周】通勤质感 秋冬重磅新品半松紧腰垂感口袋西裤 灰色 L（120-135斤） | AA38: 女装/女士精品>裤子>西装裤/正装裤 | AB38: XHS-3JY7805CH7GG | AC38: 689dee2db292580015c1974d | AD38: 1 | AE38: 359 | AF38: 359 | AH38: 0 | AI38: 0 | AJ38: 0 | AK38: 0.05 | AL38: 0 | AM38: -17.95 | AN38: 359 | AO38: 359 | AP38: 0 | AQ38: 否 | AR38: 0 | AS38: 0.006 | AT38: -2.15 | AU38: 650d6e9f000000001603a6ac | AV38: 老板周. | AW38: 达人带货 | AZ38: 0 | BA38: 0 | BB38: 0 | BC38: 0 | BD38: 0
A39: =YEAR(V39) -> 2025 | B39: =MONTH(V39) -> 8 | C39: =R39 -> P770795099673396171 | D39: =COUNTIF(R:R,R39) -> 1 | E39: =COUNTIF($R$2:R39,R39) -> 1 | F39: {=INDEX(订单明细!BQ:BQ,MATCH(R39&AC39,订单明细!A:A&订单明细!O:O,0))} -> Z2363-灰色-M | G39: =LEFT(F39,FIND("-",F39)-1) -> Z2363 | H39: {=_xlfn.IFS(C39=0,"",I39>0,AD39,AND(I39<0,I39>-30),0,I39<=-30,-1)} -> 1 | I39: =AF39 -> 359 | J39: =AI39+AJ39 -> 0 | K39: =IF(AZ39<=0,AZ39,AZ39/COUNTIFS(R:R,R39,AZ:AZ,">0")) -> 0 | L39: =AM39 -> -17.95 | M39: =AT39 -> -2.15 | O39: =SUM(I39:N39) -> 338.9 | R39: P770795099673396171 | T39: 2025-08-15 15:31:39 | U39: 2025-08-27 14:42:54 | V39: 2025-08-31 15:15:19 | W39: 结算入账 | X39: 店铺余额 | Y39: 338.9 | Z39: 【老板周】通勤质感 秋冬 · 【老板周】通勤质感 秋冬重磅新品半松紧腰垂感口袋西裤 灰色 M（100-120斤） | AA39: 女装/女士精品>裤子>西装裤/正装裤 | AB39: XHS-3JY78059ZB40 | AC39: 689dee2db292580015c1974b | AD39: 1 | AE39: 359 | AF39: 359 | AH39: 0 | AI39: 0 | AJ39: 0 | AK39: 0.05 | AL39: 0 | AM39: -17.95 | AN39: 359 | AO39: 359 | AP39: 0 | AQ39: 否 | AR39: 0 | AS39: 0.006 | AT39: -2.15 | AU39: 650d6e9f000000001603a6ac | AV39: 老板周. | AW39: 达人带货 | AZ39: 0 | BA39: 0 | BB39: 0 | BC39: 0 | BD39: 0
A40: =YEAR(V40) -> 2025 | B40: =MONTH(V40) -> 8 | C40: =R40 -> P770800038248138451 | D40: =COUNTIF(R:R,R40) -> 4 | E40: =COUNTIF($R$2:R40,R40) -> 1 | F40: {=INDEX(订单明细!BQ:BQ,MATCH(R40&AC40,订单明细!A:A&订单明细!O:O,0))} -> Z2380-藏青色 | G40: =LEFT(F40,FIND("-",F40)-1) -> Z2380 | H40: {=_xlfn.IFS(C40=0,"",I40>0,AD40,AND(I40<0,I40>-30),0,I40<=-30,-1)} -> -1 | I40: =AF40 -> -199 | J40: =AI40+AJ40 -> 0 | K40: =IF(AZ40<=0,AZ40,AZ40/COUNTIFS(R:R,R40,AZ:AZ,">0")) -> 0 | L40: =AM40 -> 9.95 | M40: =AT40 -> 1.19 | O40: =SUM(I40:N40) -> -187.86 | R40: P770800038248138451 | S40: R4813845165840954 | T40: 2025-08-15 16:53:58 | U40: 2025-08-23 12:45:29 | V40: 2025-08-31 14:58:04 | W40: 退款 | X40: 店铺余额 | Y40: -187.86 | Z40: 【老板周】百搭气质 秋冬 · 【老板周】百搭气质 秋冬新款百搭造型感气质三角巾 藏青色 | AA40: 服饰配件/皮带/帽子/围巾>围巾/丝巾/披肩 | AB40: XHS-3JY9BQCVPTDS | AC40: 689dee541ea4cb00155e6f96 | AD40: 0 | AE40: -199 | AF40: -199 | AG40: 0 | AH40: 0 | AI40: 0 | AJ40: 0 | AK40: 0 | AL40: 0 | AM40: 9.95 | AN40: 0 | AO40: 0 | AP40: 0 | AQ40: 否 | AR40: 0 | AS40: 0 | AT40: 1.19 | AU40: 650d6e9f000000001603a6ac | AV40: 老板周. | AW40: 达人带货 | AZ40: 0 | BA40: 0 | BB40: 0 | BC40: 0 | BD40: 0
A41: =YEAR(V41) -> 2025 | B41: =MONTH(V41) -> 8 | C41: =R41 -> P770800038248138451 | D41: =COUNTIF(R:R,R41) -> 4 | E41: =COUNTIF($R$2:R41,R41) -> 2 | F41: {=INDEX(订单明细!BQ:BQ,MATCH(R41&AC41,订单明细!A:A&订单明细!O:O,0))} -> Z2380-黑色 | G41: =LEFT(F41,FIND("-",F41)-1) -> Z2380 | H41: {=_xlfn.IFS(C41=0,"",I41>0,AD41,AND(I41<0,I41>-30),0,I41<=-30,-1)} -> -1 | I41: =AF41 -> -199 | J41: =AI41+AJ41 -> 0 | K41: =IF(AZ41<=0,AZ41,AZ41/COUNTIFS(R:R,R41,AZ:AZ,">0")) -> 0 | L41: =AM41 -> 9.95 | M41: =AT41 -> 1.19 | O41: =SUM(I41:N41) -> -187.86 | R41: P770800038248138451 | S41: R4813845165856171 | T41: 2025-08-15 16:53:58 | U41: 2025-08-23 12:55:22 | V41: 2025-08-31 14:58:04 | W41: 退款 | X41: 店铺余额 | Y41: -187.86 | Z41: 【老板周】百搭气质 秋冬 · 【老板周】百搭气质 秋冬新款百搭造型感气质三角巾 黑色 | AA41: 服饰配件/皮带/帽子/围巾>围巾/丝巾/披肩 | AB41: XHS-3JY9BQCQQ0OW | AC41: 689dee541ea4cb00155e6f94 | AD41: 0 | AE41: -199 | AF41: -199 | AG41: 0 | AH41: 0 | AI41: 0 | AJ41: 0 | AK41: 0 | AL41: 0 | AM41: 9.95 | AN41: 0 | AO41: 0 | AP41: 0 | AQ41: 否 | AR41: 0 | AS41: 0 | AT41: 1.19 | AU41: 650d6e9f000000001603a6ac | AV41: 老板周. | AW41: 达人带货 | AZ41: 0 | BA41: 0 | BB41: 0 | BC41: 0 | BD41: 0
A42: =YEAR(V42) -> 2025 | B42: =MONTH(V42) -> 8 | C42: =R42 -> P770815073365177321 | D42: =COUNTIF(R:R,R42) -> 2 | E42: =COUNTIF($R$2:R42,R42) -> 1 | F42: {=INDEX(订单明细!BQ:BQ,MATCH(R42&AC42,订单明细!A:A&订单明细!O:O,0))} -> Z2378-灰色-S | G42: =LEFT(F42,FIND("-",F42)-1) -> Z2378 | H42: {=_xlfn.IFS(C42=0,"",I42>0,AD42,AND(I42<0,I42>-30),0,I42<=-30,-1)} -> -1 | I42: =AF42 -> -179 | J42: =AI42+AJ42 -> 0 | K42: =IF(AZ42<=0,AZ42,AZ42/COUNTIFS(R:R,R42,AZ:AZ,">0")) -> 0 | L42: =AM42 -> 8.95 | M42: =AT42 -> 1.07 | O42: =SUM(I42:N42) -> -168.98 | R42: P770815073365177321 | S42: R6517732120696464 | T42: 2025-08-15 21:04:33 | U42: 2025-08-24 19:50:23 | V42: 2025-08-31 14:58:04 | W42: 退款 | X42: 店铺余额 | Y42: -168.98 | Z42: 【老板周】小众日系 秋冬 · 【老板周】小众日系 秋冬叠穿时髦下摆不规则宽松马甲 灰色 S（80-100斤） | AA42: 女装/女士精品>马夹 | AB42: XHS-3JY8RM3UZL6O | AC42: 689dee45c34eef00157e1207 | AD42: 0 | AE42: -179 | AF42: -179 | AG42: 0 | AH42: 0 | AI42: 0 | AJ42: 0 | AK42: 0 | AL42: 0 | AM42: 8.95 | AN42: 0 | AO42: 0 | AP42: 0 | AQ42: 否 | AR42: 0 | AS42: 0 | AT42: 1.07 | AU42: 650d6e9f000000001603a6ac | AV42: 老板周. | AW42: 达人带货 | AZ42: 0 | BA42: 0 | BB42: 0 | BC42: 0 | BD42: 0
A43: =YEAR(V43) -> 2025 | B43: =MONTH(V43) -> 8 | C43: =R43 -> P770815073365177321 | D43: =COUNTIF(R:R,R43) -> 2 | E43: =COUNTIF($R$2:R43,R43) -> 2 | F43: {=INDEX(订单明细!BQ:BQ,MATCH(R43&AC43,订单明细!A:A&订单明细!O:O,0))} -> Z2378-灰色-S | G43: =LEFT(F43,FIND("-",F43)-1) -> Z2378 | H43: {=_xlfn.IFS(C43=0,"",I43>0,AD43,AND(I43<0,I43>-30),0,I43<=-30,-1)} -> 1 | I43: =AF43 -> 179 | J43: =AI43+AJ43 -> 0 | K43: =IF(AZ43<=0,AZ43,AZ43/COUNTIFS(R:R,R43,AZ:AZ,">0")) -> 0 | L43: =AM43 -> -8.95 | M43: =AT43 -> -1.07 | O43: =SUM(I43:N43) -> 168.98 | R43: P770815073365177321 | T43: 2025-08-15 21:04:33 | U43: 2025-08-27 14:44:36 | V43: 2025-08-31 14:58:04 | W43: 结算入账 | X43: 店铺余额 | Y43: 168.98 | Z43: 【老板周】小众日系 秋冬 · 【老板周】小众日系 秋冬叠穿时髦下摆不规则宽松马甲 灰色 S（80-100斤） | AA43: 女装/女士精品>马夹 | AB43: XHS-3JY8RM3UZL6O | AC43: 689dee45c34eef00157e1207 | AD43: 1 | AE43: 179 | AF43: 179 | AH43: 0 | AI43: 0 | AJ43: 0 | AK43: 0.05 | AL43: 0 | AM43: -8.95 | AN43: 179 | AO43: 179 | AP43: 0 | AQ43: 否 | AR43: 0 | AS43: 0.006 | AT43: -1.07 | AU43: 650d6e9f000000001603a6ac | AV43: 老板周. | AW43: 达人带货 | AZ43: 0 | BA43: 0 | BB43: 0 | BC43: 0 | BD43: 0
A44: =YEAR(V44) -> 2025 | B44: =MONTH(V44) -> 8 | C44: =R44 -> P770800038248138451 | D44: =COUNTIF(R:R,R44) -> 4 | E44: =COUNTIF($R$2:R44,R44) -> 3 | F44: {=INDEX(订单明细!BQ:BQ,MATCH(R44&AC44,订单明细!A:A&订单明细!O:O,0))} -> Z2380-黑色 | G44: =LEFT(F44,FIND("-",F44)-1) -> Z2380 | H44: {=_xlfn.IFS(C44=0,"",I44>0,AD44,AND(I44<0,I44>-30),0,I44<=-30,-1)} -> 1 | I44: =AF44 -> 199 | J44: =AI44+AJ44 -> 0 | K44: =IF(AZ44<=0,AZ44,AZ44/COUNTIFS(R:R,R44,AZ:AZ,">0")) -> 0 | L44: =AM44 -> -9.95 | M44: =AT44 -> -1.19 | O44: =SUM(I44:N44) -> 187.86 | R44: P770800038248138451 | T44: 2025-08-15 16:53:58 | U44: 2025-08-27 14:46:38 | V44: 2025-08-31 14:58:04 | W44: 结算入账 | X44: 店铺余额 | Y44: 375.72 | Z44: 【老板周】百搭气质 秋冬 · 【老板周】百搭气质 秋冬新款百搭造型感气质三角巾 黑色 | AA44: 服饰配件/皮带/帽子/围巾>围巾/丝巾/披肩 | AB44: XHS-3JY9BQCQQ0OW | AC44: 689dee541ea4cb00155e6f94 | AD44: 1 | AE44: 199 | AF44: 199 | AH44: 0 | AI44: 0 | AJ44: 0 | AK44: 0.05 | AL44: 0 | AM44: -9.95 | AN44: 199 | AO44: 199 | AP44: 0 | AQ44: 否 | AR44: 0 | AS44: 0.006 | AT44: -1.19 | AU44: 650d6e9f000000001603a6ac | AV44: 老板周. | AW44: 达人带货 | AZ44: 0 | BA44: 0 | BB44: 0 | BC44: 0 | BD44: 0
A45: =YEAR(V45) -> 2025 | B45: =MONTH(V45) -> 8 | C45: =R45 -> P770800038248138451 | D45: =COUNTIF(R:R,R45) -> 4 | E45: =COUNTIF($R$2:R45,R45) -> 4 | F45: {=INDEX(订单明细!BQ:BQ,MATCH(R45&AC45,订单明细!A:A&订单明细!O:O,0))} -> Z2380-藏青色 | G45: =LEFT(F45,FIND("-",F45)-1) -> Z2380 | H45: {=_xlfn.IFS(C45=0,"",I45>0,AD45,AND(I45<0,I45>-30),0,I45<=-30,-1)} -> 1 | I45: =AF45 -> 199 | J45: =AI45+AJ45 -> 0 | K45: =IF(AZ45<=0,AZ45,AZ45/COUNTIFS(R:R,R45,AZ:AZ,">0")) -> 0 | L45: =AM45 -> -9.95 | M45: =AT45 -> -1.19 | O45: =SUM(I45:N45) -> 187.86 | R45: P770800038248138451 | T45: 2025-08-15 16:53:58 | U45: 2025-08-27 14:46:38 | V45: 2025-08-31 14:58:04 | W45: 结算入账 | X45: 店铺余额 | Y45: 375.72 | Z45: 【老板周】百搭气质 秋冬 · 【老板周】百搭气质 秋冬新款百搭造型感气质三角巾 藏青色 | AA45: 服饰配件/皮带/帽子/围巾>围巾/丝巾/披肩 | AB45: XHS-3JY9BQCVPTDS | AC45: 689dee541ea4cb00155e6f96 | AD45: 1 | AE45: 199 | AF45: 199 | AH45: 0 | AI45: 0 | AJ45: 0 | AK45: 0.05 | AL45: 0 | AM45: -9.95 | AN45: 199 | AO45: 199 | AP45: 0 | AQ45: 否 | AR45: 0 | AS45: 0.006 | AT45: -1.19 | AU45: 650d6e9f000000001603a6ac | AV45: 老板周. | AW45: 达人带货 | AZ45: 0 | BA45: 0 | BB45: 0 | BC45: 0 | BD45: 0
A46: =YEAR(V46) -> 2025 | B46: =MONTH(V46) -> 8 | C46: =R46 -> P770645880641023381 | D46: =COUNTIF(R:R,R46) -> 2 | E46: =COUNTIF($R$2:R46,R46) -> 1 | F46: {=INDEX(订单明细!BQ:BQ,MATCH(R46&AC46,订单明细!A:A&订单明细!O:O,0))} -> Z1576-黑色-M | G46: =LEFT(F46,FIND("-",F46)-1) -> Z1576 | H46: {=_xlfn.IFS(C46=0,"",I46>0,AD46,AND(I46<0,I46>-30),0,I46<=-30,-1)} -> -1 | I46: =AF46 -> -199 | J46: =AI46+AJ46 -> 0 | K46: =IF(AZ46<=0,AZ46,AZ46/COUNTIFS(R:R,R46,AZ:AZ,">0")) -> 0 | L46: =AM46 -> 9.95 | M46: =AT46 -> 1.19 | O46: =SUM(I46:N46) -> -187.86 | R46: P770645880641023381 | S46: R4102338144623173 | T46: 2025-08-13 22:04:40 | U46: 2025-08-25 14:12:58 | V46: 2025-08-31 14:38:22 | W46: 退款 | X46: 店铺余额 | Y46: -187.86 | Z46: 【老板周】时髦撞色 春季 · 【老板周】时髦撞色 春季新款假两件显瘦长袖打底T恤上衣 黑色 M（100-120斤） | AA46: 女装/女士精品>T恤 | AB46: XHS-2Z0D3J1YAL8G | AC46: 6896fe48057f570015d29244 | AD46: 0 | AE46: -199 | AF46: -199 | AG46: 0 | AH46: 0 | AI46: 0 | AJ46: 0 | AK46: 0 | AL46: 0 | AM46: 9.95 | AN46: 0 | AO46: 0 | AP46: 0 | AQ46: 否 | AR46: 0 | AS46: 0 | AT46: 1.19 | AU46: 650d6e9f000000001603a6ac | AV46: 老板周. | AW46: 达人带货 | AZ46: 0 | BA46: 0 | BB46: 0 | BC46: 0 | BD46: 0
A47: =YEAR(V47) -> 2025 | B47: =MONTH(V47) -> 8 | C47: =R47 -> P770645880641023381 | D47: =COUNTIF(R:R,R47) -> 2 | E47: =COUNTIF($R$2:R47,R47) -> 2 | F47: {=INDEX(订单明细!BQ:BQ,MATCH(R47&AC47,订单明细!A:A&订单明细!O:O,0))} -> Z1576-黑色-M | G47: =LEFT(F47,FIND("-",F47)-1) -> Z1576 | H47: {=_xlfn.IFS(C47=0,"",I47>0,AD47,AND(I47<0,I47>-30),0,I47<=-30,-1)} -> 1 | I47: =AF47 -> 199 | J47: =AI47+AJ47 -> 0 | K47: =IF(AZ47<=0,AZ47,AZ47/COUNTIFS(R:R,R47,AZ:AZ,">0")) -> 0 | L47: =AM47 -> -9.95 | M47: =AT47 -> -1.19 | O47: =SUM(I47:N47) -> 187.86 | R47: P770645880641023381 | T47: 2025-08-13 22:04:40 | U47: 2025-08-27 14:20:40 | V47: 2025-08-31 14:38:22 | W47: 结算入账 | X47: 店铺余额 | Y47: 187.86 | Z47: 【老板周】时髦撞色 春季 · 【老板周】时髦撞色 春季新款假两件显瘦长袖打底T恤上衣 黑色 M（100-120斤） | AA47: 女装/女士精品>T恤 | AB47: XHS-2Z0D3J1YAL8G | AC47: 6896fe48057f570015d29244 | AD47: 1 | AE47: 199 | AF47: 199 | AH47: 0 | AI47: 0 | AJ47: 0 | AK47: 0.05 | AL47: 0 | AM47: -9.95 | AN47: 199 | AO47: 199 | AP47: 0 | AQ47: 否 | AR47: 0 | AS47: 0.006 | AT47: -1.19 | AU47: 650d6e9f000000001603a6ac | AV47: 老板周. | AW47: 达人带货 | AZ47: 0 | BA47: 0 | BB47: 0 | BC47: 0 | BD47: 0
A48: =YEAR(V48) -> 2025 | B48: =MONTH(V48) -> 8 | C48: =R48 -> P770799979667284611 | D48: =COUNTIF(R:R,R48) -> 2 | E48: =COUNTIF($R$2:R48,R48) -> 1 | F48: {=INDEX(订单明细!BQ:BQ,MATCH(R48&AC48,订单明细!A:A&订单明细!O:O,0))} -> Z2380-藏青色 | G48: =LEFT(F48,FIND("-",F48)-1) -> Z2380 | H48: {=_xlfn.IFS(C48=0,"",I48>0,AD48,AND(I48<0,I48>-30),0,I48<=-30,-1)} -> -1 | I48: =AF48 -> -199 | J48: =AI48+AJ48 -> 0 | K48: =IF(AZ48<=0,AZ48,AZ48/COUNTIFS(R:R,R48,AZ:AZ,">0")) -> 0 | L48: =AM48 -> 9.95 | M48: =AT48 -> 1.19 | O48: =SUM(I48:N48) -> -187.86 | R48: P770799979667284611 | S48: R6728461164648415 | T48: 2025-08-15 16:52:59 | U48: 2025-08-27 14:18:33 | V48: 2025-08-31 14:28:00 | W48: 退款 | X48: 店铺余额 | Y48: -187.86 | Z48: 【老板周】百搭气质 秋冬 · 【老板周】百搭气质 秋冬新款百搭造型感气质三角巾 藏青色 | AA48: 服饰配件/皮带/帽子/围巾>围巾/丝巾/披肩 | AB48: XHS-3JY9BQCVPTDS | AC48: 689dee541ea4cb00155e6f96 | AD48: 0 | AE48: -199 | AF48: -199 | AG48: 0 | AH48: 0 | AI48: 0 | AJ48: 0 | AK48: 0 | AL48: 0 | AM48: 9.95 | AN48: 0 | AO48: 0 | AP48: 0 | AQ48: 否 | AR48: 0 | AS48: 0 | AT48: 1.19 | AU48: 650d6e9f000000001603a6ac | AV48: 老板周. | AW48: 达人带货 | AZ48: 0 | BA48: 0 | BB48: 0 | BC48: 0 | BD48: 0
A49: =YEAR(V49) -> 2025 | B49: =MONTH(V49) -> 8 | C49: =R49 -> P770798337207284891 | D49: =COUNTIF(R:R,R49) -> 2 | E49: =COUNTIF($R$2:R49,R49) -> 1 | F49: {=INDEX(订单明细!BQ:BQ,MATCH(R49&AC49,订单明细!A:A&订单明细!O:O,0))} -> Z2378-花纱色-M | G49: =LEFT(F49,FIND("-",F49)-1) -> Z2378 | H49: {=_xlfn.IFS(C49=0,"",I49>0,AD49,AND(I49<0,I49>-30),0,I49<=-30,-1)} -> -1 | I49: =AF49 -> -179 | J49: =AI49+AJ49 -> 0 | K49: =IF(AZ49<=0,AZ49,AZ49/COUNTIFS(R:R,R49,AZ:AZ,">0")) -> 0 | L49: =AM49 -> 8.95 | M49: =AT49 -> 1.07 | O49: =SUM(I49:N49) -> -168.98 | R49: P770798337207284891 | S49: R0728489164679306 | T49: 2025-08-15 16:25:37 | U49: 2025-08-27 14:18:33 | V49: 2025-08-31 14:28:00 | W49: 退款 | X49: 店铺余额 | Y49: -168.98 | Z49: 【老板周】小众日系 秋冬 · 【老板周】小众日系 秋冬叠穿时髦下摆不规则宽松马甲 花纱色 M（100-135斤） | AA49: 女装/女士精品>马夹 | AB49: XHS-3JY8RM360LQ8 | AC49: 689dee45c34eef00157e11fd | AD49: 0 | AE49: -179 | AF49: -179 | AG49: 0 | AH49: 0 | AI49: 0 | AJ49: 0 | AK49: 0 | AL49: 0 | AM49: 8.95 | AN49: 0 | AO49: 0 | AP49: 0 | AQ49: 否 | AR49: 0 | AS49: 0 | AT49: 1.07 | AU49: 650d6e9f000000001603a6ac | AV49: 老板周. | AW49: 达人带货 | AZ49: 0 | BA49: 0 | BB49: 0 | BC49: 0 | BD49: 0
A50: =YEAR(V50) -> 2025 | B50: =MONTH(V50) -> 8 | C50: =R50 -> P770798387983284011 | D50: =COUNTIF(R:R,R50) -> 2 | E50: =COUNTIF($R$2:R50,R50) -> 1 | F50: {=INDEX(订单明细!BQ:BQ,MATCH(R50&AC50,订单明细!A:A&订单明细!O:O,0))} -> Z1248-黑色-M | G50: =LEFT(F50,FIND("-",F50)-1) -> Z1248 | H50: {=_xlfn.IFS(C50=0,"",I50>0,AD50,AND(I50<0,I50>-30),0,I50<=-30,-1)} -> -1 | I50: =AF50 -> -199 | J50: =AI50+AJ50 -> 0 | K50: =IF(AZ50<=0,AZ50,AZ50/COUNTIFS(R:R,R50,AZ:AZ,">0")) -> 0 | L50: =AM50 -> 9.95 | M50: =AT50 -> 1.19 | O50: =SUM(I50:N50) -> -187.86 | R50: P770798387983284011 | S50: R8328401169215658 | T50: 2025-08-15 16:26:28 | U50: 2025-08-27 14:18:33 | V50: 2025-08-31 14:28:00 | W50: 退款 | X50: 店铺余额 | Y50: -187.86 | Z50: 【老板周】舒适经典 新款 · 【老板周】舒适经典 新款柔软细腻无缝一体半高领打底衫 黑色 M（100-120斤） | AA50: 女士内衣/男士内衣/家居服>打底衣 | AB50: XHS-2PMHDZ8YH728 | AC50: 689d92c8956aac0015f36638 | AD50: 0 | AE50: -199 | AF50: -199 | AG50: 0 | AH50: 0 | AI50: 0 | AJ50: 0 | AK50: 0 | AL50: 0 | AM50: 9.95 | AN50: 0 | AO50: 0 | AP50: 0 | AQ50: 否 | AR50: 0 | AS50: 0 | AT50: 1.19 | AU50: 650d6e9f000000001603a6ac | AV50: 老板周. | AW50: 达人带货 | AZ50: 0 | BA50: 0 | BB50: 0 | BC50: 0 | BD50: 0
A51: =YEAR(V51) -> 2025 | B51: =MONTH(V51) -> 8 | C51: =R51 -> P770822898182284051 | D51: =COUNTIF(R:R,R51) -> 2 | E51: =COUNTIF($R$2:R51,R51) -> 1 | F51: {=INDEX(订单明细!BQ:BQ,MATCH(R51&AC51,订单明细!A:A&订单明细!O:O,0))} -> Z2376-黑白条纹-M | G51: =LEFT(F51,FIND("-",F51)-1) -> Z2376 | H51: {=_xlfn.IFS(C51=0,"",I51>0,AD51,AND(I51<0,I51>-30),0,I51<=-30,-1)} -> -1 | I51: =AF51 -> -219 | J51: =AI51+AJ51 -> 0 | K51: =IF(AZ51<=0,AZ51,AZ51/COUNTIFS(R:R,R51,AZ:AZ,">0")) -> 0 | L51: =AM51 -> 10.95 | M51: =AT51 -> 1.31 | O51: =SUM(I51:N51) -> -206.74 | R51: P770822898182284051 | S51: R8228405164600003 | T51: 2025-08-15 23:14:58 | U51: 2025-08-27 14:18:33 | V51: 2025-08-31 14:28:00 | W51: 退款 | X51: 店铺余额 | Y51: -206.74 | Z51: 【老板周】经典慵懒 秋季 · 【老板周】经典慵懒 秋季经典撞色条纹镂空针织上衣 黑白条纹 M（100-135斤） | AA51: 女装/女士精品>毛针织衫 | AB51: XHS-3JY88WA16VWG | AC51: 689dee3bbc668f00150ae4a1 | AD51: 0 | AE51: -219 | AF51: -219 | AG51: 0 | AH51: 0 | AI51: 0 | AJ51: 0 | AK51: 0 | AL51: 0 | AM51: 10.95 | AN51: 0 | AO51: 0 | AP51: 0 | AQ51: 否 | AR51: 0 | AS51: 0 | AT51: 1.31 | AU51: 650d6e9f000000001603a6ac | AV51: 老板周. | AW51: 达人带货 | AZ51: 0 | BA51: 0 | BB51: 0 | BC51: 0 | BD51: 0
A52: =YEAR(V52) -> 2025 | B52: =MONTH(V52) -> 8 | C52: =R52 -> P770822898182284051 | D52: =COUNTIF(R:R,R52) -> 2 | E52: =COUNTIF($R$2:R52,R52) -> 2 | F52: {=INDEX(订单明细!BQ:BQ,MATCH(R52&AC52,订单明细!A:A&订单明细!O:O,0))} -> Z2376-黑白条纹-M | G52: =LEFT(F52,FIND("-",F52)-1) -> Z2376 | H52: {=_xlfn.IFS(C52=0,"",I52>0,AD52,AND(I52<0,I52>-30),0,I52<=-30,-1)} -> 1 | I52: =AF52 -> 219 | J52: =AI52+AJ52 -> 0 | K52: =IF(AZ52<=0,AZ52,AZ52/COUNTIFS(R:R,R52,AZ:AZ,">0")) -> 0 | L52: =AM52 -> -10.95 | M52: =AT52 -> -1.31 | O52: =SUM(I52:N52) -> 206.74 | R52: P770822898182284051 | T52: 2025-08-15 23:14:58 | U52: 2025-08-27 14:18:33 | V52: 2025-08-31 14:28:00 | W52: 结算入账 | X52: 店铺余额 | Y52: 206.74 | Z52: 【老板周】经典慵懒 秋季 · 【老板周】经典慵懒 秋季经典撞色条纹镂空针织上衣 黑白条纹 M（100-135斤） | AA52: 女装/女士精品>毛针织衫 | AB52: XHS-3JY88WA16VWG | AC52: 689dee3bbc668f00150ae4a1 | AD52: 1 | AE52: 219 | AF52: 219 | AH52: 0 | AI52: 0 | AJ52: 0 | AK52: 0.05 | AL52: 0 | AM52: -10.95 | AN52: 219 | AO52: 219 | AP52: 0 | AQ52: 否 | AR52: 0 | AS52: 0.006 | AT52: -1.31 | AU52: 650d6e9f000000001603a6ac | AV52: 老板周. | AW52: 达人带货 | AZ52: 0 | BA52: 0 | BB52: 0 | BC52: 0 | BD52: 0
A53: =YEAR(V53) -> 2025 | B53: =MONTH(V53) -> 8 | C53: =R53 -> P770799979667284611 | D53: =COUNTIF(R:R,R53) -> 2 | E53: =COUNTIF($R$2:R53,R53) -> 2 | F53: {=INDEX(订单明细!BQ:BQ,MATCH(R53&AC53,订单明细!A:A&订单明细!O:O,0))} -> Z2380-藏青色 | G53: =LEFT(F53,FIND("-",F53)-1) -> Z2380 | H53: {=_xlfn.IFS(C53=0,"",I53>0,AD53,AND(I53<0,I53>-30),0,I53<=-30,-1)} -> 1 | I53: =AF53 -> 199 | J53: =AI53+AJ53 -> 0 | K53: =IF(AZ53<=0,AZ53,AZ53/COUNTIFS(R:R,R53,AZ:AZ,">0")) -> 0 | L53: =AM53 -> -9.95 | M53: =AT53 -> -1.19 | O53: =SUM(I53:N53) -> 187.86 | R53: P770799979667284611 | T53: 2025-08-15 16:52:59 | U53: 2025-08-27 14:18:33 | V53: 2025-08-31 14:28:00 | W53: 结算入账 | X53: 店铺余额 | Y53: 187.86 | Z53: 【老板周】百搭气质 秋冬 · 【老板周】百搭气质 秋冬新款百搭造型感气质三角巾 藏青色 | AA53: 服饰配件/皮带/帽子/围巾>围巾/丝巾/披肩 | AB53: XHS-3JY9BQCVPTDS | AC53: 689dee541ea4cb00155e6f96 | AD53: 1 | AE53: 199 | AF53: 199 | AH53: 0 | AI53: 0 | AJ53: 0 | AK53: 0.05 | AL53: 0 | AM53: -9.95 | AN53: 199 | AO53: 199 | AP53: 0 | AQ53: 否 | AR53: 0 | AS53: 0.006 | AT53: -1.19 | AU53: 650d6e9f000000001603a6ac | AV53: 老板周. | AW53: 达人带货 | AZ53: 0 | BA53: 0 | BB53: 0 | BC53: 0 | BD53: 0
A54: =YEAR(V54) -> 2025 | B54: =MONTH(V54) -> 8 | C54: =R54 -> P770798387983284011 | D54: =COUNTIF(R:R,R54) -> 2 | E54: =COUNTIF($R$2:R54,R54) -> 2 | F54: {=INDEX(订单明细!BQ:BQ,MATCH(R54&AC54,订单明细!A:A&订单明细!O:O,0))} -> Z1248-黑色-M | G54: =LEFT(F54,FIND("-",F54)-1) -> Z1248 | H54: {=_xlfn.IFS(C54=0,"",I54>0,AD54,AND(I54<0,I54>-30),0,I54<=-30,-1)} -> 1 | I54: =AF54 -> 199 | J54: =AI54+AJ54 -> 0 | K54: =IF(AZ54<=0,AZ54,AZ54/COUNTIFS(R:R,R54,AZ:AZ,">0")) -> 0 | L54: =AM54 -> -9.95 | M54: =AT54 -> -1.19 | O54: =SUM(I54:N54) -> 187.86 | R54: P770798387983284011 | T54: 2025-08-15 16:26:28 | U54: 2025-08-27 14:18:33 | V54: 2025-08-31 14:28:00 | W54: 结算入账 | X54: 店铺余额 | Y54: 187.86 | Z54: 【老板周】舒适经典 新款 · 【老板周】舒适经典 新款柔软细腻无缝一体半高领打底衫 黑色 M（100-120斤） | AA54: 女士内衣/男士内衣/家居服>打底衣 | AB54: XHS-2PMHDZ8YH728 | AC54: 689d92c8956aac0015f36638 | AD54: 1 | AE54: 199 | AF54: 199 | AH54: 0 | AI54: 0 | AJ54: 0 | AK54: 0.05 | AL54: 0 | AM54: -9.95 | AN54: 199 | AO54: 199 | AP54: 0 | AQ54: 否 | AR54: 0 | AS54: 0.006 | AT54: -1.19 | AU54: 650d6e9f000000001603a6ac | AV54: 老板周. | AW54: 达人带货 | AZ54: 0 | BA54: 0 | BB54: 0 | BC54: 0 | BD54: 0
A55: =YEAR(V55) -> 2025 | B55: =MONTH(V55) -> 8 | C55: =R55 -> P770798337207284891 | D55: =COUNTIF(R:R,R55) -> 2 | E55: =COUNTIF($R$2:R55,R55) -> 2 | F55: {=INDEX(订单明细!BQ:BQ,MATCH(R55&AC55,订单明细!A:A&订单明细!O:O,0))} -> Z2378-花纱色-M | G55: =LEFT(F55,FIND("-",F55)-1) -> Z2378 | H55: {=_xlfn.IFS(C55=0,"",I55>0,AD55,AND(I55<0,I55>-30),0,I55<=-30,-1)} -> 1 | I55: =AF55 -> 179 | J55: =AI55+AJ55 -> 0 | K55: =IF(AZ55<=0,AZ55,AZ55/COUNTIFS(R:R,R55,AZ:AZ,">0")) -> 0 | L55: =AM55 -> -8.95 | M55: =AT55 -> -1.07 | O55: =SUM(I55:N55) -> 168.98 | R55: P770798337207284891 | T55: 2025-08-15 16:25:37 | U55: 2025-08-27 14:18:33 | V55: 2025-08-31 14:28:00 | W55: 结算入账 | X55: 店铺余额 | Y55: 168.98 | Z55: 【老板周】小众日系 秋冬 · 【老板周】小众日系 秋冬叠穿时髦下摆不规则宽松马甲 花纱色 M（100-135斤） | AA55: 女装/女士精品>马夹 | AB55: XHS-3JY8RM360LQ8 | AC55: 689dee45c34eef00157e11fd | AD55: 1 | AE55: 179 | AF55: 179 | AH55: 0 | AI55: 0 | AJ55: 0 | AK55: 0.05 | AL55: 0 | AM55: -8.95 | AN55: 179 | AO55: 179 | AP55: 0 | AQ55: 否 | AR55: 0 | AS55: 0.006 | AT55: -1.07 | AU55: 650d6e9f000000001603a6ac | AV55: 老板周. | AW55: 达人带货 | AZ55: 0 | BA55: 0 | BB55: 0 | BC55: 0 | BD55: 0
A56: =YEAR(V56) -> 2025 | B56: =MONTH(V56) -> 8 | C56: =R56 -> P770795108315278051 | D56: =COUNTIF(R:R,R56) -> 2 | E56: =COUNTIF($R$2:R56,R56) -> 1 | F56: {=INDEX(订单明细!BQ:BQ,MATCH(R56&AC56,订单明细!A:A&订单明细!O:O,0))} -> Z2363-黑色-M | G56: =LEFT(F56,FIND("-",F56)-1) -> Z2363 | H56: {=_xlfn.IFS(C56=0,"",I56>0,AD56,AND(I56<0,I56>-30),0,I56<=-30,-1)} -> -1 | I56: =AF56 -> -359 | J56: =AI56+AJ56 -> 0 | K56: =IF(AZ56<=0,AZ56,AZ56/COUNTIFS(R:R,R56,AZ:AZ,">0")) -> 0 | L56: =AM56 -> 17.95 | M56: =AT56 -> 2.15 | O56: =SUM(I56:N56) -> -338.9 | R56: P770795108315278051 | S56: R1527805166706445 | T56: 2025-08-15 15:31:48 | U56: 2025-08-28 11:45:00 | V56: 2025-08-31 14:18:21 | W56: 退款 | X56: 店铺余额 | Y56: -338.9 | Z56: 【老板周】通勤质感 秋冬 · 【老板周】通勤质感 秋冬重磅新品半松紧腰垂感口袋西裤 黑色 M（100-120斤） | AA56: 女装/女士精品>裤子>西装裤/正装裤 | AB56: XHS-3JY7804XHTDS | AC56: 689dee2db292580015c19745 | AD56: 0 | AE56: -359 | AF56: -359 | AG56: 0 | AH56: 0 | AI56: 0 | AJ56: 0 | AK56: 0 | AL56: 0 | AM56: 17.95 | AN56: 0 | AO56: 0 | AP56: 0 | AQ56: 否 | AR56: 0 | AS56: 0 | AT56: 2.15 | AU56: 650d6e9f000000001603a6ac | AV56: 老板周. | AW56: 达人带货 | AZ56: 0 | BA56: 0 | BB56: 0 | BC56: 0 | BD56: 0
A57: =YEAR(V57) -> 2025 | B57: =MONTH(V57) -> 8 | C57: =R57 -> P770795400699278151 | D57: =COUNTIF(R:R,R57) -> 2 | E57: =COUNTIF($R$2:R57,R57) -> 1 | F57: {=INDEX(订单明细!BQ:BQ,MATCH(R57&AC57,订单明细!A:A&订单明细!O:O,0))} -> Z2363-灰色-M | G57: =LEFT(F57,FIND("-",F57)-1) -> Z2363 | H57: {=_xlfn.IFS(C57=0,"",I57>0,AD57,AND(I57<0,I57>-30),0,I57<=-30,-1)} -> -1 | I57: =AF57 -> -359 | J57: =AI57+AJ57 -> 0 | K57: =IF(AZ57<=0,AZ57,AZ57/COUNTIFS(R:R,R57,AZ:AZ,">0")) -> 0 | L57: =AM57 -> 17.95 | M57: =AT57 -> 2.15 | O57: =SUM(I57:N57) -> -338.9 | R57: P770795400699278151 | S57: R9927815166637890 | T57: 2025-08-15 15:36:40 | U57: 2025-08-28 11:45:00 | V57: 2025-08-31 14:18:21 | W57: 退款 | X57: 店铺余额 | Y57: -338.9 | Z57: 【老板周】通勤质感 秋冬 · 【老板周】通勤质感 秋冬重磅新品半松紧腰垂感口袋西裤 灰色 M（100-120斤） | AA57: 女装/女士精品>裤子>西装裤/正装裤 | AB57: XHS-3JY78059ZB40 | AC57: 689dee2db292580015c1974b | AD57: 0 | AE57: -359 | AF57: -359 | AG57: 0 | AH57: 0 | AI57: 0 | AJ57: 0 | AK57: 0 | AL57: 0 | AM57: 17.95 | AN57: 0 | AO57: 0 | AP57: 0 | AQ57: 否 | AR57: 0 | AS57: 0 | AT57: 2.15 | AU57: 650d6e9f000000001603a6ac | AV57: 老板周. | AW57: 达人带货 | AZ57: 0 | BA57: 0 | BB57: 0 | BC57: 0 | BD57: 0
A58: =YEAR(V58) -> 2025 | B58: =MONTH(V58) -> 8 | C58: =R58 -> P770983921263440451 | D58: =COUNTIF(R:R,R58) -> 2 | E58: =COUNTIF($R$2:R58,R58) -> 1 | F58: {=INDEX(订单明细!BQ:BQ,MATCH(R58&AC58,订单明细!A:A&订单明细!O:O,0))} -> Z2218-黑色-L | G58: =LEFT(F58,FIND("-",F58)-1) -> Z2218 | H58: {=_xlfn.IFS(C58=0,"",I58>0,AD58,AND(I58<0,I58>-30),0,I58<=-30,-1)} -> -1 | I58: =AF58 -> -229 | J58: =AI58+AJ58 -> 0 | K58: =IF(AZ58<=0,AZ58,AZ58/COUNTIFS(R:R,R58,AZ:AZ,">0")) -> 0 | L58: =AM58 -> 11.45 | M58: =AT58 -> 1.37 | O58: =SUM(I58:N58) -> -216.18 | R58: P770983921263440451 | S58: R6344045174935685 | T58: 2025-08-17 19:58:41 | U58: 2025-08-27 15:24:48 | V58: 2025-08-31 14:18:21 | W58: 退款 | X58: 店铺余额 | Y58: -216.18 | Z58: 【老板周】法式随性 夏季 · 【老板周】法式随性 夏季时髦叠门襟无袖设计感开叉马甲 黑色 L（120-135斤） | AA58: 女装/女士精品>马夹 | AB58: XHS-3FAGCOT6V0U8 | AC58: 689704bae53c1000157cfaa0 | AD58: 0 | AE58: -229 | AF58: -229 | AG58: 0 | AH58: 0 | AI58: 0 | AJ58: 0 | AK58: 0 | AL58: 0 | AM58: 11.45 | AN58: 0 | AO58: 0 | AP58: 0 | AQ58: 否 | AR58: 0 | AS58: 0 | AT58: 1.37 | AU58: 650d6e9f000000001603a6ac | AV58: 老板周. | AW58: 达人带货 | AZ58: 0 | BA58: 0 | BB58: 0 | BC58: 0 | BD58: 0
A59: =YEAR(V59) -> 2025 | B59: =MONTH(V59) -> 8 | C59: =R59 -> P770983921263440451 | D59: =COUNTIF(R:R,R59) -> 2 | E59: =COUNTIF($R$2:R59,R59) -> 2 | F59: {=INDEX(订单明细!BQ:BQ,MATCH(R59&AC59,订单明细!A:A&订单明细!O:O,0))} -> Z2218-黑色-L | G59: =LEFT(F59,FIND("-",F59)-1) -> Z2218 | H59: {=_xlfn.IFS(C59=0,"",I59>0,AD59,AND(I59<0,I59>-30),0,I59<=-30,-1)} -> 1 | I59: =AF59 -> 229 | J59: =AI59+AJ59 -> 0 | K59: =IF(AZ59<=0,AZ59,AZ59/COUNTIFS(R:R,R59,AZ:AZ,">0")) -> 0 | L59: =AM59 -> -11.45 | M59: =AT59 -> -1.37 | O59: =SUM(I59:N59) -> 216.18 | R59: P770983921263440451 | T59: 2025-08-17 19:58:41 | U59: 2025-08-24 20:35:14 | V59: 2025-08-31 14:18:21 | W59: 结算入账 | X59: 店铺余额 | Y59: 216.18 | Z59: 【老板周】法式随性 夏季 · 【老板周】法式随性 夏季时髦叠门襟无袖设计感开叉马甲 黑色 L（120-135斤） | AA59: 女装/女士精品>马夹 | AB59: XHS-3FAGCOT6V0U8 | AC59: 689704bae53c1000157cfaa0 | AD59: 1 | AE59: 229 | AF59: 229 | AH59: 0 | AI59: 0 | AJ59: 0 | AK59: 0.05 | AL59: 0 | AM59: -11.45 | AN59: 229 | AO59: 229 | AP59: 0 | AQ59: 否 | AR59: 0 | AS59: 0.006 | AT59: -1.37 | AU59: 650d6e9f000000001603a6ac | AV59: 老板周. | AW59: 达人带货 | AZ59: 0 | BA59: 0 | BB59: 0 | BC59: 0 | BD59: 0
A60: =YEAR(V60) -> 2025 | B60: =MONTH(V60) -> 8 | C60: =R60 -> P770795400699278151 | D60: =COUNTIF(R:R,R60) -> 2 | E60: =COUNTIF($R$2:R60,R60) -> 2 | F60: {=INDEX(订单明细!BQ:BQ,MATCH(R60&AC60,订单明细!A:A&订单明细!O:O,0))} -> Z2363-灰色-M | G60: =LEFT(F60,FIND("-",F60)-1) -> Z2363 | H60: {=_xlfn.IFS(C60=0,"",I60>0,AD60,AND(I60<0,I60>-30),0,I60<=-30,-1)} -> 1 | I60: =AF60 -> 359 | J60: =AI60+AJ60 -> 0 | K60: =IF(AZ60<=0,AZ60,AZ60/COUNTIFS(R:R,R60,AZ:AZ,">0")) -> 0 | L60: =AM60 -> -17.95 | M60: =AT60 -> -2.15 | O60: =SUM(I60:N60) -> 338.9 | R60: P770795400699278151 | T60: 2025-08-15 15:36:40 | U60: 2025-08-27 11:48:59 | V60: 2025-08-31 14:18:21 | W60: 结算入账 | X60: 店铺余额 | Y60: 338.9 | Z60: 【老板周】通勤质感 秋冬 · 【老板周】通勤质感 秋冬重磅新品半松紧腰垂感口袋西裤 灰色 M（100-120斤） | AA60: 女装/女士精品>裤子>西装裤/正装裤 | AB60: XHS-3JY78059ZB40 | AC60: 689dee2db292580015c1974b | AD60: 1 | AE60: 359 | AF60: 359 | AH60: 0 | AI60: 0 | AJ60: 0 | AK60: 0.05 | AL60: 0 | AM60: -17.95 | AN60: 359 | AO60: 359 | AP60: 0 | AQ60: 否 | AR60: 0 | AS60: 0.006 | AT60: -2.15 | AU60: 650d6e9f000000001603a6ac | AV60: 老板周. | AW60: 达人带货 | AZ60: 0 | BA60: 0 | BB60: 0 | BC60: 0 | BD60: 0
A61: =YEAR(V61) -> 2025 | B61: =MONTH(V61) -> 8 | C61: =R61 -> P770795108315278051 | D61: =COUNTIF(R:R,R61) -> 2 | E61: =COUNTIF($R$2:R61,R61) -> 2 | F61: {=INDEX(订单明细!BQ:BQ,MATCH(R61&AC61,订单明细!A:A&订单明细!O:O,0))} -> Z2363-黑色-M | G61: =LEFT(F61,FIND("-",F61)-1) -> Z2363 | H61: {=_xlfn.IFS(C61=0,"",I61>0,AD61,AND(I61<0,I61>-30),0,I61<=-30,-1)} -> 1 | I61: =AF61 -> 359 | J61: =AI61+AJ61 -> 0 | K61: =IF(AZ61<=0,AZ61,AZ61/COUNTIFS(R:R,R61,AZ:AZ,">0")) -> 0 | L61: =AM61 -> -17.95 | M61: =AT61 -> -2.15 | O61: =SUM(I61:N61) -> 338.9 | R61: P770795108315278051 | T61: 2025-08-15 15:31:48 | U61: 2025-08-27 11:49:06 | V61: 2025-08-31 14:18:21 | W61: 结算入账 | X61: 店铺余额 | Y61: 338.9 | Z61: 【老板周】通勤质感 秋冬 · 【老板周】通勤质感 秋冬重磅新品半松紧腰垂感口袋西裤 黑色 M（100-120斤） | AA61: 女装/女士精品>裤子>西装裤/正装裤 | AB61: XHS-3JY7804XHTDS | AC61: 689dee2db292580015c19745 | AD61: 1 | AE61: 359 | AF61: 359 | AH61: 0 | AI61: 0 | AJ61: 0 | AK61: 0.05 | AL61: 0 | AM61: -17.95 | AN61: 359 | AO61: 359 | AP61: 0 | AQ61: 否 | AR61: 0 | AS61: 0.006 | AT61: -2.15 | AU61: 650d6e9f000000001603a6ac | AV61: 老板周. | AW61: 达人带货 | AZ61: 0 | BA61: 0 | BB61: 0 | BC61: 0 | BD61: 0
A62: =YEAR(V62) -> 2025 | B62: =MONTH(V62) -> 8 | C62: =R62 -> P770796470293501151 | D62: =COUNTIF(R:R,R62) -> 2 | E62: =COUNTIF($R$2:R62,R62) -> 1 | F62: {=INDEX(订单明细!BQ:BQ,MATCH(R62&AC62,订单明细!A:A&订单明细!O:O,0))} -> Z1248-黑色-L | G62: =LEFT(F62,FIND("-",F62)-1) -> Z1248 | H62: {=_xlfn.IFS(C62=0,"",I62>0,AD62,AND(I62<0,I62>-30),0,I62<=-30,-1)} -> -1 | I62: =AF62 -> -199 | J62: =AI62+AJ62 -> 0 | K62: =IF(AZ62<=0,AZ62,AZ62/COUNTIFS(R:R,R62,AZ:AZ,">0")) -> 0 | L62: =AM62 -> 9.95 | M62: =AT62 -> 1.19 | O62: =SUM(I62:N62) -> -187.86 | R62: P770796470293501151 | S62: R9350115148146774 | T62: 2025-08-15 15:54:30 | U62: 2025-08-24 21:46:31 | V62: 2025-08-31 14:18:20 | W62: 退款 | X62: 店铺余额 | Y62: -187.86 | Z62: 【老板周】舒适经典 新款 · 【老板周】舒适经典 新款柔软细腻无缝一体半高领打底衫 黑色 L（120-135斤） | AA62: 女士内衣/男士内衣/家居服>打底衣 | AB62: XHS-2PMHE0F2J5DS | AC62: 689d92c8956aac0015f3663a | AD62: 0 | AE62: -199 | AF62: -199 | AG62: 0 | AH62: 0 | AI62: 0 | AJ62: 0 | AK62: 0 | AL62: 0 | AM62: 9.95 | AN62: 0 | AO62: 0 | AP62: 0 | AQ62: 否 | AR62: 0 | AS62: 0 | AT62: 1.19 | AU62: 650d6e9f000000001603a6ac | AV62: 老板周. | AW62: 达人带货 | AZ62: 0 | BA62: 0 | BB62: 0 | BC62: 0 | BD62: 0
A63: =YEAR(V63) -> 2025 | B63: =MONTH(V63) -> 8 | C63: =R63 -> P770796470293501151 | D63: =COUNTIF(R:R,R63) -> 2 | E63: =COUNTIF($R$2:R63,R63) -> 2 | F63: {=INDEX(订单明细!BQ:BQ,MATCH(R63&AC63,订单明细!A:A&订单明细!O:O,0))} -> Z1248-黑色-L | G63: =LEFT(F63,FIND("-",F63)-1) -> Z1248 | H63: {=_xlfn.IFS(C63=0,"",I63>0,AD63,AND(I63<0,I63>-30),0,I63<=-30,-1)} -> 1 | I63: =AF63 -> 199 | J63: =AI63+AJ63 -> 0 | K63: =IF(AZ63<=0,AZ63,AZ63/COUNTIFS(R:R,R63,AZ:AZ,">0")) -> 0 | L63: =AM63 -> -9.95 | M63: =AT63 -> -1.19 | O63: =SUM(I63:N63) -> 187.86 | R63: P770796470293501151 | T63: 2025-08-15 15:54:30 | U63: 2025-08-27 14:00:06 | V63: 2025-08-31 14:18:20 | W63: 结算入账 | X63: 店铺余额 | Y63: 187.86 | Z63: 【老板周】舒适经典 新款 · 【老板周】舒适经典 新款柔软细腻无缝一体半高领打底衫 黑色 L（120-135斤） | AA63: 女士内衣/男士内衣/家居服>打底衣 | AB63: XHS-2PMHE0F2J5DS | AC63: 689d92c8956aac0015f3663a | AD63: 1 | AE63: 199 | AF63: 199 | AH63: 0 | AI63: 0 | AJ63: 0 | AK63: 0.05 | AL63: 0 | AM63: -9.95 | AN63: 199 | AO63: 199 | AP63: 0 | AQ63: 否 | AR63: 0 | AS63: 0.006 | AT63: -1.19 | AU63: 650d6e9f000000001603a6ac | AV63: 老板周. | AW63: 达人带货 | AZ63: 0 | BA63: 0 | BB63: 0 | BC63: 0 | BD63: 0
A64: =YEAR(V64) -> 2025 | B64: =MONTH(V64) -> 8 | C64: =R64 -> P770797313602194761 | D64: =COUNTIF(R:R,R64) -> 2 | E64: =COUNTIF($R$2:R64,R64) -> 1 | F64: {=INDEX(订单明细!BQ:BQ,MATCH(R64&AC64,订单明细!A:A&订单明细!O:O,0))} -> Z1744-黑色-L | G64: =LEFT(F64,FIND("-",F64)-1) -> Z1744 | H64: {=_xlfn.IFS(C64=0,"",I64>0,AD64,AND(I64<0,I64>-30),0,I64<=-30,-1)} -> -1 | I64: =AF64 -> -289 | J64: =AI64+AJ64 -> 0 | K64: =IF(AZ64<=0,AZ64,AZ64/COUNTIFS(R:R,R64,AZ:AZ,">0")) -> 0 | L64: =AM64 -> 14.45 | M64: =AT64 -> 1.73 | O64: =SUM(I64:N64) -> -272.82 | R64: P770797313602194761 | S64: R0219476121665775 | T64: 2025-08-15 16:08:33 | U64: 2025-08-24 12:07:11 | V64: 2025-08-31 14:07:16 | W64: 退款 | X64: 店铺余额 | Y64: -272.82 | Z64: 【老板周】小众休闲 春季 · 【老板周】小众休闲 春季单口袋翻领设计感廓形百搭衬衫 黑色 L（120-135斤） | AA64: 女装/女士精品>衬衫 | AB64: XHS-33LDRKJ82328 | AC64: 689d98fa3b9d470015b74588 | AD64: 0 | AE64: -289 | AF64: -289 | AG64: 0 | AH64: 0 | AI64: 0 | AJ64: 0 | AK64: 0 | AL64: 0 | AM64: 14.45 | AN64: 0 | AO64: 0 | AP64: 0 | AQ64: 否 | AR64: 0 | AS64: 0 | AT64: 1.73 | AU64: 650d6e9f000000001603a6ac | AV64: 老板周. | AW64: 达人带货 | AZ64: 0 | BA64: 0 | BB64: 0 | BC64: 0 | BD64: 0
A65: =YEAR(V65) -> 2025 | B65: =MONTH(V65) -> 8 | C65: =R65 -> P770797313602194761 | D65: =COUNTIF(R:R,R65) -> 2 | E65: =COUNTIF($R$2:R65,R65) -> 2 | F65: {=INDEX(订单明细!BQ:BQ,MATCH(R65&AC65,订单明细!A:A&订单明细!O:O,0))} -> Z1744-黑色-L | G65: =LEFT(F65,FIND("-",F65)-1) -> Z1744 | H65: {=_xlfn.IFS(C65=0,"",I65>0,AD65,AND(I65<0,I65>-30),0,I65<=-30,-1)} -> 1 | I65: =AF65 -> 289 | J65: =AI65+AJ65 -> 0 | K65: =IF(AZ65<=0,AZ65,AZ65/COUNTIFS(R:R,R65,AZ:AZ,">0")) -> 0 | L65: =AM65 -> -14.45 | M65: =AT65 -> -1.73 | O65: =SUM(I65:N65) -> 272.82 | R65: P770797313602194761 | T65: 2025-08-15 16:08:33 | U65: 2025-08-27 13:56:03 | V65: 2025-08-31 14:07:16 | W65: 结算入账 | X65: 店铺余额 | Y65: 272.82 | Z65: 【老板周】小众休闲 春季 · 【老板周】小众休闲 春季单口袋翻领设计感廓形百搭衬衫 黑色 L（120-135斤） | AA65: 女装/女士精品>衬衫 | AB65: XHS-33LDRKJ82328 | AC65: 689d98fa3b9d470015b74588 | AD65: 1 | AE65: 289 | AF65: 289 | AH65: 0 | AI65: 0 | AJ65: 0 | AK65: 0.05 | AL65: 0 | AM65: -14.45 | AN65: 289 | AO65: 289 | AP65: 0 | AQ65: 否 | AR65: 0 | AS65: 0.006 | AT65: -1.73 | AU65: 650d6e9f000000001603a6ac | AV65: 老板周. | AW65: 达人带货 | AZ65: 0 | BA65: 0 | BB65: 0 | BC65: 0 | BD65: 0
A66: =YEAR(V66) -> 2025 | B66: =MONTH(V66) -> 8 | C66: =R66 -> P770990197404134041 | D66: =COUNTIF(R:R,R66) -> 2 | E66: =COUNTIF($R$2:R66,R66) -> 1 | F66: {=INDEX(订单明细!BQ:BQ,MATCH(R66&AC66,订单明细!A:A&订单明细!O:O,0))} -> Z2308-黑色-M | G66: =LEFT(F66,FIND("-",F66)-1) -> Z2308 | H66: {=_xlfn.IFS(C66=0,"",I66>0,AD66,AND(I66<0,I66>-30),0,I66<=-30,-1)} -> -1 | I66: =AF66 -> -339 | J66: =AI66+AJ66 -> 0 | K66: =IF(AZ66<=0,AZ66,AZ66/COUNTIFS(R:R,R66,AZ:AZ,">0")) -> 0 | L66: =AM66 -> 16.95 | M66: =AT66 -> 2.03 | O66: =SUM(I66:N66) -> -320.02 | R66: P770990197404134041 | S66: R0413404195862919 | T66: 2025-08-17 21:43:17 | U66: 2025-08-25 16:01:04 | V66: 2025-08-31 13:58:03 | W66: 退款 | X66: 店铺余额 | Y66: -320.02 | Z66: 【老板周】夏季新款 小众 · 【老板周】夏季新款 小众轻盈空气感重工泡泡绉小飞袖上衣 黑色 M（100-120斤） | AA66: 女装/女士精品>T恤 | AB66: XHS-3HO32A90HCZK | AC66: 68949ffbc34eef001610ef46 | AD66: 0 | AE66: -339 | AF66: -339 | AG66: 0 | AH66: 0 | AI66: 0 | AJ66: 0 | AK66: 0 | AL66: 0 | AM66: 16.95 | AN66: 0 | AO66: 0 | AP66: 0 | AQ66: 否 | AR66: 0 | AS66: 0 | AT66: 2.03 | AU66: 650d6e9f000000001603a6ac | AV66: 老板周. | AW66: 达人带货 | AZ66: 0 | BA66: 0 | BB66: 0 | BC66: 0 | BD66: 0
A67: =YEAR(V67) -> 2025 | B67: =MONTH(V67) -> 8 | C67: =R67 -> P770798353781374661 | D67: =COUNTIF(R:R,R67) -> 2 | E67: =COUNTIF($R$2:R67,R67) -> 1 | F67: {=INDEX(订单明细!BQ:BQ,MATCH(R67&AC67,订单明细!A:A&订单明细!O:O,0))} -> Z2378-灰色-S | G67: =LEFT(F67,FIND("-",F67)-1) -> Z2378 | H67: {=_xlfn.IFS(C67=0,"",I67>0,AD67,AND(I67<0,I67>-30),0,I67<=-30,-1)} -> -1 | I67: =AF67 -> -179 | J67: =AI67+AJ67 -> 0 | K67: =IF(AZ67<=0,AZ67,AZ67/COUNTIFS(R:R,R67,AZ:AZ,">0")) -> 0 | L67: =AM67 -> 8.95 | M67: =AT67 -> 1.07 | O67: =SUM(I67:N67) -> -168.98 | R67: P770798353781374661 | S67: R8137466135191193 | T67: 2025-08-15 16:25:53 | U67: 2025-08-25 16:14:30 | V67: 2025-08-31 13:58:03 | W67: 退款 | X67: 店铺余额 | Y67: -168.98 | Z67: 【老板周】小众日系 秋冬 · 【老板周】小众日系 秋冬叠穿时髦下摆不规则宽松马甲 灰色 S（80-100斤） | AA67: 女装/女士精品>马夹 | AB67: XHS-3JY8RM3UZL6O | AC67: 689dee45c34eef00157e1207 | AD67: 0 | AE67: -179 | AF67: -179 | AG67: 0 | AH67: 0 | AI67: 0 | AJ67: 0 | AK67: 0 | AL67: 0 | AM67: 8.95 | AN67: 0 | AO67: 0 | AP67: 0 | AQ67: 否 | AR67: 0 | AS67: 0 | AT67: 1.07 | AU67: 650d6e9f000000001603a6ac | AV67: 老板周. | AW67: 达人带货 | AZ67: 0 | BA67: 0 | BB67: 0 | BC67: 0 | BD67: 0
A68: =YEAR(V68) -> 2025 | B68: =MONTH(V68) -> 8 | C68: =R68 -> P770990197404134041 | D68: =COUNTIF(R:R,R68) -> 2 | E68: =COUNTIF($R$2:R68,R68) -> 2 | F68: {=INDEX(订单明细!BQ:BQ,MATCH(R68&AC68,订单明细!A:A&订单明细!O:O,0))} -> Z2308-黑色-M | G68: =LEFT(F68,FIND("-",F68)-1) -> Z2308 | H68: {=_xlfn.IFS(C68=0,"",I68>0,AD68,AND(I68<0,I68>-30),0,I68<=-30,-1)} -> 1 | I68: =AF68 -> 339 | J68: =AI68+AJ68 -> 0 | K68: =IF(AZ68<=0,AZ68,AZ68/COUNTIFS(R:R,R68,AZ:AZ,">0")) -> 0 | L68: =AM68 -> -16.95 | M68: =AT68 -> -2.03 | O68: =SUM(I68:N68) -> 320.02 | R68: P770990197404134041 | T68: 2025-08-17 21:43:17 | U68: 2025-08-27 13:48:11 | V68: 2025-08-31 13:58:03 | W68: 结算入账 | X68: 店铺余额 | Y68: 320.02 | Z68: 【老板周】夏季新款 小众 · 【老板周】夏季新款 小众轻盈空气感重工泡泡绉小飞袖上衣 黑色 M（100-120斤） | AA68: 女装/女士精品>T恤 | AB68: XHS-3HO32A90HCZK | AC68: 68949ffbc34eef001610ef46 | AD68: 1 | AE68: 339 | AF68: 339 | AH68: 0 | AI68: 0 | AJ68: 0 | AK68: 0.05 | AL68: 0 | AM68: -16.95 | AN68: 339 | AO68: 339 | AP68: 0 | AQ68: 否 | AR68: 0 | AS68: 0.006 | AT68: -2.03 | AU68: 650d6e9f000000001603a6ac | AV68: 老板周. | AW68: 达人带货 | AZ68: 0 | BA68: 0 | BB68: 0 | BC68: 0 | BD68: 0
A69: =YEAR(V69) -> 2025 | B69: =MONTH(V69) -> 8 | C69: =R69 -> P770798353781374661 | D69: =COUNTIF(R:R,R69) -> 2 | E69: =COUNTIF($R$2:R69,R69) -> 2 | F69: {=INDEX(订单明细!BQ:BQ,MATCH(R69&AC69,订单明细!A:A&订单明细!O:O,0))} -> Z2378-灰色-S | G69: =LEFT(F69,FIND("-",F69)-1) -> Z2378 | H69: {=_xlfn.IFS(C69=0,"",I69>0,AD69,AND(I69<0,I69>-30),0,I69<=-30,-1)} -> 1 | I69: =AF69 -> 179 | J69: =AI69+AJ69 -> 0 | K69: =IF(AZ69<=0,AZ69,AZ69/COUNTIFS(R:R,R69,AZ:AZ,">0")) -> 0 | L69: =AM69 -> -8.95 | M69: =AT69 -> -1.07 | O69: =SUM(I69:N69) -> 168.98 | R69: P770798353781374661 | T69: 2025-08-15 16:25:53 | U69: 2025-08-27 13:41:04 | V69: 2025-08-31 13:58:03 | W69: 结算入账 | X69: 店铺余额 | Y69: 168.98 | Z69: 【老板周】小众日系 秋冬 · 【老板周】小众日系 秋冬叠穿时髦下摆不规则宽松马甲 灰色 S（80-100斤） | AA69: 女装/女士精品>马夹 | AB69: XHS-3JY8RM3UZL6O | AC69: 689dee45c34eef00157e1207 | AD69: 1 | AE69: 179 | AF69: 179 | AH69: 0 | AI69: 0 | AJ69: 0 | AK69: 0.05 | AL69: 0 | AM69: -8.95 | AN69: 179 | AO69: 179 | AP69: 0 | AQ69: 否 | AR69: 0 | AS69: 0.006 | AT69: -1.07 | AU69: 650d6e9f000000001603a6ac | AV69: 老板周. | AW69: 达人带货 | AZ69: 0 | BA69: 0 | BB69: 0 | BC69: 0 | BD69: 0
A70: =YEAR(V70) -> 2025 | B70: =MONTH(V70) -> 8 | C70: =R70 -> P770809432946213601 | D70: =COUNTIF(R:R,R70) -> 2 | E70: =COUNTIF($R$2:R70,R70) -> 1 | F70: {=INDEX(订单明细!BQ:BQ,MATCH(R70&AC70,订单明细!A:A&订单明细!O:O,0))} -> Z2365-灰色-M | G70: =LEFT(F70,FIND("-",F70)-1) -> Z2365 | H70: {=_xlfn.IFS(C70=0,"",I70>0,AD70,AND(I70<0,I70>-30),0,I70<=-30,-1)} -> -1 | I70: =AF70 -> -219 | J70: =AI70+AJ70 -> 0 | K70: =IF(AZ70<=0,AZ70,AZ70/COUNTIFS(R:R,R70,AZ:AZ,">0")) -> 0 | L70: =AM70 -> 10.95 | M70: =AT70 -> 1.31 | O70: =SUM(I70:N70) -> -206.74 | R70: P770809432946213601 | S70: R4621360104909250 | T70: 2025-08-15 19:30:32 | U70: 2025-08-25 16:10:49 | V70: 2025-08-31 13:27:42 | W70: 退款 | X70: 店铺余额 | Y70: -206.74 | Z70: 【老板周】极简主义 秋冬 · 【老板周】极简主义 秋冬新款复古卷边前短后长针织上衣 灰色 M（100-135斤） | AA70: 女装/女士精品>毛针织衫 | AB70: XHS-3JY9LAGFRNR4 | AC70: 689dee5baa1e7b00156ae7c2 | AD70: 0 | AE70: -219 | AF70: -219 | AG70: 0 | AH70: 0 | AI70: 0 | AJ70: 0 | AK70: 0 | AL70: 0 | AM70: 10.95 | AN70: 0 | AO70: 0 | AP70: 0 | AQ70: 否 | AR70: 0 | AS70: 0 | AT70: 1.31 | AU70: 650d6e9f000000001603a6ac | AV70: 老板周. | AW70: 达人带货 | AZ70: 0 | BA70: 0 | BB70: 0 | BC70: 0 | BD70: 0
A71: =YEAR(V71) -> 2025 | B71: =MONTH(V71) -> 8 | C71: =R71 -> P770809432946213601 | D71: =COUNTIF(R:R,R71) -> 2 | E71: =COUNTIF($R$2:R71,R71) -> 2 | F71: {=INDEX(订单明细!BQ:BQ,MATCH(R71&AC71,订单明细!A:A&订单明细!O:O,0))} -> Z2365-灰色-M | G71: =LEFT(F71,FIND("-",F71)-1) -> Z2365 | H71: {=_xlfn.IFS(C71=0,"",I71>0,AD71,AND(I71<0,I71>-30),0,I71<=-30,-1)} -> 1 | I71: =AF71 -> 219 | J71: =AI71+AJ71 -> 0 | K71: =IF(AZ71<=0,AZ71,AZ71/COUNTIFS(R:R,R71,AZ:AZ,">0")) -> 0 | L71: =AM71 -> -10.95 | M71: =AT71 -> -1.31 | O71: =SUM(I71:N71) -> 206.74 | R71: P770809432946213601 | T71: 2025-08-15 19:30:32 | U71: 2025-08-27 13:17:15 | V71: 2025-08-31 13:27:42 | W71: 结算入账 | X71: 店铺余额 | Y71: 206.74 | Z71: 【老板周】极简主义 秋冬 · 【老板周】极简主义 秋冬新款复古卷边前短后长针织上衣 灰色 M（100-135斤） | AA71: 女装/女士精品>毛针织衫 | AB71: XHS-3JY9LAGFRNR4 | AC71: 689dee5baa1e7b00156ae7c2 | AD71: 1 | AE71: 219 | AF71: 219 | AH71: 0 | AI71: 0 | AJ71: 0 | AK71: 0.05 | AL71: 0 | AM71: -10.95 | AN71: 219 | AO71: 219 | AP71: 0 | AQ71: 否 | AR71: 0 | AS71: 0.006 | AT71: -1.31 | AU71: 650d6e9f000000001603a6ac | AV71: 老板周. | AW71: 达人带货 | AZ71: 0 | BA71: 0 | BB71: 0 | BC71: 0 | BD71: 0
A72: =YEAR(V72) -> 2025 | B72: =MONTH(V72) -> 8 | C72: =R72 -> P770794260083193631 | D72: =COUNTIF(R:R,R72) -> 1 | E72: =COUNTIF($R$2:R72,R72) -> 1 | F72: {=INDEX(订单明细!BQ:BQ,MATCH(R72&AC72,订单明细!A:A&订单明细!O:O,0))} -> Z1248-黑色-L | G72: =LEFT(F72,FIND("-",F72)-1) -> Z1248 | H72: {=_xlfn.IFS(C72=0,"",I72>0,AD72,AND(I72<0,I72>-30),0,I72<=-30,-1)} -> 1 | I72: =AF72 -> 199 | J72: =AI72+AJ72 -> 0 | K72: =IF(AZ72<=0,AZ72,AZ72/COUNTIFS(R:R,R72,AZ:AZ,">0")) -> 0 | L72: =AM72 -> -9.95 | M72: =AT72 -> -1.19 | O72: =SUM(I72:N72) -> 187.86 | R72: P770794260083193631 | T72: 2025-08-15 15:17:40 | U72: 2025-08-27 12:31:45 | V72: 2025-08-31 13:00:49 | W72: 结算入账 | X72: 店铺余额 | Y72: 187.86 | Z72: 【老板周】舒适经典 新款 · 【老板周】舒适经典 新款柔软细腻无缝一体半高领打底衫 黑色 L（120-135斤） | AA72: 女士内衣/男士内衣/家居服>打底衣 | AB72: XHS-2PMHE0F2J5DS | AC72: 689d92c8956aac0015f3663a | AD72: 1 | AE72: 199 | AF72: 199 | AH72: 0 | AI72: 0 | AJ72: 0 | AK72: 0.05 | AL72: 0 | AM72: -9.95 | AN72: 199 | AO72: 199 | AP72: 0 | AQ72: 否 | AR72: 0 | AS72: 0.006 | AT72: -1.19 | AU72: 650d6e9f000000001603a6ac | AV72: 老板周. | AW72: 达人带货 | AZ72: 0 | BA72: 0 | BB72: 0 | BC72: 0 | BD72: 0
A73: =YEAR(V73) -> 2025 | B73: =MONTH(V73) -> 8 | C73: =R73 -> P770625887719453891 | D73: =COUNTIF(R:R,R73) -> 2 | E73: =COUNTIF($R$2:R73,R73) -> 1 | F73: {=INDEX(订单明细!BQ:BQ,MATCH(R73&AC73,订单明细!A:A&订单明细!O:O,0))} -> Z2284-牛仔蓝色-L | G73: =LEFT(F73,FIND("-",F73)-1) -> Z2284 | H73: {=_xlfn.IFS(C73=0,"",I73>0,AD73,AND(I73<0,I73>-30),0,I73<=-30,-1)} -> -1 | I73: =AF73 -> -399 | J73: =AI73+AJ73 -> 0 | K73: =IF(AZ73<=0,AZ73,AZ73/COUNTIFS(R:R,R73,AZ:AZ,">0")) -> 0 | L73: =AM73 -> 19.95 | M73: =AT73 -> 2.39 | O73: =SUM(I73:N73) -> -376.66 | R73: P770625887719453891 | S73: R1945389187966553 | T73: 2025-08-13 16:31:27 | U73: 2025-08-30 16:28:36 | V73: 2025-08-31 12:15:26 | W73: 退款 | X73: 店铺余额 | Y73: -376.66 | Z73: 【老板周】休闲经典 秋冬 · 【老板周】休闲经典 秋冬新品时髦百搭牛仔破洞背带裤 牛仔蓝色 L（120-135斤） | AA73: 女装/女士精品>连体衣/裤 | AB73: XHS-3JR16LNXWRGG | AC73: 689b434256a70c0015776467 | AD73: 0 | AE73: -399 | AF73: -399 | AG73: 0 | AH73: 0 | AI73: 0 | AJ73: 0 | AK73: 0 | AL73: 0 | AM73: 19.95 | AN73: 0 | AO73: 0 | AP73: 0 | AQ73: 否 | AR73: 0 | AS73: 0 | AT73: 2.39 | AU73: 650d6e9f000000001603a6ac | AV73: 老板周. | AW73: 达人带货 | AZ73: 0 | BA73: 0 | BB73: 0 | BC73: 0 | BD73: 0
A74: =YEAR(V74) -> 2025 | B74: =MONTH(V74) -> 8 | C74: =R74 -> P770643835711413521 | D74: =COUNTIF(R:R,R74) -> 6 | E74: =COUNTIF($R$2:R74,R74) -> 1 | F74: {=INDEX(订单明细!BQ:BQ,MATCH(R74&AC74,订单明细!A:A&订单明细!O:O,0))} -> Z1645-黑色-S | G74: =LEFT(F74,FIND("-",F74)-1) -> Z1645 | H74: {=_xlfn.IFS(C74=0,"",I74>0,AD74,AND(I74<0,I74>-30),0,I74<=-30,-1)} -> -1 | I74: =AF74 -> -189 | J74: =AI74+AJ74 -> 0 | K74: =IF(AZ74<=0,AZ74,AZ74/COUNTIFS(R:R,R74,AZ:AZ,">0")) -> 0 | L74: =AM74 -> 9.45 | M74: =AT74 -> 0 | O74: =SUM(I74:N74) -> -179.55 | R74: P770643835711413521 | S74: R1141352150688208 | T74: 2025-08-13 21:30:35 | U74: 2025-08-25 10:31:17 | V74: 2025-08-31 12:15:26 | W74: 退款 | X74: 店铺余额 | Y74: -179.55 | Z74: 【老板周】舒适休闲 极简 · 【老板周】舒适休闲 极简短版腰头抽绳设计宽松半身裙 黑色 S（80-100斤） | AA74: 女装/女士精品>半身裙 | AB74: XHS-2Z4TJTXW55OG | AC74: 6896fe67c165480015b3eb00 | AD74: 0 | AE74: -189 | AF74: -189 | AG74: 0 | AH74: 0 | AI74: 0 | AJ74: 0 | AK74: 0 | AL74: 0 | AM74: 9.45 | AN74: 0 | AO74: 0 | AP74: 0 | AQ74: 否 | AR74: 0 | AS74: 0 | AT74: 0 | AZ74: 0 | BA74: 0 | BB74: 0 | BC74: 0 | BD74: 0
A75: =YEAR(V75) -> 2025 | B75: =MONTH(V75) -> 8 | C75: =R75 -> P770643835711413521 | D75: =COUNTIF(R:R,R75) -> 6 | E75: =COUNTIF($R$2:R75,R75) -> 2 | F75: {=INDEX(订单明细!BQ:BQ,MATCH(R75&AC75,订单明细!A:A&订单明细!O:O,0))} -> Z1576-黑色-S | G75: =LEFT(F75,FIND("-",F75)-1) -> Z1576 | H75: {=_xlfn.IFS(C75=0,"",I75>0,AD75,AND(I75<0,I75>-30),0,I75<=-30,-1)} -> -1 | I75: =AF75 -> -199 | J75: =AI75+AJ75 -> 0 | K75: =IF(AZ75<=0,AZ75,AZ75/COUNTIFS(R:R,R75,AZ:AZ,">0")) -> 0 | L75: =AM75 -> 9.95 | M75: =AT75 -> 1.19 | O75: =SUM(I75:N75) -> -187.86 | R75: P770643835711413521 | S75: R1141352150668192 | T75: 2025-08-13 21:30:35 | U75: 2025-08-25 10:32:17 | V75: 2025-08-31 12:15:26 | W75: 退款 | X75: 店铺余额 | Y75: -187.86 | Z75: 【老板周】时髦撞色 春季 · 【老板周】时髦撞色 春季新款假两件显瘦长袖打底T恤上衣 黑色 S（80-100斤） | AA75: 女装/女士精品>T恤 | AB75: XHS-2Z0D3IBQCYKG | AC75: 6896fe48057f570015d29242 | AD75: 0 | AE75: -199 | AF75: -199 | AG75: 0 | AH75: 0 | AI75: 0 | AJ75: 0 | AK75: 0 | AL75: 0 | AM75: 9.95 | AN75: 0 | AO75: 0 | AP75: 0 | AQ75: 否 | AR75: 0 | AS75: 0 | AT75: 1.19 | AU75: 650d6e9f000000001603a6ac | AV75: 老板周. | AW75: 达人带货 | AZ75: 0 | BA75: 0 | BB75: 0 | BC75: 0 | BD75: 0
A76: =YEAR(V76) -> 2025 | B76: =MONTH(V76) -> 8 | C76: =R76 -> P770643835711413521 | D76: =COUNTIF(R:R,R76) -> 6 | E76: =COUNTIF($R$2:R76,R76) -> 3 | F76: {=INDEX(订单明细!BQ:BQ,MATCH(R76&AC76,订单明细!A:A&订单明细!O:O,0))} -> Z1640-黑色-S | G76: =LEFT(F76,FIND("-",F76)-1) -> Z1640 | H76: {=_xlfn.IFS(C76=0,"",I76>0,AD76,AND(I76<0,I76>-30),0,I76<=-30,-1)} -> -1 | I76: =AF76 -> -289 | J76: =AI76+AJ76 -> 0 | K76: =IF(AZ76<=0,AZ76,AZ76/COUNTIFS(R:R,R76,AZ:AZ,">0")) -> 0 | L76: =AM76 -> 14.45 | M76: =AT76 -> 1.73 | O76: =SUM(I76:N76) -> -272.82 | R76: P770643835711413521 | S76: R1141352150628113 | T76: 2025-08-13 21:30:35 | U76: 2025-08-24 23:50:33 | V76: 2025-08-31 12:15:26 | W76: 退款 | X76: 店铺余额 | Y76: -272.82 | Z76: 【老板周】日系极简 春季 · 【老板周】日系极简 春季新品圆领简约设计感无袖马甲 黑色 S（80-100斤） | AA76: 女装/女士精品>马夹 | AB76: XHS-31AJPPHCTL34 | AC76: 6896fe5c3b9d47001590a856 | AD76: 0 | AE76: -289 | AF76: -289 | AG76: 0 | AH76: 0 | AI76: 0 | AJ76: 0 | AK76: 0 | AL76: 0 | AM76: 14.45 | AN76: 0 | AO76: 0 | AP76: 0 | AQ76: 否 | AR76: 0 | AS76: 0 | AT76: 1.73 | AU76: 650d6e9f000000001603a6ac | AV76: 老板周. | AW76: 达人带货 | AZ76: 0 | BA76: 0 | BB76: 0 | BC76: 0 | BD76: 0
A77: =YEAR(V77) -> 2025 | B77: =MONTH(V77) -> 8 | C77: =R77 -> P770643835711413521 | D77: =COUNTIF(R:R,R77) -> 6 | E77: =COUNTIF($R$2:R77,R77) -> 4 | F77: {=INDEX(订单明细!BQ:BQ,MATCH(R77&AC77,订单明细!A:A&订单明细!O:O,0))} -> Z1576-黑色-S | G77: =LEFT(F77,FIND("-",F77)-1) -> Z1576 | H77: {=_xlfn.IFS(C77=0,"",I77>0,AD77,AND(I77<0,I77>-30),0,I77<=-30,-1)} -> 1 | I77: =AF77 -> 199 | J77: =AI77+AJ77 -> 0 | K77: =IF(AZ77<=0,AZ77,AZ77/COUNTIFS(R:R,R77,AZ:AZ,">0")) -> 0 | L77: =AM77 -> -9.95 | M77: =AT77 -> -1.19 | O77: =SUM(I77:N77) -> 187.86 | R77: P770643835711413521 | T77: 2025-08-13 21:30:35 | U77: 2025-08-27 11:52:32 | V77: 2025-08-31 12:15:26 | W77: 结算入账 | X77: 店铺余额 | Y77: 640.23 | Z77: 【老板周】时髦撞色 春季 · 【老板周】时髦撞色 春季新款假两件显瘦长袖打底T恤上衣 黑色 S（80-100斤） | AA77: 女装/女士精品>T恤 | AB77: XHS-2Z0D3IBQCYKG | AC77: 6896fe48057f570015d29242 | AD77: 1 | AE77: 199 | AF77: 199 | AH77: 0 | AI77: 0 | AJ77: 0 | AK77: 0.05 | AL77: 0 | AM77: -9.95 | AN77: 199 | AO77: 199 | AP77: 0 | AQ77: 否 | AR77: 0 | AS77: 0.006 | AT77: -1.19 | AU77: 650d6e9f000000001603a6ac | AV77: 老板周. | AW77: 达人带货 | AZ77: 0 | BA77: 0 | BB77: 0 | BC77: 0 | BD77: 0
A78: =YEAR(V78) -> 2025 | B78: =MONTH(V78) -> 8 | C78: =R78 -> P770643835711413521 | D78: =COUNTIF(R:R,R78) -> 6 | E78: =COUNTIF($R$2:R78,R78) -> 5 | F78: {=INDEX(订单明细!BQ:BQ,MATCH(R78&AC78,订单明细!A:A&订单明细!O:O,0))} -> Z1640-黑色-S | G78: =LEFT(F78,FIND("-",F78)-1) -> Z1640 | H78: {=_xlfn.IFS(C78=0,"",I78>0,AD78,AND(I78<0,I78>-30),0,I78<=-30,-1)} -> 1 | I78: =AF78 -> 289 | J78: =AI78+AJ78 -> 0 | K78: =IF(AZ78<=0,AZ78,AZ78/COUNTIFS(R:R,R78,AZ:AZ,">0")) -> 0 | L78: =AM78 -> -14.45 | M78: =AT78 -> -1.73 | O78: =SUM(I78:N78) -> 272.82 | R78: P770643835711413521 | T78: 2025-08-13 21:30:35 | U78: 2025-08-27 11:52:32 | V78: 2025-08-31 12:15:26 | W78: 结算入账 | X78: 店铺余额 | Y78: 640.23 | Z78: 【老板周】日系极简 春季 · 【老板周】日系极简 春季新品圆领简约设计感无袖马甲 黑色 S（80-100斤） | AA78: 女装/女士精品>马夹 | AB78: XHS-31AJPPHCTL34 | AC78: 6896fe5c3b9d47001590a856 | AD78: 1 | AE78: 289 | AF78: 289 | AH78: 0 | AI78: 0 | AJ78: 0 | AK78: 0.05 | AL78: 0 | AM78: -14.45 | AN78: 289 | AO78: 289 | AP78: 0 | AQ78: 否 | AR78: 0 | AS78: 0.006 | AT78: -1.73 | AU78: 650d6e9f000000001603a6ac | AV78: 老板周. | AW78: 达人带货 | AZ78: 0 | BA78: 0 | BB78: 0 | BC78: 0 | BD78: 0
A79: =YEAR(V79) -> 2025 | B79: =MONTH(V79) -> 8 | C79: =R79 -> P770643835711413521 | D79: =COUNTIF(R:R,R79) -> 6 | E79: =COUNTIF($R$2:R79,R79) -> 6 | F79: {=INDEX(订单明细!BQ:BQ,MATCH(R79&AC79,订单明细!A:A&订单明细!O:O,0))} -> Z1645-黑色-S | G79: =LEFT(F79,FIND("-",F79)-1) -> Z1645 | H79: {=_xlfn.IFS(C79=0,"",I79>0,AD79,AND(I79<0,I79>-30),0,I79<=-30,-1)} -> 1 | I79: =AF79 -> 189 | J79: =AI79+AJ79 -> 0 | K79: =IF(AZ79<=0,AZ79,AZ79/COUNTIFS(R:R,R79,AZ:AZ,">0")) -> 0 | L79: =AM79 -> -9.45 | M79: =AT79 -> 0 | O79: =SUM(I79:N79) -> 179.55 | R79: P770643835711413521 | T79: 2025-08-13 21:30:35 | U79: 2025-08-27 11:52:32 | V79: 2025-08-31 12:15:26 | W79: 结算入账 | X79: 店铺余额 | Y79: 640.23 | Z79: 【老板周】舒适休闲 极简 · 【老板周】舒适休闲 极简短版腰头抽绳设计宽松半身裙 黑色 S（80-100斤） | AA79: 女装/女士精品>半身裙 | AB79: XHS-2Z4TJTXW55OG | AC79: 6896fe67c165480015b3eb00 | AD79: 1 | AE79: 189 | AF79: 189 | AH79: 0 | AI79: 0 | AJ79: 0 | AK79: 0.05 | AL79: 0 | AM79: -9.45 | AN79: 189 | AO79: 189 | AP79: 0 | AQ79: 否 | AR79: 0 | AS79: 0 | AT79: 0 | AZ79: 0 | BA79: 0 | BB79: 0 | BC79: 0 | BD79: 0
A80: =YEAR(V80) -> 2025 | B80: =MONTH(V80) -> 8 | C80: =R80 -> P770625887719453891 | D80: =COUNTIF(R:R,R80) -> 2 | E80: =COUNTIF($R$2:R80,R80) -> 2 | F80: {=INDEX(订单明细!BQ:BQ,MATCH(R80&AC80,订单明细!A:A&订单明细!O:O,0))} -> Z2284-牛仔蓝色-L | G80: =LEFT(F80,FIND("-",F80)-1) -> Z2284 | H80: {=_xlfn.IFS(C80=0,"",I80>0,AD80,AND(I80<0,I80>-30),0,I80<=-30,-1)} -> 1 | I80: =AF80 -> 399 | J80: =AI80+AJ80 -> 0 | K80: =IF(AZ80<=0,AZ80,AZ80/COUNTIFS(R:R,R80,AZ:AZ,">0")) -> 0 | L80: =AM80 -> -19.95 | M80: =AT80 -> -2.39 | O80: =SUM(I80:N80) -> 376.66 | R80: P770625887719453891 | T80: 2025-08-13 16:31:27 | U80: 2025-08-24 20:43:59 | V80: 2025-08-31 12:15:26 | W80: 结算入账 | X80: 店铺余额 | Y80: 376.66 | Z80: 【老板周】休闲经典 秋冬 · 【老板周】休闲经典 秋冬新品时髦百搭牛仔破洞背带裤 牛仔蓝色 L（120-135斤） | AA80: 女装/女士精品>连体衣/裤 | AB80: XHS-3JR16LNXWRGG | AC80: 689b434256a70c0015776467 | AD80: 1 | AE80: 399 | AF80: 399 | AH80: 0 | AI80: 0 | AJ80: 0 | AK80: 0.05 | AL80: 0 | AM80: -19.95 | AN80: 399 | AO80: 399 | AP80: 0 | AQ80: 否 | AR80: 0 | AS80: 0.006 | AT80: -2.39 | AU80: 650d6e9f000000001603a6ac | AV80: 老板周. | AW80: 达人带货 | AZ80: 0 | BA80: 0 | BB80: 0 | BC80: 0 | BD80: 0
A81: =YEAR(V81) -> 2025 | B81: =MONTH(V81) -> 8 | C81: =R81 -> P770986869946371481 | D81: =COUNTIF(R:R,R81) -> 4 | E81: =COUNTIF($R$2:R81,R81) -> 1 | F81: {=INDEX(订单明细!BQ:BQ,MATCH(R81&AC81,订单明细!A:A&订单明细!O:O,0))} -> Z2218-黑色-M | G81: =LEFT(F81,FIND("-",F81)-1) -> Z2218 | H81: {=_xlfn.IFS(C81=0,"",I81>0,AD81,AND(I81<0,I81>-30),0,I81<=-30,-1)} -> -1 | I81: =AF81 -> -229 | J81: =AI81+AJ81 -> 0 | K81: =IF(AZ81<=0,AZ81,AZ81/COUNTIFS(R:R,R81,AZ:AZ,">0")) -> 0 | L81: =AM81 -> 11.45 | M81: =AT81 -> 1.37 | O81: =SUM(I81:N81) -> -216.18 | R81: P770986869946371481 | S81: R4637148133227398 | T81: 2025-08-17 20:47:49 | U81: 2025-08-25 12:32:23 | V81: 2025-08-31 11:59:48 | W81: 退款 | X81: 店铺余额 | Y81: -216.18 | Z81: 【老板周】法式随性 夏季 · 【老板周】法式随性 夏季时髦叠门襟无袖设计感开叉马甲 黑色 M（100-120斤） | AA81: 女装/女士精品>马夹 | AB81: XHS-3FAGCOT1V85C | AC81: 689704bae53c1000157cfa9e | AD81: 0 | AE81: -229 | AF81: -229 | AG81: 0 | AH81: 0 | AI81: 0 | AJ81: 0 | AK81: 0 | AL81: 0 | AM81: 11.45 | AN81: 0 | AO81: 0 | AP81: 0 | AQ81: 否 | AR81: 0 | AS81: 0 | AT81: 1.37 | AU81: 650d6e9f000000001603a6ac | AV81: 老板周. | AW81: 达人带货 | AZ81: 0 | BA81: 0 | BB81: 0 | BC81: 0 | BD81: 0
A82: =YEAR(V82) -> 2025 | B82: =MONTH(V82) -> 8 | C82: =R82 -> P770986869946371481 | D82: =COUNTIF(R:R,R82) -> 4 | E82: =COUNTIF($R$2:R82,R82) -> 2 | F82: {=INDEX(订单明细!BQ:BQ,MATCH(R82&AC82,订单明细!A:A&订单明细!O:O,0))} -> Z2218-黑色-S | G82: =LEFT(F82,FIND("-",F82)-1) -> Z2218 | H82: {=_xlfn.IFS(C82=0,"",I82>0,AD82,AND(I82<0,I82>-30),0,I82<=-30,-1)} -> -1 | I82: =AF82 -> -229 | J82: =AI82+AJ82 -> 0 | K82: =IF(AZ82<=0,AZ82,AZ82/COUNTIFS(R:R,R82,AZ:AZ,">0")) -> 0 | L82: =AM82 -> 11.45 | M82: =AT82 -> 1.37 | O82: =SUM(I82:N82) -> -216.18 | R82: P770986869946371481 | S82: R4637148133202968 | T82: 2025-08-17 20:47:49 | U82: 2025-08-25 12:31:23 | V82: 2025-08-31 11:59:48 | W82: 退款 | X82: 店铺余额 | Y82: -216.18 | Z82: 【老板周】法式随性 夏季 · 【老板周】法式随性 夏季时髦叠门襟无袖设计感开叉马甲 黑色 S（80-100斤） | AA82: 女装/女士精品>马夹 | AB82: XHS-3FAGCOSWVFGG | AC82: 689704bae53c1000157cfa9c | AD82: 0 | AE82: -229 | AF82: -229 | AG82: 0 | AH82: 0 | AI82: 0 | AJ82: 0 | AK82: 0 | AL82: 0 | AM82: 11.45 | AN82: 0 | AO82: 0 | AP82: 0 | AQ82: 否 | AR82: 0 | AS82: 0 | AT82: 1.37 | AU82: 650d6e9f000000001603a6ac | AV82: 老板周. | AW82: 达人带货 | AZ82: 0 | BA82: 0 | BB82: 0 | BC82: 0 | BD82: 0
A83: =YEAR(V83) -> 2025 | B83: =MONTH(V83) -> 8 | C83: =R83 -> P770628663394212021 | D83: =COUNTIF(R:R,R83) -> 2 | E83: =COUNTIF($R$2:R83,R83) -> 1 | F83: {=INDEX(订单明细!BQ:BQ,MATCH(R83&AC83,订单明细!A:A&订单明细!O:O,0))} -> Z2333-米白色-M | G83: =LEFT(F83,FIND("-",F83)-1) -> Z2333 | H83: {=_xlfn.IFS(C83=0,"",I83>0,AD83,AND(I83<0,I83>-30),0,I83<=-30,-1)} -> -1 | I83: =AF83 -> -169 | J83: =AI83+AJ83 -> 0 | K83: =IF(AZ83<=0,AZ83,AZ83/COUNTIFS(R:R,R83,AZ:AZ,">0")) -> 0 | L83: =AM83 -> 8.45 | M83: =AT83 -> 1.01 | O83: =SUM(I83:N83) -> -159.54 | R83: P770628663394212021 | S83: R9421202111594216 | T83: 2025-08-13 17:17:43 | U83: 2025-08-25 17:50:58 | V83: 2025-08-31 11:59:48 | W83: 退款 | X83: 店铺余额 | Y83: -159.54 | Z83: 【老板周】法式复古 秋冬 · 【老板周】法式复古 秋冬新品不规则纹理白天鹅针织上衣 米白色 M（100-120斤） | AA83: 女装/女士精品>毛针织衫 | AB83: XHS-3IRG3JNFDGJK | AC83: 6894abfd581ea2001544ce80 | AD83: 0 | AE83: -169 | AF83: -169 | AG83: 0 | AH83: 0 | AI83: 0 | AJ83: 0 | AK83: 0 | AL83: 0 | AM83: 8.45 | AN83: 0 | AO83: 0 | AP83: 0 | AQ83: 否 | AR83: 0 | AS83: 0 | AT83: 1.01 | AU83: 650d6e9f000000001603a6ac | AV83: 老板周. | AW83: 达人带货 | AZ83: 0 | BA83: 0 | BB83: 0 | BC83: 0 | BD83: 0
A84: =YEAR(V84) -> 2025 | B84: =MONTH(V84) -> 8 | C84: =R84 -> P770990615215304131 | D84: =COUNTIF(R:R,R84) -> 2 | E84: =COUNTIF($R$2:R84,R84) -> 1 | F84: {=INDEX(订单明细!BQ:BQ,MATCH(R84&AC84,订单明细!A:A&订单明细!O:O,0))} -> Z2233-黄绿色-S | G84: =LEFT(F84,FIND("-",F84)-1) -> Z2233 | H84: {=_xlfn.IFS(C84=0,"",I84>0,AD84,AND(I84<0,I84>-30),0,I84<=-30,-1)} -> -1 | I84: =AF84 -> -269 | J84: =AI84+AJ84 -> 0 | K84: =IF(AZ84<=0,AZ84,AZ84/COUNTIFS(R:R,R84,AZ:AZ,">0")) -> 0 | L84: =AM84 -> 13.45 | M84: =AT84 -> 1.61 | O84: =SUM(I84:N84) -> -253.94 | R84: P770990615215304131 | S84: R1530413144788905 | T84: 2025-08-17 21:50:15 | U84: 2025-08-25 09:49:42 | V84: 2025-08-31 11:59:48 | W84: 退款 | X84: 店铺余额 | Y84: -253.94 | Z84: 【老板周】休闲腔调 夏季 · 【老板周】休闲腔调 夏季薄款圆领口袋设计百搭三角T恤 黄绿色 S（80-100斤） | AA84: 女装/女士精品>T恤 | AB84: XHS-3G6Z6JI0FO5C | AC84: 6896e3fdd48cf90015433efa | AD84: 0 | AE84: -269 | AF84: -269 | AG84: 0 | AH84: 0 | AI84: 0 | AJ84: 0 | AK84: 0 | AL84: 0 | AM84: 13.45 | AN84: 0 | AO84: 0 | AP84: 0 | AQ84: 否 | AR84: 0 | AS84: 0 | AT84: 1.61 | AU84: 650d6e9f000000001603a6ac | AV84: 老板周. | AW84: 达人带货 | AZ84: 0 | BA84: 0 | BB84: 0 | BC84: 0 | BD84: 0
A85: =YEAR(V85) -> 2025 | B85: =MONTH(V85) -> 8 | C85: =R85 -> P770990615215304131 | D85: =COUNTIF(R:R,R85) -> 2 | E85: =COUNTIF($R$2:R85,R85) -> 2 | F85: {=INDEX(订单明细!BQ:BQ,MATCH(R85&AC85,订单明细!A:A&订单明细!O:O,0))} -> Z2233-黄绿色-S | G85: =LEFT(F85,FIND("-",F85)-1) -> Z2233 | H85: {=_xlfn.IFS(C85=0,"",I85>0,AD85,AND(I85<0,I85>-30),0,I85<=-30,-1)} -> 1 | I85: =AF85 -> 269 | J85: =AI85+AJ85 -> 0 | K85: =IF(AZ85<=0,AZ85,AZ85/COUNTIFS(R:R,R85,AZ:AZ,">0")) -> 0 | L85: =AM85 -> -13.45 | M85: =AT85 -> -1.61 | O85: =SUM(I85:N85) -> 253.94 | R85: P770990615215304131 | T85: 2025-08-17 21:50:15 | U85: 2025-08-27 11:35:16 | V85: 2025-08-31 11:59:48 | W85: 结算入账 | X85: 店铺余额 | Y85: 253.94 | Z85: 【老板周】休闲腔调 夏季 · 【老板周】休闲腔调 夏季薄款圆领口袋设计百搭三角T恤 黄绿色 S（80-100斤） | AA85: 女装/女士精品>T恤 | AB85: XHS-3G6Z6JI0FO5C | AC85: 6896e3fdd48cf90015433efa | AD85: 1 | AE85: 269 | AF85: 269 | AH85: 0 | AI85: 0 | AJ85: 0 | AK85: 0.05 | AL85: 0 | AM85: -13.45 | AN85: 269 | AO85: 269 | AP85: 0 | AQ85: 否 | AR85: 0 | AS85: 0.006 | AT85: -1.61 | AU85: 650d6e9f000000001603a6ac | AV85: 老板周. | AW85: 达人带货 | AZ85: 0 | BA85: 0 | BB85: 0 | BC85: 0 | BD85: 0
A86: =YEAR(V86) -> 2025 | B86: =MONTH(V86) -> 8 | C86: =R86 -> P770986869946371481 | D86: =COUNTIF(R:R,R86) -> 4 | E86: =COUNTIF($R$2:R86,R86) -> 3 | F86: {=INDEX(订单明细!BQ:BQ,MATCH(R86&AC86,订单明细!A:A&订单明细!O:O,0))} -> Z2218-黑色-S | G86: =LEFT(F86,FIND("-",F86)-1) -> Z2218 | H86: {=_xlfn.IFS(C86=0,"",I86>0,AD86,AND(I86<0,I86>-30),0,I86<=-30,-1)} -> 1 | I86: =AF86 -> 229 | J86: =AI86+AJ86 -> 0 | K86: =IF(AZ86<=0,AZ86,AZ86/COUNTIFS(R:R,R86,AZ:AZ,">0")) -> 0 | L86: =AM86 -> -11.45 | M86: =AT86 -> -1.37 | O86: =SUM(I86:N86) -> 216.18 | R86: P770986869946371481 | T86: 2025-08-17 20:47:49 | U86: 2025-08-27 11:37:31 | V86: 2025-08-31 11:59:48 | W86: 结算入账 | X86: 店铺余额 | Y86: 432.36 | Z86: 【老板周】法式随性 夏季 · 【老板周】法式随性 夏季时髦叠门襟无袖设计感开叉马甲 黑色 S（80-100斤） | AA86: 女装/女士精品>马夹 | AB86: XHS-3FAGCOSWVFGG | AC86: 689704bae53c1000157cfa9c | AD86: 1 | AE86: 229 | AF86: 229 | AH86: 0 | AI86: 0 | AJ86: 0 | AK86: 0.05 | AL86: 0 | AM86: -11.45 | AN86: 229 | AO86: 229 | AP86: 0 | AQ86: 否 | AR86: 0 | AS86: 0.006 | AT86: -1.37 | AU86: 650d6e9f000000001603a6ac | AV86: 老板周. | AW86: 达人带货 | AZ86: 0 | BA86: 0 | BB86: 0 | BC86: 0 | BD86: 0
A87: =YEAR(V87) -> 2025 | B87: =MONTH(V87) -> 8 | C87: =R87 -> P770986869946371481 | D87: =COUNTIF(R:R,R87) -> 4 | E87: =COUNTIF($R$2:R87,R87) -> 4 | F87: {=INDEX(订单明细!BQ:BQ,MATCH(R87&AC87,订单明细!A:A&订单明细!O:O,0))} -> Z2218-黑色-M | G87: =LEFT(F87,FIND("-",F87)-1) -> Z2218 | H87: {=_xlfn.IFS(C87=0,"",I87>0,AD87,AND(I87<0,I87>-30),0,I87<=-30,-1)} -> 1 | I87: =AF87 -> 229 | J87: =AI87+AJ87 -> 0 | K87: =IF(AZ87<=0,AZ87,AZ87/COUNTIFS(R:R,R87,AZ:AZ,">0")) -> 0 | L87: =AM87 -> -11.45 | M87: =AT87 -> -1.37 | O87: =SUM(I87:N87) -> 216.18 | R87: P770986869946371481 | T87: 2025-08-17 20:47:49 | U87: 2025-08-27 11:37:31 | V87: 2025-08-31 11:59:48 | W87: 结算入账 | X87: 店铺余额 | Y87: 432.36 | Z87: 【老板周】法式随性 夏季 · 【老板周】法式随性 夏季时髦叠门襟无袖设计感开叉马甲 黑色 M（100-120斤） | AA87: 女装/女士精品>马夹 | AB87: XHS-3FAGCOT1V85C | AC87: 689704bae53c1000157cfa9e | AD87: 1 | AE87: 229 | AF87: 229 | AH87: 0 | AI87: 0 | AJ87: 0 | AK87: 0.05 | AL87: 0 | AM87: -11.45 | AN87: 229 | AO87: 229 | AP87: 0 | AQ87: 否 | AR87: 0 | AS87: 0.006 | AT87: -1.37 | AU87: 650d6e9f000000001603a6ac | AV87: 老板周. | AW87: 达人带货 | AZ87: 0 | BA87: 0 | BB87: 0 | BC87: 0 | BD87: 0
A88: =YEAR(V88) -> 2025 | B88: =MONTH(V88) -> 8 | C88: =R88 -> P770628663394212021 | D88: =COUNTIF(R:R,R88) -> 2 | E88: =COUNTIF($R$2:R88,R88) -> 2 | F88: {=INDEX(订单明细!BQ:BQ,MATCH(R88&AC88,订单明细!A:A&订单明细!O:O,0))} -> Z2333-米白色-M | G88: =LEFT(F88,FIND("-",F88)-1) -> Z2333 | H88: {=_xlfn.IFS(C88=0,"",I88>0,AD88,AND(I88<0,I88>-30),0,I88<=-30,-1)} -> 1 | I88: =AF88 -> 169 | J88: =AI88+AJ88 -> 0 | K88: =IF(AZ88<=0,AZ88,AZ88/COUNTIFS(R:R,R88,AZ:AZ,">0")) -> 0 | L88: =AM88 -> -8.45 | M88: =AT88 -> -1.01 | O88: =SUM(I88:N88) -> 159.54 | R88: P770628663394212021 | T88: 2025-08-13 17:17:43 | U88: 2025-08-27 11:35:49 | V88: 2025-08-31 11:59:48 | W88: 结算入账 | X88: 店铺余额 | Y88: 159.54 | Z88: 【老板周】法式复古 秋冬 · 【老板周】法式复古 秋冬新品不规则纹理白天鹅针织上衣 米白色 M（100-120斤） | AA88: 女装/女士精品>毛针织衫 | AB88: XHS-3IRG3JNFDGJK | AC88: 6894abfd581ea2001544ce80 | AD88: 1 | AE88: 169 | AF88: 169 | AH88: 0 | AI88: 0 | AJ88: 0 | AK88: 0.05 | AL88: 0 | AM88: -8.45 | AN88: 169 | AO88: 169 | AP88: 0 | AQ88: 否 | AR88: 0 | AS88: 0.006 | AT88: -1.01 | AU88: 650d6e9f000000001603a6ac | AV88: 老板周. | AW88: 达人带货 | AZ88: 0 | BA88: 0 | BB88: 0 | BC88: 0 | BD88: 0
A89: =YEAR(V89) -> 2025 | B89: =MONTH(V89) -> 8 | C89: =R89 -> P770796465763337081 | D89: =COUNTIF(R:R,R89) -> 1 | E89: =COUNTIF($R$2:R89,R89) -> 1 | F89: {=INDEX(订单明细!BQ:BQ,MATCH(R89&AC89,订单明细!A:A&订单明细!O:O,0))} -> Z1248-杏色-M | G89: =LEFT(F89,FIND("-",F89)-1) -> Z1248 | H89: {=_xlfn.IFS(C89=0,"",I89>0,AD89,AND(I89<0,I89>-30),0,I89<=-30,-1)} -> 1 | I89: =AF89 -> 199 | J89: =AI89+AJ89 -> 0 | K89: =IF(AZ89<=0,AZ89,AZ89/COUNTIFS(R:R,R89,AZ:AZ,">0")) -> 0 | L89: =AM89 -> -9.95 | M89: =AT89 -> -1.19 | O89: =SUM(I89:N89) -> 187.86 | R89: P770796465763337081 | T89: 2025-08-15 15:54:25 | U89: 2025-08-27 11:14:15 | V89: 2025-08-31 11:47:24 | W89: 结算入账 | X89: 店铺余额 | Y89: 187.86 | Z89: 【老板周】舒适经典 新款 · 【老板周】舒适经典 新款柔软细腻无缝一体半高领打底衫 杏色 M（100-120斤） | AA89: 女士内衣/男士内衣/家居服>打底衣 | AB89: XHS-3JXERVVVBFUO | AC89: 689d9a9c731333000196a4cd | AD89: 1 | AE89: 199 | AF89: 199 | AH89: 0 | AI89: 0 | AJ89: 0 | AK89: 0.05 | AL89: 0 | AM89: -9.95 | AN89: 199 | AO89: 199 | AP89: 0 | AQ89: 否 | AR89: 0 | AS89: 0.006 | AT89: -1.19 | AU89: 650d6e9f000000001603a6ac | AV89: 老板周. | AW89: 达人带货 | AZ89: 0 | BA89: 0 | BB89: 0 | BC89: 0 | BD89: 0
A90: =YEAR(V90) -> 2025 | B90: =MONTH(V90) -> 8 | C90: =R90 -> P770794613000337021 | D90: =COUNTIF(R:R,R90) -> 1 | E90: =COUNTIF($R$2:R90,R90) -> 1 | F90: {=INDEX(订单明细!BQ:BQ,MATCH(R90&AC90,订单明细!A:A&订单明细!O:O,0))} -> Z1248-黑色-M | G90: =LEFT(F90,FIND("-",F90)-1) -> Z1248 | H90: {=_xlfn.IFS(C90=0,"",I90>0,AD90,AND(I90<0,I90>-30),0,I90<=-30,-1)} -> 1 | I90: =AF90 -> 199 | J90: =AI90+AJ90 -> 0 | K90: =IF(AZ90<=0,AZ90,AZ90/COUNTIFS(R:R,R90,AZ:AZ,">0")) -> 0 | L90: =AM90 -> -9.95 | M90: =AT90 -> -1.19 | O90: =SUM(I90:N90) -> 187.86 | R90: P770794613000337021 | T90: 2025-08-15 15:23:33 | U90: 2025-08-27 11:14:53 | V90: 2025-08-31 11:47:24 | W90: 结算入账 | X90: 店铺余额 | Y90: 187.86 | Z90: 【老板周】舒适经典 新款 · 【老板周】舒适经典 新款柔软细腻无缝一体半高领打底衫 黑色 M（100-120斤） | AA90: 女士内衣/男士内衣/家居服>打底衣 | AB90: XHS-2PMHDZ8YH728 | AC90: 689d92c8956aac0015f36638 | AD90: 1 | AE90: 199 | AF90: 199 | AH90: 0 | AI90: 0 | AJ90: 0 | AK90: 0.05 | AL90: 0 | AM90: -9.95 | AN90: 199 | AO90: 199 | AP90: 0 | AQ90: 否 | AR90: 0 | AS90: 0.006 | AT90: -1.19 | AU90: 650d6e9f000000001603a6ac | AV90: 老板周. | AW90: 达人带货 | AZ90: 0 | BA90: 0 | BB90: 0 | BC90: 0 | BD90: 0
A91: =YEAR(V91) -> 2025 | B91: =MONTH(V91) -> 8 | C91: =R91 -> P770796110033183261 | D91: =COUNTIF(R:R,R91) -> 2 | E91: =COUNTIF($R$2:R91,R91) -> 1 | F91: {=INDEX(订单明细!BQ:BQ,MATCH(R91&AC91,订单明细!A:A&订单明细!O:O,0))} -> Z2378-花纱色-S | G91: =LEFT(F91,FIND("-",F91)-1) -> Z2378 | H91: {=_xlfn.IFS(C91=0,"",I91>0,AD91,AND(I91<0,I91>-30),0,I91<=-30,-1)} -> -1 | I91: =AF91 -> -179 | J91: =AI91+AJ91 -> 0 | K91: =IF(AZ91<=0,AZ91,AZ91/COUNTIFS(R:R,R91,AZ:AZ,">0")) -> 0 | L91: =AM91 -> 8.95 | M91: =AT91 -> 1.07 | O91: =SUM(I91:N91) -> -168.98 | R91: P770796110033183261 | S91: R3318326126160277 | T91: 2025-08-15 15:48:30 | U91: 2025-08-25 20:54:30 | V91: 2025-08-31 11:46:59 | W91: 退款 | X91: 店铺余额 | Y91: -168.98 | Z91: 【老板周】小众日系 秋冬 · 【老板周】小众日系 秋冬叠穿时髦下摆不规则宽松马甲 花纱色 S（80-100斤） | AA91: 女装/女士精品>马夹 | AB91: XHS-3JY8RM310T1C | AC91: 689dee45c34eef00157e11fb | AD91: 0 | AE91: -179 | AF91: -179 | AG91: 0 | AH91: 0 | AI91: 0 | AJ91: 0 | AK91: 0 | AL91: 0 | AM91: 8.95 | AN91: 0 | AO91: 0 | AP91: 0 | AQ91: 否 | AR91: 0 | AS91: 0 | AT91: 1.07 | AU91: 650d6e9f000000001603a6ac | AV91: 老板周. | AW91: 达人带货 | AZ91: 0 | BA91: 0 | BB91: 0 | BC91: 0 | BD91: 0
A92: =YEAR(V92) -> 2025 | B92: =MONTH(V92) -> 8 | C92: =R92 -> P770796110033183261 | D92: =COUNTIF(R:R,R92) -> 2 | E92: =COUNTIF($R$2:R92,R92) -> 2 | F92: {=INDEX(订单明细!BQ:BQ,MATCH(R92&AC92,订单明细!A:A&订单明细!O:O,0))} -> Z2378-花纱色-S | G92: =LEFT(F92,FIND("-",F92)-1) -> Z2378 | H92: {=_xlfn.IFS(C92=0,"",I92>0,AD92,AND(I92<0,I92>-30),0,I92<=-30,-1)} -> 1 | I92: =AF92 -> 179 | J92: =AI92+AJ92 -> 0 | K92: =IF(AZ92<=0,AZ92,AZ92/COUNTIFS(R:R,R92,AZ:AZ,">0")) -> 0 | L92: =AM92 -> -8.95 | M92: =AT92 -> -1.07 | O92: =SUM(I92:N92) -> 168.98 | R92: P770796110033183261 | T92: 2025-08-15 15:48:30 | U92: 2025-08-27 11:24:41 | V92: 2025-08-31 11:46:59 | W92: 结算入账 | X92: 店铺余额 | Y92: 168.98 | Z92: 【老板周】小众日系 秋冬 · 【老板周】小众日系 秋冬叠穿时髦下摆不规则宽松马甲 花纱色 S（80-100斤） | AA92: 女装/女士精品>马夹 | AB92: XHS-3JY8RM310T1C | AC92: 689dee45c34eef00157e11fb | AD92: 1 | AE92: 179 | AF92: 179 | AH92: 0 | AI92: 0 | AJ92: 0 | AK92: 0.05 | AL92: 0 | AM92: -8.95 | AN92: 179 | AO92: 179 | AP92: 0 | AQ92: 否 | AR92: 0 | AS92: 0.006 | AT92: -1.07 | AU92: 650d6e9f000000001603a6ac | AV92: 老板周. | AW92: 达人带货 | AZ92: 0 | BA92: 0 | BB92: 0 | BC92: 0 | BD92: 0
A93: =YEAR(V93) -> 2025 | B93: =MONTH(V93) -> 8 | C93: =R93 -> P770797478381146081 | D93: =COUNTIF(R:R,R93) -> 1 | E93: =COUNTIF($R$2:R93,R93) -> 1 | F93: {=INDEX(订单明细!BQ:BQ,MATCH(R93&AC93,订单明细!A:A&订单明细!O:O,0))} -> Z2363-灰色-M | G93: =LEFT(F93,FIND("-",F93)-1) -> Z2363 | H93: {=_xlfn.IFS(C93=0,"",I93>0,AD93,AND(I93<0,I93>-30),0,I93<=-30,-1)} -> 1 | I93: =AF93 -> 359 | J93: =AI93+AJ93 -> 0 | K93: =IF(AZ93<=0,AZ93,AZ93/COUNTIFS(R:R,R93,AZ:AZ,">0")) -> 0 | L93: =AM93 -> -17.95 | M93: =AT93 -> -2.15 | O93: =SUM(I93:N93) -> 338.9 | R93: P770797478381146081 | T93: 2025-08-15 16:11:18 | U93: 2025-08-27 11:01:59 | V93: 2025-08-31 11:41:04 | W93: 结算入账 | X93: 店铺余额 | Y93: 338.9 | Z93: 【老板周】通勤质感 秋冬 · 【老板周】通勤质感 秋冬重磅新品半松紧腰垂感口袋西裤 灰色 M（100-120斤） | AA93: 女装/女士精品>裤子>西装裤/正装裤 | AB93: XHS-3JY78059ZB40 | AC93: 689dee2db292580015c1974b | AD93: 1 | AE93: 359 | AF93: 359 | AH93: 0 | AI93: 0 | AJ93: 0 | AK93: 0.05 | AL93: 0 | AM93: -17.95 | AN93: 359 | AO93: 359 | AP93: 0 | AQ93: 否 | AR93: 0 | AS93: 0.006 | AT93: -2.15 | AU93: 650d6e9f000000001603a6ac | AV93: 老板周. | AW93: 达人带货 | AZ93: 0 | BA93: 0 | BB93: 0 | BC93: 0 | BD93: 0
A94: =YEAR(V94) -> 2025 | B94: =MONTH(V94) -> 8 | C94: =R94 -> P770633097859472931 | D94: =COUNTIF(R:R,R94) -> 2 | E94: =COUNTIF($R$2:R94,R94) -> 1 | F94: {=INDEX(订单明细!BQ:BQ,MATCH(R94&AC94,订单明细!A:A&订单明细!O:O,0))} -> Z1581-黑色-L | G94: =LEFT(F94,FIND("-",F94)-1) -> Z1581 | H94: {=_xlfn.IFS(C94=0,"",I94>0,AD94,AND(I94<0,I94>-30),0,I94<=-30,-1)} -> -1 | I94: =AF94 -> -289 | J94: =AI94+AJ94 -> 0 | K94: =IF(AZ94<=0,AZ94,AZ94/COUNTIFS(R:R,R94,AZ:AZ,">0")) -> 0 | L94: =AM94 -> 14.45 | M94: =AT94 -> 1.73 | O94: =SUM(I94:N94) -> -272.82 | R94: P770633097859472931 | S94: R5947293108593952 | T94: 2025-08-13 18:31:37 | U94: 2025-08-27 11:09:08 | V94: 2025-08-31 11:29:41 | W94: 退款 | X94: 店铺余额 | Y94: -272.82 | Z94: 【老板周】松弛感 春夏新 · 【老板周】松弛感 春夏新款简约休闲宽松阔腿弯刀私服裤 黑色 L（120-135斤） | AA94: 女装/女士精品>裤子>休闲裤 | AB94: XHS-2Z0FTM8FFZEO | AC94: 6896fe335cb63500154f597b | AD94: 0 | AE94: -289 | AF94: -289 | AG94: 0 | AH94: 0 | AI94: 0 | AJ94: 0 | AK94: 0 | AL94: 0 | AM94: 14.45 | AN94: 0 | AO94: 0 | AP94: 0 | AQ94: 否 | AR94: 0 | AS94: 0 | AT94: 1.73 | AU94: 650d6e9f000000001603a6ac | AV94: 老板周. | AW94: 达人带货 | AZ94: 0 | BA94: 0 | BB94: 0 | BC94: 0 | BD94: 0
A95: =YEAR(V95) -> 2025 | B95: =MONTH(V95) -> 8 | C95: =R95 -> P770633097859472931 | D95: =COUNTIF(R:R,R95) -> 2 | E95: =COUNTIF($R$2:R95,R95) -> 2 | F95: {=INDEX(订单明细!BQ:BQ,MATCH(R95&AC95,订单明细!A:A&订单明细!O:O,0))} -> Z1581-黑色-L | G95: =LEFT(F95,FIND("-",F95)-1) -> Z1581 | H95: {=_xlfn.IFS(C95=0,"",I95>0,AD95,AND(I95<0,I95>-30),0,I95<=-30,-1)} -> 1 | I95: =AF95 -> 289 | J95: =AI95+AJ95 -> 0 | K95: =IF(AZ95<=0,AZ95,AZ95/COUNTIFS(R:R,R95,AZ:AZ,">0")) -> 0 | L95: =AM95 -> -14.45 | M95: =AT95 -> -1.73 | O95: =SUM(I95:N95) -> 272.82 | R95: P770633097859472931 | T95: 2025-08-13 18:31:37 | U95: 2025-08-27 11:09:07 | V95: 2025-08-31 11:29:41 | W95: 结算入账 | X95: 店铺余额 | Y95: 272.82 | Z95: 【老板周】松弛感 春夏新 · 【老板周】松弛感 春夏新款简约休闲宽松阔腿弯刀私服裤 黑色 L（120-135斤） | AA95: 女装/女士精品>裤子>休闲裤 | AB95: XHS-2Z0FTM8FFZEO | AC95: 6896fe335cb63500154f597b | AD95: 1 | AE95: 289 | AF95: 289 | AH95: 0 | AI95: 0 | AJ95: 0 | AK95: 0.05 | AL95: 0 | AM95: -14.45 | AN95: 289 | AO95: 289 | AP95: 0 | AQ95: 否 | AR95: 0 | AS95: 0.006 | AT95: -1.73 | AU95: 650d6e9f000000001603a6ac | AV95: 老板周. | AW95: 达人带货 | AZ95: 0 | BA95: 0 | BB95: 0 | BC95: 0 | BD95: 0
